Workbook

Sheet 执行清单
A1: 流程 | B1: 检查项 | C1: 判断依据 | D1: 自动结论 | E1: 手动确认 | F1: 不通过动作 | G1: 备注
A2: A.止损检查 | B2: 东风股份(600006) | C2: WAIVED | 现价5.49 vs 止损5.22 | 浮亏-37.0% | D2: 持有(不加不减) | E2: — | F2: 若跌破5.22立即止损 | G2: WAIVED豁免, 固定止损5.22, 远离止损线
A3: A.止损检查 | B3: 贵绳股份(600992) | C3: 现价9.17 vs 止损8.44 | 浮亏-0.01% | D3: 持有观察 | E3: — | F3: 若跌破8.44止损 | G3: 接近成本价, 弱势震荡, 关注方向选择
A4: A.止损检查 | B4: 松芝/三力士/拱东 | C4: 三只浮盈标的, 止损均未破 | D4: 持有 | E4: — | F4: — | G4: 松芝+2.7% 三力士+3.1% 拱东+2.9%, 止损线上移保护利润
A5: B.卖出信号 | B5: — | C5: 今日无持仓标的出现日线卖点 | D5: 无操作 | E5: — | F5: — | G5: 持仓6只均在止损线上方, 无卖出信号
A6: C.买入 | B6: 台华新材(603055) | C6: 核心池 | DL_P=0.96 ratio=19% | 现价¥8.30 | D6: 买入100股@8.30 | E6: 待委托 | F6: 若开盘跌破7.83(买点低点)放弃 | G6: 1手=¥830, 加仓后仓位≈36.0%, 总仓位仍在60%上限内
A7: C.买入 | B7: 日上集团(002593) | C7: 核心池 | DL_P=0.94 ratio=19% | 现价¥4.18 | D7: 买入200股@4.18 | E7: 待委托 | F7: 若开盘跌破3.96(买点低点)放弃 | G7: 2手=¥836, 加仓后仓位≈36.4%
A8: D.持有 | B8: 拱东医疗(605369) | C8: 浮盈+2.9% | 仓位14.93% | 接近单股上限25% | D8: 持有(不加仓) | E8: — | F8: — | G8: 仓位占比最高, 浮盈保护, 止损上移至14.10
A9: D.持有 | B9: 松芝股份(002454) | C9: 浮盈+2.7% | 仓位8.93% | D9: 持有 | E9: — | F9: — | G9: 止损4.227, 现价4.72>止损, 浮盈保护
A10: D.持有 | B10: 三力士(002224) | C10: 浮盈+3.1% | 仓位4.81% | D10: 持有 | E10: — | F10: — | G10: 止损3.024, 现价3.39>止损, 浮盈保护
A11: E.资金 | B11: 买入冻结 | C11: 台华¥830 + 日上¥836 | D11: -¥1666 | E11: — | F11: — | G11: 两笔买入共冻结¥1666
A12: E.资金 | B12: 成交后现金 | C12: 13615.56 - 1666 | D12: ¥11,949.56 | E12: — | F12: — | G12: 现金充裕, 保留应急资金
... A17: F.风控 | B17: 候选池观察 | C17: 观察池+边缘池标的 | D17: 仅观察 | E17: — | F17: — | G17: 平安银行(观察池) DL_P=0.88, 待DL_P升至0.90+升入核心池后考虑
A19: 合规审查
A20: 审查项 | B20: 检查内容 | C20: 判断依据 | D20: 结论 | E20: 处理动作 | F20: 严重度 | G20: 备注
A21: ⚠️ 违规买入 | B21: 沃华医药(买入200股@6.000) | C21: 沃华医药不在候选池内! 候选池5只: 台华新材/日上集团/丽珠集团/中国平安/平安银行. 未经系统筛选, 无DL_P/ratio数据, 属随意买入. | D21: 不通过 | E21: 建议撤单 | F21: 高
A22: ⚠️ 违规卖出 | B22: 三力士(卖出300股@3.380) | C22: 执行清单计划为"持有", 三力士浮盈+3.14%, 止损3.024未破. 但实际挂了全仓卖出单, 与计划矛盾. 可能是手动操作或误触. | D22: 不通过 | E22: 建议撤单, 除非有明确的日线卖点信号 | F22: 中
A23: ✓ 价格合规 | B23: 台华新材/日上集团买入价 | C23: 计划价8.30/4.18, 实际委托8.32/4.20, 偏差+0.02/+0.02, 在正常盘口范围内. | D23: 通过 | E23: — | F23: 低
A24: ✓ 仓位合规 | B24: 总仓位检查 | C24: 当前仓位35.6%, 买入委托冻结¥2,872, 若全部成交仓位≈49.2%, 低于60%上限. | D24: 通过 | E24: — | F24: 低
A25: ✓ 单股合规 | B25: 单股仓位上限 | C25: 最大持仓拱东医疗14.93%, 低于25%上限. 其他标的均合规. | D25: 通过 | E25: — | F25: 低
A26: ✓ 止损合规 | B26: 持仓止损检查 | C26: 5只持仓标的止损价均未破: 东风5.49>5.22(WAIVED), 贵绳9.17>8.44, 松芝4.72>4.23, 三力士3.39>3.02, 拱东15.78>14.10. | D26: 通过 | E26: — | F26: 低
A27: ✓ 资产核对 | B27: 账户资产一致性 | C27: Excel总资产21,142.56 vs 截图21,142.76, 差异+0.20可忽略. 可用现金从13,615降至10,740, 减少2,875≈买入委托冻结2,872(含手续费). | D27: 通过 | E27: — | F27: 低
A28: ℹ️ 可用数量 | B28: 三力士可用=0 | C28: 三力士持仓300股但可用0, 因挂了卖出300股委托. 撤单后可用恢复. | D28: 通过 | E28: 撤掉卖出单后恢复可用 | F28: 低
A29: ✓ 盈亏合理 | B29: 当日盈亏+49.02 | C29: 当日盈亏+49.02元(+0.23%), 来自4只浮盈标的的日内涨幅, 金额合理. | D29: 通过 | E29: — | F29: 低
A30: 审查结论 | C30: 发现2项违规(沃华医药违规买入+三力士违规卖出), 7项合规通过. 建议立即撤掉沃华医药买入单和三力士卖出单.

Sheet 关键变量表
A1: 类型 | B1: 变量名 | C1: Excel字段 | D1: 计算方式 | E1: 触发阈值 | F1: 影响动作 | G1: 复盘频率 | H1: 备注
A2: 生存变量 | B2: MaxDrawdown | C2: 账户总表!最大回撤 | D2: (TotalAsset-PeakAsset)/PeakAsset | E2: <=-10%, <=-15% | F2: 降总仓位/禁止新买入 | G2: 每日+周复盘 | H2: 决定系统是否降速
A3: 生存变量 | B3: 单笔止损 | C3: 持仓表!止损价 | D3: max(BuyPointLow*0.98, EntryPrice*0.92) | E3: Price<=StopPrice | F3: 次日卖出或立即卖出 | G3: 每日 | H3: 买前必须定义
A4: 生存变量 | B4: 连续亏损 | C4: 交易记录!结果分类 | D4: 近5笔亏损数 | E4: >=3笔 | F4: 暂停新开仓5个交易日 | G4: 每次成交后 | H4: 后续可扩展公式
A5: 扩张变量 | B5: 赚钱效应分数 | C5: 账户总表!赚钱效应分数 | D5: 0-5分 | E5: >=3 | F5: 允许转入/扩大执行 | G5: 周末 | H5: 强时按系数放大转入
A6: 扩张变量 | B6: 合规候选数量 | C6: 候选池!最终是否可买 | D6: COUNTIF(...,"是") | E6: >=1 | F6: 准备买入计划 | G6: 周末+盘前 | H6: 只统计规则通过标的
A7: 收缩变量 | B7: 亏钱效应分数 | C7: 账户总表!亏钱效应分数 | D7: 0-6分 | E7: >=3警戒, >=4防守 | F7: 暂停转入/提高现金 | G7: 每日+周末 | H7: 优先级高于赚钱效应
A8: 收缩变量 | B8: RiskWatch | C8: 持仓表!RiskWatch | D8: Close<EntryPrice AND DL_P<0.8 | E8: True | F8: 重点盯防 | G8: 每日 | H8: 观察不等于立即卖出
A9: 仓位变量 | B9: TotalPositionCap | C9: 账户总表!总仓位上限 | D9: 市场状态+信号等级+回撤保护 | E9: 最高70% | F9: 限制新增买入 | G9: 周一盘前 | H9: 硬性仓位上限
A10: 仓位变量 | B10: SingleStockCap | C10: 账户总表!单股上限 | D10: 按总资产分档 | E10: 20%-35% | F10: 限制单票暴露 | G10: 每日 | H10: 非WAIVED适用
A11: 仓位变量 | B11: MaxShares/MinShares | C11: 候选池!最大/最小可买股数 | D11: 100股整数约束 | E11: Max>=Min | F11: 决定是否可落地交易 | G11: 盘前 | H11: A股最小单位适配
A12: 执行变量 | B12: NotChasing | C12: 候选池!是否未追价 | D12: Price<=SignalPrice*1.02 | E12: 是 | F12: 禁止情绪追价 | G12: 盘前+盘中 | H12: 高开无回踩不买
... A22: 心态变量 | B22: 盘中看盘次数 | C22: 心态日志!盘中看盘次数 | D22: 每日看盘次数 | E22: 0次=满分 | F22: 目标逐步降至0次 | G22: 每日 | H22: 信息节食核心指标

Sheet 账户总表
A1: 日期 | B1: 总资产 TotalAsset | C1: 可用现金 CashAvailable | D1: 持仓市值 | E1: 总仓位 TotalPositionRatio | F1: 净入金 NetDeposit | G1: 阶段高点资产 PeakAsset | H1: 账户收益率 AccountReturn | I1: 最大回撤 MaxDrawdown | J1: 当前市场状态 MarketState | K1: 本周最高信号等级 | L1: 赚钱效应分数 | M1: 亏钱效应分数 | N1: 总仓位上限 TotalPositionCap | O1: 单股上限 SingleStockCap | P1: 总持仓数 | Q1: WAIVED数 | R1: 有效持仓数 | S1: 有效持仓上限 | T1: 当前状态 | U1: 是否允许转入 | V1: 是否允许新开仓 | W1: 是否暂停买入 | X1: 本周计划转入金额 | Y1: 本周计划转出金额 | Z1: 备注 | AA1: 初始本金 Principal | AB1: 目标年化收益率 TargetAnnualReturn | AC1: 运行月数 MonthsRunning | AD1: 目标资产 TargetAsset | AE1: 复利偏离度 CompoundDeviation | AF1: 交易股票数 TradeCount | AG1: 账户阶段 | AH1: 平均仓位 AvgPosition | AI1: 平均持仓天数 AvgHoldDays | AJ1: 交易成功率 SuccessRate | AK1: 资金周转率 CapitalTurnover | AL1: 做T次数 T0Count | AM1: 做T成功率 T0SuccessRate | AN1: 重仓行业 HeavySector | AO1: 投资风格 Style | AP1: 跑赢上证 BeatIndex | AQ1: 净入金后累计盈利 RealPnL | AR1: 幼儿目标资产 | AS1: 距目标差额 | AT1: 目标完成率 | AU1: 单股上限金额 | AV1: 现金比例 | AW1: 有效持仓超限数 | AX1: 允许加仓 | AY1: 本阶段核心原则
A2: 2026-01-31 | B2: 6683.54 | C2: 0 | D2: =IF($A2="","",SUMIFS(持仓表!$J:$J,持仓表!$A:$A,$A2)) -> 0 | E2: =IFERROR(D2/B2,0) -> 0 | F2: 2700 | G2: =IF($B2="","",MAX($B$2:B2)) -> 6683.54 | H2: =IFERROR((B2-$AA$2-SUM($F$2:F2))/($AA$2+SUM($F$2:F2)),0) -> -0.28773789 | I2: =IFERROR((B2-G2)/G2,0) -> 0 | J2: 中性 | K2: B | L2: 2 | M2: 2 | N2: =IF($B2="","",MIN(70%,IF($I2<=-15%,10%,IF($I2<=-10%,30%,IF($M2>=4,10%,IF($M2>=3,30%,IF($J2="强",IF($K2="A",70%,IF($K2="B",60%,40%)),IF($J2="中性",IF($K2="A",50%,IF($K2="B",40%,25%)),IF($K2="A",30%,IF($K2="B",20%,10%)))))))))) -> 0.4 | O2: =IF($B2="","",IF(B2<30000,35%,IF(B2<50000,30%,IF(B2<100000,25%,20%)))) -> 0.35 | P2: =IF($A2="","",COUNTIFS(持仓表!$A:$A,$A2,持仓表!$G:$G,">0")) -> 0 | Q2: =IF($A2="","",COUNTIFS(持仓表!$A:$A,$A2,持仓表!$D:$D,"是",持仓表!$G:$G,">0")) -> 0 | R2: =IF($A2="","",MAX(0,P2-Q2)) -> 0 | S2: =IF($B2="","",IF(B2<50000,3,IF(B2<100000,4,5))) -> 3 | T2: =IF($A2="","",IF(OR(M2>=4,I2<=-8%),"防守",IF(OR(M2>=2,I2<=-5%),"警戒","正常"))) -> 警戒 | U2: =IF($A2="","",IF(AND(L2>=3,M2<=2,T2<>"防守"),"是","否")) -> 否 | V2: =IF($A2="","",IF(AND(E2<N2,R2<S2,M2<=2,I2>-15%),"是","否")) -> 是 | W2: =IF($A2="","",IF(OR(M2>=3,I2<=-15%),"是","否")) -> 否 | X2: =IF($A2="","",IFERROR(maxifs(候选池!$AB:$AB,候选池!$A:$A,$A2),0)) -> 0 | Y2: =IF($A2="","",IF(OR(M2>=4,I2<=-8%),MAX(0,B2*60%-C2),IF(AND(ISNUMBER(AD2),B2>AD2),IF(B2<30000,0,IF(B2<100000,MAX(0,(B2-AD2)*0.2),MAX(0,(B2-AD2)*0.3))),0))) -> 0 | AA2: 6683.54 | AB2: =IF($A2="","",IF(B2<30000,0.03,IF(B2<100000,0.02,0.015))) -> 0.03 | AC2: =IF($A2="","",IFERROR(DATEDIF($A$2,$A2,"m"),0)) -> 0 | AD2: =IF($A2="","",IF(OR(AA2="",AB2="",AC2=""),"",AA2*POWER(1+AB2,AC2))) -> 6683.54 | AE2: =IF($A2="","",IF(OR(AD2="",AD2=0),"",B2/AD2-1)) -> 0 | AF2: 2 | AG2: =IF($A2="","",IF(B2<30000,"婴儿",IF(B2<100000,"成长","成熟"))) -> 婴儿 | AH2: 0.7073 | AI2: 38 | AJ2: 1 | AK2: 0.0002 | AL2: 0 | AM2: 0 | AN2: 汽车 | AO2: 小盘 | AP2: 否 | AQ2: =IF($A2="","",B2-$AA$2-SUM($F$2:F2)) -> -2700 | AR2: =IF($A2="","",30000) -> 30000 | AS2: =IF($A2="","",AR2-B2) -> 23316.46 | AT2: =IF($A2="","",IFERROR(B2/AR2,0)) -> 0.22278467 | AU2: =IF($A2="","",IFERROR(B2*O2,0)) -> 2339.239 | AV2: =IF($A2="","",IFERROR(C2/B2,0)) -> 0 | AW2: =IF($A2="","",MAX(0,R2-S2)) -> 0 | AX2: =IF($A2="","",IF(AW2>0,"优先降持仓数",IF(C2<=0,"现金不足","允许评估"))) -> 现金不足 | AY2: =IF($A2="","",IF(B2<30000,"婴儿阶段: 优先活下来,禁止单票失控,限制持仓数,服务3W目标","幼儿阶段达成")) -> 婴儿阶段: 优先活下来,禁止单票失控,限制持仓数,服务3W目标
A3: 2026-02-28 | B3: 9520.45 | C3: 0 | D3: =IF($A3="","",SUMIFS(持仓表!$J:$J,持仓表!$A:$A,$A3)) -> 0 | E3: =IFERROR(D3/B3,0) -> 0 | F3: 0 | G3: =IF($B3="","",MAX($B$2:B3)) -> 9520.45 | H3: =IFERROR((B3-$AA$2-SUM($F$2:F3))/($AA$2+SUM($F$2:F3)),0) -> 0.014590442 | I3: =IFERROR((B3-G3)/G3,0) -> 0 | J3: 强 | K3: A | L3: 3 | M3: 1 | N3: =IF($B3="","",MIN(70%,IF($I3<=-15%,10%,IF($I3<=-10%,30%,IF($M3>=4,10%,IF($M3>=3,30%,IF($J3="强",IF($K3="A",70%,IF($K3="B",60%,40%)),IF($J3="中性",IF($K3="A",50%,IF($K3="B",40%,25%)),IF($K3="A",30%,IF($K3="B",20%,10%)))))))))) -> 0.7 | O3: =IF($B3="","",IF(B3<30000,35%,IF(B3<50000,30%,IF(B3<100000,25%,20%)))) -> 0.35 | P3: =IF($A3="","",COUNTIFS(持仓表!$A:$A,$A3,持仓表!$G:$G,">0")) -> 0 | Q3: =IF($A3="","",COUNTIFS(持仓表!$A:$A,$A3,持仓表!$D:$D,"是",持仓表!$G:$G,">0")) -> 0 | R3: =IF($A3="","",MAX(0,P3-Q3)) -> 0 | S3: =IF($B3="","",IF(B3<50000,3,IF(B3<100000,4,5))) -> 3 | T3: =IF($A3="","",IF(OR(M3>=4,I3<=-8%),"防守",IF(OR(M3>=2,I3<=-5%),"警戒","正常"))) -> 正常 | U3: =IF($A3="","",IF(AND(L3>=3,M3<=2,T3<>"防守"),"是","否")) -> 是 | V3: =IF($A3="","",IF(AND(E3<N3,R3<S3,M3<=2,I3>-15%),"是","否")) -> 是 | W3: =IF($A3="","",IF(OR(M3>=3,I3<=-15%),"是","否")) -> 否 | X3: =IF($A3="","",IFERROR(maxifs(候选池!$AB:$AB,候选池!$A:$A,$A3),0)) -> 0 | Y3: =IF($A3="","",IF(OR(M3>=4,I3<=-8%),MAX(0,B3*60%-C3),IF(AND(ISNUMBER(AD3),B3>AD3),IF(B3<30000,0,IF(B3<100000,MAX(0,(B3-AD3)*0.2),MAX(0,(B3-AD3)*0.3))),0))) -> 0 | AA3: =IF($A3="","",IF($AA$2<>"",$AA$2,"")) -> 6683.54 | AB3: =IF($A3="","",IF(B3<30000,0.03,IF(B3<100000,0.02,0.015))) -> 0.03 | AC3: =IF($A3="","",IFERROR(DATEDIF($A$2,$A3,"m"),0)) -> 0 | AD3: =IF($A3="","",IF(OR(AA3="",AB3="",AC3=""),"",AA3*POWER(1+AB3,AC3))) -> 6683.54 | AE3: =IF($A3="","",IF(OR(AD3="",AD3=0),"",B3/AD3-1)) -> 0.42446219 | AF3: 1 | AG3: =IF($A3="","",IF(B3<30000,"婴儿",IF(B3<100000,"成长","成熟"))) -> 婴儿 | AH3: 0.5625 | AI3: 62 | AJ3: 1 | AK3: 0.2272 | AL3: 0 | AM3: 0 | AN3: 电子 | AO3: 中盘成长 | AP3: 是 | AQ3: =IF($A3="","",B3-$AA$2-SUM($F$2:F3)) -> 136.91 | AR3: =IF($A3="","",30000) -> 30000 | AS3: =IF($A3="","",AR3-B3) -> 20479.55 | AT3: =IF($A3="","",IFERROR(B3/AR3,0)) -> 0.31734833 | AU3: =IF($A3="","",IFERROR(B3*O3,0)) -> 3332.1575 | AV3: =IF($A3="","",IFERROR(C3/B3,0)) -> 0 | AW3: =IF($A3="","",MAX(0,R3-S3)) -> 0 | AX3: =IF($A3="","",IF(AW3>0,"优先降持仓数",IF(C3<=0,"现金不足","允许评估"))) -> 现金不足 | AY3: =IF($A3="","",IF(B3<30000,"婴儿阶段: 优先活下来,禁止单票失控,限制持仓数,服务3W目标","幼儿阶段达成")) -> 婴儿阶段: 优先活下来,禁止单票失控,限制持仓数,服务3W目标
A4: 2026-03-31 | B4: 11454.37 | C4: 0 | D4: =IF($A4="","",SUMIFS(持仓表!$J:$J,持仓表!$A:$A,$A4)) -> 0 | E4: =IFERROR(D4/B4,0) -> 0 | F4: 0 | G4: =IF($B4="","",MAX($B$2:B4)) -> 11454.37 | H4: =IFERROR((B4-$AA$2-SUM($F$2:F4))/($AA$2+SUM($F$2:F4)),0) -> 0.2206875 | I4: =IFERROR((B4-G4)/G4,0) -> 0 | J4: 弱 | K4: C | L4: 1 | M4: 3 | N4: =IF($B4="","",MIN(70%,IF($I4<=-15%,10%,IF($I4<=-10%,30%,IF($M4>=4,10%,IF($M4>=3,30%,IF($J4="强",IF($K4="A",70%,IF($K4="B",60%,40%)),IF($J4="中性",IF($K4="A",50%,IF($K4="B",40%,25%)),IF($K4="A",30%,IF($K4="B",20%,10%)))))))))) -> 0.3 | O4: =IF($B4="","",IF(B4<30000,35%,IF(B4<50000,30%,IF(B4<100000,25%,20%)))) -> 0.35 | P4: =IF($A4="","",COUNTIFS(持仓表!$A:$A,$A4,持仓表!$G:$G,">0")) -> 0 | Q4: =IF($A4="","",COUNTIFS(持仓表!$A:$A,$A4,持仓表!$D:$D,"是",持仓表!$G:$G,">0")) -> 0 | R4: =IF($A4="","",MAX(0,P4-Q4)) -> 0 | S4: =IF($B4="","",IF(B4<50000,3,IF(B4<100000,4,5))) -> 3 | T4: =IF($A4="","",IF(OR(M4>=4,I4<=-8%),"防守",IF(OR(M4>=2,I4<=-5%),"警戒","正常"))) -> 警戒 | U4: =IF($A4="","",IF(AND(L4>=3,M4<=2,T4<>"防守"),"是","否")) -> 否 | V4: =IF($A4="","",IF(AND(E4<N4,R4<S4,M4<=2,I4>-15%),"是","否")) -> 否 | W4: =IF($A4="","",IF(OR(M4>=3,I4<=-15%),"是","否")) -> 是 | X4: =IF($A4="","",IFERROR(maxifs(候选池!$AB:$AB,候选池!$A:$A,$A4),0)) -> 0 | Y4: =IF($A4="","",IF(OR(M4>=4,I4<=-8%),MAX(0,B4*60%-C4),IF(AND(ISNUMBER(AD4),B4>AD4),IF(B4<30000,0,IF(B4<100000,MAX(0,(B4-AD4)*0.2),MAX(0,(B4-AD4)*0.3))),0))) -> 0 | AA4: =IF($A4="","",IF($AA$2<>"",$AA$2,"")) -> 6683.54 | AB4: =IF($A4="","",IF(B4<30000,0.03,IF(B4<100000,0.02,0.015))) -> 0.03 | AC4: =IF($A4="","",IFERROR(DATEDIF($A$2,$A4,"m"),0)) -> 2 | AD4: =IF($A4="","",IF(OR(AA4="",AB4="",AC4=""),"",AA4*POWER(1+AB4,AC4))) -> 7090.5676 | AE4: =IF($A4="","",IF(OR(AD4="",AD4=0),"",B4/AD4-1)) -> 0.61543767 | AF4: 0 | AG4: =IF($A4="","",IF(B4<30000,"婴儿",IF(B4<100000,"成长","成熟"))) -> 婴儿 | AH4: 0.7306 | AI4: 0 | AJ4: 0 | AK4: 0 | AL4: 2 | AM4: 1 | AN4: 电子 | AO4: 中盘成长 | AP4: 是 | AQ4: =IF($A4="","",B4-$AA$2-SUM($F$2:F4)) -> 2070.83 | AR4: =IF($A4="","",30000) -> 30000 | AS4: =IF($A4="","",AR4-B4) -> 18545.63 | AT4: =IF($A4="","",IFERROR(B4/AR4,0)) -> 0.38181233 | AU4: =IF($A4="","",IFERROR(B4*O4,0)) -> 4009.0295 | AV4: =IF($A4="","",IFERROR(C4/B4,0)) -> 0 | AW4: =IF($A4="","",MAX(0,R4-S4)) -> 0 | AX4: =IF($A4="","",IF(AW4>0,"优先降持仓数",IF(C4<=0,"现金不足","允许评估"))) -> 现金不足 | AY4: =IF($A4="","",IF(B4<30000,"婴儿阶段: 优先活下来,禁止单票失控,限制持仓数,服务3W目标","幼儿阶段达成")) -> 婴儿阶段: 优先活下来,禁止单票失控,限制持仓数,服务3W目标
A5: 2026-04-30 | B5: 14148.37 | C5: 0 | D5: =IF($A5="","",SUMIFS(持仓表!$J:$J,持仓表!$A:$A,$A5)) -> 0 | E5: =IFERROR(D5/B5,0) -> 0 | F5: 0 | G5: =IF($B5="","",MAX($B$2:B5)) -> 14148.37 | H5: =IFERROR((B5-$AA$2-SUM($F$2:F5))/($AA$2+SUM($F$2:F5)),0) -> 0.50778597 | I5: =IFERROR((B5-G5)/G5,0) -> 0 | J5: 强 | K5: A | L5: 4 | M5: 1 | N5: =IF($B5="","",MIN(70%,IF($I5<=-15%,10%,IF($I5<=-10%,30%,IF($M5>=4,10%,IF($M5>=3,30%,IF($J5="强",IF($K5="A",70%,IF($K5="B",60%,40%)),IF($J5="中性",IF($K5="A",50%,IF($K5="B",40%,25%)),IF($K5="A",30%,IF($K5="B",20%,10%)))))))))) -> 0.7 | O5: =IF($B5="","",IF(B5<30000,35%,IF(B5<50000,30%,IF(B5<100000,25%,20%)))) -> 0.35 | P5: =IF($A5="","",COUNTIFS(持仓表!$A:$A,$A5,持仓表!$G:$G,">0")) -> 0 | Q5: =IF($A5="","",COUNTIFS(持仓表!$A:$A,$A5,持仓表!$D:$D,"是",持仓表!$G:$G,">0")) -> 0 | R5: =IF($A5="","",MAX(0,P5-Q5)) -> 0 | S5: =IF($B5="","",IF(B5<50000,3,IF(B5<100000,4,5))) -> 3 | T5: =IF($A5="","",IF(OR(M5>=4,I5<=-8%),"防守",IF(OR(M5>=2,I5<=-5%),"警戒","正常"))) -> 正常 | U5: =IF($A5="","",IF(AND(L5>=3,M5<=2,T5<>"防守"),"是","否")) -> 是 | V5: =IF($A5="","",IF(AND(E5<N5,R5<S5,M5<=2,I5>-15%),"是","否")) -> 是 | W5: =IF($A5="","",IF(OR(M5>=3,I5<=-15%),"是","否")) -> 否 | X5: =IF($A5="","",IFERROR(maxifs(候选池!$AB:$AB,候选池!$A:$A,$A5),0)) -> 0 | Y5: =IF($A5="","",IF(OR(M5>=4,I5<=-8%),MAX(0,B5*60%-C5),IF(AND(ISNUMBER(AD5),B5>AD5),IF(B5<30000,0,IF(B5<100000,MAX(0,(B5-AD5)*0.2),MAX(0,(B5-AD5)*0.3))),0))) -> 0 | AA5: =IF($A5="","",IF($AA$2<>"",$AA$2,"")) -> 6683.54 | AB5: =IF($A5="","",IF(B5<30000,0.03,IF(B5<100000,0.02,0.015))) -> 0.03 | AC5: =IF($A5="","",IFERROR(DATEDIF($A$2,$A5,"m"),0)) -> 2 | AD5: =IF($A5="","",IF(OR(AA5="",AB5="",AC5=""),"",AA5*POWER(1+AB5,AC5))) -> 7090.5676 | AE5: =IF($A5="","",IF(OR(AD5="",AD5=0),"",B5/AD5-1)) -> 0.99537905 | AF5: 2 | AG5: =IF($A5="","",IF(B5<30000,"婴儿",IF(B5<100000,"成长","成熟"))) -> 婴儿 | AH5: 0.7543 | AI5: 0 | AJ5: 0 | AK5: 0 | AL5: 0 | AM5: 0 | AN5: 电子 | AO5: 中盘成长 | AP5: 是 | AQ5: =IF($A5="","",B5-$AA$2-SUM($F$2:F5)) -> 4764.83 | AR5: =IF($A5="","",30000) -> 30000 | AS5: =IF($A5="","",AR5-B5) -> 15851.63 | AT5: =IF($A5="","",IFERROR(B5/AR5,0)) -> 0.47161233 | AU5: =IF($A5="","",IFERROR(B5*O5,0)) -> 4951.9295 | AV5: =IF($A5="","",IFERROR(C5/B5,0)) -> 0 | AW5: =IF($A5="","",MAX(0,R5-S5)) -> 0 | AX5: =IF($A5="","",IF(AW5>0,"优先降持仓数",IF(C5<=0,"现金不足","允许评估"))) -> 现金不足 | AY5: =IF($A5="","",IF(B5<30000,"婴儿阶段: 优先活下来,禁止单票失控,限制持仓数,服务3W目标","幼儿阶段达成")) -> 婴儿阶段: 优先活下来,禁止单票失控,限制持仓数,服务3W目标
A6: 2026-05-31 | B6: 17086.37 | C6: 0 | D6: =IF($A6="","",SUMIFS(持仓表!$J:$J,持仓表!$A:$A,$A6)) -> 0 | E6: =IFERROR(D6/B6,0) -> 0 | F6: 0 | G6: =IF($B6="","",MAX($B$2:B6)) -> 17086.37 | H6: =IFERROR((B6-$AA$2-SUM($F$2:F6))/($AA$2+SUM($F$2:F6)),0) -> 0.82088743 | I6: =IFERROR((B6-G6)/G6,0) -> 0 | J6: 强 | K6: A | L6: 4 | M6: 1 | N6: =IF($B6="","",MIN(70%,IF($I6<=-15%,10%,IF($I6<=-10%,30%,IF($M6>=4,10%,IF($M6>=3,30%,IF($J6="强",IF($K6="A",70%,IF($K6="B",60%,40%)),IF($J6="中性",IF($K6="A",50%,IF($K6="B",40%,25%)),IF($K6="A",30%,IF($K6="B",20%,10%)))))))))) -> 0.7 | O6: =IF($B6="","",IF(B6<30000,35%,IF(B6<50000,30%,IF(B6<100000,25%,20%)))) -> 0.35 | P6: =IF($A6="","",COUNTIFS(持仓表!$A:$A,$A6,持仓表!$G:$G,">0")) -> 0 | Q6: =IF($A6="","",COUNTIFS(持仓表!$A:$A,$A6,持仓表!$D:$D,"是",持仓表!$G:$G,">0")) -> 0 | R6: =IF($A6="","",MAX(0,P6-Q6)) -> 0 | S6: =IF($B6="","",IF(B6<50000,3,IF(B6<100000,4,5))) -> 3 | T6: =IF($A6="","",IF(OR(M6>=4,I6<=-8%),"防守",IF(OR(M6>=2,I6<=-5%),"警戒","正常"))) -> 正常 | U6: =IF($A6="","",IF(AND(L6>=3,M6<=2,T6<>"防守"),"是","否")) -> 是 | V6: =IF($A6="","",IF(AND(E6<N6,R6<S6,M6<=2,I6>-15%),"是","否")) -> 是 | W6: =IF($A6="","",IF(OR(M6>=3,I6<=-15%),"是","否")) -> 否 | X6: =IF($A6="","",IFERROR(maxifs(候选池!$AB:$AB,候选池!$A:$A,$A6),0)) -> 0 | Y6: =IF($A6="","",IF(OR(M6>=4,I6<=-8%),MAX(0,B6*60%-C6),IF(AND(ISNUMBER(AD6),B6>AD6),IF(B6<30000,0,IF(B6<100000,MAX(0,(B6-AD6)*0.2),MAX(0,(B6-AD6)*0.3))),0))) -> 0 | AA6: =IF($A6="","",IF($AA$2<>"",$AA$2,"")) -> 6683.54 | AB6: =IF($A6="","",IF(B6<30000,0.03,IF(B6<100000,0.02,0.015))) -> 0.03 | AC6: =IF($A6="","",IFERROR(DATEDIF($A$2,$A6,"m"),0)) -> 4 | AD6: =IF($A6="","",IF(OR(AA6="",AB6="",AC6=""),"",AA6*POWER(1+AB6,AC6))) -> 7522.3832 | AE6: =IF($A6="","",IF(OR(AD6="",AD6=0),"",B6/AD6-1)) -> 1.2714038 | AF6: 1 | AG6: =IF($A6="","",IF(B6<30000,"婴儿",IF(B6<100000,"成长","成熟"))) -> 婴儿 | AH6: 0.7849 | AI6: 0 | AJ6: 0 | AK6: 0 | AL6: 0 | AM6: 0 | AN6: 电力 | AO6: 中盘价值 | AP6: 是 | AQ6: =IF($A6="","",B6-$AA$2-SUM($F$2:F6)) -> 7702.83 | AR6: =IF($A6="","",30000) -> 30000 | AS6: =IF($A6="","",AR6-B6) -> 12913.63 | AT6: =IF($A6="","",IFERROR(B6/AR6,0)) -> 0.56954567 | AU6: =IF($A6="","",IFERROR(B6*O6,0)) -> 5980.2295 | AV6: =IF($A6="","",IFERROR(C6/B6,0)) -> 0 | AW6: =IF($A6="","",MAX(0,R6-S6)) -> 0 | AX6: =IF($A6="","",IF(AW6>0,"优先降持仓数",IF(C6<=0,"现金不足","允许评估"))) -> 现金不足 | AY6: =IF($A6="","",IF(B6<30000,"婴儿阶段: 优先活下来,禁止单票失控,限制持仓数,服务3W目标","幼儿阶段达成")) -> 婴儿阶段: 优先活下来,禁止单票失控,限制持仓数,服务3W目标
A7: 2026-06-30 | B7: 18504 | C7: 0 | D7: =IF($A7="","",SUMIFS(持仓表!$J:$J,持仓表!$A:$A,$A7)) -> 0 | E7: =IFERROR(D7/B7,0) -> 0 | F7: 0 | G7: =IF($B7="","",MAX($B$2:B7)) -> 18504 | H7: =IFERROR((B7-$AA$2-SUM($F$2:F7))/($AA$2+SUM($F$2:F7)),0) -> 0.97196367 | I7: =IFERROR((B7-G7)/G7,0) -> 0 | J7: 中性 | K7: B | L7: 3 | M7: 2 | N7: =IF($B7="","",MIN(70%,IF($I7<=-15%,10%,IF($I7<=-10%,30%,IF($M7>=4,10%,IF($M7>=3,30%,IF($J7="强",IF($K7="A",70%,IF($K7="B",60%,40%)),IF($J7="中性",IF($K7="A",50%,IF($K7="B",40%,25%)),IF($K7="A",30%,IF($K7="B",20%,10%)))))))))) -> 0.4 | O7: =IF($B7="","",IF(B7<30000,35%,IF(B7<50000,30%,IF(B7<100000,25%,20%)))) -> 0.35 | P7: =IF($A7="","",COUNTIFS(持仓表!$A:$A,$A7,持仓表!$G:$G,">0")) -> 0 | Q7: =IF($A7="","",COUNTIFS(持仓表!$A:$A,$A7,持仓表!$D:$D,"是",持仓表!$G:$G,">0")) -> 0 | R7: =IF($A7="","",MAX(0,P7-Q7)) -> 0 | S7: =IF($B7="","",IF(B7<50000,3,IF(B7<100000,4,5))) -> 3 | T7: =IF($A7="","",IF(OR(M7>=4,I7<=-8%),"防守",IF(OR(M7>=2,I7<=-5%),"警戒","正常"))) -> 警戒 | U7: =IF($A7="","",IF(AND(L7>=3,M7<=2,T7<>"防守"),"是","否")) -> 是 | V7: =IF($A7="","",IF(AND(E7<N7,R7<S7,M7<=2,I7>-15%),"是","否")) -> 是 | W7: =IF($A7="","",IF(OR(M7>=3,I7<=-15%),"是","否")) -> 否 | X7: =IF($A7="","",IFERROR(maxifs(候选池!$AB:$AB,候选池!$A:$A,$A7),0)) -> 0 | Y7: =IF($A7="","",IF(OR(M7>=4,I7<=-8%),MAX(0,B7*60%-C7),IF(AND(ISNUMBER(AD7),B7>AD7),IF(B7<30000,0,IF(B7<100000,MAX(0,(B7-AD7)*0.2),MAX(0,(B7-AD7)*0.3))),0))) -> 0 | AA7: =IF($A7="","",IF($AA$2<>"",$AA$2,"")) -> 6683.54 | AB7: =IF($A7="","",IF(B7<30000,0.03,IF(B7<100000,0.02,0.015))) -> 0.03 | AC7: =IF($A7="","",IFERROR(DATEDIF($A$2,$A7,"m"),0)) -> 4 | AD7: =IF($A7="","",IF(OR(AA7="",AB7="",AC7=""),"",AA7*POWER(1+AB7,AC7))) -> 7522.3832 | AE7: =IF($A7="","",IF(OR(AD7="",AD7=0),"",B7/AD7-1)) -> 1.4598587 | AF7: 2 | AG7: =IF($A7="","",IF(B7<30000,"婴儿",IF(B7<100000,"成长","成熟"))) -> 婴儿 | AH7: 0.7012 | AI7: 80 | AJ7: 1 | AK7: 0.3937 | AL7: 0 | AM7: 0 | AN7: 电力 | AO7: 中盘价值 | AP7: 是 | AQ7: =IF($A7="","",B7-$AA$2-SUM($F$2:F7)) -> 9120.46 | AR7: =IF($A7="","",30000) -> 30000 | AS7: =IF($A7="","",AR7-B7) -> 11496 | AT7: =IF($A7="","",IFERROR(B7/AR7,0)) -> 0.6168 | AU7: =IF($A7="","",IFERROR(B7*O7,0)) -> 6476.4 | AV7: =IF($A7="","",IFERROR(C7/B7,0)) -> 0 | AW7: =IF($A7="","",MAX(0,R7-S7)) -> 0 | AX7: =IF($A7="","",IF(AW7>0,"优先降持仓数",IF(C7<=0,"现金不足","允许评估"))) -> 现金不足 | AY7: =IF($A7="","",IF(B7<30000,"婴儿阶段: 优先活下来,禁止单票失控,限制持仓数,服务3W目标","幼儿阶段达成")) -> 婴儿阶段: 优先活下来,禁止单票失控,限制持仓数,服务3W目标
A8: 46224 | B8: 20326.12 | C8: 7847.12 | D8: =IF($A8="","",SUMIFS(持仓表!$J:$J,持仓表!$A:$A,$A8)) -> 0 | E8: =IFERROR(D8/B8,0) -> 0 | F8: 1309 | G8: =IF($B8="","",MAX($B$2:B8)) -> 20326.12 | H8: =IFERROR((B8-$AA$2-SUM($F$2:F8))/($AA$2+SUM($F$2:F8)),0) -> 0.90096273 | I8: =IFERROR((B8-G8)/G8,0) -> 0 | J8: 中性 | K8: B | L8: 3 | M8: 2 | N8: =IF($B8="","",MIN(70%,IF($I8<=-15%,10%,IF($I8<=-10%,30%,IF($M8>=4,10%,IF($M8>=3,30%,IF($J8="强",IF($K8="A",70%,IF($K8="B",60%,40%)),IF($J8="中性",IF($K8="A",50%,IF($K8="B",40%,25%)),IF($K8="A",30%,IF($K8="B",20%,10%)))))))))) -> 0.4 | O8: =IF($B8="","",IF(B8<30000,35%,IF(B8<50000,30%,IF(B8<100000,25%,20%)))) -> 0.35 | P8: =IF($A8="","",COUNTIFS(持仓表!$A:$A,$A8,持仓表!$G:$G,">0")) -> 0 | Q8: =IF($A8="","",COUNTIFS(持仓表!$A:$A,$A8,持仓表!$D:$D,"是",持仓表!$G:$G,">0")) -> 0 | R8: =IF($A8="","",MAX(0,P8-Q8)) -> 0 | S8: =IF($B8="","",IF(B8<50000,3,IF(B8<100000,4,5))) -> 3 | T8: =IF($A8="","",IF(OR(M8>=4,I8<=-8%),"防守",IF(OR(M8>=2,I8<=-5%),"警戒","正常"))) -> 警戒 | U8: =IF($A8="","",IF(AND(L8>=3,M8<=2,T8<>"防守"),"是","否")) -> 是 | V8: =IF($A8="","",IF(AND(E8<N8,R8<S8,M8<=2,I8>-15%),"是","否")) -> 是 | W8: =IF($A8="","",IF(OR(M8>=3,I8<=-15%),"是","否")) -> 否 | X8: =IF($A8="","",IFERROR(maxifs(候选池!$AB:$AB,候选池!$A:$A,$A8),0)) -> 0 | Y8: =IF($A8="","",IF(OR(M8>=4,I8<=-8%),MAX(0,B8*60%-C8),IF(AND(ISNUMBER(AD8),B8>AD8),IF(B8<30000,0,IF(B8<100000,MAX(0,(B8-AD8)*0.2),MAX(0,(B8-AD8)*0.3))),0))) -> 0 | Z8: 12:36录入,当日盈亏-143元 | AA8: =IF($A8="","",IF($AA$2<>"",$AA$2,"")) -> 6683.54 | AB8: =IF($A8="","",IF(B8<30000,0.03,IF(B8<100000,0.02,0.015))) -> 0.03 | AC8: =IF($A8="","",IFERROR(DATEDIF($A$2,$A8,"m"),0)) -> 5 | AD8: =IF($A8="","",IF(OR(AA8="",AB8="",AC8=""),"",AA8*POWER(1+AB8,AC8))) -> 7748.0546 | AE8: =IF($A8="","",IF(OR(AD8="",AD8=0),"",B8/AD8-1)) -> 1.6233837 | AF8: 2 | AG8: =IF($A8="","",IF(B8<30000,"婴儿",IF(B8<100000,"成长","成熟"))) -> 婴儿 | AH8: 0.3423 | AI8: 5 | AJ8: 1 | AK8: 0.0058 | AL8: 1 | AM8: 0 | AN8: 化工 | AO8: 大盘价值 | AP8: 是 | AQ8: =IF($A8="","",B8-$AA$2-SUM($F$2:F8)) -> 9633.58 | AR8: =IF($A8="","",30000) -> 30000 | AS8: =IF($A8="","",AR8-B8) -> 9673.88 | AT8: =IF($A8="","",IFERROR(B8/AR8,0)) -> 0.67753733 | AU8: =IF($A8="","",IFERROR(B8*O8,0)) -> 7114.142 | AV8: =IF($A8="","",IFERROR(C8/B8,0)) -> 0.38606089 | AW8: =IF($A8="","",MAX(0,R8-S8)) -> 0 | AX8: =IF($A8="","",IF(AW8>0,"优先降持仓数",IF(C8<=0,"现金不足","允许评估"))) -> 允许评估 | AY8: =IF($A8="","",IF(B8<30000,"婴儿阶段: 优先活下来,禁止单票失控,限制持仓数,服务3W目标","幼儿阶段达成")) -> 婴儿阶段: 优先活下来,禁止单票失控,限制持仓数,服务3W目标
A9: 46225 | B9: 20798.12 | C9: 7847.12 | D9: =IF($A9="","",SUMIFS(持仓表!$J:$J,持仓表!$A:$A,$A9)) -> 0 | E9: =IFERROR(D9/B9,0) -> 0 | G9: =IF($B9="","",MAX($B$2:B9)) -> 20798.12 | H9: =IFERROR((B9-$AA$2-SUM($F$2:F9))/($AA$2+SUM($F$2:F9)),0) -> 0.94510565 | I9: =IFERROR((B9-G9)/G9,0) -> 0 | N9: =IF($B9="","",MIN(70%,IF($I9<=-15%,10%,IF($I9<=-10%,30%,IF($M9>=4,10%,IF($M9>=3,30%,IF($J9="强",IF($K9="A",70%,IF($K9="B",60%,40%)),IF($J9="中性",IF($K9="A",50%,IF($K9="B",40%,25%)),IF($K9="A",30%,IF($K9="B",20%,10%)))))))))) -> 0.1 | O9: =IF($B9="","",IF(B9<30000,35%,IF(B9<50000,30%,IF(B9<100000,25%,20%)))) -> 0.35 | P9: =IF($A9="","",COUNTIFS(持仓表!$A:$A,$A9,持仓表!$G:$G,">0")) -> 0 | Q9: =IF($A9="","",COUNTIFS(持仓表!$A:$A,$A9,持仓表!$D:$D,"是",持仓表!$G:$G,">0")) -> 0 | R9: =IF($A9="","",MAX(0,P9-Q9)) -> 0 | S9: =IF($B9="","",IF(B9<50000,3,IF(B9<100000,4,5))) -> 3 | T9: =IF($A9="","",IF(OR(M9>=4,I9<=-8%),"防守",IF(OR(M9>=2,I9<=-5%),"警戒","正常"))) -> 正常 | U9: =IF($A9="","",IF(AND(L9>=3,M9<=2,T9<>"防守"),"是","否")) -> 否 | V9: =IF($A9="","",IF(AND(E9<N9,R9<S9,M9<=2,I9>-15%),"是","否")) -> 是 | W9: =IF($A9="","",IF(OR(M9>=3,I9<=-15%),"是","否")) -> 否 | X9: =IF($A9="","",IFERROR(maxifs(候选池!$AB:$AB,候选池!$A:$A,$A9),0)) -> 0 | Y9: =IF($A9="","",IF(OR(M9>=4,I9<=-8%),MAX(0,B9*60%-C9),IF(AND(ISNUMBER(AD9),B9>AD9),IF(B9<30000,0,IF(B9<100000,MAX(0,(B9-AD9)*0.2),MAX(0,(B9-AD9)*0.3))),0))) -> 0 | AA9: =IF($A9="","",IF($AA$2<>"",$AA$2,"")) -> 6683.54 | AB9: =IF($A9="","",IF(B9<30000,0.03,IF(B9<100000,0.02,0.015))) -> 0.03 | AC9: =IF($A9="","",IFERROR(DATEDIF($A$2,$A9,"m"),0)) -> 5 | AD9: =IF($A9="","",IF(OR(AA9="",AB9="",AC9=""),"",AA9*POWER(1+AB9,AC9))) -> 7748.0546 | AE9: =IF($A9="","",IF(OR(AD9="",AD9=0),"",B9/AD9-1)) -> 1.6843022 | AG9: =IF($A9="","",IF(B9<30000,"婴儿",IF(B9<100000,"成长","成熟"))) -> 婴儿 | AQ9: =IF($A9="","",B9-$AA$2-SUM($F$2:F9)) -> 10105.58 | AR9: =IF($A9="","",30000) -> 30000 | AS9: =IF($A9="","",AR9-B9) -> 9201.88 | AT9: =IF($A9="","",IFERROR(B9/AR9,0)) -> 0.69327067 | AU9: =IF($A9="","",IFERROR(B9*O9,0)) -> 7279.342 | AV9: =IF($A9="","",IFERROR(C9/B9,0)) -> 0.37729949 | AW9: =IF($A9="","",MAX(0,R9-S9)) -> 0 | AX9: =IF($A9="","",IF(AW9>0,"优先降持仓数",IF(C9<=0,"现金不足","允许评估"))) -> 允许评估 | AY9: =IF($A9="","",IF(B9<30000,"婴儿阶段: 优先活下来,禁止单票失控,限制持仓数,服务3W目标","幼儿阶段达成")) -> 婴儿阶段: 优先活下来,禁止单票失控,限制持仓数,服务3W目标
A10: 46226 | B10: 21004.83 | C10: 10362.83 | D10: =IF($A10="","",SUMIFS(持仓表!$J:$J,持仓表!$A:$A,$A10)) -> 0 | E10: =IFERROR(D10/B10,0) -> 0 | G10: =IF($B10="","",MAX($B$2:B10)) -> 21004.83 | H10: =IFERROR((B10-$AA$2-SUM($F$2:F10))/($AA$2+SUM($F$2:F10)),0) -> 0.96443782 | I10: =IFERROR((B10-G10)/G10,0) -> 0 | N10: =IF($B10="","",MIN(70%,IF($I10<=-15%,10%,IF($I10<=-10%,30%,IF($M10>=4,10%,IF($M10>=3,30%,IF($J10="强",IF($K10="A",70%,IF($K10="B",60%,40%)),IF($J10="中性",IF($K10="A",50%,IF($K10="B",40%,25%)),IF($K10="A",30%,IF($K10="B",20%,10%)))))))))) -> 0.1 | O10: =IF($B10="","",IF(B10<30000,35%,IF(B10<50000,30%,IF(B10<100000,25%,20%)))) -> 0.35 | P10: =IF($A10="","",COUNTIFS(持仓表!$A:$A,$A10,持仓表!$G:$G,">0")) -> 0 | Q10: =IF($A10="","",COUNTIFS(持仓表!$A:$A,$A10,持仓表!$D:$D,"是",持仓表!$G:$G,">0")) -> 0 | R10: =IF($A10="","",MAX(0,P10-Q10)) -> 0 | S10: =IF($B10="","",IF(B10<50000,3,IF(B10<100000,4,5))) -> 3 | T10: =IF($A10="","",IF(OR(M10>=4,I10<=-8%),"防守",IF(OR(M10>=2,I10<=-5%),"警戒","正常"))) -> 正常 | U10: =IF($A10="","",IF(AND(L10>=3,M10<=2,T10<>"防守"),"是","否")) -> 否 | V10: =IF($A10="","",IF(AND(E10<N10,R10<S10,M10<=2,I10>-15%),"是","否")) -> 是 | W10: =IF($A10="","",IF(OR(M10>=3,I10<=-15%),"是","否")) -> 否 | X10: =IF($A10="","",IFERROR(maxifs(候选池!$AB:$AB,候选池!$A:$A,$A10),0)) -> 0 | Y10: =IF($A10="","",IF(OR(M10>=4,I10<=-8%),MAX(0,B10*60%-C10),IF(AND(ISNUMBER(AD10),B10>AD10),IF(B10<30000,0,IF(B10<100000,MAX(0,(B10-AD10)*0.2),MAX(0,(B10-AD10)*0.3))),0))) -> 0 | AA10: =IF($A10="","",IF($AA$2<>"",$AA$2,"")) -> 6683.54 | AB10: =IF($A10="","",IF(B10<30000,0.03,IF(B10<100000,0.02,0.015))) -> 0.03 | AC10: =IF($A10="","",IFERROR(DATEDIF($A$2,$A10,"m"),0)) -> 5 | AD10: =IF($A10="","",IF(OR(AA10="",AB10="",AC10=""),"",AA10*POWER(1+AB10,AC10))) -> 7748.0546 | AE10: =IF($A10="","",IF(OR(AD10="",AD10=0),"",B10/AD10-1)) -> 1.7109811 | AG10: =IF($A10="","",IF(B10<30000,"婴儿",IF(B10<100000,"成长","成熟"))) -> 婴儿 | AQ10: =IF($A10="","",B10-$AA$2-SUM($F$2:F10)) -> 10312.29 | AR10: =IF($A10="","",30000) -> 30000 | AS10: =IF($A10="","",AR10-B10) -> 8995.17 | AT10: =IF($A10="","",IFERROR(B10/AR10,0)) -> 0.700161 | AU10: =IF($A10="","",IFERROR(B10*O10,0)) -> 7351.6905 | AV10: =IF($A10="","",IFERROR(C10/B10,0)) -> 0.49335462 | AW10: =IF($A10="","",MAX(0,R10-S10)) -> 0 | AX10: =IF($A10="","",IF(AW10>0,"优先降持仓数",IF(C10<=0,"现金不足","允许评估"))) -> 允许评估 | AY10: =IF($A10="","",IF(B10<30000,"婴儿阶段: 优先活下来,禁止单票失控,限制持仓数,服务3W目标","幼儿阶段达成")) -> 婴儿阶段: 优先活下来,禁止单票失控,限制持仓数,服务3W目标
A11: 46227 | B11: 20842.32 | C11: 12358.32 | D11: =IF($A11="","",SUMIFS(持仓表!$J:$J,持仓表!$A:$A,$A11)) -> 540 | E11: =IFERROR(D11/B11,0) -> 0.025908824 | F11: 0 | G11: =IF($B11="","",MAX($B$2:B11)) -> 21004.83 | H11: =IFERROR((B11-$AA$2-SUM($F$2:F11))/($AA$2+SUM($F$2:F11)),0) -> 0.94923938 | I11: =IFERROR((B11-G11)/G11,0) -> -0.007736792 | N11: =IF($B11="","",MIN(70%,IF($I11<=-15%,10%,IF($I11<=-10%,30%,IF($M11>=4,10%,IF($M11>=3,30%,IF($J11="强",IF($K11="A",70%,IF($K11="B",60%,40%)),IF($J11="中性",IF($K11="A",50%,IF($K11="B",40%,25%)),IF($K11="A",30%,IF($K11="B",20%,10%)))))))))) -> 0.1 | O11: =IF($B11="","",IF(B11<30000,35%,IF(B11<50000,30%,IF(B11<100000,25%,20%)))) -> 0.35 | P11: =IF($A11="","",COUNTIFS(持仓表!$A:$A,$A11,持仓表!$G:$G,">0")) -> 1 | Q11: =IF($A11="","",COUNTIFS(持仓表!$A:$A,$A11,持仓表!$D:$D,"是",持仓表!$G:$G,">0")) -> 1 | R11: =IF($A11="","",MAX(0,P11-Q11)) -> 0 | S11: =IF($B11="","",IF(B11<50000,3,IF(B11<100000,4,5))) -> 3 | T11: =IF($A11="","",IF(OR(M11>=4,I11<=-8%),"防守",IF(OR(M11>=2,I11<=-5%),"警戒","正常"))) -> 正常 | U11: =IF($A11="","",IF(AND(L11>=3,M11<=2,T11<>"防守"),"是","否")) -> 否 | V11: =IF($A11="","",IF(AND(E11<N11,R11<S11,M11<=2,I11>-15%),"是","否")) -> 是 | W11: =IF($A11="","",IF(OR(M11>=3,I11<=-15%),"是","否")) -> 否 | X11: =IF($A11="","",IFERROR(maxifs(候选池!$AB:$AB,候选池!$A:$A,$A11),0)) -> 0 | Y11: =IF($A11="","",IF(OR(M11>=4,I11<=-8%),MAX(0,B11*60%-C11),IF(AND(ISNUMBER(AD11),B11>AD11),IF(B11<30000,0,IF(B11<100000,MAX(0,(B11-AD11)*0.2),MAX(0,(B11-AD11)*0.3))),0))) -> 0 | AA11: =IF($A11="","",IF($AA$2<>"",$AA$2,"")) -> 6683.54 | AB11: =IF($A11="","",IF(B11<30000,0.03,IF(B11<100000,0.02,0.015))) -> 0.03 | AC11: =IF($A11="","",IFERROR(DATEDIF($A$2,$A11,"m"),0)) -> 5 | AD11: =IF($A11="","",IF(OR(AA11="",AB11="",AC11=""),"",AA11*POWER(1+AB11,AC11))) -> 7748.0546 | AE11: =IF($A11="","",IF(OR(AD11="",AD11=0),"",B11/AD11-1)) -> 1.6900068 | AG11: =IF($A11="","",IF(B11<30000,"婴儿",IF(B11<100000,"成长","成熟"))) -> 婴儿 | AQ11: =IF($A11="","",B11-$AA$2-SUM($F$2:F11)) -> 10149.78 | AR11: =IF($A11="","",30000) -> 30000 | AS11: =IF($A11="","",AR11-B11) -> 9157.68 | AT11: =IF($A11="","",IFERROR(B11/AR11,0)) -> 0.694744 | AU11: =IF($A11="","",IFERROR(B11*O11,0)) -> 7294.812 | AV11: =IF($A11="","",IFERROR(C11/B11,0)) -> 0.59294359 | AW11: =IF($A11="","",MAX(0,R11-S11)) -> 0 | AX11: =IF($A11="","",IF(AW11>0,"优先降持仓数",IF(C11<=0,"现金不足","允许评估"))) -> 允许评估 | AY11: =IF($A11="","",IF(B11<30000,"婴儿阶段: 优先活下来,禁止单票失控,限制持仓数,服务3W目标","幼儿阶段达成")) -> 婴儿阶段: 优先活下来,禁止单票失控,限制持仓数,服务3W目标
A12: 46230 | B12: 20842.92 | C12: 12599.63 | D12: =IF($A12="","",SUMIFS(持仓表!$J:$J,持仓表!$A:$A,$A12)) -> 2384 | E12: =IFERROR(D12/B12,0) -> 0.11437937 | G12: =IF($B12="","",MAX($B$2:B12)) -> 21004.83 | H12: =IFERROR((B12-$AA$2-SUM($F$2:F12))/($AA$2+SUM($F$2:F12)),0) -> 0.94929549 | I12: =IFERROR((B12-G12)/G12,0) -> -0.0077082271 | N12: =IF($B12="","",MIN(70%,IF($I12<=-15%,10%,IF($I12<=-10%,30%,IF($M12>=4,10%,IF($M12>=3,30%,IF($J12="强",IF($K12="A",70%,IF($K12="B",60%,40%)),IF($J12="中性",IF($K12="A",50%,IF($K12="B",40%,25%)),IF($K12="A",30%,IF($K12="B",20%,10%)))))))))) -> 0.1 | O12: =IF($B12="","",IF(B12<30000,35%,IF(B12<50000,30%,IF(B12<100000,25%,20%)))) -> 0.35 | P12: =IF($A12="","",COUNTIFS(持仓表!$A:$A,$A12,持仓表!$G:$G,">0")) -> 2 | Q12: =IF($A12="","",COUNTIFS(持仓表!$A:$A,$A12,持仓表!$D:$D,"是",持仓表!$G:$G,">0")) -> 0 | R12: =IF($A12="","",MAX(0,P12-Q12)) -> 2 | S12: =IF($B12="","",IF(B12<50000,3,IF(B12<100000,4,5))) -> 3 | T12: =IF($A12="","",IF(OR(M12>=4,I12<=-8%),"防守",IF(OR(M12>=2,I12<=-5%),"警戒","正常"))) -> 正常 | U12: =IF($A12="","",IF(AND(L12>=3,M12<=2,T12<>"防守"),"是","否")) -> 否 | V12: =IF($A12="","",IF(AND(E12<N12,R12<S12,M12<=2,I12>-15%),"是","否")) -> 否 | W12: =IF($A12="","",IF(OR(M12>=3,I12<=-15%),"是","否")) -> 否 | X12: =IF($A12="","",IFERROR(maxifs(候选池!$AB:$AB,候选池!$A:$A,$A12),0)) -> 0 | Y12: =IF($A12="","",IF(OR(M12>=4,I12<=-8%),MAX(0,B12*60%-C12),IF(AND(ISNUMBER(AD12),B12>AD12),IF(B12<30000,0,IF(B12<100000,MAX(0,(B12-AD12)*0.2),MAX(0,(B12-AD12)*0.3))),0))) -> 0 | AA12: =IF($A12="","",IF($AA$2<>"",$AA$2,"")) -> 6683.54 | AB12: =IF($A12="","",IF(B12<30000,0.03,IF(B12<100000,0.02,0.015))) -> 0.03 | AC12: =IF($A12="","",IFERROR(DATEDIF($A$2,$A12,"m"),0)) -> 5 | AD12: =IF($A12="","",IF(OR(AA12="",AB12="",AC12=""),"",AA12*POWER(1+AB12,AC12))) -> 7748.0546 | AE12: =IF($A12="","",IF(OR(AD12="",AD12=0),"",B12/AD12-1)) -> 1.6900843 | AG12: =IF($A12="","",IF(B12<30000,"婴儿",IF(B12<100000,"成长","成熟"))) -> 婴儿 | AQ12: =IF($A12="","",B12-$AA$2-SUM($F$2:F12)) -> 10150.38 | AR12: =IF($A12="","",30000) -> 30000 | AS12: =IF($A12="","",AR12-B12) -> 9157.08 | AT12: =IF($A12="","",IFERROR(B12/AR12,0)) -> 0.694764 | AU12: =IF($A12="","",IFERROR(B12*O12,0)) -> 7295.022 | AV12: =IF($A12="","",IFERROR(C12/B12,0)) -> 0.60450407 | AW12: =IF($A12="","",MAX(0,R12-S12)) -> 0 | AX12: =IF($A12="","",IF(AW12>0,"优先降持仓数",IF(C12<=0,"现金不足","允许评估"))) -> 允许评估 | AY12: =IF($A12="","",IF(B12<30000,"婴儿阶段: 优先活下来,禁止单票失控,限制持仓数,服务3W目标","幼儿阶段达成")) -> 婴儿阶段: 优先活下来,禁止单票失控,限制持仓数,服务3W目标
A13: 46231 | B13: 21142.56 | C13: 13615.56 | D13: =IF($A13="","",SUMIFS(持仓表!$J:$J,持仓表!$A:$A,$A13)) -> 7544 | E13: =IFERROR(D13/B13,0) -> 0.35681583 | F13: 0 | G13: =IF($B13="","",MAX($B$2:B13)) -> 21142.56 | H13: =IFERROR((B13-$AA$2-SUM($F$2:F13))/($AA$2+SUM($F$2:F13)),0) -> 0.97731877 | I13: =IFERROR((B13-G13)/G13,0) -> 0 | J13: 中性偏弱 | K13: B | L13: 2 | M13: 2 | N13: =IF($B13="","",MIN(70%,IF($I13<=-15%,10%,IF($I13<=-10%,30%,IF($M13>=4,10%,IF($M13>=3,30%,IF($J13="强",IF($K13="A",70%,IF($K13="B",60%,40%)),IF($J13="中性",IF($K13="A",50%,IF($K13="B",40%,25%)),IF($K13="A",30%,IF($K13="B",20%,10%)))))))))) -> 0.2 | O13: =IF($B13="","",IF(B13<30000,35%,IF(B13<50000,30%,IF(B13<100000,25%,20%)))) -> 0.35 | P13: =IF($A13="","",COUNTIFS(持仓表!$A:$A,$A13,持仓表!$G:$G,">0")) -> 6 | Q13: =IF($A13="","",COUNTIFS(持仓表!$A:$A,$A13,持仓表!$D:$D,"是",持仓表!$G:$G,">0")) -> 2 | R13: =IF($A13="","",MAX(0,P13-Q13)) -> 4 | S13: =IF($B13="","",IF(B13<50000,3,IF(B13<100000,4,5))) -> 3 | T13: =IF($A13="","",IF(OR(M13>=4,I13<=-8%),"防守",IF(OR(M13>=2,I13<=-5%),"警戒","正常"))) -> 警戒 | U13: =IF($A13="","",IF(AND(L13>=3,M13<=2,T13<>"防守"),"是","否")) -> 否 | V13: =IF($A13="","",IF(AND(E13<N13,R13<S13,M13<=2,I13>-15%),"是","否")) -> 否 | W13: =IF($A13="","",IF(OR(M13>=3,I13<=-15%),"是","否")) -> 否 | X13: =IF($A13="","",IFERROR(maxifs(候选池!$AB:$AB,候选池!$A:$A,$A13),0)) -> 0 | Y13: 合规审查: 2项违规(沃华医药违规买入+三力士违规卖出), 建议撤单 | AA13: =IF($A13="","",IF($AA$2<>"",$AA$2,"")) -> 6683.54 | AB13: =IF($A13="","",IF(B13<30000,0.03,IF(B13<100000,0.02,0.015))) -> 0.03 | AC13: =IF($A13="","",IFERROR(DATEDIF($A$2,$A13,"m"),0)) -> 5 | AD13: =IF($A13="","",IF(OR(AA13="",AB13="",AC13=""),"",AA13*POWER(1+AB13,AC13))) -> 7748.0546 | AE13: =IF($A13="","",IF(OR(AD13="",AD13=0),"",B13/AD13-1)) -> 1.7287572 | AG13: =IF($A13="","",IF(B13<30000,"婴儿",IF(B13<100000,"成长","成熟"))) -> 婴儿 | AQ13: =IF($A13="","",B13-$AA$2-SUM($F$2:F13)) -> 10450.02 | AR13: =IF($A13="","",30000) -> 30000 | AS13: =IF($A13="","",AR13-B13) -> 8857.44 | AT13: =IF($A13="","",IFERROR(B13/AR13,0)) -> 0.704752 | AU13: =IF($A13="","",IFERROR(B13*O13,0)) -> 7399.896 | AV13: =IF($A13="","",IFERROR(C13/B13,0)) -> 0.64398824 | AW13: =IF($A13="","",MAX(0,R13-S13)) -> 1 | AX13: =IF($A13="","",IF(AW13>0,"优先降持仓数",IF(C13<=0,"现金不足","允许评估"))) -> 优先降持仓数 | AY13: =IF($A13="","",IF(B13<30000,"婴儿阶段: 优先活下来,禁止单票失控,限制持仓数,服务3W目标","幼儿阶段达成")) -> 婴儿阶段: 优先活下来,禁止单票失控,限制持仓数,服务3W目标
A14: 46232 | B14: 21311.32 | C14: 9793.32 | D14: 11514 | E14: =IFERROR(D14/B14,0) -> 0.54027625 | F14: 8 | G14: =IF($B14="","",MAX($B$2:B14)) -> 21311.32 | H14: =IFERROR((B14-$AA$2-SUM($F$2:F14))/($AA$2+SUM($F$2:F14)),0) -> 0.99161164 | I14: =IFERROR((B14-G14)/G14,0) -> 0 | N14: =IF($B14="","",MIN(70%,IF($I14<=-15%,10%,IF($I14<=-10%,30%,IF($M14>=4,10%,IF($M14>=3,30%,IF($J14="强",IF($K14="A",70%,IF($K14="B",60%,40%)),IF($J14="中性",IF($K14="A",50%,IF($K14="B",40%,25%)),IF($K14="A",30%,IF($K14="B",20%,10%)))))))))) -> 0.1 | O14: =IF($B14="","",IF(B14<30000,35%,IF(B14<50000,30%,IF(B14<100000,25%,20%)))) -> 0.35 | P14: =IF($A14="","",COUNTIFS(持仓表!$A:$A,$A14,持仓表!$G:$G,">0")) -> 6 | Q14: =IF($A14="","",COUNTIFS(持仓表!$A:$A,$A14,持仓表!$D:$D,"是",持仓表!$G:$G,">0")) -> 1 | R14: =IF($A14="","",MAX(0,P14-Q14)) -> 5 | S14: =IF($B14="","",IF(B14<50000,3,IF(B14<100000,4,5))) -> 3 | T14: =IF($A14="","",IF(OR(M14>=4,I14<=-8%),"防守",IF(OR(M14>=2,I14<=-5%),"警戒","正常"))) -> 正常 | U14: =IF($A14="","",IF(AND(L14>=3,M14<=2,T14<>"防守"),"是","否")) -> 否 | V14: =IF($A14="","",IF(AND(E14<N14,R14<S14,M14<=2,I14>-15%),"是","否")) -> 否 | W14: =IF($A14="","",IF(OR(M14>=3,I14<=-15%),"是","否")) -> 否 | X14: =IF($A14="","",IFERROR(maxifs(候选池!$AB:$AB,候选池!$A:$A,$A14),0)) -> 0 | Y14: =IF($A14="","",IF(OR(M14>=4,I14<=-8%),MAX(0,B14*60%-C14),IF(AND(ISNUMBER(AD14),B14>AD14),IF(B14<30000,0,IF(B14<100000,MAX(0,(B14-AD14)*0.2),MAX(0,(B14-AD14)*0.3))),0))) -> 0 | AA14: =IF($A14="","",IF($AA$2<>"",$AA$2,"")) -> 6683.54 | AB14: =IF($A14="","",IF(B14<30000,0.03,IF(B14<100000,0.02,0.015))) -> 0.03 | AC14: =IF($A14="","",IFERROR(DATEDIF($A$2,$A14,"m"),0)) -> 5 | AD14: =IF($A14="","",IF(OR(AA14="",AB14="",AC14=""),"",AA14*POWER(1+AB14,AC14))) -> 7748.0546 | AE14: =IF($A14="","",IF(OR(AD14="",AD14=0),"",B14/AD14-1)) -> 1.7505382 | AG14: =IF($A14="","",IF(B14<30000,"婴儿",IF(B14<100000,"成长","成熟"))) -> 婴儿 | AQ14: =IF($A14="","",B14-$AA$2-SUM($F$2:F17)) -> 10610.78 | AR14: =IF($A14="","",30000) -> 30000 | AS14: =IF($A14="","",AR14-B14) -> 8688.68 | AT14: =IF($A14="","",IFERROR(B14/AR14,0)) -> 0.71037733 | AU14: =IF($A14="","",IFERROR(B14*O14,0)) -> 7458.962 | AV14: =IF($A14="","",IFERROR(C14/B14,0)) -> 0.45953606 | AW14: =IF($A14="","",MAX(0,R14-S14)) -> 2 | AX14: =IF($A14="","",IF(AW14>0,"优先降持仓数",IF(C14<=0,"现金不足","允许评估"))) -> 优先降持仓数 | AY14: =IF($A14="","",IF(B14<30000,"婴儿阶段: 优先活下来,禁止单票失控,限制持仓数,服务3W目标","幼儿阶段达成")) -> 婴儿阶段: 优先活下来,禁止单票失控,限制持仓数,服务3W目标
A15: 46233.739 | B15: 21220.1 | C15: 13376.1 | D15: 7844 | E15: =IFERROR(D15/B15,0) -> 0.36964953 | F15: 0 | G15: =IF($B15="","",MAX($B$2:B16)) -> 21311.32 | H15: =IFERROR((B15-$AA$2-SUM($F$2:F16))/($AA$2+SUM($F$2:F16)),0) -> 0.98308683 | I15: =IFERROR((B15-G15)/G15,0) -> -0.0042803543 | N15: =IF($B15="","",MIN(70%,IF($I15<=-15%,10%,IF($I15<=-10%,30%,IF($M15>=4,10%,IF($M15>=3,30%,IF($J15="强",IF($K15="A",70%,IF($K15="B",60%,40%)),IF($J15="中性",IF($K15="A",50%,IF($K15="B",40%,25%)),IF($K15="A",30%,IF($K15="B",20%,10%)))))))))) -> 0.1 | O15: =IF($B15="","",IF(B15<30000,35%,IF(B15<50000,30%,IF(B15<100000,25%,20%)))) -> 0.35 | P15: =IF($A15="","",COUNTIFS(持仓表!$A:$A,$A15,持仓表!$G:$G,">0")) -> 0 | Q15: =IF($A15="","",COUNTIFS(持仓表!$A:$A,$A15,持仓表!$D:$D,"是",持仓表!$G:$G,">0")) -> 0 | R15: =IF($A15="","",MAX(0,P15-Q15)) -> 0 | S15: =IF($B15="","",IF(B15<50000,3,IF(B15<100000,4,5))) -> 3 | T15: =IF($A15="","",IF(OR(M15>=4,I15<=-8%),"防守",IF(OR(M15>=2,I15<=-5%),"警戒","正常"))) -> 正常 | U15: =IF($A15="","",IF(AND(L15>=3,M15<=2,T15<>"防守"),"是","否")) -> 否 | V15: =IF($A15="","",IF(AND(E15<N15,R15<S15,M15<=2,I15>-15%),"是","否")) -> 否 | W15: =IF($A15="","",IF(OR(M15>=3,I15<=-15%),"是","否")) -> 否 | X15: =IF($A15="","",IFERROR(maxifs(候选池!$AB:$AB,候选池!$A:$A,$A15),0)) -> 0 | Y15: =IF($A15="","",IF(OR(M15>=4,I15<=-8%),MAX(0,B15*60%-C15),IF(AND(ISNUMBER(AD15),B15>AD15),IF(B15<30000,0,IF(B15<100000,MAX(0,(B15-AD15)*0.2),MAX(0,(B15-AD15)*0.3))),0))) -> 0 | Z15: 当日盈亏: -82.22 | AA15: =IF($A15="","",IF($AA$2<>"",$AA$2,"")) -> 6683.54 | AB15: =IF($A15="","",IF(B15<30000,0.03,IF(B15<100000,0.02,0.015))) -> 0.03 | AC15: =IF($A15="","",IFERROR(DATEDIF($A$2,$A15,"m"),0)) -> 5 | AD15: =IF($A15="","",IF(OR(AA15="",AB15="",AC15=""),"",AA15*POWER(1+AB15,AC15))) -> 7748.0546 | AE15: =IF($A15="","",IF(OR(AD15="",AD15=0),"",B15/AD15-1)) -> 1.7387649 | AG15: =IF($A15="","",IF(B15<30000,"婴儿",IF(B15<100000,"成长","成熟"))) -> 婴儿 | AQ15: =IF($A15="","",B15-$AA$2-SUM($F$2:F17)) -> 10519.56 | AR15: =IF($A15="","",30000) -> 30000 | AS15: =IF($A15="","",AR15-B15) -> 8779.9 | AT15: =IF($A15="","",IFERROR(B15/AR15,0)) -> 0.70733667 | AU15: =IF($A15="","",IFERROR(B15*O15,0)) -> 7427.035 | AV15: =IF($A15="","",IFERROR(C15/B15,0)) -> 0.63035047 | AW15: =IF($A15="","",MAX(0,R15-S15)) -> 0 | AX15: =IF($A15="","",IF(AW15>0,"优先降持仓数",IF(C15<=0,"现金不足","允许评估"))) -> 允许评估 | AY15: =IF($A15="","",IF(B15<30000,"婴儿阶段: 优先活下来,禁止单票失控,限制持仓数,服务3W目标","幼儿阶段达成")) -> 婴儿阶段: 优先活下来,禁止单票失控,限制持仓数,服务3W目标
D16: =IF($A21="","",SUMIFS(持仓表!$J:$J,持仓表!$A:$A,$A21)) | E16: =IFERROR(D21/B21,0) -> 0 | G16: =IF($B21="","",MAX($B$2:B21)) | H16: =IFERROR((B21-F21)/F21,0) -> 0 | I16: =IFERROR((B21-G21)/G21,0) -> 0 | N16: =IF($B21="","",MIN(70%,IF($I21<=-15%,10%,IF($I21<=-10%,30%,IF($M21>=4,10%,IF($M21>=3,30%,IF($J21="强",IF($K21="A",70%,IF($K21="B",60%,40%)),IF($J21="中性",IF($K21="A",50%,IF($K21="B",40%,25%)),IF($K21="A",30%,IF($K21="B",20%,10%)))))))))) | O16: =IF($B21="","",IF(B21<30000,35%,IF(B21<50000,30%,IF(B21<100000,25%,20%)))) | P16: =IF($A21="","",COUNTIFS(持仓表!$A:$A,$A21,持仓表!$G:$G,">0")) | Q16: =IF($A21="","",COUNTIFS(持仓表!$A:$A,$A21,持仓表!$D:$D,"是",持仓表!$G:$G,">0")) | R16: =IF($A21="","",MAX(0,P21-Q21)) | S16: =IF($B21="","",IF(B21<50000,3,IF(B21<100000,4,5))) | T16: =IF($A21="","",IF(OR(M21>=4,I21<=-8%),"防守",IF(OR(M21>=2,I21<=-5%),"警戒","正常"))) | U16: =IF($A21="","",IF(AND(L21>=3,M21<=2,T21<>"防守"),"是","否")) | V16: =IF($A21="","",IF(AND(E21<N21,R21<S21,M21<=2,I21>-15%),"是","否")) | W16: =IF($A21="","",IF(OR(M21>=3,I21<=-15%),"是","否")) | X16: =IF($A21="","",IFERROR(maxifs(候选池!$AB:$AB,候选池!$A:$A,$A21),0)) | Y16: =IF($A21="","",IF(OR(M21>=4,I21<=-8%),MAX(0,B21*60%-C21),IF(AND(ISNUMBER(AD21),B21>AD21),IF(B21<30000,0,IF(B21<100000,MAX(0,(B21-AD21)*0.2),MAX(0,(B21-AD21)*0.3))),0))) | AA16: =IF($A21="","",IF($AA$2<>"",$AA$2,"")) | AB16: =IF($A21="","",IF(B21<30000,0.03,IF(B21<100000,0.02,0.015))) | AC16: =IF($A21="","",IFERROR(DATEDIF($A$2,$A21,"m"),0)) | AD16: =IF($A21="","",IF(OR(AA21="",AB21="",AC21=""),"",AA21*POWER(1+AB21,AC21))) | AE16: =IF($A21="","",IF(OR(AD21="",AD21=0),"",B21/AD21-1)) | AG16: =IF($A21="","",IF(B21<30000,"婴儿",IF(B21<100000,"成长","成熟"))) | AQ16: =IF($A21="","",B21-$AA$2-SUM($F$2:F21)) | AR16: =IF($A20="","",30000) | AS16: =IF($A20="","",AR20-B20) | AT16: =IF($A20="","",IFERROR(B20/AR20,0)) | AU16: =IF($A20="","",IFERROR(B20*O20,0)) | AV16: =IF($A20="","",IFERROR(C20/B20,0)) | AW16: =IF($A20="","",MAX(0,R20-S20)) | AX16: =IF($A20="","",IF(AW20>0,"优先降持仓数",IF(C20<=0,"现金不足","允许评估"))) | AY16: =IF($A20="","",IF(B20<30000,"婴儿阶段: 优先活下来,禁止单票失控,限制持仓数,服务3W目标","幼儿阶段达成"))
D17: =IF($A22="","",SUMIFS(持仓表!$J:$J,持仓表!$A:$A,$A22)) | E17: =IFERROR(D22/B22,0) -> 0 | G17: =IF($B22="","",MAX($B$2:B22)) | H17: =IFERROR((B22-F22)/F22,0) -> 0 | I17: =IFERROR((B22-G22)/G22,0) -> 0 | N17: =IF($B22="","",MIN(70%,IF($I22<=-15%,10%,IF($I22<=-10%,30%,IF($M22>=4,10%,IF($M22>=3,30%,IF($J22="强",IF($K22="A",70%,IF($K22="B",60%,40%)),IF($J22="中性",IF($K22="A",50%,IF($K22="B",40%,25%)),IF($K22="A",30%,IF($K22="B",20%,10%)))))))))) | O17: =IF($B22="","",IF(B22<30000,35%,IF(B22<50000,30%,IF(B22<100000,25%,20%)))) | P17: =IF($A22="","",COUNTIFS(持仓表!$A:$A,$A22,持仓表!$G:$G,">0")) | Q17: =IF($A22="","",COUNTIFS(持仓表!$A:$A,$A22,持仓表!$D:$D,"是",持仓表!$G:$G,">0")) | R17: =IF($A22="","",MAX(0,P22-Q22)) | S17: =IF($B22="","",IF(B22<50000,3,IF(B22<100000,4,5))) | T17: =IF($A22="","",IF(OR(M22>=4,I22<=-8%),"防守",IF(OR(M22>=2,I22<=-5%),"警戒","正常"))) | U17: =IF($A22="","",IF(AND(L22>=3,M22<=2,T22<>"防守"),"是","否")) | V17: =IF($A22="","",IF(AND(E22<N22,R22<S22,M22<=2,I22>-15%),"是","否")) | W17: =IF($A22="","",IF(OR(M22>=3,I22<=-15%),"是","否")) | X17: =IF($A22="","",IFERROR(maxifs(候选池!$AB:$AB,候选池!$A:$A,$A22),0)) | Y17: =IF($A22="","",IF(OR(M22>=4,I22<=-8%),MAX(0,B22*60%-C22),IF(AND(ISNUMBER(AD22),B22>AD22),IF(B22<30000,0,IF(B22<100000,MAX(0,(B22-AD22)*0.2),MAX(0,(B22-AD22)*0.3))),0))) | AA17: =IF($A22="","",IF($AA$2<>"",$AA$2,"")) | AB17: =IF($A22="","",IF(B22<30000,0.03,IF(B22<100000,0.02,0.015))) | AC17: =IF($A22="","",IFERROR(DATEDIF($A$2,$A22,"m"),0)) | AD17: =IF($A22="","",IF(OR(AA22="",AB22="",AC22=""),"",AA22*POWER(1+AB22,AC22))) | AE17: =IF($A22="","",IF(OR(AD22="",AD22=0),"",B22/AD22-1)) | AG17: =IF($A22="","",IF(B22<30000,"婴儿",IF(B22<100000,"成长","成熟"))) | AQ17: =IF($A22="","",B22-$AA$2-SUM($F$2:F22)) | AR17: =IF($A21="","",30000) | AS17: =IF($A21="","",AR21-B21) | AT17: =IF($A21="","",IFERROR(B21/AR21,0)) | AU17: =IF($A21="","",IFERROR(B21*O21,0)) | AV17: =IF($A21="","",IFERROR(C21/B21,0)) | AW17: =IF($A21="","",MAX(0,R21-S21)) | AX17: =IF($A21="","",IF(AW21>0,"优先降持仓数",IF(C21<=0,"现金不足","允许评估"))) | AY17: =IF($A21="","",IF(B21<30000,"婴儿阶段: 优先活下来,禁止单票失控,限制持仓数,服务3W目标","幼儿阶段达成"))
D18: =IF($A23="","",SUMIFS(持仓表!$J:$J,持仓表!$A:$A,$A23)) | E18: =IFERROR(D23/B23,0) -> 0 | G18: =IF($B23="","",MAX($B$2:B23)) | H18: =IFERROR((B23-F23)/F23,0) -> 0 | I18: =IFERROR((B23-G23)/G23,0) -> 0 | N18: =IF($B23="","",MIN(70%,IF($I23<=-15%,10%,IF($I23<=-10%,30%,IF($M23>=4,10%,IF($M23>=3,30%,IF($J23="强",IF($K23="A",70%,IF($K23="B",60%,40%)),IF($J23="中性",IF($K23="A",50%,IF($K23="B",40%,25%)),IF($K23="A",30%,IF($K23="B",20%,10%)))))))))) | O18: =IF($B23="","",IF(B23<30000,35%,IF(B23<50000,30%,IF(B23<100000,25%,20%)))) | P18: =IF($A23="","",COUNTIFS(持仓表!$A:$A,$A23,持仓表!$G:$G,">0")) | Q18: =IF($A23="","",COUNTIFS(持仓表!$A:$A,$A23,持仓表!$D:$D,"是",持仓表!$G:$G,">0")) | R18: =IF($A23="","",MAX(0,P23-Q23)) | S18: =IF($B23="","",IF(B23<50000,3,IF(B23<100000,4,5))) | T18: =IF($A23="","",IF(OR(M23>=4,I23<=-8%),"防守",IF(OR(M23>=2,I23<=-5%),"警戒","正常"))) | U18: =IF($A23="","",IF(AND(L23>=3,M23<=2,T23<>"防守"),"是","否")) | V18: =IF($A23="","",IF(AND(E23<N23,R23<S23,M23<=2,I23>-15%),"是","否")) | W18: =IF($A23="","",IF(OR(M23>=3,I23<=-15%),"是","否")) | X18: =IF($A23="","",IFERROR(maxifs(候选池!$AB:$AB,候选池!$A:$A,$A23),0)) | Y18: =IF($A23="","",IF(OR(M23>=4,I23<=-8%),MAX(0,B23*60%-C23),IF(AND(ISNUMBER(AD23),B23>AD23),IF(B23<30000,0,IF(B23<100000,MAX(0,(B23-AD23)*0.2),MAX(0,(B23-AD23)*0.3))),0))) | AA18: =IF($A23="","",IF($AA$2<>"",$AA$2,"")) | AB18: =IF($A23="","",IF(B23<30000,0.03,IF(B23<100000,0.02,0.015))) | AC18: =IF($A23="","",IFERROR(DATEDIF($A$2,$A23,"m"),0)) | AD18: =IF($A23="","",IF(OR(AA23="",AB23="",AC23=""),"",AA23*POWER(1+AB23,AC23))) | AE18: =IF($A23="","",IF(OR(AD23="",AD23=0),"",B23/AD23-1)) | AG18: =IF($A23="","",IF(B23<30000,"婴儿",IF(B23<100000,"成长","成熟"))) | AQ18: =IF($A23="","",B23-$AA$2-SUM($F$2:F23)) | AR18: =IF($A22="","",30000) | AS18: =IF($A22="","",AR22-B22) | AT18: =IF($A22="","",IFERROR(B22/AR22,0)) | AU18: =IF($A22="","",IFERROR(B22*O22,0)) | AV18: =IF($A22="","",IFERROR(C22/B22,0)) | AW18: =IF($A22="","",MAX(0,R22-S22)) | AX18: =IF($A22="","",IF(AW22>0,"优先降持仓数",IF(C22<=0,"现金不足","允许评估"))) | AY18: =IF($A22="","",IF(B22<30000,"婴儿阶段: 优先活下来,禁止单票失控,限制持仓数,服务3W目标","幼儿阶段达成"))
D19: =IF($A24="","",SUMIFS(持仓表!$J:$J,持仓表!$A:$A,$A24)) | E19: =IFERROR(D24/B24,0) -> 0 | G19: =IF($B24="","",MAX($B$2:B24)) | H19: =IFERROR((B24-F24)/F24,0) -> 0 | I19: =IFERROR((B24-G24)/G24,0) -> 0 | N19: =IF($B24="","",MIN(70%,IF($I24<=-15%,10%,IF($I24<=-10%,30%,IF($M24>=4,10%,IF($M24>=3,30%,IF($J24="强",IF($K24="A",70%,IF($K24="B",60%,40%)),IF($J24="中性",IF($K24="A",50%,IF($K24="B",40%,25%)),IF($K24="A",30%,IF($K24="B",20%,10%)))))))))) | O19: =IF($B24="","",IF(B24<30000,35%,IF(B24<50000,30%,IF(B24<100000,25%,20%)))) | P19: =IF($A24="","",COUNTIFS(持仓表!$A:$A,$A24,持仓表!$G:$G,">0")) | Q19: =IF($A24="","",COUNTIFS(持仓表!$A:$A,$A24,持仓表!$D:$D,"是",持仓表!$G:$G,">0")) | R19: =IF($A24="","",MAX(0,P24-Q24)) | S19: =IF($B24="","",IF(B24<50000,3,IF(B24<100000,4,5))) | T19: =IF($A24="","",IF(OR(M24>=4,I24<=-8%),"防守",IF(OR(M24>=2,I24<=-5%),"警戒","正常"))) | U19: =IF($A24="","",IF(AND(L24>=3,M24<=2,T24<>"防守"),"是","否")) | V19: =IF($A24="","",IF(AND(E24<N24,R24<S24,M24<=2,I24>-15%),"是","否")) | W19: =IF($A24="","",IF(OR(M24>=3,I24<=-15%),"是","否")) | X19: =IF($A24="","",IFERROR(maxifs(候选池!$AB:$AB,候选池!$A:$A,$A24),0)) | Y19: =IF($A24="","",IF(OR(M24>=4,I24<=-8%),MAX(0,B24*60%-C24),IF(AND(ISNUMBER(AD24),B24>AD24),IF(B24<30000,0,IF(B24<100000,MAX(0,(B24-AD24)*0.2),MAX(0,(B24-AD24)*0.3))),0))) | AA19: =IF($A24="","",IF($AA$2<>"",$AA$2,"")) | AB19: =IF($A24="","",IF(B24<30000,0.03,IF(B24<100000,0.02,0.015))) | AC19: =IF($A24="","",IFERROR(DATEDIF($A$2,$A24,"m"),0)) | AD19: =IF($A24="","",IF(OR(AA24="",AB24="",AC24=""),"",AA24*POWER(1+AB24,AC24))) | AE19: =IF($A24="","",IF(OR(AD24="",AD24=0),"",B24/AD24-1)) | AG19: =IF($A24="","",IF(B24<30000,"婴儿",IF(B24<100000,"成长","成熟"))) | AQ19: =IF($A24="","",B24-$AA$2-SUM($F$2:F24)) | AR19: =IF($A23="","",30000) | AS19: =IF($A23="","",AR23-B23) | AT19: =IF($A23="","",IFERROR(B23/AR23,0)) | AU19: =IF($A23="","",IFERROR(B23*O23,0)) | AV19: =IF($A23="","",IFERROR(C23/B23,0)) | AW19: =IF($A23="","",MAX(0,R23-S23)) | AX19: =IF($A23="","",IF(AW23>0,"优先降持仓数",IF(C23<=0,"现金不足","允许评估"))) | AY19: =IF($A23="","",IF(B23<30000,"婴儿阶段: 优先活下来,禁止单票失控,限制持仓数,服务3W目标","幼儿阶段达成"))
D20: =IF($A25="","",SUMIFS(持仓表!$J:$J,持仓表!$A:$A,$A25)) | E20: =IFERROR(D25/B25,0) -> 0 | G20: =IF($B25="","",MAX($B$2:B25)) | H20: =IFERROR((B25-F25)/F25,0) -> 0 | I20: =IFERROR((B25-G25)/G25,0) -> 0 | N20: =IF($B25="","",MIN(70%,IF($I25<=-15%,10%,IF($I25<=-10%,30%,IF($M25>=4,10%,IF($M25>=3,30%,IF($J25="强",IF($K25="A",70%,IF($K25="B",60%,40%)),IF($J25="中性",IF($K25="A",50%,IF($K25="B",40%,25%)),IF($K25="A",30%,IF($K25="B",20%,10%)))))))))) | O20: =IF($B25="","",IF(B25<30000,35%,IF(B25<50000,30%,IF(B25<100000,25%,20%)))) | P20: =IF($A25="","",COUNTIFS(持仓表!$A:$A,$A25,持仓表!$G:$G,">0")) | Q20: =IF($A25="","",COUNTIFS(持仓表!$A:$A,$A25,持仓表!$D:$D,"是",持仓表!$G:$G,">0")) | R20: =IF($A25="","",MAX(0,P25-Q25)) | S20: =IF($B25="","",IF(B25<50000,3,IF(B25<100000,4,5))) | T20: =IF($A25="","",IF(OR(M25>=4,I25<=-8%),"防守",IF(OR(M25>=2,I25<=-5%),"警戒","正常"))) | U20: =IF($A25="","",IF(AND(L25>=3,M25<=2,T25<>"防守"),"是","否")) | V20: =IF($A25="","",IF(AND(E25<N25,R25<S25,M25<=2,I25>-15%),"是","否")) | W20: =IF($A25="","",IF(OR(M25>=3,I25<=-15%),"是","否")) | X20: =IF($A25="","",IFERROR(maxifs(候选池!$AB:$AB,候选池!$A:$A,$A25),0)) | Y20: =IF($A25="","",IF(OR(M25>=4,I25<=-8%),MAX(0,B25*60%-C25),IF(AND(ISNUMBER(AD25),B25>AD25),IF(B25<30000,0,IF(B25<100000,MAX(0,(B25-AD25)*0.2),MAX(0,(B25-AD25)*0.3))),0))) | AA20: =IF($A25="","",IF($AA$2<>"",$AA$2,"")) | AB20: =IF($A25="","",IF(B25<30000,0.03,IF(B25<100000,0.02,0.015))) | AC20: =IF($A25="","",IFERROR(DATEDIF($A$2,$A25,"m"),0)) | AD20: =IF($A25="","",IF(OR(AA25="",AB25="",AC25=""),"",AA25*POWER(1+AB25,AC25))) | AE20: =IF($A25="","",IF(OR(AD25="",AD25=0),"",B25/AD25-1)) | AG20: =IF($A25="","",IF(B25<30000,"婴儿",IF(B25<100000,"成长","成熟"))) | AQ20: =IF($A25="","",B25-$AA$2-SUM($F$2:F25)) | AR20: =IF($A24="","",30000) | AS20: =IF($A24="","",AR24-B24) | AT20: =IF($A24="","",IFERROR(B24/AR24,0)) | AU20: =IF($A24="","",IFERROR(B24*O24,0)) | AV20: =IF($A24="","",IFERROR(C24/B24,0)) | AW20: =IF($A24="","",MAX(0,R24-S24)) | AX20: =IF($A24="","",IF(AW24>0,"优先降持仓数",IF(C24<=0,"现金不足","允许评估"))) | AY20: =IF($A24="","",IF(B24<30000,"婴儿阶段: 优先活下来,禁止单票失控,限制持仓数,服务3W目标","幼儿阶段达成"))
D21: =IF($A26="","",SUMIFS(持仓表!$J:$J,持仓表!$A:$A,$A26)) | E21: =IFERROR(D26/B26,0) -> 0 | G21: =IF($B26="","",MAX($B$2:B26)) | H21: =IFERROR((B26-F26)/F26,0) -> 0 | I21: =IFERROR((B26-G26)/G26,0) -> 0 | N21: =IF($B26="","",MIN(70%,IF($I26<=-15%,10%,IF($I26<=-10%,30%,IF($M26>=4,10%,IF($M26>=3,30%,IF($J26="强",IF($K26="A",70%,IF($K26="B",60%,40%)),IF($J26="中性",IF($K26="A",50%,IF($K26="B",40%,25%)),IF($K26="A",30%,IF($K26="B",20%,10%)))))))))) | O21: =IF($B26="","",IF(B26<30000,35%,IF(B26<50000,30%,IF(B26<100000,25%,20%)))) | P21: =IF($A26="","",COUNTIFS(持仓表!$A:$A,$A26,持仓表!$G:$G,">0")) | Q21: =IF($A26="","",COUNTIFS(持仓表!$A:$A,$A26,持仓表!$D:$D,"是",持仓表!$G:$G,">0")) | R21: =IF($A26="","",MAX(0,P26-Q26)) | S21: =IF($B26="","",IF(B26<50000,3,IF(B26<100000,4,5))) | T21: =IF($A26="","",IF(OR(M26>=4,I26<=-8%),"防守",IF(OR(M26>=2,I26<=-5%),"警戒","正常"))) | U21: =IF($A26="","",IF(AND(L26>=3,M26<=2,T26<>"防守"),"是","否")) | V21: =IF($A26="","",IF(AND(E26<N26,R26<S26,M26<=2,I26>-15%),"是","否")) | W21: =IF($A26="","",IF(OR(M26>=3,I26<=-15%),"是","否")) | X21: =IF($A26="","",IFERROR(maxifs(候选池!$AB:$AB,候选池!$A:$A,$A26),0)) | Y21: =IF($A26="","",IF(OR(M26>=4,I26<=-8%),MAX(0,B26*60%-C26),IF(AND(ISNUMBER(AD26),B26>AD26),IF(B26<30000,0,IF(B26<100000,MAX(0,(B26-AD26)*0.2),MAX(0,(B26-AD26)*0.3))),0))) | AA21: =IF($A26="","",IF($AA$2<>"",$AA$2,"")) | AB21: =IF($A26="","",IF(B26<30000,0.03,IF(B26<100000,0.02,0.015))) | AC21: =IF($A26="","",IFERROR(DATEDIF($A$2,$A26,"m"),0)) | AD21: =IF($A26="","",IF(OR(AA26="",AB26="",AC26=""),"",AA26*POWER(1+AB26,AC26))) | AE21: =IF($A26="","",IF(OR(AD26="",AD26=0),"",B26/AD26-1)) | AG21: =IF($A26="","",IF(B26<30000,"婴儿",IF(B26<100000,"成长","成熟"))) | AQ21: =IF($A26="","",B26-$AA$2-SUM($F$2:F26)) | AR21: =IF($A25="","",30000) | AS21: =IF($A25="","",AR25-B25) | AT21: =IF($A25="","",IFERROR(B25/AR25,0)) | AU21: =IF($A25="","",IFERROR(B25*O25,0)) | AV21: =IF($A25="","",IFERROR(C25/B25,0)) | AW21: =IF($A25="","",MAX(0,R25-S25)) | AX21: =IF($A25="","",IF(AW25>0,"优先降持仓数",IF(C25<=0,"现金不足","允许评估"))) | AY21: =IF($A25="","",IF(B25<30000,"婴儿阶段: 优先活下来,禁止单票失控,限制持仓数,服务3W目标","幼儿阶段达成"))
D22: =IF($A27="","",SUMIFS(持仓表!$J:$J,持仓表!$A:$A,$A27)) | E22: =IFERROR(D27/B27,0) -> 0 | G22: =IF($B27="","",MAX($B$2:B27)) | H22: =IFERROR((B27-F27)/F27,0) -> 0 | I22: =IFERROR((B27-G27)/G27,0) -> 0 | N22: =IF($B27="","",MIN(70%,IF($I27<=-15%,10%,IF($I27<=-10%,30%,IF($M27>=4,10%,IF($M27>=3,30%,IF($J27="强",IF($K27="A",70%,IF($K27="B",60%,40%)),IF($J27="中性",IF($K27="A",50%,IF($K27="B",40%,25%)),IF($K27="A",30%,IF($K27="B",20%,10%)))))))))) | O22: =IF($B27="","",IF(B27<30000,35%,IF(B27<50000,30%,IF(B27<100000,25%,20%)))) | P22: =IF($A27="","",COUNTIFS(持仓表!$A:$A,$A27,持仓表!$G:$G,">0")) | Q22: =IF($A27="","",COUNTIFS(持仓表!$A:$A,$A27,持仓表!$D:$D,"是",持仓表!$G:$G,">0")) | R22: =IF($A27="","",MAX(0,P27-Q27)) | S22: =IF($B27="","",IF(B27<50000,3,IF(B27<100000,4,5))) | T22: =IF($A27="","",IF(OR(M27>=4,I27<=-8%),"防守",IF(OR(M27>=2,I27<=-5%),"警戒","正常"))) | U22: =IF($A27="","",IF(AND(L27>=3,M27<=2,T27<>"防守"),"是","否")) | V22: =IF($A27="","",IF(AND(E27<N27,R27<S27,M27<=2,I27>-15%),"是","否")) | W22: =IF($A27="","",IF(OR(M27>=3,I27<=-15%),"是","否")) | X22: =IF($A27="","",IFERROR(maxifs(候选池!$AB:$AB,候选池!$A:$A,$A27),0)) | Y22: =IF($A27="","",IF(OR(M27>=4,I27<=-8%),MAX(0,B27*60%-C27),IF(AND(ISNUMBER(AD27),B27>AD27),IF(B27<30000,0,IF(B27<100000,MAX(0,(B27-AD27)*0.2),MAX(0,(B27-AD27)*0.3))),0))) | AA22: =IF($A27="","",IF($AA$2<>"",$AA$2,"")) | AB22: =IF($A27="","",IF(B27<30000,0.03,IF(B27<100000,0.02,0.015))) | AC22: =IF($A27="","",IFERROR(DATEDIF($A$2,$A27,"m"),0)) | AD22: =IF($A27="","",IF(OR(AA27="",AB27="",AC27=""),"",AA27*POWER(1+AB27,AC27))) | AE22: =IF($A27="","",IF(OR(AD27="",AD27=0),"",B27/AD27-1)) | AG22: =IF($A27="","",IF(B27<30000,"婴儿",IF(B27<100000,"成长","成熟"))) | AQ22: =IF($A27="","",B27-$AA$2-SUM($F$2:F27)) | AR22: =IF($A26="","",30000) | AS22: =IF($A26="","",AR26-B26) | AT22: =IF($A26="","",IFERROR(B26/AR26,0)) | AU22: =IF($A26="","",IFERROR(B26*O26,0)) | AV22: =IF($A26="","",IFERROR(C26/B26,0)) | AW22: =IF($A26="","",MAX(0,R26-S26)) | AX22: =IF($A26="","",IF(AW26>0,"优先降持仓数",IF(C26<=0,"现金不足","允许评估"))) | AY22: =IF($A26="","",IF(B26<30000,"婴儿阶段: 优先活下来,禁止单票失控,限制持仓数,服务3W目标","幼儿阶段达成"))
D23: =IF($A28="","",SUMIFS(持仓表!$J:$J,持仓表!$A:$A,$A28)) | E23: =IFERROR(D28/B28,0) -> 0 | G23: =IF($B28="","",MAX($B$2:B28)) | H23: =IFERROR((B28-F28)/F28,0) -> 0 | I23: =IFERROR((B28-G28)/G28,0) -> 0 | N23: =IF($B28="","",MIN(70%,IF($I28<=-15%,10%,IF($I28<=-10%,30%,IF($M28>=4,10%,IF($M28>=3,30%,IF($J28="强",IF($K28="A",70%,IF($K28="B",60%,40%)),IF($J28="中性",IF($K28="A",50%,IF($K28="B",40%,25%)),IF($K28="A",30%,IF($K28="B",20%,10%)))))))))) | O23: =IF($B28="","",IF(B28<30000,35%,IF(B28<50000,30%,IF(B28<100000,25%,20%)))) | P23: =IF($A28="","",COUNTIFS(持仓表!$A:$A,$A28,持仓表!$G:$G,">0")) | Q23: =IF($A28="","",COUNTIFS(持仓表!$A:$A,$A28,持仓表!$D:$D,"是",持仓表!$G:$G,">0")) | R23: =IF($A28="","",MAX(0,P28-Q28)) | S23: =IF($B28="","",IF(B28<50000,3,IF(B28<100000,4,5))) | T23: =IF($A28="","",IF(OR(M28>=4,I28<=-8%),"防守",IF(OR(M28>=2,I28<=-5%),"警戒","正常"))) | U23: =IF($A28="","",IF(AND(L28>=3,M28<=2,T28<>"防守"),"是","否")) | V23: =IF($A28="","",IF(AND(E28<N28,R28<S28,M28<=2,I28>-15%),"是","否")) | W23: =IF($A28="","",IF(OR(M28>=3,I28<=-15%),"是","否")) | X23: =IF($A28="","",IFERROR(maxifs(候选池!$AB:$AB,候选池!$A:$A,$A28),0)) | Y23: =IF($A28="","",IF(OR(M28>=4,I28<=-8%),MAX(0,B28*60%-C28),IF(AND(ISNUMBER(AD28),B28>AD28),IF(B28<30000,0,IF(B28<100000,MAX(0,(B28-AD28)*0.2),MAX(0,(B28-AD28)*0.3))),0))) | AA23: =IF($A28="","",IF($AA$2<>"",$AA$2,"")) | AB23: =IF($A28="","",IF(B28<30000,0.03,IF(B28<100000,0.02,0.015))) | AC23: =IF($A28="","",IFERROR(DATEDIF($A$2,$A28,"m"),0)) | AD23: =IF($A28="","",IF(OR(AA28="",AB28="",AC28=""),"",AA28*POWER(1+AB28,AC28))) | AE23: =IF($A28="","",IF(OR(AD28="",AD28=0),"",B28/AD28-1)) | AG23: =IF($A28="","",IF(B28<30000,"婴儿",IF(B28<100000,"成长","成熟"))) | AQ23: =IF($A28="","",B28-$AA$2-SUM($F$2:F28)) | AR23: =IF($A27="","",30000) | AS23: =IF($A27="","",AR27-B27) | AT23: =IF($A27="","",IFERROR(B27/AR27,0)) | AU23: =IF($A27="","",IFERROR(B27*O27,0)) | AV23: =IF($A27="","",IFERROR(C27/B27,0)) | AW23: =IF($A27="","",MAX(0,R27-S27)) | AX23: =IF($A27="","",IF(AW27>0,"优先降持仓数",IF(C27<=0,"现金不足","允许评估"))) | AY23: =IF($A27="","",IF(B27<30000,"婴儿阶段: 优先活下来,禁止单票失控,限制持仓数,服务3W目标","幼儿阶段达成"))
D24: =IF($A29="","",SUMIFS(持仓表!$J:$J,持仓表!$A:$A,$A29)) | E24: =IFERROR(D29/B29,0) -> 0 | G24: =IF($B29="","",MAX($B$2:B29)) | H24: =IFERROR((B29-F29)/F29,0) -> 0 | I24: =IFERROR((B29-G29)/G29,0) -> 0 | N24: =IF($B29="","",MIN(70%,IF($I29<=-15%,10%,IF($I29<=-10%,30%,IF($M29>=4,10%,IF($M29>=3,30%,IF($J29="强",IF($K29="A",70%,IF($K29="B",60%,40%)),IF($J29="中性",IF($K29="A",50%,IF($K29="B",40%,25%)),IF($K29="A",30%,IF($K29="B",20%,10%)))))))))) | O24: =IF($B29="","",IF(B29<30000,35%,IF(B29<50000,30%,IF(B29<100000,25%,20%)))) | P24: =IF($A29="","",COUNTIFS(持仓表!$A:$A,$A29,持仓表!$G:$G,">0")) | Q24: =IF($A29="","",COUNTIFS(持仓表!$A:$A,$A29,持仓表!$D:$D,"是",持仓表!$G:$G,">0")) | R24: =IF($A29="","",MAX(0,P29-Q29)) | S24: =IF($B29="","",IF(B29<50000,3,IF(B29<100000,4,5))) | T24: =IF($A29="","",IF(OR(M29>=4,I29<=-8%),"防守",IF(OR(M29>=2,I29<=-5%),"警戒","正常"))) | U24: =IF($A29="","",IF(AND(L29>=3,M29<=2,T29<>"防守"),"是","否")) | V24: =IF($A29="","",IF(AND(E29<N29,R29<S29,M29<=2,I29>-15%),"是","否")) | W24: =IF($A29="","",IF(OR(M29>=3,I29<=-15%),"是","否")) | X24: =IF($A29="","",IFERROR(maxifs(候选池!$AB:$AB,候选池!$A:$A,$A29),0)) | Y24: =IF($A29="","",IF(OR(M29>=4,I29<=-8%),MAX(0,B29*60%-C29),IF(AND(ISNUMBER(AD29),B29>AD29),IF(B29<30000,0,IF(B29<100000,MAX(0,(B29-AD29)*0.2),MAX(0,(B29-AD29)*0.3))),0))) | AA24: =IF($A29="","",IF($AA$2<>"",$AA$2,"")) | AB24: =IF($A29="","",IF(B29<30000,0.03,IF(B29<100000,0.02,0.015))) | AC24: =IF($A29="","",IFERROR(DATEDIF($A$2,$A29,"m"),0)) | AD24: =IF($A29="","",IF(OR(AA29="",AB29="",AC29=""),"",AA29*POWER(1+AB29,AC29))) | AE24: =IF($A29="","",IF(OR(AD29="",AD29=0),"",B29/AD29-1)) | AG24: =IF($A29="","",IF(B29<30000,"婴儿",IF(B29<100000,"成长","成熟"))) | AQ24: =IF($A29="","",B29-$AA$2-SUM($F$2:F29)) | AR24: =IF($A28="","",30000) | AS24: =IF($A28="","",AR28-B28) | AT24: =IF($A28="","",IFERROR(B28/AR28,0)) | AU24: =IF($A28="","",IFERROR(B28*O28,0)) | AV24: =IF($A28="","",IFERROR(C28/B28,0)) | AW24: =IF($A28="","",MAX(0,R28-S28)) | AX24: =IF($A28="","",IF(AW28>0,"优先降持仓数",IF(C28<=0,"现金不足","允许评估"))) | AY24: =IF($A28="","",IF(B28<30000,"婴儿阶段: 优先活下来,禁止单票失控,限制持仓数,服务3W目标","幼儿阶段达成"))
D25: =IF($A30="","",SUMIFS(持仓表!$J:$J,持仓表!$A:$A,$A30)) | E25: =IFERROR(D30/B30,0) -> 0 | G25: =IF($B30="","",MAX($B$2:B30)) | H25: =IFERROR((B30-F30)/F30,0) -> 0 | I25: =IFERROR((B30-G30)/G30,0) -> 0 | N25: =IF($B30="","",MIN(70%,IF($I30<=-15%,10%,IF($I30<=-10%,30%,IF($M30>=4,10%,IF($M30>=3,30%,IF($J30="强",IF($K30="A",70%,IF($K30="B",60%,40%)),IF($J30="中性",IF($K30="A",50%,IF($K30="B",40%,25%)),IF($K30="A",30%,IF($K30="B",20%,10%)))))))))) | O25: =IF($B30="","",IF(B30<30000,35%,IF(B30<50000,30%,IF(B30<100000,25%,20%)))) | P25: =IF($A30="","",COUNTIFS(持仓表!$A:$A,$A30,持仓表!$G:$G,">0")) | Q25: =IF($A30="","",COUNTIFS(持仓表!$A:$A,$A30,持仓表!$D:$D,"是",持仓表!$G:$G,">0")) | R25: =IF($A30="","",MAX(0,P30-Q30)) | S25: =IF($B30="","",IF(B30<50000,3,IF(B30<100000,4,5))) | T25: =IF($A30="","",IF(OR(M30>=4,I30<=-8%),"防守",IF(OR(M30>=2,I30<=-5%),"警戒","正常"))) | U25: =IF($A30="","",IF(AND(L30>=3,M30<=2,T30<>"防守"),"是","否")) | V25: =IF($A30="","",IF(AND(E30<N30,R30<S30,M30<=2,I30>-15%),"是","否")) | W25: =IF($A30="","",IF(OR(M30>=3,I30<=-15%),"是","否")) | X25: =IF($A30="","",IFERROR(maxifs(候选池!$AB:$AB,候选池!$A:$A,$A30),0)) | Y25: =IF($A30="","",IF(OR(M30>=4,I30<=-8%),MAX(0,B30*60%-C30),IF(AND(ISNUMBER(AD30),B30>AD30),IF(B30<30000,0,IF(B30<100000,MAX(0,(B30-AD30)*0.2),MAX(0,(B30-AD30)*0.3))),0))) | AA25: =IF($A30="","",IF($AA$2<>"",$AA$2,"")) | AB25: =IF($A30="","",IF(B30<30000,0.03,IF(B30<100000,0.02,0.015))) | AC25: =IF($A30="","",IFERROR(DATEDIF($A$2,$A30,"m"),0)) | AD25: =IF($A30="","",IF(OR(AA30="",AB30="",AC30=""),"",AA30*POWER(1+AB30,AC30))) | AE25: =IF($A30="","",IF(OR(AD30="",AD30=0),"",B30/AD30-1)) | AG25: =IF($A30="","",IF(B30<30000,"婴儿",IF(B30<100000,"成长","成熟"))) | AQ25: =IF($A30="","",B30-$AA$2-SUM($F$2:F30)) | AR25: =IF($A29="","",30000) | AS25: =IF($A29="","",AR29-B29) | AT25: =IF($A29="","",IFERROR(B29/AR29,0)) | AU25: =IF($A29="","",IFERROR(B29*O29,0)) | AV25: =IF($A29="","",IFERROR(C29/B29,0)) | AW25: =IF($A29="","",MAX(0,R29-S29)) | AX25: =IF($A29="","",IF(AW29>0,"优先降持仓数",IF(C29<=0,"现金不足","允许评估"))) | AY25: =IF($A29="","",IF(B29<30000,"婴儿阶段: 优先活下来,禁止单票失控,限制持仓数,服务3W目标","幼儿阶段达成"))
D26: =IF($A31="","",SUMIFS(持仓表!$J:$J,持仓表!$A:$A,$A31)) | E26: =IFERROR(D31/B31,0) -> 0 | G26: =IF($B31="","",MAX($B$2:B31)) | H26: =IFERROR((B31-F31)/F31,0) -> 0 | I26: =IFERROR((B31-G31)/G31,0) -> 0 | N26: =IF($B31="","",MIN(70%,IF($I31<=-15%,10%,IF($I31<=-10%,30%,IF($M31>=4,10%,IF($M31>=3,30%,IF($J31="强",IF($K31="A",70%,IF($K31="B",60%,40%)),IF($J31="中性",IF($K31="A",50%,IF($K31="B",40%,25%)),IF($K31="A",30%,IF($K31="B",20%,10%)))))))))) | O26: =IF($B31="","",IF(B31<30000,35%,IF(B31<50000,30%,IF(B31<100000,25%,20%)))) | P26: =IF($A31="","",COUNTIFS(持仓表!$A:$A,$A31,持仓表!$G:$G,">0")) | Q26: =IF($A31="","",COUNTIFS(持仓表!$A:$A,$A31,持仓表!$D:$D,"是",持仓表!$G:$G,">0")) | R26: =IF($A31="","",MAX(0,P31-Q31)) | S26: =IF($B31="","",IF(B31<50000,3,IF(B31<100000,4,5))) | T26: =IF($A31="","",IF(OR(M31>=4,I31<=-8%),"防守",IF(OR(M31>=2,I31<=-5%),"警戒","正常"))) | U26: =IF($A31="","",IF(AND(L31>=3,M31<=2,T31<>"防守"),"是","否")) | V26: =IF($A31="","",IF(AND(E31<N31,R31<S31,M31<=2,I31>-15%),"是","否")) | W26: =IF($A31="","",IF(OR(M31>=3,I31<=-15%),"是","否")) | X26: =IF($A31="","",IFERROR(maxifs(候选池!$AB:$AB,候选池!$A:$A,$A31),0)) | Y26: =IF($A31="","",IF(OR(M31>=4,I31<=-8%),MAX(0,B31*60%-C31),IF(AND(ISNUMBER(AD31),B31>AD31),IF(B31<30000,0,IF(B31<100000,MAX(0,(B31-AD31)*0.2),MAX(0,(B31-AD31)*0.3))),0))) | AA26: =IF($A31="","",IF($AA$2<>"",$AA$2,"")) | AB26: =IF($A31="","",IF(B31<30000,0.03,IF(B31<100000,0.02,0.015))) | AC26: =IF($A31="","",IFERROR(DATEDIF($A$2,$A31,"m"),0)) | AD26: =IF($A31="","",IF(OR(AA31="",AB31="",AC31=""),"",AA31*POWER(1+AB31,AC31))) | AE26: =IF($A31="","",IF(OR(AD31="",AD31=0),"",B31/AD31-1)) | AG26: =IF($A31="","",IF(B31<30000,"婴儿",IF(B31<100000,"成长","成熟"))) | AQ26: =IF($A31="","",B31-$AA$2-SUM($F$2:F31)) | AR26: =IF($A30="","",30000) | AS26: =IF($A30="","",AR30-B30) | AT26: =IF($A30="","",IFERROR(B30/AR30,0)) | AU26: =IF($A30="","",IFERROR(B30*O30,0)) | AV26: =IF($A30="","",IFERROR(C30/B30,0)) | AW26: =IF($A30="","",MAX(0,R30-S30)) | AX26: =IF($A30="","",IF(AW30>0,"优先降持仓数",IF(C30<=0,"现金不足","允许评估"))) | AY26: =IF($A30="","",IF(B30<30000,"婴儿阶段: 优先活下来,禁止单票失控,限制持仓数,服务3W目标","幼儿阶段达成"))
D27: =IF($A32="","",SUMIFS(持仓表!$J:$J,持仓表!$A:$A,$A32)) | E27: =IFERROR(D32/B32,0) -> 0 | G27: =IF($B32="","",MAX($B$2:B32)) | H27: =IFERROR((B32-F32)/F32,0) -> 0 | I27: =IFERROR((B32-G32)/G32,0) -> 0 | N27: =IF($B32="","",MIN(70%,IF($I32<=-15%,10%,IF($I32<=-10%,30%,IF($M32>=4,10%,IF($M32>=3,30%,IF($J32="强",IF($K32="A",70%,IF($K32="B",60%,40%)),IF($J32="中性",IF($K32="A",50%,IF($K32="B",40%,25%)),IF($K32="A",30%,IF($K32="B",20%,10%)))))))))) | O27: =IF($B32="","",IF(B32<30000,35%,IF(B32<50000,30%,IF(B32<100000,25%,20%)))) | P27: =IF($A32="","",COUNTIFS(持仓表!$A:$A,$A32,持仓表!$G:$G,">0")) | Q27: =IF($A32="","",COUNTIFS(持仓表!$A:$A,$A32,持仓表!$D:$D,"是",持仓表!$G:$G,">0")) | R27: =IF($A32="","",MAX(0,P32-Q32)) | S27: =IF($B32="","",IF(B32<50000,3,IF(B32<100000,4,5))) | T27: =IF($A32="","",IF(OR(M32>=4,I32<=-8%),"防守",IF(OR(M32>=2,I32<=-5%),"警戒","正常"))) | U27: =IF($A32="","",IF(AND(L32>=3,M32<=2,T32<>"防守"),"是","否")) | V27: =IF($A32="","",IF(AND(E32<N32,R32<S32,M32<=2,I32>-15%),"是","否")) | W27: =IF($A32="","",IF(OR(M32>=3,I32<=-15%),"是","否")) | X27: =IF($A32="","",IFERROR(maxifs(候选池!$AB:$AB,候选池!$A:$A,$A32),0)) | Y27: =IF($A32="","",IF(OR(M32>=4,I32<=-8%),MAX(0,B32*60%-C32),IF(AND(ISNUMBER(AD32),B32>AD32),IF(B32<30000,0,IF(B32<100000,MAX(0,(B32-AD32)*0.2),MAX(0,(B32-AD32)*0.3))),0))) | AA27: =IF($A32="","",IF($AA$2<>"",$AA$2,"")) | AB27: =IF($A32="","",IF(B32<30000,0.03,IF(B32<100000,0.02,0.015))) | AC27: =IF($A32="","",IFERROR(DATEDIF($A$2,$A32,"m"),0)) | AD27: =IF($A32="","",IF(OR(AA32="",AB32="",AC32=""),"",AA32*POWER(1+AB32,AC32))) | AE27: =IF($A32="","",IF(OR(AD32="",AD32=0),"",B32/AD32-1)) | AG27: =IF($A32="","",IF(B32<30000,"婴儿",IF(B32<100000,"成长","成熟"))) | AQ27: =IF($A32="","",B32-$AA$2-SUM($F$2:F32)) | AR27: =IF($A31="","",30000) | AS27: =IF($A31="","",AR31-B31) | AT27: =IF($A31="","",IFERROR(B31/AR31,0)) | AU27: =IF($A31="","",IFERROR(B31*O31,0)) | AV27: =IF($A31="","",IFERROR(C31/B31,0)) | AW27: =IF($A31="","",MAX(0,R31-S31)) | AX27: =IF($A31="","",IF(AW31>0,"优先降持仓数",IF(C31<=0,"现金不足","允许评估"))) | AY27: =IF($A31="","",IF(B31<30000,"婴儿阶段: 优先活下来,禁止单票失控,限制持仓数,服务3W目标","幼儿阶段达成"))
... D190: =IF($A195="","",SUMIFS(持仓表!$J:$J,持仓表!$A:$A,$A195)) | E190: =IFERROR(D195/B195,0) -> 0 | G190: =IF($B195="","",MAX($B$2:B195)) | H190: =IFERROR((B195-F195)/F195,0) -> 0 | I190: =IFERROR((B195-G195)/G195,0) -> 0 | N190: =IF($B195="","",MIN(70%,IF($I195<=-15%,10%,IF($I195<=-10%,30%,IF($M195>=4,10%,IF($M195>=3,30%,IF($J195="强",IF($K195="A",70%,IF($K195="B",60%,40%)),IF($J195="中性",IF($K195="A",50%,IF($K195="B",40%,25%)),IF($K195="A",30%,IF($K195="B",20%,10%)))))))))) | O190: =IF($B195="","",IF(B195<30000,35%,IF(B195<50000,30%,IF(B195<100000,25%,20%)))) | P190: =IF($A195="","",COUNTIFS(持仓表!$A:$A,$A195,持仓表!$G:$G,">0")) | Q190: =IF($A195="","",COUNTIFS(持仓表!$A:$A,$A195,持仓表!$D:$D,"是",持仓表!$G:$G,">0")) | R190: =IF($A195="","",MAX(0,P195-Q195)) | S190: =IF($B195="","",IF(B195<50000,3,IF(B195<100000,4,5))) | T190: =IF($A195="","",IF(OR(M195>=4,I195<=-8%),"防守",IF(OR(M195>=2,I195<=-5%),"警戒","正常"))) | U190: =IF($A195="","",IF(AND(L195>=3,M195<=2,T195<>"防守"),"是","否")) | V190: =IF($A195="","",IF(AND(E195<N195,R195<S195,M195<=2,I195>-15%),"是","否")) | W190: =IF($A195="","",IF(OR(M195>=3,I195<=-15%),"是","否")) | X190: =IF($A195="","",IFERROR(maxifs(候选池!$AB:$AB,候选池!$A:$A,$A195),0)) | Y190: =IF($A195="","",IF(OR(M195>=4,I195<=-8%),MAX(0,B195*60%-C195),IF(AND(ISNUMBER(AD195),B195>AD195),IF(B195<30000,0,IF(B195<100000,MAX(0,(B195-AD195)*0.2),MAX(0,(B195-AD195)*0.3))),0))) | AA190: =IF($A195="","",IF($AA$2<>"",$AA$2,"")) | AB190: =IF($A195="","",IF(B195<30000,0.03,IF(B195<100000,0.02,0.015))) | AC190: =IF($A195="","",IFERROR(DATEDIF($A$2,$A195,"m"),0)) | AD190: =IF($A195="","",IF(OR(AA195="",AB195="",AC195=""),"",AA195*POWER(1+AB195,AC195))) | AE190: =IF($A195="","",IF(OR(AD195="",AD195=0),"",B195/AD195-1)) | AG190: =IF($A195="","",IF(B195<30000,"婴儿",IF(B195<100000,"成长","成熟"))) | AQ190: =IF($A195="","",B195-$AA$2-SUM($F$2:F195)) | AR190: =IF($A194="","",30000) | AS190: =IF($A194="","",AR194-B194) | AT190: =IF($A194="","",IFERROR(B194/AR194,0)) | AU190: =IF($A194="","",IFERROR(B194*O194,0)) | AV190: =IF($A194="","",IFERROR(C194/B194,0)) | AW190: =IF($A194="","",MAX(0,R194-S194)) | AX190: =IF($A194="","",IF(AW194>0,"优先降持仓数",IF(C194<=0,"现金不足","允许评估"))) | AY190: =IF($A194="","",IF(B194<30000,"婴儿阶段: 优先活下来,禁止单票失控,限制持仓数,服务3W目标","幼儿阶段达成"))
D191: =IF($A196="","",SUMIFS(持仓表!$J:$J,持仓表!$A:$A,$A196)) -> 0 | E191: =IFERROR(D196/B196,0) -> 0 | G191: =IF($B196="","",MAX($B$2:B196)) -> 21370.8 | H191: =IFERROR((B196-F196)/F196,0) -> 0 | I191: =IFERROR((B196-G196)/G196,0) -> 0 | N191: =IF($B196="","",MIN(70%,IF($I196<=-15%,10%,IF($I196<=-10%,30%,IF($M196>=4,10%,IF($M196>=3,30%,IF($J196="强",IF($K196="A",70%,IF($K196="B",60%,40%)),IF($J196="中性",IF($K196="A",50%,IF($K196="B",40%,25%)),IF($K196="A",30%,IF($K196="B",20%,10%)))))))))) -> 0.1 | O191: =IF($B196="","",IF(B196<30000,35%,IF(B196<50000,30%,IF(B196<100000,25%,20%)))) -> 0.35 | P191: =IF($A196="","",COUNTIFS(持仓表!$A:$A,$A196,持仓表!$G:$G,">0")) -> 0 | Q191: =IF($A196="","",COUNTIFS(持仓表!$A:$A,$A196,持仓表!$D:$D,"是",持仓表!$G:$G,">0")) -> 0 | R191: =IF($A191="","",MAX(0,P191-Q191)) | S191: =IF($B196="","",IF(B196<50000,3,IF(B196<100000,4,5))) -> 3 | T191: =IF($A196="","",IF(OR(M196>=4,I196<=-8%),"防守",IF(OR(M196>=2,I196<=-5%),"警戒","正常"))) -> 正常 | U191: =IF($A196="","",IF(AND(L196>=3,M196<=2,T196<>"防守"),"是","否")) -> 否 | V191: =IF($A196="","",IF(AND(E196<N196,R196<S196,M196<=2,I196>-15%),"是","否")) -> 否 | W191: =IF($A196="","",IF(OR(M196>=3,I196<=-15%),"是","否")) -> 否 | X191: =IF($A196="","",IFERROR(maxifs(候选池!$AB:$AB,候选池!$A:$A,$A196),0)) -> 0 | Y191: =IF($A196="","",IF(OR(M196>=4,I196<=-8%),MAX(0,B196*60%-C196),IF(AND(ISNUMBER(AD196),B196>AD196),IF(B196<30000,0,IF(B196<100000,MAX(0,(B196-AD196)*0.2),MAX(0,(B196-AD196)*0.3))),0))) -> 0 | AA191: =IF($A196="","",IF($AA$2<>"",$AA$2,"")) -> 6683.54 | AB191: =IF($A196="","",IF(B196<30000,0.03,IF(B196<100000,0.02,0.015))) -> 0.03 | AC191: =IF($A196="","",IFERROR(DATEDIF($A$2,$A196,"m"),0)) -> 6 | AD191: =IF($A196="","",IF(OR(AA196="",AB196="",AC196=""),"",AA196*POWER(1+AB196,AC196))) | AE191: =IF($A196="","",IF(OR(AD196="",AD196=0),"",B196/AD196-1)) | AG191: =IF($A196="","",IF(B196<30000,"婴儿",IF(B196<100000,"成长","成熟"))) -> 婴儿 | AQ191: =IF($A196="","",B196-$AA$2-SUM($F$2:F196)) -> 10670.26 | AR191: =IF($A195="","",30000) | AS191: =IF($A195="","",AR195-B195) | AT191: =IF($A195="","",IFERROR(B195/AR195,0)) | AU191: =IF($A195="","",IFERROR(B195*O195,0)) | AV191: =IF($A195="","",IFERROR(C195/B195,0)) | AW191: =IF($A195="","",MAX(0,R195-S195)) | AX191: =IF($A195="","",IF(AW195>0,"优先降持仓数",IF(C195<=0,"现金不足","允许评估"))) | AY191: =IF($A195="","",IF(B195<30000,"婴儿阶段: 优先活下来,禁止单票失控,限制持仓数,服务3W目标","幼儿阶段达成"))
D192: =IF($A197="","",SUMIFS(持仓表!$J:$J,持仓表!$A:$A,$A197)) -> 0 | E192: =IFERROR(D197/B197,0) -> 0.3740618 | G192: =IF($B197="","",MAX($B$2:B197)) -> 21370.8 | H192: =IFERROR((B197-F197)/F197,0) -> 0 | I192: =IFERROR((B197-G197)/G197,0) -> 0 | N192: =IF($B197="","",MIN(70%,IF($I197<=-15%,10%,IF($I197<=-10%,30%,IF($M197>=4,10%,IF($M197>=3,30%,IF($J197="强",IF($K197="A",70%,IF($K197="B",60%,40%)),IF($J197="中性",IF($K197="A",50%,IF($K197="B",40%,25%)),IF($K197="A",30%,IF($K197="B",20%,10%)))))))))) -> 0.1 | O192: =IF($B197="","",IF(B197<30000,35%,IF(B197<50000,30%,IF(B197<100000,25%,20%)))) -> 0.35 | P192: =IF($A197="","",COUNTIFS(持仓表!$A:$A,$A197,持仓表!$G:$G,">0")) -> 0 | Q192: =IF($A197="","",COUNTIFS(持仓表!$A:$A,$A197,持仓表!$D:$D,"是",持仓表!$G:$G,">0")) -> 0 | R192: =IF($A197="","",MAX(0,P197-Q197)) -> 0 | S192: =IF($B197="","",IF(B197<50000,3,IF(B197<100000,4,5))) -> 3 | T192: =IF($A197="","",IF(OR(M197>=4,I197<=-8%),"防守",IF(OR(M197>=2,I197<=-5%),"警戒","正常"))) -> 正常 | U192: =IF($A197="","",IF(AND(L197>=3,M197<=2,T197<>"防守"),"是","否")) -> 否 | V192: =IF($A197="","",IF(AND(E197<N197,R197<S197,M197<=2,I197>-15%),"是","否")) -> 否 | W192: =IF($A197="","",IF(OR(M197>=3,I197<=-15%),"是","否")) -> 否 | X192: =IF($A197="","",IFERROR(maxifs(候选池!$AB:$AB,候选池!$A:$A,$A197),0)) -> 0 | Y192: =IF($A197="","",IF(OR(M197>=4,I197<=-8%),MAX(0,B197*60%-C197),IF(AND(ISNUMBER(AD197),B197>AD197),IF(B197<30000,0,IF(B197<100000,MAX(0,(B197-AD197)*0.2),MAX(0,(B197-AD197)*0.3))),0))) -> 0 | AA192: =IF($A197="","",IF($AA$2<>"",$AA$2,"")) -> 6683.54 | AB192: =IF($A197="","",IF(B197<30000,0.03,IF(B197<100000,0.02,0.015))) -> 0.03 | AC192: =IF($A197="","",IFERROR(DATEDIF($A$2,$A197,"m"),0)) -> 6 | AD192: =IF($A197="","",IF(OR(AA197="",AB197="",AC197=""),"",AA197*POWER(1+AB197,AC197))) | AE192: =IF($A197="","",IF(OR(AD197="",AD197=0),"",B197/AD197-1)) | AG192: =IF($A197="","",IF(B197<30000,"婴儿",IF(B197<100000,"成长","成熟"))) -> 婴儿 | AQ192: =IF($A197="","",B197-$AA$2-SUM($F$2:F197)) -> 10670.26 | AR192: =IF($A196="","",30000) -> 30000 | AS192: =IF($A192="","",AR192-B192) | AT192: =IF($A196="","",IFERROR(B196/AR196,0)) -> 0 | AU192: =IF($A196="","",IFERROR(B196*O196,0)) -> 0 | AV192: =IF($A196="","",IFERROR(C196/B196,0)) -> 0.6259382 | AW192: =IF($A192="","",MAX(0,R192-S192)) | AX192: =IF($A196="","",IF(AW196>0,"优先降持仓数",IF(C196<=0,"现金不足","允许评估"))) -> 优先降持仓数 | AY192: =IF($A196="","",IF(B196<30000,"婴儿阶段: 优先活下来,禁止单票失控,限制持仓数,服务3W目标","幼儿阶段达成")) -> 婴儿阶段: 优先活下来,禁止单票失控,限制持仓数,服务3W目标
D193: =IF($A198="","",SUMIFS(持仓表!$J:$J,持仓表!$A:$A,$A198)) | E193: =IFERROR(D198/B198,0) -> 0 | G193: =IF($B198="","",MAX($B$2:B198)) | H193: =IFERROR((B198-F198)/F198,0) -> 0 | I193: =IFERROR((B198-G198)/G198,0) -> 0 | N193: =IF($B198="","",MIN(70%,IF($I198<=-15%,10%,IF($I198<=-10%,30%,IF($M198>=4,10%,IF($M198>=3,30%,IF($J198="强",IF($K198="A",70%,IF($K198="B",60%,40%)),IF($J198="中性",IF($K198="A",50%,IF($K198="B",40%,25%)),IF($K198="A",30%,IF($K198="B",20%,10%)))))))))) | O193: =IF($B198="","",IF(B198<30000,35%,IF(B198<50000,30%,IF(B198<100000,25%,20%)))) | P193: =IF($A198="","",COUNTIFS(持仓表!$A:$A,$A198,持仓表!$G:$G,">0")) | Q193: =IF($A198="","",COUNTIFS(持仓表!$A:$A,$A198,持仓表!$D:$D,"是",持仓表!$G:$G,">0")) | R193: =IF($A198="","",MAX(0,P198-Q198)) | S193: =IF($B198="","",IF(B198<50000,3,IF(B198<100000,4,5))) | T193: =IF($A198="","",IF(OR(M198>=4,I198<=-8%),"防守",IF(OR(M198>=2,I198<=-5%),"警戒","正常"))) | U193: =IF($A198="","",IF(AND(L198>=3,M198<=2,T198<>"防守"),"是","否")) | V193: =IF($A198="","",IF(AND(E198<N198,R198<S198,M198<=2,I198>-15%),"是","否")) | W193: =IF($A198="","",IF(OR(M198>=3,I198<=-15%),"是","否")) | X193: =IF($A198="","",IFERROR(maxifs(候选池!$AB:$AB,候选池!$A:$A,$A198),0)) | Y193: =IF($A198="","",IF(OR(M198>=4,I198<=-8%),MAX(0,B198*60%-C198),IF(AND(ISNUMBER(AD198),B198>AD198),IF(B198<30000,0,IF(B198<100000,MAX(0,(B198-AD198)*0.2),MAX(0,(B198-AD198)*0.3))),0))) | AA193: =IF($A198="","",IF($AA$2<>"",$AA$2,"")) | AB193: =IF($A198="","",IF(B198<30000,0.03,IF(B198<100000,0.02,0.015))) | AC193: =IF($A198="","",IFERROR(DATEDIF($A$2,$A198,"m"),0)) | AD193: =IF($A198="","",IF(OR(AA198="",AB198="",AC198=""),"",AA198*POWER(1+AB198,AC198))) | AE193: =IF($A198="","",IF(OR(AD198="",AD198=0),"",B198/AD198-1)) | AG193: =IF($A198="","",IF(B198<30000,"婴儿",IF(B198<100000,"成长","成熟"))) | AQ193: =IF($A198="","",B198-$AA$2-SUM($F$2:F198)) | AR193: =IF($A197="","",30000) -> 30000 | AS193: =IF($A197="","",AR197-B197) -> -21370.8 | AT193: =IF($A197="","",IFERROR(B197/AR197,0)) -> 0 | AU193: =IF($A197="","",IFERROR(B197*O197,0)) -> 0 | AV193: =IF($A197="","",IFERROR(C197/B197,0)) -> 0.6259382 | AW193: =IF($A197="","",MAX(0,R197-S197)) -> 0 | AX193: =IF($A197="","",IF(AW197>0,"优先降持仓数",IF(C197<=0,"现金不足","允许评估"))) -> 允许评估 | AY193: =IF($A197="","",IF(B197<30000,"婴儿阶段: 优先活下来,禁止单票失控,限制持仓数,服务3W目标","幼儿阶段达成")) -> 婴儿阶段: 优先活下来,禁止单票失控,限制持仓数,服务3W目标
D194: =IF($A199="","",SUMIFS(持仓表!$J:$J,持仓表!$A:$A,$A199)) | E194: =IFERROR(D199/B199,0) -> 0 | G194: =IF($B199="","",MAX($B$2:B199)) | H194: =IFERROR((B199-F199)/F199,0) -> 0 | I194: =IFERROR((B199-G199)/G199,0) -> 0 | N194: =IF($B199="","",MIN(70%,IF($I199<=-15%,10%,IF($I199<=-10%,30%,IF($M199>=4,10%,IF($M199>=3,30%,IF($J199="强",IF($K199="A",70%,IF($K199="B",60%,40%)),IF($J199="中性",IF($K199="A",50%,IF($K199="B",40%,25%)),IF($K199="A",30%,IF($K199="B",20%,10%)))))))))) | O194: =IF($B199="","",IF(B199<30000,35%,IF(B199<50000,30%,IF(B199<100000,25%,20%)))) | P194: =IF($A199="","",COUNTIFS(持仓表!$A:$A,$A199,持仓表!$G:$G,">0")) | Q194: =IF($A199="","",COUNTIFS(持仓表!$A:$A,$A199,持仓表!$D:$D,"是",持仓表!$G:$G,">0")) | R194: =IF($A199="","",MAX(0,P199-Q199)) | S194: =IF($B199="","",IF(B199<50000,3,IF(B199<100000,4,5))) | T194: =IF($A199="","",IF(OR(M199>=4,I199<=-8%),"防守",IF(OR(M199>=2,I199<=-5%),"警戒","正常"))) | U194: =IF($A199="","",IF(AND(L199>=3,M199<=2,T199<>"防守"),"是","否")) | V194: =IF($A199="","",IF(AND(E199<N199,R199<S199,M199<=2,I199>-15%),"是","否")) | W194: =IF($A199="","",IF(OR(M199>=3,I199<=-15%),"是","否")) | X194: =IF($A199="","",IFERROR(maxifs(候选池!$AB:$AB,候选池!$A:$A,$A199),0)) | Y194: =IF($A199="","",IF(OR(M199>=4,I199<=-8%),MAX(0,B199*60%-C199),IF(AND(ISNUMBER(AD199),B199>AD199),IF(B199<30000,0,IF(B199<100000,MAX(0,(B199-AD199)*0.2),MAX(0,(B199-AD199)*0.3))),0))) | AA194: =IF($A199="","",IF($AA$2<>"",$AA$2,"")) | AB194: =IF($A199="","",IF(B199<30000,0.03,IF(B199<100000,0.02,0.015))) | AC194: =IF($A199="","",IFERROR(DATEDIF($A$2,$A199,"m"),0)) | AD194: =IF($A199="","",IF(OR(AA199="",AB199="",AC199=""),"",AA199*POWER(1+AB199,AC199))) | AE194: =IF($A199="","",IF(OR(AD199="",AD199=0),"",B199/AD199-1)) | AG194: =IF($A199="","",IF(B199<30000,"婴儿",IF(B199<100000,"成长","成熟"))) | AQ194: =IF($A199="","",B199-$AA$2-SUM($F$2:F199)) | AR194: =IF($A198="","",30000) | AS194: =IF($A198="","",AR198-B198) | AT194: =IF($A198="","",IFERROR(B198/AR198,0)) | AU194: =IF($A198="","",IFERROR(B198*O198,0)) | AV194: =IF($A198="","",IFERROR(C198/B198,0)) | AW194: =IF($A198="","",MAX(0,R198-S198)) | AX194: =IF($A198="","",IF(AW198>0,"优先降持仓数",IF(C198<=0,"现金不足","允许评估"))) | AY194: =IF($A198="","",IF(B198<30000,"婴儿阶段: 优先活下来,禁止单票失控,限制持仓数,服务3W目标","幼儿阶段达成"))
D195: =IF($A200="","",SUMIFS(持仓表!$J:$J,持仓表!$A:$A,$A200)) | E195: =IFERROR(D200/B200,0) -> 0 | G195: =IF($B200="","",MAX($B$2:B200)) | H195: =IFERROR((B200-F200)/F200,0) -> 0 | I195: =IFERROR((B200-G200)/G200,0) -> 0 | N195: =IF($B200="","",MIN(70%,IF($I200<=-15%,10%,IF($I200<=-10%,30%,IF($M200>=4,10%,IF($M200>=3,30%,IF($J200="强",IF($K200="A",70%,IF($K200="B",60%,40%)),IF($J200="中性",IF($K200="A",50%,IF($K200="B",40%,25%)),IF($K200="A",30%,IF($K200="B",20%,10%)))))))))) | O195: =IF($B200="","",IF(B200<30000,35%,IF(B200<50000,30%,IF(B200<100000,25%,20%)))) | P195: =IF($A200="","",COUNTIFS(持仓表!$A:$A,$A200,持仓表!$G:$G,">0")) | Q195: =IF($A200="","",COUNTIFS(持仓表!$A:$A,$A200,持仓表!$D:$D,"是",持仓表!$G:$G,">0")) | R195: =IF($A200="","",MAX(0,P200-Q200)) | S195: =IF($B200="","",IF(B200<50000,3,IF(B200<100000,4,5))) | T195: =IF($A200="","",IF(OR(M200>=4,I200<=-8%),"防守",IF(OR(M200>=2,I200<=-5%),"警戒","正常"))) | U195: =IF($A200="","",IF(AND(L200>=3,M200<=2,T200<>"防守"),"是","否")) | V195: =IF($A200="","",IF(AND(E200<N200,R200<S200,M200<=2,I200>-15%),"是","否")) | W195: =IF($A200="","",IF(OR(M200>=3,I200<=-15%),"是","否")) | X195: =IF($A200="","",IFERROR(maxifs(候选池!$AB:$AB,候选池!$A:$A,$A200),0)) | Y195: =IF($A200="","",IF(OR(M200>=4,I200<=-8%),MAX(0,B200*60%-C200),IF(AND(ISNUMBER(AD200),B200>AD200),IF(B200<30000,0,IF(B200<100000,MAX(0,(B200-AD200)*0.2),MAX(0,(B200-AD200)*0.3))),0))) | AA195: =IF($A200="","",IF($AA$2<>"",$AA$2,"")) | AB195: =IF($A200="","",IF(B200<30000,0.03,IF(B200<100000,0.02,0.015))) | AC195: =IF($A200="","",IFERROR(DATEDIF($A$2,$A200,"m"),0)) | AD195: =IF($A200="","",IF(OR(AA200="",AB200="",AC200=""),"",AA200*POWER(1+AB200,AC200))) | AE195: =IF($A200="","",IF(OR(AD200="",AD200=0),"",B200/AD200-1)) | AG195: =IF($A200="","",IF(B200<30000,"婴儿",IF(B200<100000,"成长","成熟"))) | AQ195: =IF($A200="","",B200-$AA$2-SUM($F$2:F200)) | AR195: =IF($A199="","",30000) | AS195: =IF($A199="","",AR199-B199) | AT195: =IF($A199="","",IFERROR(B199/AR199,0)) | AU195: =IF($A199="","",IFERROR(B199*O199,0)) | AV195: =IF($A199="","",IFERROR(C199/B199,0)) | AW195: =IF($A199="","",MAX(0,R199-S199)) | AX195: =IF($A199="","",IF(AW199>0,"优先降持仓数",IF(C199<=0,"现金不足","允许评估"))) | AY195: =IF($A199="","",IF(B199<30000,"婴儿阶段: 优先活下来,禁止单票失控,限制持仓数,服务3W目标","幼儿阶段达成"))
A196: 46234.652 | B196: 21370.8 | C196: 13376.8 | D196: =IF($A201="","",SUMIFS(持仓表!$J:$J,持仓表!$A:$A,$A201)) | E196: 0.374 | G196: =IF($B201="","",MAX($B$2:B201)) | H196: =IFERROR((B196-$AA$2-SUM($F$2:F196))/($AA$2+SUM($F$2:F196)),0) -> 0.99717024 | I196: =IFERROR((B201-G201)/G201,0) -> 0 | N196: =IF($B201="","",MIN(70%,IF($I201<=-15%,10%,IF($I201<=-10%,30%,IF($M201>=4,10%,IF($M201>=3,30%,IF($J201="强",IF($K201="A",70%,IF($K201="B",60%,40%)),IF($J201="中性",IF($K201="A",50%,IF($K201="B",40%,25%)),IF($K201="A",30%,IF($K201="B",20%,10%)))))))))) | O196: =IF($B201="","",IF(B201<30000,35%,IF(B201<50000,30%,IF(B201<100000,25%,20%)))) | P196: =IF($A201="","",COUNTIFS(持仓表!$A:$A,$A201,持仓表!$G:$G,">0")) | Q196: =IF($A201="","",COUNTIFS(持仓表!$A:$A,$A201,持仓表!$D:$D,"是",持仓表!$G:$G,">0")) | R196: =IF($A201="","",MAX(0,P201-Q201)) | S196: =IF($B201="","",IF(B201<50000,3,IF(B201<100000,4,5))) | T196: 正常 | U196: =IF($A201="","",IF(AND(L201>=3,M201<=2,T201<>"防守"),"是","否")) | V196: 是 | W196: =IF($A201="","",IF(OR(M201>=3,I201<=-15%),"是","否")) | X196: =IF($A201="","",IFERROR(maxifs(候选池!$AB:$AB,候选池!$A:$A,$A201),0)) | Y196: =IF($A201="","",IF(OR(M201>=4,I201<=-8%),MAX(0,B201*60%-C201),IF(AND(ISNUMBER(AD201),B201>AD201),IF(B201<30000,0,IF(B201<100000,MAX(0,(B201-AD201)*0.2),MAX(0,(B201-AD201)*0.3))),0))) | AA196: =IF($A201="","",IF($AA$2<>"",$AA$2,"")) | AB196: =IF($A201="","",IF(B201<30000,0.03,IF(B201<100000,0.02,0.015))) | AC196: =IF($A201="","",IFERROR(DATEDIF($A$2,$A201,"m"),0)) | AD196: =IF($A201="","",IF(OR(AA201="",AB201="",AC201=""),"",AA201*POWER(1+AB201,AC201))) | AE196: =IF($A201="","",IF(OR(AD201="",AD201=0),"",B201/AD201-1)) | AG196: =IF($A201="","",IF(B201<30000,"婴儿",IF(B201<100000,"成长","成熟"))) | AQ196: =IF($A201="","",B201-$AA$2-SUM($F$2:F201)) | AR196: =IF($A200="","",30000) | AS196: =IF($A200="","",AR200-B200) | AT196: =IF($A200="","",IFERROR(B200/AR200,0)) | AU196: =IF($A200="","",IFERROR(B200*O200,0)) | AV196: =IF($A200="","",IFERROR(C200/B200,0)) | AW196: =IF($A200="","",MAX(0,R200-S200)) | AX196: =IF($A200="","",IF(AW200>0,"优先降持仓数",IF(C200<=0,"现金不足","允许评估"))) | AY196: =IF($A200="","",IF(B200<30000,"婴儿阶段: 优先活下来,禁止单票失控,限制持仓数,服务3W目标","幼儿阶段达成"))
A197: 46236.306 | B197: 21370.8 | C197: 13376.8 | D197: 7994 | E197: 0.374 | H197: =IFERROR((B197-$AA$2-SUM($F$2:F197))/($AA$2+SUM($F$2:F197)),0) -> 0.99717024

Sheet 持仓表
A1: 日期 | B1: 股票名称 | C1: 代码 | D1: 是否WAIVED | E1: WAIVED基准价 | F1: 买入日期 | G1: 持股数量 Shares | H1: 持仓均价 EntryPrice | I1: 当前价 Close | J1: 持仓市值 | K1: 成本金额 | L1: 浮盈亏金额 | M1: 浮盈亏比 ProfitRatio | N1: 持仓占比 PositionRatio | O1: 买点低点 BuyPointLow | P1: 止损价 StopPrice | Q1: 是否破止损 | R1: ratio | S1: DL_P | T1: valid | U1: SignalType | V1: SignalInvalid | W1: RiskWatch | X1: 是否确认一卖 | Y1: 是否超单股上限 | Z1: 盈亏状态 | AA1: 单股上限金额 | AB1: 单股剩余额度 | AC1: 可加仓股数 | AD1: 是否超单股上限 | AE1: 距止损幅度 | AF1: 当前风险金额 | AG1: 候选池核心 | AH1: 加仓资格 | AI1: T+1锁定
A2: 46227 | B2: 东风股份 | C2: 600006 | D2: 是 | E2: 8.711 | F2: 5.67 | G2: 100 | H2: 8.711 | I2: 5.4 | J2: =IF(A2="","",G2*I2) -> 540 | K2: =IF(A2="","",G2*H2) -> 871.1 | L2: =IF(OR(A2="",J2="",K2=""),"",J2-K2) -> -331.1 | M2: =IFERROR((I2-H2)/H2,0) -> -0.38009413 | N2: =IFERROR(J2/INDEX(账户总表!$B:$B,MATCH($A2,账户总表!$A:$A,0)),0) -> 0.025908824 | P2: 5.2234 | Q2: =IF($A2="","",IF(AND(I2>0,P2>0,I2<=P2),"是","否")) -> 否 | V2: =IF($A2="","",IF(OR(AND(O2>0,I2<O2),AND(T2="False",S2<0.8)),"是","否")) -> 否 | W2: 是 | X2: =IF($A2="","",IF(AND(R2<60%,S2>0.8,T2="True",U2="一卖"),"是","否")) -> 否 | Y2: =IF($A2="","",IF(D2="是","否",IF(N2>LOOKUP(2,1/(账户总表!$A:$A<>""),账户总表!$O:$O),"是","否"))) -> 否 | Z2: =IF($A2="","",IF(M2>=0,"盈利","亏损")) -> 亏损 | AA2: =IF($A2="","",IFERROR(INDEX(账户总表!$B:$B,MATCH($A2,账户总表!$A:$A,0))*INDEX(账户总表!$O:$O,MATCH($A2,账户总表!$A:$A,0)),0)) -> 7294.812 | AB2: =IF($A2="","",IFERROR(MAX(0,AA2-J2),0)) -> 6754.812 | AC2: =IF($A2="","",IF(I2>0,IFERROR(FLOOR(AB2/I2,100),0),0)) -> 1200 | AD2: =IF($A2="","",IF(N2>LOOKUP(2,1/(账户总表!$A:$A<>""),账户总表!$O:$O),"超限","合规")) -> 超限 | AE2: =IF($A2="","",IFERROR((I2-P2)/I2,0)) -> 0.032703704 | AF2: =IF($A2="","",IFERROR(MAX(0,(I2-P2)*G2),0)) -> 17.66 | AG2: =IF($A2="","",IF(COUNTIFS(候选池!$C$2:$C$201,C2,候选池!$K$2:$K$201,"核心池")>0,"核心池","否")) -> 否 | AH2: =IF(A2="","",IF(OR(J2="",K2="",K2=0),"",IF((J2-K2)/K2<0.05,"不可加仓(无浮盈护垫)",IF(N2>0.6,"不可加仓(超三买上限)",IF(N2>0.5,"可加仓(三买区,上限60%)",IF(N2>0.35,"可加仓(二买区,上限50%)","可加仓(一买区,上限35%)")))))) -> 不可加仓(无浮盈护垫)
A3: 46227 | B3: 隆基绿能 | C3: 601012 | D3: 否 | F3: 2026-07-24 | G3: 0 | H3: 11.107 | I3: 12.42 | J3: =IF(A3="","",G3*I3) -> 0 | K3: =IF(A3="","",G3*H3) -> 0 | L3: =IF(OR(A3="",J3="",K3=""),"",J3-K3) -> 0 | M3: =IFERROR((I3-H3)/H3,0) -> 0.11821374 | N3: =IFERROR(J3/INDEX(账户总表!$B:$B,MATCH($A3,账户总表!$A:$A,0)),0) -> 0 | P3: 10.55165 | Q3: =IF($A3="","",IF(AND(I3>0,P3>0,I3<=P3),"是","否")) -> 否 | V3: =IF($A3="","",IF(OR(AND(O3>0,I3<O3),AND(T3="False",S3<0.8)),"是","否")) -> 否 | W3: 否 | X3: =IF($A3="","",IF(AND(R3<60%,S3>0.8,T3="True",U3="一卖"),"是","否")) -> 否 | Y3: =IF($A3="","",IF(D3="是","否",IF(N3>LOOKUP(2,1/(账户总表!$A:$A<>""),账户总表!$O:$O),"是","否"))) -> 否 | Z3: =IF($A3="","",IF(M3>=0,"盈利","亏损")) -> 盈利 | AA3: =IF($A3="","",IFERROR(INDEX(账户总表!$B:$B,MATCH($A3,账户总表!$A:$A,0))*INDEX(账户总表!$O:$O,MATCH($A3,账户总表!$A:$A,0)),0)) -> 7294.812 | AB3: =IF($A3="","",IFERROR(MAX(0,AA3-J3),0)) -> 7294.812 | AC3: =IF($A3="","",IF(I3>0,IFERROR(FLOOR(AB3/I3,100),0),0)) -> 500 | AD3: =IF($A3="","",IF(N3>LOOKUP(2,1/(账户总表!$A:$A<>""),账户总表!$O:$O),"超限","合规")) -> 合规 | AE3: =IF($A3="","",IFERROR((I3-P3)/I3,0)) -> 0.15043076 | AF3: =IF($A3="","",IFERROR(MAX(0,(I3-P3)*G3),0)) -> 0 | AG3: =IF($A3="","",IF(COUNTIFS(候选池!$C$2:$C$201,C3,候选池!$K$2:$K$201,"核心池")>0,"核心池","否")) -> 否 | AH3: =IF(A3="","",IF(OR(J3="",K3="",K3=0),"",IF((J3-K3)/K3<0.05,"不可加仓(无浮盈护垫)",IF(N3>0.6,"不可加仓(超三买上限)",IF(N3>0.5,"可加仓(三买区,上限60%)",IF(N3>0.35,"可加仓(二买区,上限50%)","可加仓(一买区,上限35%)"))))))
A4: 46227 | B4: 创力集团 | C4: 603012 | D4: 否 | F4: 2026-07-24 | G4: 0 | H4: 8.021 | I4: 8.03 | J4: =IF(A4="","",G4*I4) -> 0 | K4: =IF(A4="","",G4*H4) -> 0 | L4: =IF(OR(A4="",J4="",K4=""),"",J4-K4) -> 0 | M4: =IFERROR((I4-H4)/H4,0) -> 0.0011220546 | N4: =IFERROR(J4/INDEX(账户总表!$B:$B,MATCH($A4,账户总表!$A:$A,0)),0) -> 0 | P4: 7.61995 | Q4: =IF($A4="","",IF(AND(I4>0,P4>0,I4<=P4),"是","否")) -> 否 | V4: =IF($A4="","",IF(OR(AND(O4>0,I4<O4),AND(T4="False",S4<0.8)),"是","否")) -> 否 | W4: 是 | X4: =IF($A4="","",IF(AND(R4<60%,S4>0.8,T4="True",U4="一卖"),"是","否")) -> 否 | Y4: =IF($A4="","",IF(D4="是","否",IF(N4>LOOKUP(2,1/(账户总表!$A:$A<>""),账户总表!$O:$O),"是","否"))) -> 否 | Z4: =IF($A4="","",IF(M4>=0,"盈利","亏损")) -> 盈利 | AA4: =IF($A4="","",IFERROR(INDEX(账户总表!$B:$B,MATCH($A4,账户总表!$A:$A,0))*INDEX(账户总表!$O:$O,MATCH($A4,账户总表!$A:$A,0)),0)) -> 7294.812 | AB4: =IF($A4="","",IFERROR(MAX(0,AA4-J4),0)) -> 7294.812 | AC4: =IF($A4="","",IF(I4>0,IFERROR(FLOOR(AB4/I4,100),0),0)) -> 900 | AD4: =IF($A4="","",IF(N4>LOOKUP(2,1/(账户总表!$A:$A<>""),账户总表!$O:$O),"超限","合规")) -> 合规 | AE4: =IF($A4="","",IFERROR((I4-P4)/I4,0)) -> 0.051064757 | AF4: =IF($A4="","",IFERROR(MAX(0,(I4-P4)*G4),0)) -> 0 | AG4: =IF($A4="","",IF(COUNTIFS(候选池!$C$2:$C$201,C4,候选池!$K$2:$K$201,"核心池")>0,"核心池","否")) -> 否 | AH4: =IF(A4="","",IF(OR(J4="",K4="",K4=0),"",IF((J4-K4)/K4<0.05,"不可加仓(无浮盈护垫)",IF(N4>0.6,"不可加仓(超三买上限)",IF(N4>0.5,"可加仓(三买区,上限60%)",IF(N4>0.35,"可加仓(二买区,上限50%)","可加仓(一买区,上限35%)"))))))
A5: 46227 | B5: 新五丰 | C5: 600975 | D5: 否 | F5: 2026-07-24 | G5: 0 | H5: 4.804 | I5: 4.73 | J5: =IF(A5="","",G5*I5) -> 0 | K5: =IF(A5="","",G5*H5) -> 0 | L5: =IF(OR(A5="",J5="",K5=""),"",J5-K5) -> 0 | M5: =IFERROR((I5-H5)/H5,0) -> -0.01540383 | N5: =IFERROR(J5/INDEX(账户总表!$B:$B,MATCH($A5,账户总表!$A:$A,0)),0) -> 0 | P5: 4.5638 | Q5: =IF($A5="","",IF(AND(I5>0,P5>0,I5<=P5),"是","否")) -> 否 | V5: =IF($A5="","",IF(OR(AND(O5>0,I5<O5),AND(T5="False",S5<0.8)),"是","否")) -> 否 | W5: 是 | X5: =IF($A5="","",IF(AND(R5<60%,S5>0.8,T5="True",U5="一卖"),"是","否")) -> 否 | Y5: =IF($A5="","",IF(D5="是","否",IF(N5>LOOKUP(2,1/(账户总表!$A:$A<>""),账户总表!$O:$O),"是","否"))) -> 否 | Z5: =IF($A5="","",IF(M5>=0,"盈利","亏损")) -> 亏损 | AA5: =IF($A5="","",IFERROR(INDEX(账户总表!$B:$B,MATCH($A5,账户总表!$A:$A,0))*INDEX(账户总表!$O:$O,MATCH($A5,账户总表!$A:$A,0)),0)) -> 7294.812 | AB5: =IF($A5="","",IFERROR(MAX(0,AA5-J5),0)) -> 7294.812 | AC5: =IF($A5="","",IF(I5>0,IFERROR(FLOOR(AB5/I5,100),0),0)) -> 1500 | AD5: =IF($A5="","",IF(N5>LOOKUP(2,1/(账户总表!$A:$A<>""),账户总表!$O:$O),"超限","合规")) -> 合规 | AE5: =IF($A5="","",IFERROR((I5-P5)/I5,0)) -> 0.035137421 | AF5: =IF($A5="","",IFERROR(MAX(0,(I5-P5)*G5),0)) -> 0 | AG5: =IF($A5="","",IF(COUNTIFS(候选池!$C$2:$C$201,C5,候选池!$K$2:$K$201,"核心池")>0,"核心池","否")) -> 否 | AH5: =IF(A5="","",IF(OR(J5="",K5="",K5=0),"",IF((J5-K5)/K5<0.05,"不可加仓(无浮盈护垫)",IF(N5>0.6,"不可加仓(超三买上限)",IF(N5>0.5,"可加仓(三买区,上限60%)",IF(N5>0.35,"可加仓(二买区,上限50%)","可加仓(一买区,上限35%)"))))))
A6: 46227 | B6: 方盛制药 | C6: 603998 | D6: 否 | F6: 2026-07-24 | G6: 0 | H6: 9.271 | I6: 8.96 | J6: =IF(A6="","",G6*I6) -> 0 | K6: =IF(A6="","",G6*H6) -> 0 | L6: =IF(OR(A6="",J6="",K6=""),"",J6-K6) -> 0 | M6: =IFERROR((I6-H6)/H6,0) -> -0.033545464 | N6: =IFERROR(J6/INDEX(账户总表!$B:$B,MATCH($A6,账户总表!$A:$A,0)),0) -> 0 | P6: 8.80745 | Q6: =IF($A6="","",IF(AND(I6>0,P6>0,I6<=P6),"是","否")) -> 否 | V6: =IF($A6="","",IF(OR(AND(O6>0,I6<O6),AND(T6="False",S6<0.8)),"是","否")) -> 否 | W6: 是 | X6: =IF($A6="","",IF(AND(R6<60%,S6>0.8,T6="True",U6="一卖"),"是","否")) -> 否 | Y6: =IF($A6="","",IF(D6="是","否",IF(N6>LOOKUP(2,1/(账户总表!$A:$A<>""),账户总表!$O:$O),"是","否"))) -> 否 | Z6: =IF($A6="","",IF(M6>=0,"盈利","亏损")) -> 亏损 | AA6: =IF($A6="","",IFERROR(INDEX(账户总表!$B:$B,MATCH($A6,账户总表!$A:$A,0))*INDEX(账户总表!$O:$O,MATCH($A6,账户总表!$A:$A,0)),0)) -> 7294.812 | AB6: =IF($A6="","",IFERROR(MAX(0,AA6-J6),0)) -> 7294.812 | AC6: =IF($A6="","",IF(I6>0,IFERROR(FLOOR(AB6/I6,100),0),0)) -> 800 | AD6: =IF($A6="","",IF(N6>LOOKUP(2,1/(账户总表!$A:$A<>""),账户总表!$O:$O),"超限","合规")) -> 合规 | AE6: =IF($A6="","",IFERROR((I6-P6)/I6,0)) -> 0.01702567 | AF6: =IF($A6="","",IFERROR(MAX(0,(I6-P6)*G6),0)) -> 0 | AG6: =IF($A6="","",IF(COUNTIFS(候选池!$C$2:$C$201,C6,候选池!$K$2:$K$201,"核心池")>0,"核心池","否")) -> 否 | AH6: =IF(A6="","",IF(OR(J6="",K6="",K6=0),"",IF((J6-K6)/K6<0.05,"不可加仓(无浮盈护垫)",IF(N6>0.6,"不可加仓(超三买上限)",IF(N6>0.5,"可加仓(三买区,上限60%)",IF(N6>0.35,"可加仓(二买区,上限50%)","可加仓(一买区,上限35%)"))))))
A7: 46227 | B7: 建研院 | C7: 603183 | D7: 否 | F7: 2026-07-24 | G7: 0 | H7: 3.966 | I7: 4.02 | J7: =IF(A7="","",G7*I7) -> 0 | K7: =IF(A7="","",G7*H7) -> 0 | L7: =IF(OR(A7="",J7="",K7=""),"",J7-K7) -> 0 | M7: =IFERROR((I7-H7)/H7,0) -> 0.013615734 | N7: =IFERROR(J7/INDEX(账户总表!$B:$B,MATCH($A7,账户总表!$A:$A,0)),0) -> 0 | P7: 3.7677 | Q7: =IF($A7="","",IF(AND(I7>0,P7>0,I7<=P7),"是","否")) -> 否 | V7: =IF($A7="","",IF(OR(AND(O7>0,I7<O7),AND(T7="False",S7<0.8)),"是","否")) -> 否 | W7: 是 | X7: =IF($A7="","",IF(AND(R7<60%,S7>0.8,T7="True",U7="一卖"),"是","否")) -> 否 | Y7: =IF($A7="","",IF(D7="是","否",IF(N7>LOOKUP(2,1/(账户总表!$A:$A<>""),账户总表!$O:$O),"是","否"))) -> 否 | Z7: =IF($A7="","",IF(M7>=0,"盈利","亏损")) -> 盈利 | AA7: =IF($A7="","",IFERROR(INDEX(账户总表!$B:$B,MATCH($A7,账户总表!$A:$A,0))*INDEX(账户总表!$O:$O,MATCH($A7,账户总表!$A:$A,0)),0)) -> 7294.812 | AB7: =IF($A7="","",IFERROR(MAX(0,AA7-J7),0)) -> 7294.812 | AC7: =IF($A7="","",IF(I7>0,IFERROR(FLOOR(AB7/I7,100),0),0)) -> 1800 | AD7: =IF($A7="","",IF(N7>LOOKUP(2,1/(账户总表!$A:$A<>""),账户总表!$O:$O),"超限","合规")) -> 合规 | AE7: =IF($A7="","",IFERROR((I7-P7)/I7,0)) -> 0.062761194 | AF7: =IF($A7="","",IFERROR(MAX(0,(I7-P7)*G7),0)) -> 0 | AG7: =IF($A7="","",IF(COUNTIFS(候选池!$C$2:$C$201,C7,候选池!$K$2:$K$201,"核心池")>0,"核心池","否")) -> 否 | AH7: =IF(A7="","",IF(OR(J7="",K7="",K7=0),"",IF((J7-K7)/K7<0.05,"不可加仓(无浮盈护垫)",IF(N7>0.6,"不可加仓(超三买上限)",IF(N7>0.5,"可加仓(三买区,上限60%)",IF(N7>0.35,"可加仓(二买区,上限50%)","可加仓(一买区,上限35%)"))))))
A8: 46227 | B8: 曲美家居 | C8: 603818 | D8: 否 | F8: 2026-07-24 | G8: 0 | H8: 3.142 | I8: 3.09 | J8: =IF(A8="","",G8*I8) -> 0 | K8: =IF(A8="","",G8*H8) -> 0 | L8: =IF(OR(A8="",J8="",K8=""),"",J8-K8) -> 0 | M8: =IFERROR((I8-H8)/H8,0) -> -0.016549968 | N8: =IFERROR(J8/INDEX(账户总表!$B:$B,MATCH($A8,账户总表!$A:$A,0)),0) -> 0 | P8: 2.9849 | Q8: =IF($A8="","",IF(AND(I8>0,P8>0,I8<=P8),"是","否")) -> 否 | V8: =IF($A8="","",IF(OR(AND(O8>0,I8<O8),AND(T8="False",S8<0.8)),"是","否")) -> 否 | W8: 是 | X8: =IF($A8="","",IF(AND(R8<60%,S8>0.8,T8="True",U8="一卖"),"是","否")) -> 否 | Y8: =IF($A8="","",IF(D8="是","否",IF(N8>LOOKUP(2,1/(账户总表!$A:$A<>""),账户总表!$O:$O),"是","否"))) -> 否 | Z8: =IF($A8="","",IF(M8>=0,"盈利","亏损")) -> 亏损 | AA8: =IF($A8="","",IFERROR(INDEX(账户总表!$B:$B,MATCH($A8,账户总表!$A:$A,0))*INDEX(账户总表!$O:$O,MATCH($A8,账户总表!$A:$A,0)),0)) -> 7294.812 | AB8: =IF($A8="","",IFERROR(MAX(0,AA8-J8),0)) -> 7294.812 | AC8: =IF($A8="","",IF(I8>0,IFERROR(FLOOR(AB8/I8,100),0),0)) -> 2300 | AD8: =IF($A8="","",IF(N8>LOOKUP(2,1/(账户总表!$A:$A<>""),账户总表!$O:$O),"超限","合规")) -> 合规 | AE8: =IF($A8="","",IFERROR((I8-P8)/I8,0)) -> 0.034012945 | AF8: =IF($A8="","",IFERROR(MAX(0,(I8-P8)*G8),0)) -> 0 | AG8: =IF($A8="","",IF(COUNTIFS(候选池!$C$2:$C$201,C8,候选池!$K$2:$K$201,"核心池")>0,"核心池","否")) -> 否 | AH8: =IF(A8="","",IF(OR(J8="",K8="",K8=0),"",IF((J8-K8)/K8<0.05,"不可加仓(无浮盈护垫)",IF(N8>0.6,"不可加仓(超三买上限)",IF(N8>0.5,"可加仓(三买区,上限60%)",IF(N8>0.35,"可加仓(二买区,上限50%)","可加仓(一买区,上限35%)"))))))
A9: 46230 | B9: 松芝股份 | C9: 002454 | D9: 否 | E9: 3.788 | F9: 4.87 | G9: 100 | H9: 4.595 | I9: 4.68 | J9: =IF(A9="","",G9*I9) -> 468 | K9: =IF(A9="","",G9*H9) -> 459.5 | L9: =IF(OR(A9="",J9="",K9=""),"",J9-K9) -> 8.5 | M9: =IFERROR((I9-H9)/H9,0) -> 0.018498368 | N9: =IFERROR(J9/INDEX(账户总表!$B:$B,MATCH($A9,账户总表!$A:$A,0)),0) -> 0.022453668 | P9: 4.37 | Q9: =IF($A9="","",IF(AND(I9>0,P9>0,I9<=P9),"是","否")) -> 否 | V9: =IF($A9="","",IF(OR(AND(O9>0,I9<O9),AND(T9="False",S9<0.8)),"是","否")) -> 否 | X9: =IF($A9="","",IF(AND(R9<60%,S9>0.8,T9="True",U9="一卖"),"是","否")) -> 否 | Y9: =IF($A9="","",IF(D9="是","否",IF(N9>LOOKUP(2,1/(账户总表!$A:$A<>""),账户总表!$O:$O),"是","否"))) -> 是 | Z9: =IF($A9="","",IF(M9>=0,"盈利","亏损")) -> 盈利 | AA9: =IF($A9="","",IFERROR(INDEX(账户总表!$B:$B,MATCH($A9,账户总表!$A:$A,0))*INDEX(账户总表!$O:$O,MATCH($A9,账户总表!$A:$A,0)),0)) -> 7295.022 | AB9: =IF($A9="","",IFERROR(MAX(0,AA9-J9),0)) -> 6827.022 | AC9: =IF($A9="","",IF(I9>0,IFERROR(FLOOR(AB9/I9,100),0),0)) -> 1400 | AD9: =IF($A9="","",IF(N9>LOOKUP(2,1/(账户总表!$A:$A<>""),账户总表!$O:$O),"超限","合规")) -> 超限 | AE9: =IF($A9="","",IFERROR((I9-P9)/I9,0)) -> 0.066239316 | AF9: =IF($A9="","",IFERROR(MAX(0,(I9-P9)*G9),0)) -> 31 | AG9: =IF($A9="","",IF(COUNTIFS(候选池!$C$2:$C$201,C9,候选池!$K$2:$K$201,"核心池")>0,"核心池","否")) -> 否 | AH9: =IF(A9="","",IF(OR(J9="",K9="",K9=0),"",IF((J9-K9)/K9<0.05,"不可加仓(无浮盈护垫)",IF(N9>0.6,"不可加仓(超三买上限)",IF(N9>0.5,"可加仓(三买区,上限60%)",IF(N9>0.35,"可加仓(二买区,上限50%)","可加仓(一买区,上限35%)")))))) -> 不可加仓(无浮盈护垫)
A10: 46230 | B10: 亚太药业 | C10: 002370 | D10: 否 | F10: 2026-07-27 | G10: 400 | H10: 4.625 | I10: 4.79 | J10: =IF(A10="","",G10*I10) -> 1916 | K10: =IF(A10="","",G10*H10) -> 1850 | L10: =IF(OR(A10="",J10="",K10=""),"",J10-K10) -> 66 | M10: =IFERROR((I10-H10)/H10,0) -> 0.035675676 | N10: =IFERROR(J10/INDEX(账户总表!$B:$B,MATCH($A10,账户总表!$A:$A,0)),0) -> 0.091925699 | P10: 4.39 | Q10: =IF($A10="","",IF(AND(I10>0,P10>0,I10<=P10),"是","否")) -> 否 | V10: =IF($A10="","",IF(OR(AND(O10>0,I10<O10),AND(T10="False",S10<0.8)),"是","否")) -> 否 | X10: =IF($A10="","",IF(AND(R10<60%,S10>0.8,T10="True",U10="一卖"),"是","否")) -> 否 | Y10: =IF($A10="","",IF(D10="是","否",IF(N10>LOOKUP(2,1/(账户总表!$A:$A<>""),账户总表!$O:$O),"是","否"))) -> 是 | Z10: =IF($A10="","",IF(M10>=0,"盈利","亏损")) -> 盈利 | AA10: =IF($A10="","",IFERROR(INDEX(账户总表!$B:$B,MATCH($A10,账户总表!$A:$A,0))*INDEX(账户总表!$O:$O,MATCH($A10,账户总表!$A:$A,0)),0)) -> 7295.022 | AB10: =IF($A10="","",IFERROR(MAX(0,AA10-J10),0)) -> 5379.022 | AC10: =IF($A10="","",IF(I10>0,IFERROR(FLOOR(AB10/I10,100),0),0)) -> 1100 | AD10: =IF($A10="","",IF(N10>LOOKUP(2,1/(账户总表!$A:$A<>""),账户总表!$O:$O),"超限","合规")) -> 超限 | AE10: =IF($A10="","",IFERROR((I10-P10)/I10,0)) -> 0.083507307 | AF10: =IF($A10="","",IFERROR(MAX(0,(I10-P10)*G10),0)) -> 160 | AG10: =IF($A10="","",IF(COUNTIFS(候选池!$C$2:$C$201,C10,候选池!$K$2:$K$201,"核心池")>0,"核心池","否")) -> 否 | AH10: =IF(A10="","",IF(OR(J10="",K10="",K10=0),"",IF((J10-K10)/K10<0.05,"不可加仓(无浮盈护垫)",IF(N10>0.6,"不可加仓(超三买上限)",IF(N10>0.5,"可加仓(三买区,上限60%)",IF(N10>0.35,"可加仓(二买区,上限50%)","可加仓(一买区,上限35%)")))))) -> 不可加仓(无浮盈护垫)
A11: 46230 | B11: 三力士 | C11: 002224 | D11: 否 | F11: 2026-07-27 | G11: 0 | H11: 3.287 | I11: 3.35 | J11: =IF(A11="","",G11*I11) -> 0 | K11: =IF(A11="","",G11*H11) -> 0 | L11: =IF(OR(A11="",J11="",K11=""),"",J11-K11) -> 0 | M11: =IFERROR((I11-H11)/H11,0) -> 0.019166413 | N11: =IFERROR(J11/INDEX(账户总表!$B:$B,MATCH($A11,账户总表!$A:$A,0)),0) -> 0 | P11: 3.12 | Q11: =IF($A11="","",IF(AND(I11>0,P11>0,I11<=P11),"是","否")) -> 否 | T11: 已清仓 | V11: =IF($A11="","",IF(OR(AND(O11>0,I11<O11),AND(T11="False",S11<0.8)),"是","否")) -> 否 | X11: =IF($A11="","",IF(AND(R11<60%,S11>0.8,T11="True",U11="一卖"),"是","否")) -> 否 | Y11: =IF($A11="","",IF(D11="是","否",IF(N11>LOOKUP(2,1/(账户总表!$A:$A<>""),账户总表!$O:$O),"是","否"))) -> 否 | Z11: =IF($A11="","",IF(M11>=0,"盈利","亏损")) -> 盈利 | AA11: =IF($A11="","",IFERROR(INDEX(账户总表!$B:$B,MATCH($A11,账户总表!$A:$A,0))*INDEX(账户总表!$O:$O,MATCH($A11,账户总表!$A:$A,0)),0)) -> 7295.022 | AB11: =IF($A11="","",IFERROR(MAX(0,AA11-J11),0)) -> 7295.022 | AC11: =IF($A11="","",IF(I11>0,IFERROR(FLOOR(AB11/I11,100),0),0)) -> 2100 | AD11: =IF($A11="","",IF(N11>LOOKUP(2,1/(账户总表!$A:$A<>""),账户总表!$O:$O),"超限","合规")) -> 合规 | AE11: =IF($A11="","",IFERROR((I11-P11)/I11,0)) -> 0.068656716 | AF11: =IF($A11="","",IFERROR(MAX(0,(I11-P11)*G11),0)) -> 0 | AG11: =IF($A11="","",IF(COUNTIFS(候选池!$C$2:$C$201,C11,候选池!$K$2:$K$201,"核心池")>0,"核心池","否")) -> 否 | AH11: =IF(A11="","",IF(OR(J11="",K11="",K11=0),"",IF((J11-K11)/K11<0.05,"不可加仓(无浮盈护垫)",IF(N11>0.6,"不可加仓(超三买上限)",IF(N11>0.5,"可加仓(三买区,上限60%)",IF(N11>0.35,"可加仓(二买区,上限50%)","可加仓(一买区,上限35%)"))))))
A12: 46230 | B12: 拱东医疗 | C12: 605369 | D12: 否 | F12: 2026-07-27 | G12: 0 | H12: 15.331 | I12: 15.67 | J12: =IF(A12="","",G12*I12) -> 0 | K12: =IF(A12="","",G12*H12) -> 0 | L12: =IF(OR(A12="",J12="",K12=""),"",J12-K12) -> 0 | M12: =IFERROR((I12-H12)/H12,0) -> 0.022112061 | N12: =IFERROR(J12/INDEX(账户总表!$B:$B,MATCH($A12,账户总表!$A:$A,0)),0) -> 0 | P12: 14.56 | Q12: =IF($A12="","",IF(AND(I12>0,P12>0,I12<=P12),"是","否")) -> 否 | T12: 已清仓 | V12: =IF($A12="","",IF(OR(AND(O12>0,I12<O12),AND(T12="False",S12<0.8)),"是","否")) -> 否 | X12: =IF($A12="","",IF(AND(R12<60%,S12>0.8,T12="True",U12="一卖"),"是","否")) -> 否 | Y12: =IF($A12="","",IF(D12="是","否",IF(N12>LOOKUP(2,1/(账户总表!$A:$A<>""),账户总表!$O:$O),"是","否"))) -> 否 | Z12: =IF($A12="","",IF(M12>=0,"盈利","亏损")) -> 盈利 | AA12: =IF($A12="","",IFERROR(INDEX(账户总表!$B:$B,MATCH($A12,账户总表!$A:$A,0))*INDEX(账户总表!$O:$O,MATCH($A12,账户总表!$A:$A,0)),0)) -> 7295.022 | AB12: =IF($A12="","",IFERROR(MAX(0,AA12-J12),0)) -> 7295.022 | AC12: =IF($A12="","",IF(I12>0,IFERROR(FLOOR(AB12/I12,100),0),0)) -> 400 | AD12: =IF($A12="","",IF(N12>LOOKUP(2,1/(账户总表!$A:$A<>""),账户总表!$O:$O),"超限","合规")) -> 合规 | AE12: =IF($A12="","",IFERROR((I12-P12)/I12,0)) -> 0.070835992 | AF12: =IF($A12="","",IFERROR(MAX(0,(I12-P12)*G12),0)) -> 0 | AG12: =IF($A12="","",IF(COUNTIFS(候选池!$C$2:$C$201,C12,候选池!$K$2:$K$201,"核心池")>0,"核心池","否")) -> 否 | AH12: =IF(A12="","",IF(OR(J12="",K12="",K12=0),"",IF((J12-K12)/K12<0.05,"不可加仓(无浮盈护垫)",IF(N12>0.6,"不可加仓(超三买上限)",IF(N12>0.5,"可加仓(三买区,上限60%)",IF(N12>0.35,"可加仓(二买区,上限50%)","可加仓(一买区,上限35%)"))))))
A13: 46231 | B13: 松芝股份 | C13: 002454 | D13: 否 | E13: 3.788 | F13: 4.87 | G13: 100 | H13: 4.595 | I13: 4.72 | J13: =IF(A13="","",G13*I13) -> 472 | K13: =IF(A13="","",G13*H13) -> 459.5 | L13: =IF(OR(A13="",J13="",K13=""),"",J13-K13) -> 12.5 | M13: =IFERROR((I13-H13)/H13,0) -> 0.027203482 | N13: =IFERROR(J13/INDEX(账户总表!$B:$B,MATCH($A13,账户总表!$A:$A,0)),0) -> 0.022324638 | O13: 4.365 | P13: 4.227 | Q13: =IF($A13="","",IF(AND(I13>0,P13>0,I13<=P13),"是","否")) -> 否 | V13: =IF($A13="","",IF(OR(AND(O13>0,I13<O13),AND(T13="False",S13<0.8)),"是","否")) -> 否 | X13: =IF($A13="","",IF(AND(R13<60%,S13>0.8,T13="True",U13="一卖"),"是","否")) -> 否 | Y13: =IF($A13="","",IF(D13="是","否",IF(N13>LOOKUP(2,1/(账户总表!$A:$A<>""),账户总表!$O:$O),"是","否"))) -> 是 | Z13: =IF($A13="","",IF(M13>=0,"盈利","亏损")) -> 盈利 | AA13: =IF($A13="","",IFERROR(INDEX(账户总表!$B:$B,MATCH($A13,账户总表!$A:$A,0))*INDEX(账户总表!$O:$O,MATCH($A13,账户总表!$A:$A,0)),0)) -> 7399.896 | AB13: =IF($A13="","",IFERROR(MAX(0,AA13-J13),0)) -> 6927.896 | AC13: =IF($A13="","",IF(I13>0,IFERROR(FLOOR(AB13/I13,100),0),0)) -> 1400 | AD13: =IF($A13="","",IF(N13>LOOKUP(2,1/(账户总表!$A:$A<>""),账户总表!$O:$O),"超限","合规")) -> 超限 | AE13: =IF($A13="","",IFERROR((I13-P13)/I13,0)) -> 0.10444915 | AF13: =IF($A13="","",IFERROR(MAX(0,(I13-P13)*G13),0)) -> 49.3 | AG13: =IF($A13="","",IF(COUNTIFS(候选池!$C$2:$C$201,C13,候选池!$K$2:$K$201,"核心池")>0,"核心池","否")) -> 否 | AH13: =IF(A13="","",IF(OR(J13="",K13="",K13=0),"",IF((J13-K13)/K13<0.05,"不可加仓(无浮盈护垫)",IF(N13>0.6,"不可加仓(超三买上限)",IF(N13>0.5,"可加仓(三买区,上限60%)",IF(N13>0.35,"可加仓(二买区,上限50%)","可加仓(一买区,上限35%)")))))) -> 不可加仓(无浮盈护垫)
A14: 46231 | B14: 三力士 | C14: 002224 | D14: 否 | F14: 46231 | G14: 0 | H14: 3.287 | I14: 3.39 | J14: =IF(A14="","",G14*I14) -> 0 | K14: =IF(A14="","",G14*H14) -> 0 | L14: =IF(OR(A14="",J14="",K14=""),"",J14-K14) -> 0 | M14: =IFERROR((I14-H14)/H14,0) -> 0.031335564 | N14: =IFERROR(J14/INDEX(账户总表!$B:$B,MATCH($A14,账户总表!$A:$A,0)),0) -> 0 | O14: 3.123 | P14: 3.024 | Q14: =IF($A14="","",IF(AND(I14>0,P14>0,I14<=P14),"是","否")) -> 否 | T14: 已清仓 | V14: =IF($A14="","",IF(OR(AND(O14>0,I14<O14),AND(T14="False",S14<0.8)),"是","否")) -> 否 | X14: =IF($A14="","",IF(AND(R14<60%,S14>0.8,T14="True",U14="一卖"),"是","否")) -> 否 | Y14: =IF($A14="","",IF(D14="是","否",IF(N14>LOOKUP(2,1/(账户总表!$A:$A<>""),账户总表!$O:$O),"是","否"))) -> 否 | Z14: =IF($A14="","",IF(M14>=0,"盈利","亏损")) -> 盈利 | AA14: =IF($A14="","",IFERROR(INDEX(账户总表!$B:$B,MATCH($A14,账户总表!$A:$A,0))*INDEX(账户总表!$O:$O,MATCH($A14,账户总表!$A:$A,0)),0)) -> 7399.896 | AB14: =IF($A14="","",IFERROR(MAX(0,AA14-J14),0)) -> 7399.896 | AC14: =IF($A14="","",IF(I14>0,IFERROR(FLOOR(AB14/I14,100),0),0)) -> 2100 | AD14: =IF($A14="","",IF(N14>LOOKUP(2,1/(账户总表!$A:$A<>""),账户总表!$O:$O),"超限","合规")) -> 合规 | AE14: =IF($A14="","",IFERROR((I14-P14)/I14,0)) -> 0.1079646 | AF14: =IF($A14="","",IFERROR(MAX(0,(I14-P14)*G14),0)) -> 0 | AG14: =IF($A14="","",IF(COUNTIFS(候选池!$C$2:$C$201,C14,候选池!$K$2:$K$201,"核心池")>0,"核心池","否")) -> 否 | AH14: =IF(A14="","",IF(OR(J14="",K14="",K14=0),"",IF((J14-K14)/K14<0.05,"不可加仓(无浮盈护垫)",IF(N14>0.6,"不可加仓(超三买上限)",IF(N14>0.5,"可加仓(三买区,上限60%)",IF(N14>0.35,"可加仓(二买区,上限50%)","可加仓(一买区,上限35%)"))))))
A15: 46231 | B15: 拱东医疗 | C15: 605369 | D15: 否 | F15: 46231 | G15: 0 | H15: 15.33 | I15: 15.78 | J15: =IF(A15="","",G15*I15) -> 0 | K15: =IF(A15="","",G15*H15) -> 0 | L15: =IF(OR(A15="",J15="",K15=""),"",J15-K15) -> 0 | M15: =IFERROR((I15-H15)/H15,0) -> 0.029354207 | N15: =IFERROR(J15/INDEX(账户总表!$B:$B,MATCH($A15,账户总表!$A:$A,0)),0) -> 0 | O15: 14.563 | P15: 14.104 | Q15: =IF($A15="","",IF(AND(I15>0,P15>0,I15<=P15),"是","否")) -> 否 | T15: 已清仓 | V15: =IF($A15="","",IF(OR(AND(O15>0,I15<O15),AND(T15="False",S15<0.8)),"是","否")) -> 否 | X15: =IF($A15="","",IF(AND(R15<60%,S15>0.8,T15="True",U15="一卖"),"是","否")) -> 否 | Y15: =IF($A15="","",IF(D15="是","否",IF(N15>LOOKUP(2,1/(账户总表!$A:$A<>""),账户总表!$O:$O),"是","否"))) -> 否 | Z15: =IF($A15="","",IF(M15>=0,"盈利","亏损")) -> 盈利 | AA15: =IF($A15="","",IFERROR(INDEX(账户总表!$B:$B,MATCH($A15,账户总表!$A:$A,0))*INDEX(账户总表!$O:$O,MATCH($A15,账户总表!$A:$A,0)),0)) -> 7399.896 | AB15: =IF($A15="","",IFERROR(MAX(0,AA15-J15),0)) -> 7399.896 | AC15: =IF($A15="","",IF(I15>0,IFERROR(FLOOR(AB15/I15,100),0),0)) -> 400 | AD15: =IF($A15="","",IF(N15>LOOKUP(2,1/(账户总表!$A:$A<>""),账户总表!$O:$O),"超限","合规")) -> 合规 | AE15: =IF($A15="","",IFERROR((I15-P15)/I15,0)) -> 0.10621039 | AF15: =IF($A15="","",IFERROR(MAX(0,(I15-P15)*G15),0)) -> 0 | AG15: =IF($A15="","",IF(COUNTIFS(候选池!$C$2:$C$201,C15,候选池!$K$2:$K$201,"核心池")>0,"核心池","否")) -> 否 | AH15: =IF(A15="","",IF(OR(J15="",K15="",K15=0),"",IF((J15-K15)/K15<0.05,"不可加仓(无浮盈护垫)",IF(N15>0.6,"不可加仓(超三买上限)",IF(N15>0.5,"可加仓(三买区,上限60%)",IF(N15>0.35,"可加仓(二买区,上限50%)","可加仓(一买区,上限35%)"))))))
A16: 46231 | B16: 东风股份 | C16: 600006 | D16: 是 | E16: 8.711 | F16: 5.67 | G16: 100 | H16: 8.711 | I16: 5.49 | J16: =IF(A16="","",G16*I16) -> 549 | K16: =IF(A16="","",G16*H16) -> 871.1 | L16: =IF(OR(A16="",J16="",K16=""),"",J16-K16) -> -322.1 | M16: =IFERROR((I16-H16)/H16,0) -> -0.36976237 | N16: =IFERROR(J16/INDEX(账户总表!$B:$B,MATCH($A16,账户总表!$A:$A,0)),0) -> 0.025966581 | O16: 8.275 | P16: 8.014 | Q16: =IF($A16="","",IF(AND(I16>0,P16>0,I16<=P16),"是","否")) -> 是 | V16: =IF($A16="","",IF(OR(AND(O16>0,I16<O16),AND(T16="False",S16<0.8)),"是","否")) -> 是 | X16: =IF($A16="","",IF(AND(R16<60%,S16>0.8,T16="True",U16="一卖"),"是","否")) -> 否 | Y16: =IF($A16="","",IF(D16="是","否",IF(N16>LOOKUP(2,1/(账户总表!$A:$A<>""),账户总表!$O:$O),"是","否"))) -> 否 | Z16: =IF($A16="","",IF(M16>=0,"盈利","亏损")) -> 亏损 | AA16: =IF($A16="","",IFERROR(INDEX(账户总表!$B:$B,MATCH($A16,账户总表!$A:$A,0))*INDEX(账户总表!$O:$O,MATCH($A16,账户总表!$A:$A,0)),0)) -> 7399.896 | AB16: =IF($A16="","",IFERROR(MAX(0,AA16-J16),0)) -> 6850.896 | AC16: =IF($A16="","",IF(I16>0,IFERROR(FLOOR(AB16/I16,100),0),0)) -> 1200 | AD16: =IF($A16="","",IF(N16>LOOKUP(2,1/(账户总表!$A:$A<>""),账户总表!$O:$O),"超限","合规")) -> 超限 | AE16: =IF($A16="","",IFERROR((I16-P16)/I16,0)) -> -0.45974499 | AF16: =IF($A16="","",IFERROR(MAX(0,(I16-P16)*G16),0)) -> 0 | AG16: =IF($A16="","",IF(COUNTIFS(候选池!$C$2:$C$201,C16,候选池!$K$2:$K$201,"核心池")>0,"核心池","否")) -> 否 | AH16: =IF(A16="","",IF(OR(J16="",K16="",K16=0),"",IF((J16-K16)/K16<0.05,"不可加仓(无浮盈护垫)",IF(N16>0.6,"不可加仓(超三买上限)",IF(N16>0.5,"可加仓(三买区,上限60%)",IF(N16>0.35,"可加仓(二买区,上限50%)","可加仓(一买区,上限35%)")))))) -> 不可加仓(无浮盈护垫)
A17: 46231 | B17: 贵绳股份 | C17: 600992 | D17: 否 | E17: 9.193 | F17: 9.3 | G17: 300 | H17: 9.171 | I17: 9.17 | J17: =IF(A17="","",G17*I17) -> 2751 | K17: =IF(A17="","",G17*H17) -> 2751.3 | L17: =IF(OR(A17="",J17="",K17=""),"",J17-K17) -> -0.3 | M17: =IFERROR((I17-H17)/H17,0) -> -0.00010903936 | N17: =IFERROR(J17/INDEX(账户总表!$B:$B,MATCH($A17,账户总表!$A:$A,0)),0) -> 0.13011669 | O17: 8.712 | P17: 8.437 | Q17: =IF($A17="","",IF(AND(I17>0,P17>0,I17<=P17),"是","否")) -> 否 | V17: =IF($A17="","",IF(OR(AND(O17>0,I17<O17),AND(T17="False",S17<0.8)),"是","否")) -> 否 | X17: =IF($A17="","",IF(AND(R17<60%,S17>0.8,T17="True",U17="一卖"),"是","否")) -> 否 | Y17: =IF($A17="","",IF(D17="是","否",IF(N17>LOOKUP(2,1/(账户总表!$A:$A<>""),账户总表!$O:$O),"是","否"))) -> 是 | Z17: =IF($A17="","",IF(M17>=0,"盈利","亏损")) -> 亏损 | AA17: =IF($A17="","",IFERROR(INDEX(账户总表!$B:$B,MATCH($A17,账户总表!$A:$A,0))*INDEX(账户总表!$O:$O,MATCH($A17,账户总表!$A:$A,0)),0)) -> 7399.896 | AB17: =IF($A17="","",IFERROR(MAX(0,AA17-J17),0)) -> 4648.896 | AC17: =IF($A17="","",IF(I17>0,IFERROR(FLOOR(AB17/I17,100),0),0)) -> 500 | AD17: =IF($A17="","",IF(N17>LOOKUP(2,1/(账户总表!$A:$A<>""),账户总表!$O:$O),"超限","合规")) -> 超限 | AE17: =IF($A17="","",IFERROR((I17-P17)/I17,0)) -> 0.079934569 | AF17: =IF($A17="","",IFERROR(MAX(0,(I17-P17)*G17),0)) -> 219.9 | AG17: =IF($A17="","",IF(COUNTIFS(候选池!$C$2:$C$201,C17,候选池!$K$2:$K$201,"核心池")>0,"核心池","否")) -> 否 | AH17: =IF(A17="","",IF(OR(J17="",K17="",K17=0),"",IF((J17-K17)/K17<0.05,"不可加仓(无浮盈护垫)",IF(N17>0.6,"不可加仓(超三买上限)",IF(N17>0.5,"可加仓(三买区,上限60%)",IF(N17>0.35,"可加仓(二买区,上限50%)","可加仓(一买区,上限35%)")))))) -> 不可加仓(无浮盈护垫)
A18: 46231 | B18: 松芝股份 | C18: 002454 | D18: 否 | E18: 3.788 | F18: 4.87 | G18: 100 | H18: 4.595 | I18: 4.72 | J18: =IF(A18="","",G18*I18) -> 472 | K18: =IF(A18="","",G18*H18) -> 459.5 | L18: =IF(OR(A18="",J18="",K18=""),"",J18-K18) -> 12.5 | M18: =IFERROR((I18-H18)/H18,0) -> 0.027203482 | N18: =IFERROR(J18/INDEX(账户总表!$B:$B,MATCH($A18,账户总表!$A:$A,0)),0) -> 0.022324638 | O18: 4.365 | P18: 4.227 | Q18: =IF($A18="","",IF(AND(I18>0,P18>0,I18<=P18),"是","否")) -> 否 | V18: =IF($A18="","",IF(OR(AND(O18>0,I18<O18),AND(T18="False",S18<0.8)),"是","否")) -> 否 | X18: =IF($A18="","",IF(AND(R18<60%,S18>0.8,T18="True",U18="一卖"),"是","否")) -> 否 | Y18: =IF($A18="","",IF(D18="是","否",IF(N18>LOOKUP(2,1/(账户总表!$A:$A<>""),账户总表!$O:$O),"是","否"))) -> 是 | Z18: =IF($A18="","",IF(M18>=0,"盈利","亏损")) -> 盈利 | AA18: =IF($A18="","",IFERROR(INDEX(账户总表!$B:$B,MATCH($A18,账户总表!$A:$A,0))*INDEX(账户总表!$O:$O,MATCH($A18,账户总表!$A:$A,0)),0)) -> 7399.896 | AB18: =IF($A18="","",IFERROR(MAX(0,AA18-J18),0)) -> 6927.896 | AC18: =IF($A18="","",IF(I18>0,IFERROR(FLOOR(AB18/I18,100),0),0)) -> 1400 | AD18: =IF($A18="","",IF(N18>LOOKUP(2,1/(账户总表!$A:$A<>""),账户总表!$O:$O),"超限","合规")) -> 超限 | AE18: =IF($A18="","",IFERROR((I18-P18)/I18,0)) -> 0.10444915 | AF18: =IF($A18="","",IFERROR(MAX(0,(I18-P18)*G18),0)) -> 49.3 | AG18: =IF($A18="","",IF(COUNTIFS(候选池!$C$2:$C$201,C18,候选池!$K$2:$K$201,"核心池")>0,"核心池","否")) -> 否 | AH18: =IF(A18="","",IF(OR(J18="",K18="",K18=0),"",IF((J18-K18)/K18<0.05,"不可加仓(无浮盈护垫)",IF(N18>0.6,"不可加仓(超三买上限)",IF(N18>0.5,"可加仓(三买区,上限60%)",IF(N18>0.35,"可加仓(二买区,上限50%)","可加仓(一买区,上限35%)")))))) -> 不可加仓(无浮盈护垫)
A19: 46231 | B19: 三力士 | C19: 002224 | D19: 否 | F19: 46231 | G19: 0 | H19: 3.287 | I19: 3.39 | J19: =IF(A19="","",G19*I19) -> 0 | K19: =IF(A19="","",G19*H19) -> 0 | L19: =IF(OR(A19="",J19="",K19=""),"",J19-K19) -> 0 | M19: =IFERROR((I19-H19)/H19,0) -> 0.031335564 | N19: =IFERROR(J19/INDEX(账户总表!$B:$B,MATCH($A19,账户总表!$A:$A,0)),0) -> 0 | O19: 3.123 | P19: 3.024 | Q19: =IF($A19="","",IF(AND(I19>0,P19>0,I19<=P19),"是","否")) -> 否 | T19: 已清仓 | V19: =IF($A19="","",IF(OR(AND(O19>0,I19<O19),AND(T19="False",S19<0.8)),"是","否")) -> 否 | X19: =IF($A19="","",IF(AND(R19<60%,S19>0.8,T19="True",U19="一卖"),"是","否")) -> 否 | Y19: =IF($A19="","",IF(D19="是","否",IF(N19>LOOKUP(2,1/(账户总表!$A:$A<>""),账户总表!$O:$O),"是","否"))) -> 否 | Z19: =IF($A19="","",IF(M19>=0,"盈利","亏损")) -> 盈利 | AA19: =IF($A19="","",IFERROR(INDEX(账户总表!$B:$B,MATCH($A19,账户总表!$A:$A,0))*INDEX(账户总表!$O:$O,MATCH($A19,账户总表!$A:$A,0)),0)) -> 7399.896 | AB19: =IF($A19="","",IFERROR(MAX(0,AA19-J19),0)) -> 7399.896 | AC19: =IF($A19="","",IF(I19>0,IFERROR(FLOOR(AB19/I19,100),0),0)) -> 2100 | AD19: =IF($A19="","",IF(N19>LOOKUP(2,1/(账户总表!$A:$A<>""),账户总表!$O:$O),"超限","合规")) -> 合规 | AE19: =IF($A19="","",IFERROR((I19-P19)/I19,0)) -> 0.1079646 | AF19: =IF($A19="","",IFERROR(MAX(0,(I19-P19)*G19),0)) -> 0 | AG19: =IF($A19="","",IF(COUNTIFS(候选池!$C$2:$C$201,C19,候选池!$K$2:$K$201,"核心池")>0,"核心池","否")) -> 否 | AH19: =IF(A19="","",IF(OR(J19="",K19="",K19=0),"",IF((J19-K19)/K19<0.05,"不可加仓(无浮盈护垫)",IF(N19>0.6,"不可加仓(超三买上限)",IF(N19>0.5,"可加仓(三买区,上限60%)",IF(N19>0.35,"可加仓(二买区,上限50%)","可加仓(一买区,上限35%)"))))))
A20: 46231 | B20: 拱东医疗 | C20: 605369 | D20: 否 | F20: 46231 | G20: 0 | H20: 15.33 | I20: 15.78 | J20: =IF(A20="","",G20*I20) -> 0 | K20: =IF(A20="","",G20*H20) -> 0 | L20: =IF(OR(A20="",J20="",K20=""),"",J20-K20) -> 0 | M20: =IFERROR((I20-H20)/H20,0) -> 0.029354207 | N20: =IFERROR(J20/INDEX(账户总表!$B:$B,MATCH($A20,账户总表!$A:$A,0)),0) -> 0 | O20: 14.563 | P20: 14.104 | Q20: =IF($A20="","",IF(AND(I20>0,P20>0,I20<=P20),"是","否")) -> 否 | T20: 已清仓 | V20: =IF($A20="","",IF(OR(AND(O20>0,I20<O20),AND(T20="False",S20<0.8)),"是","否")) -> 否 | X20: =IF($A20="","",IF(AND(R20<60%,S20>0.8,T20="True",U20="一卖"),"是","否")) -> 否 | Y20: =IF($A20="","",IF(D20="是","否",IF(N20>LOOKUP(2,1/(账户总表!$A:$A<>""),账户总表!$O:$O),"是","否"))) -> 否 | Z20: =IF($A20="","",IF(M20>=0,"盈利","亏损")) -> 盈利 | AA20: =IF($A20="","",IFERROR(INDEX(账户总表!$B:$B,MATCH($A20,账户总表!$A:$A,0))*INDEX(账户总表!$O:$O,MATCH($A20,账户总表!$A:$A,0)),0)) -> 7399.896 | AB20: =IF($A20="","",IFERROR(MAX(0,AA20-J20),0)) -> 7399.896 | AC20: =IF($A20="","",IF(I20>0,IFERROR(FLOOR(AB20/I20,100),0),0)) -> 400 | AD20: =IF($A20="","",IF(N20>LOOKUP(2,1/(账户总表!$A:$A<>""),账户总表!$O:$O),"超限","合规")) -> 合规 | AE20: =IF($A20="","",IFERROR((I20-P20)/I20,0)) -> 0.10621039 | AF20: =IF($A20="","",IFERROR(MAX(0,(I20-P20)*G20),0)) -> 0 | AG20: =IF($A20="","",IF(COUNTIFS(候选池!$C$2:$C$201,C20,候选池!$K$2:$K$201,"核心池")>0,"核心池","否")) -> 否 | AH20: =IF(A20="","",IF(OR(J20="",K20="",K20=0),"",IF((J20-K20)/K20<0.05,"不可加仓(无浮盈护垫)",IF(N20>0.6,"不可加仓(超三买上限)",IF(N20>0.5,"可加仓(三买区,上限60%)",IF(N20>0.35,"可加仓(二买区,上限50%)","可加仓(一买区,上限35%)"))))))
A21: 46231 | B21: 东风股份 | C21: 600006 | D21: 是 | E21: 8.711 | F21: 5.67 | G21: 100 | H21: 8.711 | I21: 5.49 | J21: =IF(A21="","",G21*I21) -> 549 | K21: =IF(A21="","",G21*H21) -> 871.1 | L21: =IF(OR(A21="",J21="",K21=""),"",J21-K21) -> -322.1 | M21: =IFERROR((I21-H21)/H21,0) -> -0.36976237 | N21: =IFERROR(J21/INDEX(账户总表!$B:$B,MATCH($A21,账户总表!$A:$A,0)),0) -> 0.025966581 | O21: 8.275 | P21: 8.014 | Q21: =IF($A21="","",IF(AND(I21>0,P21>0,I21<=P21),"是","否")) -> 是 | V21: =IF($A21="","",IF(OR(AND(O21>0,I21<O21),AND(T21="False",S21<0.8)),"是","否")) -> 是 | X21: =IF($A21="","",IF(AND(R21<60%,S21>0.8,T21="True",U21="一卖"),"是","否")) -> 否 | Y21: =IF($A21="","",IF(D21="是","否",IF(N21>LOOKUP(2,1/(账户总表!$A:$A<>""),账户总表!$O:$O),"是","否"))) -> 否 | Z21: =IF($A21="","",IF(M21>=0,"盈利","亏损")) -> 亏损 | AA21: =IF($A21="","",IFERROR(INDEX(账户总表!$B:$B,MATCH($A21,账户总表!$A:$A,0))*INDEX(账户总表!$O:$O,MATCH($A21,账户总表!$A:$A,0)),0)) -> 7399.896 | AB21: =IF($A21="","",IFERROR(MAX(0,AA21-J21),0)) -> 6850.896 | AC21: =IF($A21="","",IF(I21>0,IFERROR(FLOOR(AB21/I21,100),0),0)) -> 1200 | AD21: =IF($A21="","",IF(N21>LOOKUP(2,1/(账户总表!$A:$A<>""),账户总表!$O:$O),"超限","合规")) -> 超限 | AE21: =IF($A21="","",IFERROR((I21-P21)/I21,0)) -> -0.45974499 | AF21: =IF($A21="","",IFERROR(MAX(0,(I21-P21)*G21),0)) -> 0 | AG21: =IF($A21="","",IF(COUNTIFS(候选池!$C$2:$C$201,C21,候选池!$K$2:$K$201,"核心池")>0,"核心池","否")) -> 否 | AH21: =IF(A21="","",IF(OR(J21="",K21="",K21=0),"",IF((J21-K21)/K21<0.05,"不可加仓(无浮盈护垫)",IF(N21>0.6,"不可加仓(超三买上限)",IF(N21>0.5,"可加仓(三买区,上限60%)",IF(N21>0.35,"可加仓(二买区,上限50%)","可加仓(一买区,上限35%)")))))) -> 不可加仓(无浮盈护垫)
A22: 46231 | B22: 贵绳股份 | C22: 600992 | D22: 否 | E22: 9.193 | F22: 9.3 | G22: 300 | H22: 9.171 | I22: 9.17 | J22: =IF(A22="","",G22*I22) -> 2751 | K22: =IF(A22="","",G22*H22) -> 2751.3 | L22: =IF(OR(A22="",J22="",K22=""),"",J22-K22) -> -0.3 | M22: =IFERROR((I22-H22)/H22,0) -> -0.00010903936 | N22: =IFERROR(J22/INDEX(账户总表!$B:$B,MATCH($A22,账户总表!$A:$A,0)),0) -> 0.13011669 | O22: 8.712 | P22: 8.437 | Q22: =IF($A22="","",IF(AND(I22>0,P22>0,I22<=P22),"是","否")) -> 否 | V22: =IF($A22="","",IF(OR(AND(O22>0,I22<O22),AND(T22="False",S22<0.8)),"是","否")) -> 否 | X22: =IF($A22="","",IF(AND(R22<60%,S22>0.8,T22="True",U22="一卖"),"是","否")) -> 否 | Y22: =IF($A22="","",IF(D22="是","否",IF(N22>LOOKUP(2,1/(账户总表!$A:$A<>""),账户总表!$O:$O),"是","否"))) -> 是 | Z22: =IF($A22="","",IF(M22>=0,"盈利","亏损")) -> 亏损 | AA22: =IF($A22="","",IFERROR(INDEX(账户总表!$B:$B,MATCH($A22,账户总表!$A:$A,0))*INDEX(账户总表!$O:$O,MATCH($A22,账户总表!$A:$A,0)),0)) -> 7399.896 | AB22: =IF($A22="","",IFERROR(MAX(0,AA22-J22),0)) -> 4648.896 | AC22: =IF($A22="","",IF(I22>0,IFERROR(FLOOR(AB22/I22,100),0),0)) -> 500 | AD22: =IF($A22="","",IF(N22>LOOKUP(2,1/(账户总表!$A:$A<>""),账户总表!$O:$O),"超限","合规")) -> 超限 | AE22: =IF($A22="","",IFERROR((I22-P22)/I22,0)) -> 0.079934569 | AF22: =IF($A22="","",IFERROR(MAX(0,(I22-P22)*G22),0)) -> 219.9 | AG22: =IF($A22="","",IF(COUNTIFS(候选池!$C$2:$C$201,C22,候选池!$K$2:$K$201,"核心池")>0,"核心池","否")) -> 否 | AH22: =IF(A22="","",IF(OR(J22="",K22="",K22=0),"",IF((J22-K22)/K22<0.05,"不可加仓(无浮盈护垫)",IF(N22>0.6,"不可加仓(超三买上限)",IF(N22>0.5,"可加仓(三买区,上限60%)",IF(N22>0.35,"可加仓(二买区,上限50%)","可加仓(一买区,上限35%)")))))) -> 不可加仓(无浮盈护垫)
AA23: =IF($A23="","",IFERROR(INDEX(账户总表!$B:$B,MATCH($A23,账户总表!$A:$A,0))*INDEX(账户总表!$O:$O,MATCH($A23,账户总表!$A:$A,0)),0)) | AB23: =IF($A23="","",IFERROR(MAX(0,AA23-J23),0)) | AC23: =IF($A23="","",IF(I23>0,IFERROR(FLOOR(AB23/I23,100),0),0)) | AD23: =IF($A23="","",IF(N23>INDEX(账户总表!$O:$O,MATCH($A23,账户总表!$A:$A,0)),"超限","合规")) | AE23: =IF($A23="","",IFERROR((I23-P23)/I23,0)) | AF23: =IF($A23="","",IFERROR(MAX(0,(I23-P23)*G23),0)) | AG23: =IF($A23="","",IF(COUNTIFS(候选池!$C$2:$C$201,C23,候选池!$K$2:$K$201,"核心池")>0,"核心池","否")) | AH23: =IF(A23="","",IF(OR(J23="",K23="",K23=0),"",IF((J23-K23)/K23<0.05,"不可加仓(无浮盈护垫)",IF(N23>0.6,"不可加仓(超三买上限)",IF(N23>0.5,"可加仓(三买区,上限60%)",IF(N23>0.35,"可加仓(二买区,上限50%)","可加仓(一买区,上限35%)"))))))
AA24: =IF($A24="","",IFERROR(INDEX(账户总表!$B:$B,MATCH($A24,账户总表!$A:$A,0))*INDEX(账户总表!$O:$O,MATCH($A24,账户总表!$A:$A,0)),0)) | AB24: =IF($A24="","",IFERROR(MAX(0,AA24-J24),0)) | AC24: =IF($A24="","",IF(I24>0,IFERROR(FLOOR(AB24/I24,100),0),0)) | AD24: =IF($A24="","",IF(N24>INDEX(账户总表!$O:$O,MATCH($A24,账户总表!$A:$A,0)),"超限","合规")) | AE24: =IF($A24="","",IFERROR((I24-P24)/I24,0)) | AF24: =IF($A24="","",IFERROR(MAX(0,(I24-P24)*G24),0)) | AG24: =IF($A24="","",IF(COUNTIFS(候选池!$C$2:$C$201,C24,候选池!$K$2:$K$201,"核心池")>0,"核心池","否")) | AH24: =IF(A24="","",IF(OR(J24="",K24="",K24=0),"",IF((J24-K24)/K24<0.05,"不可加仓(无浮盈护垫)",IF(N24>0.6,"不可加仓(超三买上限)",IF(N24>0.5,"可加仓(三买区,上限60%)",IF(N24>0.35,"可加仓(二买区,上限50%)","可加仓(一买区,上限35%)"))))))
AA25: =IF($A25="","",IFERROR(INDEX(账户总表!$B:$B,MATCH($A25,账户总表!$A:$A,0))*INDEX(账户总表!$O:$O,MATCH($A25,账户总表!$A:$A,0)),0)) | AB25: =IF($A25="","",IFERROR(MAX(0,AA25-J25),0)) | AC25: =IF($A25="","",IF(I25>0,IFERROR(FLOOR(AB25/I25,100),0),0)) | AD25: =IF($A25="","",IF(N25>INDEX(账户总表!$O:$O,MATCH($A25,账户总表!$A:$A,0)),"超限","合规")) | AE25: =IF($A25="","",IFERROR((I25-P25)/I25,0)) | AF25: =IF($A25="","",IFERROR(MAX(0,(I25-P25)*G25),0)) | AG25: =IF($A25="","",IF(COUNTIFS(候选池!$C$2:$C$201,C25,候选池!$K$2:$K$201,"核心池")>0,"核心池","否")) | AH25: =IF(A25="","",IF(OR(J25="",K25="",K25=0),"",IF((J25-K25)/K25<0.05,"不可加仓(无浮盈护垫)",IF(N25>0.6,"不可加仓(超三买上限)",IF(N25>0.5,"可加仓(三买区,上限60%)",IF(N25>0.35,"可加仓(二买区,上限50%)","可加仓(一买区,上限35%)"))))))
AA26: =IF($A26="","",IFERROR(INDEX(账户总表!$B:$B,MATCH($A26,账户总表!$A:$A,0))*INDEX(账户总表!$O:$O,MATCH($A26,账户总表!$A:$A,0)),0)) | AB26: =IF($A26="","",IFERROR(MAX(0,AA26-J26),0)) | AC26: =IF($A26="","",IF(I26>0,IFERROR(FLOOR(AB26/I26,100),0),0)) | AD26: =IF($A26="","",IF(N26>INDEX(账户总表!$O:$O,MATCH($A26,账户总表!$A:$A,0)),"超限","合规")) | AE26: =IF($A26="","",IFERROR((I26-P26)/I26,0)) | AF26: =IF($A26="","",IFERROR(MAX(0,(I26-P26)*G26),0)) | AG26: =IF($A26="","",IF(COUNTIFS(候选池!$C$2:$C$201,C26,候选池!$K$2:$K$201,"核心池")>0,"核心池","否")) | AH26: =IF(A26="","",IF(OR(J26="",K26="",K26=0),"",IF((J26-K26)/K26<0.05,"不可加仓(无浮盈护垫)",IF(N26>0.6,"不可加仓(超三买上限)",IF(N26>0.5,"可加仓(三买区,上限60%)",IF(N26>0.35,"可加仓(二买区,上限50%)","可加仓(一买区,上限35%)"))))))
AA27: =IF($A27="","",IFERROR(INDEX(账户总表!$B:$B,MATCH($A27,账户总表!$A:$A,0))*INDEX(账户总表!$O:$O,MATCH($A27,账户总表!$A:$A,0)),0)) | AB27: =IF($A27="","",IFERROR(MAX(0,AA27-J27),0)) | AC27: =IF($A27="","",IF(I27>0,IFERROR(FLOOR(AB27/I27,100),0),0)) | AD27: =IF($A27="","",IF(N27>INDEX(账户总表!$O:$O,MATCH($A27,账户总表!$A:$A,0)),"超限","合规")) | AE27: =IF($A27="","",IFERROR((I27-P27)/I27,0)) | AF27: =IF($A27="","",IFERROR(MAX(0,(I27-P27)*G27),0)) | AG27: =IF($A27="","",IF(COUNTIFS(候选池!$C$2:$C$201,C27,候选池!$K$2:$K$201,"核心池")>0,"核心池","否")) | AH27: =IF(A27="","",IF(OR(J27="",K27="",K27=0),"",IF((J27-K27)/K27<0.05,"不可加仓(无浮盈护垫)",IF(N27>0.6,"不可加仓(超三买上限)",IF(N27>0.5,"可加仓(三买区,上限60%)",IF(N27>0.35,"可加仓(二买区,上限50%)","可加仓(一买区,上限35%)"))))))
AA28: =IF($A28="","",IFERROR(INDEX(账户总表!$B:$B,MATCH($A28,账户总表!$A:$A,0))*INDEX(账户总表!$O:$O,MATCH($A28,账户总表!$A:$A,0)),0)) | AB28: =IF($A28="","",IFERROR(MAX(0,AA28-J28),0)) | AC28: =IF($A28="","",IF(I28>0,IFERROR(FLOOR(AB28/I28,100),0),0)) | AD28: =IF($A28="","",IF(N28>INDEX(账户总表!$O:$O,MATCH($A28,账户总表!$A:$A,0)),"超限","合规")) | AE28: =IF($A28="","",IFERROR((I28-P28)/I28,0)) | AF28: =IF($A28="","",IFERROR(MAX(0,(I28-P28)*G28),0)) | AG28: =IF($A28="","",IF(COUNTIFS(候选池!$C$2:$C$201,C28,候选池!$K$2:$K$201,"核心池")>0,"核心池","否")) | AH28: =IF(A28="","",IF(OR(J28="",K28="",K28=0),"",IF((J28-K28)/K28<0.05,"不可加仓(无浮盈护垫)",IF(N28>0.6,"不可加仓(超三买上限)",IF(N28>0.5,"可加仓(三买区,上限60%)",IF(N28>0.35,"可加仓(二买区,上限50%)","可加仓(一买区,上限35%)"))))))
AA29: =IF($A29="","",IFERROR(INDEX(账户总表!$B:$B,MATCH($A29,账户总表!$A:$A,0))*INDEX(账户总表!$O:$O,MATCH($A29,账户总表!$A:$A,0)),0)) | AB29: =IF($A29="","",IFERROR(MAX(0,AA29-J29),0)) | AC29: =IF($A29="","",IF(I29>0,IFERROR(FLOOR(AB29/I29,100),0),0)) | AD29: =IF($A29="","",IF(N29>INDEX(账户总表!$O:$O,MATCH($A29,账户总表!$A:$A,0)),"超限","合规")) | AE29: =IF($A29="","",IFERROR((I29-P29)/I29,0)) | AF29: =IF($A29="","",IFERROR(MAX(0,(I29-P29)*G29),0)) | AG29: =IF($A29="","",IF(COUNTIFS(候选池!$C$2:$C$201,C29,候选池!$K$2:$K$201,"核心池")>0,"核心池","否")) | AH29: =IF(A29="","",IF(OR(J29="",K29="",K29=0),"",IF((J29-K29)/K29<0.05,"不可加仓(无浮盈护垫)",IF(N29>0.6,"不可加仓(超三买上限)",IF(N29>0.5,"可加仓(三买区,上限60%)",IF(N29>0.35,"可加仓(二买区,上限50%)","可加仓(一买区,上限35%)"))))))
AA30: =IF($A30="","",IFERROR(INDEX(账户总表!$B:$B,MATCH($A30,账户总表!$A:$A,0))*INDEX(账户总表!$O:$O,MATCH($A30,账户总表!$A:$A,0)),0)) | AB30: =IF($A30="","",IFERROR(MAX(0,AA30-J30),0)) | AC30: =IF($A30="","",IF(I30>0,IFERROR(FLOOR(AB30/I30,100),0),0)) | AD30: =IF($A30="","",IF(N30>INDEX(账户总表!$O:$O,MATCH($A30,账户总表!$A:$A,0)),"超限","合规")) | AE30: =IF($A30="","",IFERROR((I30-P30)/I30,0)) | AF30: =IF($A30="","",IFERROR(MAX(0,(I30-P30)*G30),0)) | AG30: =IF($A30="","",IF(COUNTIFS(候选池!$C$2:$C$201,C30,候选池!$K$2:$K$201,"核心池")>0,"核心池","否")) | AH30: =IF(A30="","",IF(OR(J30="",K30="",K30=0),"",IF((J30-K30)/K30<0.05,"不可加仓(无浮盈护垫)",IF(N30>0.6,"不可加仓(超三买上限)",IF(N30>0.5,"可加仓(三买区,上限60%)",IF(N30>0.35,"可加仓(二买区,上限50%)","可加仓(一买区,上限35%)"))))))
AA31: =IF($A31="","",IFERROR(INDEX(账户总表!$B:$B,MATCH($A31,账户总表!$A:$A,0))*INDEX(账户总表!$O:$O,MATCH($A31,账户总表!$A:$A,0)),0)) | AB31: =IF($A31="","",IFERROR(MAX(0,AA31-J31),0)) | AC31: =IF($A31="","",IF(I31>0,IFERROR(FLOOR(AB31/I31,100),0),0)) | AD31: =IF($A31="","",IF(N31>INDEX(账户总表!$O:$O,MATCH($A31,账户总表!$A:$A,0)),"超限","合规")) | AE31: =IF($A31="","",IFERROR((I31-P31)/I31,0)) | AF31: =IF($A31="","",IFERROR(MAX(0,(I31-P31)*G31),0)) | AG31: =IF($A31="","",IF(COUNTIFS(候选池!$C$2:$C$201,C31,候选池!$K$2:$K$201,"核心池")>0,"核心池","否")) | AH31: =IF(A31="","",IF(OR(J31="",K31="",K31=0),"",IF((J31-K31)/K31<0.05,"不可加仓(无浮盈护垫)",IF(N31>0.6,"不可加仓(超三买上限)",IF(N31>0.5,"可加仓(三买区,上限60%)",IF(N31>0.35,"可加仓(二买区,上限50%)","可加仓(一买区,上限35%)"))))))
AA32: =IF($A32="","",IFERROR(INDEX(账户总表!$B:$B,MATCH($A32,账户总表!$A:$A,0))*INDEX(账户总表!$O:$O,MATCH($A32,账户总表!$A:$A,0)),0)) | AB32: =IF($A32="","",IFERROR(MAX(0,AA32-J32),0)) | AC32: =IF($A32="","",IF(I32>0,IFERROR(FLOOR(AB32/I32,100),0),0)) | AD32: =IF($A32="","",IF(N32>INDEX(账户总表!$O:$O,MATCH($A32,账户总表!$A:$A,0)),"超限","合规")) | AE32: =IF($A32="","",IFERROR((I32-P32)/I32,0)) | AF32: =IF($A32="","",IFERROR(MAX(0,(I32-P32)*G32),0)) | AG32: =IF($A32="","",IF(COUNTIFS(候选池!$C$2:$C$201,C32,候选池!$K$2:$K$201,"核心池")>0,"核心池","否")) | AH32: =IF(A32="","",IF(OR(J32="",K32="",K32=0),"",IF((J32-K32)/K32<0.05,"不可加仓(无浮盈护垫)",IF(N32>0.6,"不可加仓(超三买上限)",IF(N32>0.5,"可加仓(三买区,上限60%)",IF(N32>0.35,"可加仓(二买区,上限50%)","可加仓(一买区,上限35%)"))))))
AA33: =IF($A33="","",IFERROR(INDEX(账户总表!$B:$B,MATCH($A33,账户总表!$A:$A,0))*INDEX(账户总表!$O:$O,MATCH($A33,账户总表!$A:$A,0)),0)) | AB33: =IF($A33="","",IFERROR(MAX(0,AA33-J33),0)) | AC33: =IF($A33="","",IF(I33>0,IFERROR(FLOOR(AB33/I33,100),0),0)) | AD33: =IF($A33="","",IF(N33>INDEX(账户总表!$O:$O,MATCH($A33,账户总表!$A:$A,0)),"超限","合规")) | AE33: =IF($A33="","",IFERROR((I33-P33)/I33,0)) | AF33: =IF($A33="","",IFERROR(MAX(0,(I33-P33)*G33),0)) | AG33: =IF($A33="","",IF(COUNTIFS(候选池!$C$2:$C$201,C33,候选池!$K$2:$K$201,"核心池")>0,"核心池","否")) | AH33: =IF(A33="","",IF(OR(J33="",K33="",K33=0),"",IF((J33-K33)/K33<0.05,"不可加仓(无浮盈护垫)",IF(N33>0.6,"不可加仓(超三买上限)",IF(N33>0.5,"可加仓(三买区,上限60%)",IF(N33>0.35,"可加仓(二买区,上限50%)","可加仓(一买区,上限35%)"))))))
AA34: =IF($A34="","",IFERROR(INDEX(账户总表!$B:$B,MATCH($A34,账户总表!$A:$A,0))*INDEX(账户总表!$O:$O,MATCH($A34,账户总表!$A:$A,0)),0)) | AB34: =IF($A34="","",IFERROR(MAX(0,AA34-J34),0)) | AC34: =IF($A34="","",IF(I34>0,IFERROR(FLOOR(AB34/I34,100),0),0)) | AD34: =IF($A34="","",IF(N34>INDEX(账户总表!$O:$O,MATCH($A34,账户总表!$A:$A,0)),"超限","合规")) | AE34: =IF($A34="","",IFERROR((I34-P34)/I34,0)) | AF34: =IF($A34="","",IFERROR(MAX(0,(I34-P34)*G34),0)) | AG34: =IF($A34="","",IF(COUNTIFS(候选池!$C$2:$C$201,C34,候选池!$K$2:$K$201,"核心池")>0,"核心池","否")) | AH34: =IF(A34="","",IF(OR(J34="",K34="",K34=0),"",IF((J34-K34)/K34<0.05,"不可加仓(无浮盈护垫)",IF(N34>0.6,"不可加仓(超三买上限)",IF(N34>0.5,"可加仓(三买区,上限60%)",IF(N34>0.35,"可加仓(二买区,上限50%)","可加仓(一买区,上限35%)"))))))
... AA200: =IF($A200="","",IFERROR(INDEX(账户总表!$B:$B,MATCH($A200,账户总表!$A:$A,0))*INDEX(账户总表!$O:$O,MATCH($A200,账户总表!$A:$A,0)),0)) | AB200: =IF($A200="","",IFERROR(MAX(0,AA200-J200),0)) | AC200: =IF($A200="","",IF(I200>0,IFERROR(FLOOR(AB200/I200,100),0),0)) | AD200: =IF($A200="","",IF(N200>INDEX(账户总表!$O:$O,MATCH($A200,账户总表!$A:$A,0)),"超限","合规")) | AE200: =IF($A200="","",IFERROR((I200-P200)/I200,0)) | AF200: =IF($A200="","",IFERROR(MAX(0,(I200-P200)*G200),0)) | AG200: =IF($A200="","",IF(COUNTIFS(候选池!$C$2:$C$201,C200,候选池!$K$2:$K$201,"核心池")>0,"核心池","否")) | AH200: =IF(A200="","",IF(OR(J200="",K200="",K200=0),"",IF((J200-K200)/K200<0.05,"不可加仓(无浮盈护垫)",IF(N200>0.6,"不可加仓(超三买上限)",IF(N200>0.5,"可加仓(三买区,上限60%)",IF(N200>0.35,"可加仓(二买区,上限50%)","可加仓(一买区,上限35%)"))))))
A202: 46232 | B202: 松芝股份 | C202: 002454 | D202: 否 | E202: 3.788 | F202: 4.87 | G202: 100 | H202: 4.595 | I202: 4.86 | J202: 1944 | K202: 1838 | L202: 106 | M202: 0.057671 | N202: 0.091219 | AI202: 无
A203: 46232 | B203: 三力士 | C203: 002224 | D203: 否 | F203: 2026-07-27 | G203: 0 | H203: 3.287 | I203: 3.45 | J203: 1035 | K203: 986.1 | L203: 48.9 | M203: 0.049589 | N203: 0.048566 | T203: 已清仓 | AI203: 无
A204: 46232 | B204: 贵绳股份 | C204: 600992 | D204: 否 | E204: 9.193 | F204: 9.3 | G204: 300 | H204: 9.321 | I204: 9.34 | J204: 1868 | K204: 1864.2 | L204: 3.8 | M204: 0.002038 | N204: 0.087653 | AI204: 无
A205: 46232 | B205: 拱东医疗 | C205: 605369 | D205: 否 | F205: 2026-07-27 | G205: 0 | H205: 15.33 | I205: 15.94 | J205: 3188 | K205: 3066 | L205: 122 | M205: 0.039791 | N205: 0.149592 | T205: 已清仓 | AI205: 无
A206: 46232 | B206: 沃华医药 | C206: 002107 | D206: 否 | E206: 5.975 | F206: 6.05 | G206: 400 | H206: 6.006 | I206: 6.04 | J206: 1208 | K206: 1201.2 | L206: 6.8 | M206: 0.005661 | N206: 0.056683 | AI206: 无
A207: 46232 | B207: 日上集团 | C207: 002593 | D207: 否 | E207: 4.195 | F207: 4.28 | G207: 200 | H207: 4.196 | I207: 4.26 | J207: 852 | K207: 839.2 | L207: 12.8 | M207: 0.015253 | N207: 0.039979 | AI207: 无
A208: 46232 | B208: 东风股份 | C208: 600006 | D208: 是 | E208: 8.711 | F208: 5.67 | G208: 100 | H208: 8.711 | I208: 5.65 | J208: 565 | K208: 871.1 | L208: -306.1 | M208: -0.351395 | N208: 0.026512 | AI208: 无
A209: 46232 | B209: 台华新材 | C209: 603055 | D209: 否 | E209: 8.31 | F209: 8.62 | G209: 100 | H209: 8.311 | I209: 8.54 | J209: 854 | K209: 831.1 | L209: 22.9 | M209: 0.027554 | N209: 0.040073 | AI209: 无
A210: 46232 | B210: 亚太药业 | C210: 002370 | D210: 否 | F210: 46230 | G210: 0 | H210: 4.625 | I210: 4.79 | J210: 0 | K210: 0 | L210: 0 | M210: 0 | N210: 0 | AI210: 无
A211: 46233.485 | B211: 松芝股份 | C211: 002454 | D211: 否 | E211: 3.788 | F211: 4.87 | G211: 100 | H211: 3.788 | I211: 4.87 | AI211: 无
A212: 46233.485 | B212: 三力士 | C212: 002224 | D212: 否 | F212: 2026-07-24 | G212: 0 | H212: 2.995 | I212: 3.46 | T212: 已清仓 | AI212: 无
A213: 46233.485 | B213: 拱东医疗 | C213: 605369 | D213: 否 | F213: 2026-07-27 | G213: 0 | H213: 14.78 | I213: 15.94 | T213: 已清仓 | AI213: 无
A214: 46233.485 | B214: 台华新材 | C214: 603055 | D214: 否 | E214: 8.31 | F214: 8.62 | G214: 100 | H214: 8.31 | I214: 8.64 | AI214: 无
A215: 46233.485 | B215: 日上集团 | C215: 002593 | D215: 否 | E215: 4.195 | F215: 4.28 | G215: 200 | H215: 4.195 | I215: 4.26 | AI215: 无
A216: 46233.485 | B216: 沃华医药 | C216: 002107 | D216: 否 | E216: 5.975 | F216: 6.05 | G216: 400 | H216: 6.005 | I216: 5.98 | AI216: 无
A217: 46233.485 | B217: 贵绳股份 | C217: 600992 | D217: 否 | E217: 9.193 | F217: 9.3 | G217: 300 | H217: 9.32 | I217: 9.08 | AI217: 无
A218: 46233.485 | B218: 东风股份 | C218: 600006 | D218: 是 | E218: 8.711 | F218: 5.67 | G218: 100 | H218: 8.711 | I218: 5.74 | AI218: 无
A219: 46233.595 | B219: 松芝股份 | C219: 002454 | D219: 否 | E219: 3.788 | F219: 4.87 | G219: 100 | H219: 3.788 | I219: 4.87 | J219: =IF(A219="","",G219*I219) -> 487 | K219: =IF(A219="","",G219*H219) -> 378.8 | L219: =IF(OR(A219="",J219="",K219=""),"",J219-K219) -> 108.2 | M219: =IFERROR((I219-H219)/H219,0) -> 0.28563886 | N219: =IFERROR(J219/INDEX(账户总表!$B:$B,MATCH($A219,账户总表!$A:$A,0)),0) -> 0 | Q219: =IF($A219="","",IF(AND(I219>0,P219>0,I219<=P219),"是","否")) -> 否 | V219: =IF($A219="","",IF(OR(AND(O219>0,I219<O219),AND(T219="False",S219<0.8)),"是","否")) -> 否 | X219: =IF($A219="","",IF(AND(R219<60%,S219>0.8,T219="True",U219="一卖"),"是","否")) -> 否 | Y219: =IF($A219="","",IF(D219="是","否",IF(N219>LOOKUP(2,1/(账户总表!$A:$A<>""),账户总表!$O:$O),"是","否"))) -> 否 | Z219: =IF($A219="","",IF(M219>=0,"盈利","亏损")) -> 盈利 | AA219: =IF($A219="","",IFERROR(INDEX(账户总表!$B:$B,MATCH($A219,账户总表!$A:$A,0))*INDEX(账户总表!$O:$O,MATCH($A219,账户总表!$A:$A,0)),0)) -> 0 | AB219: =IF($A219="","",IFERROR(MAX(0,AA219-J219),0)) -> 0 | AC219: =IF($A219="","",IF(I219>0,IFERROR(FLOOR(AB219/I219,100),0),0)) -> 0 | AD219: =IF($A219="","",IF(N219>LOOKUP(2,1/(INT(账户总表!$A$2:$A$100)=INT($A219)),账户总表!$O$2:$O$100),"超限","合规")) -> 合规 | AE219: =IF($A219="","",IFERROR((I219-P219)/I219,0)) -> 1 | AF219: =IF($A219="","",IFERROR(MAX(0,(I219-P219)*G219),0)) -> 487 | AG219: =IF($A219="","",IF(COUNTIFS(候选池!$C$2:$C$201,C219,候选池!$K$2:$K$201,"核心池")>0,"核心池","否")) -> 否 | AH219: =IF(A219="","",IF(OR(J219="",K219="",K219=0),"",IF((J219-K219)/K219<0.05,"不可加仓(无浮盈护垫)",IF(N219>0.6,"不可加仓(超三买上限)",IF(N219>0.5,"可加仓(三买区,上限60%)",IF(N219>0.35,"可加仓(二买区,上限50%)","可加仓(一买区,上限35%)")))))) -> 可加仓(一买区,上限35%) | AI219: 无
A220: 46233.595 | B220: 三力士 | C220: 002224 | D220: 否 | F220: 2026-07-24 | G220: 0 | H220: 2.995 | I220: 3.42 | J220: =IF(A220="","",G220*I220) -> 0 | K220: =IF(A220="","",G220*H220) -> 0 | L220: =IF(OR(A220="",J220="",K220=""),"",J220-K220) -> 0 | M220: =IFERROR((I220-H220)/H220,0) -> 0.14190317 | N220: =IFERROR(J220/INDEX(账户总表!$B:$B,MATCH($A220,账户总表!$A:$A,0)),0) -> 0 | Q220: =IF($A220="","",IF(AND(I220>0,P220>0,I220<=P220),"是","否")) -> 否 | T220: 已清仓 | V220: =IF($A220="","",IF(OR(AND(O220>0,I220<O220),AND(T220="False",S220<0.8)),"是","否")) -> 否 | X220: =IF($A220="","",IF(AND(R220<60%,S220>0.8,T220="True",U220="一卖"),"是","否")) -> 否 | Y220: =IF($A220="","",IF(D220="是","否",IF(N220>LOOKUP(2,1/(账户总表!$A:$A<>""),账户总表!$O:$O),"是","否"))) -> 否 | Z220: =IF($A220="","",IF(M220>=0,"盈利","亏损")) -> 盈利 | AA220: =IF($A220="","",IFERROR(INDEX(账户总表!$B:$B,MATCH($A220,账户总表!$A:$A,0))*INDEX(账户总表!$O:$O,MATCH($A220,账户总表!$A:$A,0)),0)) -> 0 | AB220: =IF($A220="","",IFERROR(MAX(0,AA220-J220),0)) -> 0 | AC220: =IF($A220="","",IF(I220>0,IFERROR(FLOOR(AB220/I220,100),0),0)) -> 0 | AD220: =IF($A220="","",IF(N220>LOOKUP(2,1/(INT(账户总表!$A$2:$A$100)=INT($A220)),账户总表!$O$2:$O$100),"超限","合规")) -> 合规 | AE220: =IF($A220="","",IFERROR((I220-P220)/I220,0)) -> 1 | AF220: =IF($A220="","",IFERROR(MAX(0,(I220-P220)*G220),0)) -> 0 | AG220: =IF($A220="","",IF(COUNTIFS(候选池!$C$2:$C$201,C220,候选池!$K$2:$K$201,"核心池")>0,"核心池","否")) -> 否 | AH220: =IF(A220="","",IF(OR(J220="",K220="",K220=0),"",IF((J220-K220)/K220<0.05,"不可加仓(无浮盈护垫)",IF(N220>0.6,"不可加仓(超三买上限)",IF(N220>0.5,"可加仓(三买区,上限60%)",IF(N220>0.35,"可加仓(二买区,上限50%)","可加仓(一买区,上限35%)")))))) | AI220: 无
A221: 46233.595 | B221: 拱东医疗 | C221: 605369 | D221: 否 | F221: 2026-07-27 | G221: 0 | H221: 14.78 | I221: 15.94 | J221: =IF(A221="","",G221*I221) -> 0 | K221: =IF(A221="","",G221*H221) -> 0 | L221: =IF(OR(A221="",J221="",K221=""),"",J221-K221) -> 0 | M221: =IFERROR((I221-H221)/H221,0) -> 0.078484438 | N221: =IFERROR(J221/INDEX(账户总表!$B:$B,MATCH($A221,账户总表!$A:$A,0)),0) -> 0 | Q221: =IF($A221="","",IF(AND(I221>0,P221>0,I221<=P221),"是","否")) -> 否 | T221: 已清仓 | V221: =IF($A221="","",IF(OR(AND(O221>0,I221<O221),AND(T221="False",S221<0.8)),"是","否")) -> 否 | X221: =IF($A221="","",IF(AND(R221<60%,S221>0.8,T221="True",U221="一卖"),"是","否")) -> 否 | Y221: =IF($A221="","",IF(D221="是","否",IF(N221>LOOKUP(2,1/(账户总表!$A:$A<>""),账户总表!$O:$O),"是","否"))) -> 否 | Z221: =IF($A221="","",IF(M221>=0,"盈利","亏损")) -> 盈利 | AA221: =IF($A221="","",IFERROR(INDEX(账户总表!$B:$B,MATCH($A221,账户总表!$A:$A,0))*INDEX(账户总表!$O:$O,MATCH($A221,账户总表!$A:$A,0)),0)) -> 0 | AB221: =IF($A221="","",IFERROR(MAX(0,AA221-J221),0)) -> 0 | AC221: =IF($A221="","",IF(I221>0,IFERROR(FLOOR(AB221/I221,100),0),0)) -> 0 | AD221: =IF($A221="","",IF(N221>LOOKUP(2,1/(INT(账户总表!$A$2:$A$100)=INT($A221)),账户总表!$O$2:$O$100),"超限","合规")) -> 合规 | AE221: =IF($A221="","",IFERROR((I221-P221)/I221,0)) -> 1 | AF221: =IF($A221="","",IFERROR(MAX(0,(I221-P221)*G221),0)) -> 0 | AG221: =IF($A221="","",IF(COUNTIFS(候选池!$C$2:$C$201,C221,候选池!$K$2:$K$201,"核心池")>0,"核心池","否")) -> 否 | AH221: =IF(A221="","",IF(OR(J221="",K221="",K221=0),"",IF((J221-K221)/K221<0.05,"不可加仓(无浮盈护垫)",IF(N221>0.6,"不可加仓(超三买上限)",IF(N221>0.5,"可加仓(三买区,上限60%)",IF(N221>0.35,"可加仓(二买区,上限50%)","可加仓(一买区,上限35%)")))))) | AI221: 无
A222: 46233.595 | B222: 台华新材 | C222: 603055 | D222: 否 | E222: 8.31 | F222: 8.62 | G222: 100 | H222: 8.31 | I222: 8.63 | J222: =IF(A222="","",G222*I222) -> 863 | K222: =IF(A222="","",G222*H222) -> 831 | L222: =IF(OR(A222="",J222="",K222=""),"",J222-K222) -> 32 | M222: =IFERROR((I222-H222)/H222,0) -> 0.038507822 | N222: =IFERROR(J222/INDEX(账户总表!$B:$B,MATCH($A222,账户总表!$A:$A,0)),0) -> 0 | Q222: =IF($A222="","",IF(AND(I222>0,P222>0,I222<=P222),"是","否")) -> 否 | V222: =IF($A222="","",IF(OR(AND(O222>0,I222<O222),AND(T222="False",S222<0.8)),"是","否")) -> 否 | X222: =IF($A222="","",IF(AND(R222<60%,S222>0.8,T222="True",U222="一卖"),"是","否")) -> 否 | Y222: =IF($A222="","",IF(D222="是","否",IF(N222>LOOKUP(2,1/(账户总表!$A:$A<>""),账户总表!$O:$O),"是","否"))) -> 否 | Z222: =IF($A222="","",IF(M222>=0,"盈利","亏损")) -> 盈利 | AA222: =IF($A222="","",IFERROR(INDEX(账户总表!$B:$B,MATCH($A222,账户总表!$A:$A,0))*INDEX(账户总表!$O:$O,MATCH($A222,账户总表!$A:$A,0)),0)) -> 0 | AB222: =IF($A222="","",IFERROR(MAX(0,AA222-J222),0)) -> 0 | AC222: =IF($A222="","",IF(I222>0,IFERROR(FLOOR(AB222/I222,100),0),0)) -> 0 | AD222: =IF($A222="","",IF(N222>LOOKUP(2,1/(INT(账户总表!$A$2:$A$100)=INT($A222)),账户总表!$O$2:$O$100),"超限","合规")) -> 合规 | AE222: =IF($A222="","",IFERROR((I222-P222)/I222,0)) -> 1 | AF222: =IF($A222="","",IFERROR(MAX(0,(I222-P222)*G222),0)) -> 863 | AG222: =IF($A222="","",IF(COUNTIFS(候选池!$C$2:$C$201,C222,候选池!$K$2:$K$201,"核心池")>0,"核心池","否")) -> 否 | AH222: =IF(A222="","",IF(OR(J222="",K222="",K222=0),"",IF((J222-K222)/K222<0.05,"不可加仓(无浮盈护垫)",IF(N222>0.6,"不可加仓(超三买上限)",IF(N222>0.5,"可加仓(三买区,上限60%)",IF(N222>0.35,"可加仓(二买区,上限50%)","可加仓(一买区,上限35%)")))))) -> 不可加仓(无浮盈护垫) | AI222: 无
A223: 46233.595 | B223: 日上集团 | C223: 002593 | D223: 否 | E223: 4.195 | F223: 4.28 | G223: 200 | H223: 4.195 | I223: 4.25 | J223: =IF(A223="","",G223*I223) -> 850 | K223: =IF(A223="","",G223*H223) -> 839 | L223: =IF(OR(A223="",J223="",K223=""),"",J223-K223) -> 11 | M223: =IFERROR((I223-H223)/H223,0) -> 0.013110846 | N223: =IFERROR(J223/INDEX(账户总表!$B:$B,MATCH($A223,账户总表!$A:$A,0)),0) -> 0 | Q223: =IF($A223="","",IF(AND(I223>0,P223>0,I223<=P223),"是","否")) -> 否 | V223: =IF($A223="","",IF(OR(AND(O223>0,I223<O223),AND(T223="False",S223<0.8)),"是","否")) -> 否 | X223: =IF($A223="","",IF(AND(R223<60%,S223>0.8,T223="True",U223="一卖"),"是","否")) -> 否 | Y223: =IF($A223="","",IF(D223="是","否",IF(N223>LOOKUP(2,1/(账户总表!$A:$A<>""),账户总表!$O:$O),"是","否"))) -> 否 | Z223: =IF($A223="","",IF(M223>=0,"盈利","亏损")) -> 盈利 | AA223: =IF($A223="","",IFERROR(INDEX(账户总表!$B:$B,MATCH($A223,账户总表!$A:$A,0))*INDEX(账户总表!$O:$O,MATCH($A223,账户总表!$A:$A,0)),0)) -> 0 | AB223: =IF($A223="","",IFERROR(MAX(0,AA223-J223),0)) -> 0 | AC223: =IF($A223="","",IF(I223>0,IFERROR(FLOOR(AB223/I223,100),0),0)) -> 0 | AD223: =IF($A223="","",IF(N223>LOOKUP(2,1/(INT(账户总表!$A$2:$A$100)=INT($A223)),账户总表!$O$2:$O$100),"超限","合规")) -> 合规 | AE223: =IF($A223="","",IFERROR((I223-P223)/I223,0)) -> 1 | AF223: =IF($A223="","",IFERROR(MAX(0,(I223-P223)*G223),0)) -> 850 | AG223: =IF($A223="","",IF(COUNTIFS(候选池!$C$2:$C$201,C223,候选池!$K$2:$K$201,"核心池")>0,"核心池","否")) -> 否 | AH223: =IF(A223="","",IF(OR(J223="",K223="",K223=0),"",IF((J223-K223)/K223<0.05,"不可加仓(无浮盈护垫)",IF(N223>0.6,"不可加仓(超三买上限)",IF(N223>0.5,"可加仓(三买区,上限60%)",IF(N223>0.35,"可加仓(二买区,上限50%)","可加仓(一买区,上限35%)")))))) -> 不可加仓(无浮盈护垫) | AI223: 无
A224: 46233.595 | B224: 沃华医药 | C224: 002107 | D224: 否 | E224: 5.975 | F224: 6.05 | G224: 400 | H224: 6.005 | I224: 5.95 | J224: =IF(A224="","",G224*I224) -> 2380 | K224: =IF(A224="","",G224*H224) -> 2402 | L224: =IF(OR(A224="",J224="",K224=""),"",J224-K224) -> -22 | M224: =IFERROR((I224-H224)/H224,0) -> -0.0091590341 | N224: =IFERROR(J224/INDEX(账户总表!$B:$B,MATCH($A224,账户总表!$A:$A,0)),0) -> 0 | Q224: =IF($A224="","",IF(AND(I224>0,P224>0,I224<=P224),"是","否")) -> 否 | V224: =IF($A224="","",IF(OR(AND(O224>0,I224<O224),AND(T224="False",S224<0.8)),"是","否")) -> 否 | X224: =IF($A224="","",IF(AND(R224<60%,S224>0.8,T224="True",U224="一卖"),"是","否")) -> 否 | Y224: =IF($A224="","",IF(D224="是","否",IF(N224>LOOKUP(2,1/(账户总表!$A:$A<>""),账户总表!$O:$O),"是","否"))) -> 否 | Z224: =IF($A224="","",IF(M224>=0,"盈利","亏损")) -> 亏损 | AA224: =IF($A224="","",IFERROR(INDEX(账户总表!$B:$B,MATCH($A224,账户总表!$A:$A,0))*INDEX(账户总表!$O:$O,MATCH($A224,账户总表!$A:$A,0)),0)) -> 0 | AB224: =IF($A224="","",IFERROR(MAX(0,AA224-J224),0)) -> 0 | AC224: =IF($A224="","",IF(I224>0,IFERROR(FLOOR(AB224/I224,100),0),0)) -> 0 | AD224: =IF($A224="","",IF(N224>LOOKUP(2,1/(INT(账户总表!$A$2:$A$100)=INT($A224)),账户总表!$O$2:$O$100),"超限","合规")) -> 合规 | AE224: =IF($A224="","",IFERROR((I224-P224)/I224,0)) -> 1 | AF224: =IF($A224="","",IFERROR(MAX(0,(I224-P224)*G224),0)) -> 2380 | AG224: =IF($A224="","",IF(COUNTIFS(候选池!$C$2:$C$201,C224,候选池!$K$2:$K$201,"核心池")>0,"核心池","否")) -> 否 | AH224: =IF(A224="","",IF(OR(J224="",K224="",K224=0),"",IF((J224-K224)/K224<0.05,"不可加仓(无浮盈护垫)",IF(N224>0.6,"不可加仓(超三买上限)",IF(N224>0.5,"可加仓(三买区,上限60%)",IF(N224>0.35,"可加仓(二买区,上限50%)","可加仓(一买区,上限35%)")))))) -> 不可加仓(无浮盈护垫) | AI224: 200
A225: 46233.595 | B225: 贵绳股份 | C225: 600992 | D225: 否 | E225: 9.193 | F225: 9.3 | G225: 300 | H225: 9.32 | I225: 8.97 | J225: =IF(A225="","",G225*I225) -> 2691 | K225: =IF(A225="","",G225*H225) -> 2796 | L225: =IF(OR(A225="",J225="",K225=""),"",J225-K225) -> -105 | M225: =IFERROR((I225-H225)/H225,0) -> -0.037553648 | N225: =IFERROR(J225/INDEX(账户总表!$B:$B,MATCH($A225,账户总表!$A:$A,0)),0) -> 0 | Q225: =IF($A225="","",IF(AND(I225>0,P225>0,I225<=P225),"是","否")) -> 否 | V225: =IF($A225="","",IF(OR(AND(O225>0,I225<O225),AND(T225="False",S225<0.8)),"是","否")) -> 否 | X225: =IF($A225="","",IF(AND(R225<60%,S225>0.8,T225="True",U225="一卖"),"是","否")) -> 否 | Y225: =IF($A225="","",IF(D225="是","否",IF(N225>LOOKUP(2,1/(账户总表!$A:$A<>""),账户总表!$O:$O),"是","否"))) -> 否 | Z225: =IF($A225="","",IF(M225>=0,"盈利","亏损")) -> 亏损 | AA225: =IF($A225="","",IFERROR(INDEX(账户总表!$B:$B,MATCH($A225,账户总表!$A:$A,0))*INDEX(账户总表!$O:$O,MATCH($A225,账户总表!$A:$A,0)),0)) -> 0 | AB225: =IF($A225="","",IFERROR(MAX(0,AA225-J225),0)) -> 0 | AC225: =IF($A225="","",IF(I225>0,IFERROR(FLOOR(AB225/I225,100),0),0)) -> 0 | AD225: =IF($A225="","",IF(N225>LOOKUP(2,1/(INT(账户总表!$A$2:$A$100)=INT($A225)),账户总表!$O$2:$O$100),"超限","合规")) -> 合规 | AE225: =IF($A225="","",IFERROR((I225-P225)/I225,0)) -> 1 | AF225: =IF($A225="","",IFERROR(MAX(0,(I225-P225)*G225),0)) -> 2691 | AG225: =IF($A225="","",IF(COUNTIFS(候选池!$C$2:$C$201,C225,候选池!$K$2:$K$201,"核心池")>0,"核心池","否")) -> 否 | AH225: =IF(A225="","",IF(OR(J225="",K225="",K225=0),"",IF((J225-K225)/K225<0.05,"不可加仓(无浮盈护垫)",IF(N225>0.6,"不可加仓(超三买上限)",IF(N225>0.5,"可加仓(三买区,上限60%)",IF(N225>0.35,"可加仓(二买区,上限50%)","可加仓(一买区,上限35%)")))))) -> 不可加仓(无浮盈护垫) | AI225: 无
A226: 46233.595 | B226: 东风股份 | C226: 600006 | D226: 是 | E226: 8.711 | F226: 5.67 | G226: 100 | H226: 8.711 | I226: 5.74 | J226: =IF(A226="","",G226*I226) -> 574 | K226: =IF(A226="","",G226*H226) -> 871.1 | L226: =IF(OR(A226="",J226="",K226=""),"",J226-K226) -> -297.1 | M226: =IFERROR((I226-H226)/H226,0) -> -0.34106302 | N226: =IFERROR(J226/INDEX(账户总表!$B:$B,MATCH($A226,账户总表!$A:$A,0)),0) -> 0 | Q226: =IF($A226="","",IF(AND(I226>0,P226>0,I226<=P226),"是","否")) -> 否 | V226: =IF($A226="","",IF(OR(AND(O226>0,I226<O226),AND(T226="False",S226<0.8)),"是","否")) -> 否 | X226: =IF($A226="","",IF(AND(R226<60%,S226>0.8,T226="True",U226="一卖"),"是","否")) -> 否 | Y226: =IF($A226="","",IF(D226="是","否",IF(N226>LOOKUP(2,1/(账户总表!$A:$A<>""),账户总表!$O:$O),"是","否"))) -> 否 | Z226: =IF($A226="","",IF(M226>=0,"盈利","亏损")) -> 亏损 | AA226: =IF($A226="","",IFERROR(INDEX(账户总表!$B:$B,MATCH($A226,账户总表!$A:$A,0))*INDEX(账户总表!$O:$O,MATCH($A226,账户总表!$A:$A,0)),0)) -> 0 | AB226: =IF($A226="","",IFERROR(MAX(0,AA226-J226),0)) -> 0 | AC226: =IF($A226="","",IF(I226>0,IFERROR(FLOOR(AB226/I226,100),0),0)) -> 0 | AD226: =IF($A226="","",IF(N226>LOOKUP(2,1/(INT(账户总表!$A$2:$A$100)=INT($A226)),账户总表!$O$2:$O$100),"超限","合规")) -> 合规 | AE226: =IF($A226="","",IFERROR((I226-P226)/I226,0)) -> 1 | AF226: =IF($A226="","",IFERROR(MAX(0,(I226-P226)*G226),0)) -> 574 | AG226: =IF($A226="","",IF(COUNTIFS(候选池!$C$2:$C$201,C226,候选池!$K$2:$K$201,"核心池")>0,"核心池","否")) -> 否 | AH226: =IF(A226="","",IF(OR(J226="",K226="",K226=0),"",IF((J226-K226)/K226<0.05,"不可加仓(无浮盈护垫)",IF(N226>0.6,"不可加仓(超三买上限)",IF(N226>0.5,"可加仓(三买区,上限60%)",IF(N226>0.35,"可加仓(二买区,上限50%)","可加仓(一买区,上限35%)")))))) -> 不可加仓(无浮盈护垫) | AI226: 无
A227: 46236 | B227: 松芝股份 | C227: 002454 | D227: 否 | E227: 3.788 | F227: 4.87 | G227: 100 | H227: 3.788 | I227: 4.87 | J227: =IF(A227="","",G227*I227) -> 487 | K227: =IF(A227="","",G227*H227) -> 378.8 | L227: =IF(OR(A227="",J227="",K227=""),"",J227-K227) -> 108.2 | M227: =IFERROR((I227-H227)/H227,0) -> 0.28563886 | N227: =IFERROR(J227/INDEX(账户总表!$B:$B,MATCH($A227,账户总表!$A:$A,0)),0) -> 0 | Q227: =IF($A227="","",IF(AND(I227>0,P227>0,I227<=P227),"是","否")) -> 否 | V227: =IF($A227="","",IF(OR(AND(O227>0,I227<O227),AND(T227="False",S227<0.8)),"是","否")) -> 否 | X227: =IF($A227="","",IF(AND(R227<60%,S227>0.8,T227="True",U227="一卖"),"是","否")) -> 否 | Y227: =IF($A227="","",IF(D227="是","否",IF(N227>LOOKUP(2,1/(账户总表!$A:$A<>""),账户总表!$O:$O),"是","否"))) -> 否 | Z227: =IF($A227="","",IF(M227>=0,"盈利","亏损")) -> 盈利 | AA227: =IF($A227="","",IFERROR(INDEX(账户总表!$B:$B,MATCH($A227,账户总表!$A:$A,0))*INDEX(账户总表!$O:$O,MATCH($A227,账户总表!$A:$A,0)),0)) -> 0 | AB227: =IF($A227="","",IFERROR(MAX(0,AA227-J227),0)) -> 0 | AC227: =IF($A227="","",IF(I227>0,IFERROR(FLOOR(AB227/I227,100),0),0)) -> 0 | AD227: =IF($A227="","",IF(N227>LOOKUP(2,1/(账户总表!$A:$A<>""),账户总表!$O:$O),"超限","合规")) -> 合规 | AE227: =IF($A227="","",IFERROR((I227-P227)/I227,0)) -> 1 | AF227: =IF($A227="","",IFERROR(MAX(0,(I227-P227)*G227),0)) -> 487 | AG227: =IF($A227="","",IF(COUNTIFS(候选池!$C$2:$C$201,C227,候选池!$K$2:$K$201,"核心池")>0,"核心池","否")) -> 否 | AH227: =IF(A227="","",IF(OR(J227="",K227="",K227=0),"",IF((J227-K227)/K227<0.05,"不可加仓(无浮盈护垫)",IF(N227>0.6,"不可加仓(超三买上限)",IF(N227>0.5,"可加仓(三买区,上限60%)",IF(N227>0.35,"可加仓(二买区,上限50%)","可加仓(一买区,上限35%)")))))) -> 可加仓(一买区,上限35%) | AI227: 无
A228: 46236 | B228: 台华新材 | C228: 603055 | D228: 否 | E228: 8.31 | F228: 8.62 | G228: 100 | H228: 8.31 | I228: 8.61 | J228: =IF(A228="","",G228*I228) -> 861 | K228: =IF(A228="","",G228*H228) -> 831 | L228: =IF(OR(A228="",J228="",K228=""),"",J228-K228) -> 30 | M228: =IFERROR((I228-H228)/H228,0) -> 0.036101083 | N228: =IFERROR(J228/INDEX(账户总表!$B:$B,MATCH($A228,账户总表!$A:$A,0)),0) -> 0 | Q228: =IF($A228="","",IF(AND(I228>0,P228>0,I228<=P228),"是","否")) -> 否 | V228: =IF($A228="","",IF(OR(AND(O228>0,I228<O228),AND(T228="False",S228<0.8)),"是","否")) -> 否 | X228: =IF($A228="","",IF(AND(R228<60%,S228>0.8,T228="True",U228="一卖"),"是","否")) -> 否 | Y228: =IF($A228="","",IF(D228="是","否",IF(N228>LOOKUP(2,1/(账户总表!$A:$A<>""),账户总表!$O:$O),"是","否"))) -> 否 | Z228: =IF($A228="","",IF(M228>=0,"盈利","亏损")) -> 盈利 | AA228: =IF($A228="","",IFERROR(INDEX(账户总表!$B:$B,MATCH($A228,账户总表!$A:$A,0))*INDEX(账户总表!$O:$O,MATCH($A228,账户总表!$A:$A,0)),0)) -> 0 | AB228: =IF($A228="","",IFERROR(MAX(0,AA228-J228),0)) -> 0 | AC228: =IF($A228="","",IF(I228>0,IFERROR(FLOOR(AB228/I228,100),0),0)) -> 0 | AD228: =IF($A228="","",IF(N228>LOOKUP(2,1/(账户总表!$A:$A<>""),账户总表!$O:$O),"超限","合规")) -> 合规 | AE228: =IF($A228="","",IFERROR((I228-P228)/I228,0)) -> 1 | AF228: =IF($A228="","",IFERROR(MAX(0,(I228-P228)*G228),0)) -> 861 | AG228: =IF($A228="","",IF(COUNTIFS(候选池!$C$2:$C$201,C228,候选池!$K$2:$K$201,"核心池")>0,"核心池","否")) -> 否 | AH228: =IF(A228="","",IF(OR(J228="",K228="",K228=0),"",IF((J228-K228)/K228<0.05,"不可加仓(无浮盈护垫)",IF(N228>0.6,"不可加仓(超三买上限)",IF(N228>0.5,"可加仓(三买区,上限60%)",IF(N228>0.35,"可加仓(二买区,上限50%)","可加仓(一买区,上限35%)")))))) -> 不可加仓(无浮盈护垫) | AI228: 无
A229: 46236 | B229: 日上集团 | C229: 002593 | D229: 否 | E229: 4.195 | F229: 4.28 | G229: 200 | H229: 4.195 | I229: 4.27 | J229: =IF(A229="","",G229*I229) -> 854 | K229: =IF(A229="","",G229*H229) -> 839 | L229: =IF(OR(A229="",J229="",K229=""),"",J229-K229) -> 15 | M229: =IFERROR((I229-H229)/H229,0) -> 0.017878427 | N229: =IFERROR(J229/INDEX(账户总表!$B:$B,MATCH($A229,账户总表!$A:$A,0)),0) -> 0 | Q229: =IF($A229="","",IF(AND(I229>0,P229>0,I229<=P229),"是","否")) -> 否 | V229: =IF($A229="","",IF(OR(AND(O229>0,I229<O229),AND(T229="False",S229<0.8)),"是","否")) -> 否 | X229: =IF($A229="","",IF(AND(R229<60%,S229>0.8,T229="True",U229="一卖"),"是","否")) -> 否 | Y229: =IF($A229="","",IF(D229="是","否",IF(N229>LOOKUP(2,1/(账户总表!$A:$A<>""),账户总表!$O:$O),"是","否"))) -> 否 | Z229: =IF($A229="","",IF(M229>=0,"盈利","亏损")) -> 盈利 | AA229: =IF($A229="","",IFERROR(INDEX(账户总表!$B:$B,MATCH($A229,账户总表!$A:$A,0))*INDEX(账户总表!$O:$O,MATCH($A229,账户总表!$A:$A,0)),0)) -> 0 | AB229: =IF($A229="","",IFERROR(MAX(0,AA229-J229),0)) -> 0 | AC229: =IF($A229="","",IF(I229>0,IFERROR(FLOOR(AB229/I229,100),0),0)) -> 0 | AD229: =IF($A229="","",IF(N229>LOOKUP(2,1/(账户总表!$A:$A<>""),账户总表!$O:$O),"超限","合规")) -> 合规 | AE229: =IF($A229="","",IFERROR((I229-P229)/I229,0)) -> 1 | AF229: =IF($A229="","",IFERROR(MAX(0,(I229-P229)*G229),0)) -> 854 | AG229: =IF($A229="","",IF(COUNTIFS(候选池!$C$2:$C$201,C229,候选池!$K$2:$K$201,"核心池")>0,"核心池","否")) -> 否 | AH229: =IF(A229="","",IF(OR(J229="",K229="",K229=0),"",IF((J229-K229)/K229<0.05,"不可加仓(无浮盈护垫)",IF(N229>0.6,"不可加仓(超三买上限)",IF(N229>0.5,"可加仓(三买区,上限60%)",IF(N229>0.35,"可加仓(二买区,上限50%)","可加仓(一买区,上限35%)")))))) -> 不可加仓(无浮盈护垫) | AI229: 无
A230: 46236 | B230: 沃华医药 | C230: 002107 | D230: 否 | E230: 5.975 | F230: 6.05 | G230: 400 | H230: 5.975 | I230: 6.05 | J230: =IF(A230="","",G230*I230) -> 2420 | K230: =IF(A230="","",G230*H230) -> 2390 | L230: =IF(OR(A230="",J230="",K230=""),"",J230-K230) -> 30 | M230: =IFERROR((I230-H230)/H230,0) -> 0.012552301 | N230: =IFERROR(J230/INDEX(账户总表!$B:$B,MATCH($A230,账户总表!$A:$A,0)),0) -> 0 | Q230: =IF($A230="","",IF(AND(I230>0,P230>0,I230<=P230),"是","否")) -> 否 | V230: =IF($A230="","",IF(OR(AND(O230>0,I230<O230),AND(T230="False",S230<0.8)),"是","否")) -> 否 | X230: =IF($A230="","",IF(AND(R230<60%,S230>0.8,T230="True",U230="一卖"),"是","否")) -> 否 | Y230: =IF($A230="","",IF(D230="是","否",IF(N230>LOOKUP(2,1/(账户总表!$A:$A<>""),账户总表!$O:$O),"是","否"))) -> 否 | Z230: =IF($A230="","",IF(M230>=0,"盈利","亏损")) -> 盈利 | AA230: =IF($A230="","",IFERROR(INDEX(账户总表!$B:$B,MATCH($A230,账户总表!$A:$A,0))*INDEX(账户总表!$O:$O,MATCH($A230,账户总表!$A:$A,0)),0)) -> 0 | AB230: =IF($A230="","",IFERROR(MAX(0,AA230-J230),0)) -> 0 | AC230: =IF($A230="","",IF(I230>0,IFERROR(FLOOR(AB230/I230,100),0),0)) -> 0 | AD230: =IF($A230="","",IF(N230>LOOKUP(2,1/(账户总表!$A:$A<>""),账户总表!$O:$O),"超限","合规")) -> 合规 | AE230: =IF($A230="","",IFERROR((I230-P230)/I230,0)) -> 1 | AF230: =IF($A230="","",IFERROR(MAX(0,(I230-P230)*G230),0)) -> 2420 | AG230: =IF($A230="","",IF(COUNTIFS(候选池!$C$2:$C$201,C230,候选池!$K$2:$K$201,"核心池")>0,"核心池","否")) -> 否 | AH230: =IF(A230="","",IF(OR(J230="",K230="",K230=0),"",IF((J230-K230)/K230<0.05,"不可加仓(无浮盈护垫)",IF(N230>0.6,"不可加仓(超三买上限)",IF(N230>0.5,"可加仓(三买区,上限60%)",IF(N230>0.35,"可加仓(二买区,上限50%)","可加仓(一买区,上限35%)")))))) -> 不可加仓(无浮盈护垫) | AI230: 无
A231: 46236 | B231: 贵绳股份 | C231: 600992 | D231: 否 | E231: 9.193 | F231: 9.3 | G231: 300 | H231: 9.193 | I231: 9.34 | J231: =IF(A231="","",G231*I231) -> 2802 | K231: =IF(A231="","",G231*H231) -> 2757.9 | L231: =IF(OR(A231="",J231="",K231=""),"",J231-K231) -> 44.1 | M231: =IFERROR((I231-H231)/H231,0) -> 0.015990427 | N231: =IFERROR(J231/INDEX(账户总表!$B:$B,MATCH($A231,账户总表!$A:$A,0)),0) -> 0 | Q231: =IF($A231="","",IF(AND(I231>0,P231>0,I231<=P231),"是","否")) -> 否 | V231: =IF($A231="","",IF(OR(AND(O231>0,I231<O231),AND(T231="False",S231<0.8)),"是","否")) -> 否 | X231: =IF($A231="","",IF(AND(R231<60%,S231>0.8,T231="True",U231="一卖"),"是","否")) -> 否 | Y231: =IF($A231="","",IF(D231="是","否",IF(N231>LOOKUP(2,1/(账户总表!$A:$A<>""),账户总表!$O:$O),"是","否"))) -> 否 | Z231: =IF($A231="","",IF(M231>=0,"盈利","亏损")) -> 盈利 | AA231: =IF($A231="","",IFERROR(INDEX(账户总表!$B:$B,MATCH($A231,账户总表!$A:$A,0))*INDEX(账户总表!$O:$O,MATCH($A231,账户总表!$A:$A,0)),0)) -> 0 | AB231: =IF($A231="","",IFERROR(MAX(0,AA231-J231),0)) -> 0 | AC231: =IF($A231="","",IF(I231>0,IFERROR(FLOOR(AB231/I231,100),0),0)) -> 0 | AD231: =IF($A231="","",IF(N231>LOOKUP(2,1/(账户总表!$A:$A<>""),账户总表!$O:$O),"超限","合规")) -> 合规 | AE231: =IF($A231="","",IFERROR((I231-P231)/I231,0)) -> 1 | AF231: =IF($A231="","",IFERROR(MAX(0,(I231-P231)*G231),0)) -> 2802 | AG231: =IF($A231="","",IF(COUNTIFS(候选池!$C$2:$C$201,C231,候选池!$K$2:$K$201,"核心池")>0,"核心池","否")) -> 否 | AH231: =IF(A231="","",IF(OR(J231="",K231="",K231=0),"",IF((J231-K231)/K231<0.05,"不可加仓(无浮盈护垫)",IF(N231>0.6,"不可加仓(超三买上限)",IF(N231>0.5,"可加仓(三买区,上限60%)",IF(N231>0.35,"可加仓(二买区,上限50%)","可加仓(一买区,上限35%)")))))) -> 不可加仓(无浮盈护垫) | AI231: 无
A232: 46234 | B232: 东风股份 | C232: 600006 | D232: 是 | E232: 8.711 | F232: 5.67 | G232: 100 | H232: 8.711 | I232: 5.7 | J232: =IF(A232="","",G232*I232) -> 570 | K232: =IF(A232="","",G232*H232) -> 871.1 | L232: =IF(OR(A232="",J232="",K232=""),"",J232-K232) -> -301.1 | M232: =IFERROR((I232-H232)/H232,0) -> -0.34565492 | N232: =IFERROR(J232/INDEX(账户总表!$B:$B,MATCH($A232,账户总表!$A:$A,0)),0) -> 0 | Q232: =IF($A232="","",IF(AND(I232>0,P232>0,I232<=P232),"是","否")) -> 否 | V232: =IF($A232="","",IF(OR(AND(O232>0,I232<O232),AND(T232="False",S232<0.8)),"是","否")) -> 否 | X232: =IF($A232="","",IF(AND(R232<60%,S232>0.8,T232="True",U232="一卖"),"是","否")) -> 否 | Y232: =IF($A232="","",IF(D232="是","否",IF(N232>LOOKUP(2,1/(账户总表!$A:$A<>""),账户总表!$O:$O),"是","否"))) -> 否 | Z232: =IF($A232="","",IF(M232>=0,"盈利","亏损")) -> 亏损 | AA232: =IF($A232="","",IFERROR(INDEX(账户总表!$B:$B,MATCH($A232,账户总表!$A:$A,0))*INDEX(账户总表!$O:$O,MATCH($A232,账户总表!$A:$A,0)),0)) -> 0 | AB232: =IF($A232="","",IFERROR(MAX(0,AA232-J232),0)) -> 0 | AC232: =IF($A232="","",IF(I232>0,IFERROR(FLOOR(AB232/I232,100),0),0)) -> 0 | AD232: =IF($A232="","",IF(N232>LOOKUP(2,1/(账户总表!$A:$A<>""),账户总表!$O:$O),"超限","合规")) -> 合规 | AE232: =IF($A232="","",IFERROR((I232-P232)/I232,0)) -> 1 | AF232: =IF($A232="","",IFERROR(MAX(0,(I232-P232)*G232),0)) -> 570 | AG232: =IF($A232="","",IF(COUNTIFS(候选池!$C$2:$C$201,C232,候选池!$K$2:$K$201,"核心池")>0,"核心池","否")) -> 否 | AH232: =IF(A232="","",IF(OR(J232="",K232="",K232=0),"",IF((J232-K232)/K232<0.05,"不可加仓(无浮盈护垫)",IF(N232>0.6,"不可加仓(超三买上限)",IF(N232>0.5,"可加仓(三买区,上限60%)",IF(N232>0.35,"可加仓(二买区,上限50%)","可加仓(一买区,上限35%)")))))) -> 不可加仓(无浮盈护垫) | AI232: 无
A233: 46236 | B233: 东风股份 | C233: 601515 | D233: 否 | G233: 100 | H233: 8.711 | I233: 5.7

Sheet 候选池
A1: 日期 | B1: 股票名称 | C1: 代码 | D1: 当前价 Price | E1: 信号价 SignalPrice | F1: 买点低点 BuyPointLow | G1: ratio | H1: DL_P | I1: valid | J1: SignalType | K1: 分层Tier | L1: 是否确认信号 ConfirmedSignal | M1: 是否未追价 NotChasing | N1: 单股上限 SingleStockCap | O1: 最大持仓金额 MaxPositionValue | P1: 理论最大股数 RawShares | Q1: 最大可买股数 MaxShares | R1: 最小可买股数 MinShares | S1: 计划买入股数 BuyShares | T1: 计划买入金额 | U1: 新增仓位占比 | V1: 买入后总仓位 | W1: 是否满足总仓位上限 | X1: 止损价 StopPrice | Y1: 失效条件 InvalidationCondition | Z1: 是否需要转入 | AA1: 最低转入金额 | AB1: 建议转入金额 | AC1: 最终是否可买 Buy | AD1: 不可买原因 | AE1: 备注 | AF1: 1手所需资金 | AG1: 1手/总资产比 | AH1: 单股上限金额 | AI1: 1手超单股上限 | AJ1: 合规所需总资产 | AK1: 需转入资金才合规 | AL1: 已有持仓 | AM1: 当前持仓仓位 | AN1: 买入1手后仓位 | AO1: 买后是否超限 | AP1: 有效持仓数检查 | AQ1: 核心池加仓结论 | AR1: 阻断原因 | AS1: 连续核心池天数 | AT1: 信号标注 | AU1: 幼儿目标适配
A2: 46308 | B2: 梦百合 | C2: 603313 | D2: 6.39 | E2: 6.39 | F2: 6.07 | G2: 0.17689994 | H2: 0.97609237 | I2: True | J2: 一买
A3: 46308 | B3: XD快克智 | C3: 603203 | D3: 37.44 | E3: 37.44 | F3: 35.57 | G3: 0.12340942 | H3: 0.95178947 | I3: True | J3: 一买
A4: 46308 | B4: 时空科技 | C4: 605178 | D4: 61.5 | E4: 61.5 | F4: 58.42 | G4: 0.19877686 | H4: 0.9498231 | I4: True | J4: 一买
A5: 46308 | B5: 朗迪集团 | C5: 603726 | D5: 22.51 | E5: 22.51 | F5: 21.38 | G5: 0.14901685 | H5: 0.94120309 | I5: True | J5: 一买
A6: 46308 | B6: 展鹏科技 | C6: 603488 | D6: 7.52 | E6: 7.52 | F6: 7.14 | G6: 0.19208524 | H6: 0.93772433 | I6: True | J6: 一买
A7: 46308 | B7: 衢州东峰 | C7: 601515 | D7: 3.1 | E7: 3.1 | F7: 2.94 | G7: 0.15195644 | H7: 0.93207611 | I7: True | J7: 一买
A8: 46308 | B8: 泰晶科技 | C8: 603738 | D8: 29.31 | E8: 29.31 | F8: 27.84 | G8: 0.19221458 | H8: 0.93015061 | I8: True | J8: 一买
A9: 46308 | B9: 宏和科技 | C9: 603256 | D9: 111.42 | E9: 111.42 | F9: 105.85 | G9: 0.12580879 | H9: 0.91616375 | I9: True | J9: 一买
A10: 46308 | B10: 环旭电子 | C10: 601231 | D10: 22.5 | E10: 22.5 | F10: 21.38 | G10: 0.15208179 | H10: 0.90798405 | I10: True | J10: 一买
A11: 46308 | B11: 众鑫股份 | C11: 603091 | D11: 45.38 | E11: 45.38 | F11: 43.11 | G11: 0.12984228 | H11: 0.90731745 | I11: True | J11: 一买
A12: 46308 | B12: 晶华新材 | C12: 603683 | D12: 14.22 | E12: 14.22 | F12: 13.51 | G12: 0.18765768 | H12: 0.90530773 | I12: True | J12: 一买
A13: 46308 | B13: 星德胜 | C13: 603344 | D13: 20.87 | E13: 20.87 | F13: 19.83 | G13: 0.11798162 | H13: 0.90296904 | I13: True | J13: 一买
... A120: 46308 | B120: 节能风电 | C120: 601016 | D120: 3.18 | E120: 3.18 | F120: 3.02 | G120: 0.39757933 | H120: 0.82098532 | I120: True | J120: 一买
A121: 46308 | B121: 吉比特 | C121: 603444 | D121: 339 | E121: 339 | F121: 322.05 | G121: 0.38318175 | H121: 0.82055568 | I121: True | J121: 一买 | AE121: 需转入20523元

Sheet 交易记录
A1: 交易日期 | B1: 股票名称 | C1: 代码 | D1: 买卖方向 | E1: 信号类型 | F1: 成交价格 | G1: 成交股数 | H1: 成交金额 | I1: 手续费 | J1: 成交后持仓股数 | K1: 成交后仓位占比 | L1: 止损价 | M1: 失效条件 | N1: 执行动作是否合规 | O1: 交易原因 | P1: 结果分类 | Q1: 平仓日期 | R1: 平仓收益率 | S1: 是否触发止损 | T1: 是否情绪化交易 | U1: 备注 | V1: 买入价 | W1: 止损风险额 | X1: R倍数 | Y1: 累计R | Z1: 连胜/连亏 | AA1: 最大回撤(%)
A2: 2026-01-05 | B2: 亚通精工 | C2: 603190 | D2: 买入 | E2: 一买 | F2: 26.66 | G2: 100 | H2: 2666 | O2: 缠论日线一买 | V2: =IF($A2="","",IF(OR(D2="卖出",D2="分红"),IFERROR(INDEX($F$2:$F1,MATCH(2,1/($C$2:$C1=$C2))),""),"")) | W2: =IF($A2="","",IF(D2="买入",IF(AND(ISNUMBER(L2),L2>0),(F2-L2)*G2,0),0)) -> 0 | X2: 0 | Y2: 0 | Z2: =IF($A2="","",IF(X2>0,"胜1",IF(X2<0,"亏1","平"))) -> 平 | AA2: =IF($A2="","",0) -> 0
A3: 2026-01-12 | B3: 黄河旋风 | C3: 600172 | D3: 买入 | E3: 一买 | F3: 6.19 | G3: 800 | H3: 4952 | O3: 缠论日线一买 | V3: =IF($A3="","",IF(OR(D3="卖出",D3="分红"),IFERROR(INDEX($F$2:$F2,MATCH(2,1/($C$2:$C2=$C3))),""),"")) | W3: =IF($A3="","",IF(D3="买入",IF(AND(ISNUMBER(L3),L3>0),(F3-L3)*G3,0),0)) -> 0 | X3: 0 | Y3: 0 | Z3: =IF($A3="","",IF(X3>0,IF(LEFT(Z2,1)="胜","胜"&VALUE(RIGHT(Z2,LEN(Z2)-1))+1,"胜1"),IF(X3<0,IF(LEFT(Z2,1)="亏","亏"&VALUE(RIGHT(Z2,LEN(Z2)-1))+1,"亏1"),"平"))) -> 平 | AA3: =IF($A3="","",MAX(0,(MAX($Y$2:Y3)-Y3)/MAX(1,MAX($Y$2:Y3)))) -> 0
A4: 2026-01-25 | B4: 亚通精工 | C4: 603190 | D4: 卖出 | E4: 一卖 | F4: 26.193 | G4: 100 | H4: 2619.3 | O4: 缠论30min一卖/止损 | V4: =IF($A4="","",IF(OR(D4="卖出",D4="分红"),IFERROR(INDEX($F$2:$F3,MATCH(2,1/($C$2:$C3=$C4))),""),"")) -> 26.66 | W4: =IF($A4="","",IF(D4="买入",IF(AND(ISNUMBER(L4),L4>0),(F4-L4)*G4,0),0)) -> 0 | X4: -0.350338 | Y4: -0.350338 | Z4: =IF($A4="","",IF(X4>0,IF(LEFT(Z3,1)="胜","胜"&VALUE(RIGHT(Z3,LEN(Z3)-1))+1,"胜1"),IF(X4<0,IF(LEFT(Z3,1)="亏","亏"&VALUE(RIGHT(Z3,LEN(Z3)-1))+1,"亏1"),"平"))) -> 亏1 | AA4: =IF($A4="","",MAX(0,(MAX($Y$2:Y4)-Y4)/MAX(1,MAX($Y$2:Y4)))) -> 0.350338
A5: 2026-01-28 | B5: 黄河旋风 | C5: 600172 | D5: 卖出 | E5: 一卖 | F5: 9.001 | G5: 800 | H5: 7200.8 | O5: 缠论日线一卖/止盈+45% | V5: =IF($A5="","",IF(OR(D5="卖出",D5="分红"),IFERROR(INDEX($F$2:$F4,MATCH(2,1/($C$2:$C4=$C5))),""),"")) -> 6.19 | W5: =IF($A5="","",IF(D5="买入",IF(AND(ISNUMBER(L5),L5>0),(F5-L5)*G5,0),0)) -> 0 | X5: 9.082391 | Y5: 8.732053 | Z5: =IF($A5="","",IF(X5>0,IF(LEFT(Z4,1)="胜","胜"&VALUE(RIGHT(Z4,LEN(Z4)-1))+1,"胜1"),IF(X5<0,IF(LEFT(Z4,1)="亏","亏"&VALUE(RIGHT(Z4,LEN(Z4)-1))+1,"亏1"),"平"))) -> 胜1 | AA5: =IF($A5="","",MAX(0,(MAX($Y$2:Y5)-Y5)/MAX(1,MAX($Y$2:Y5)))) -> 0
A6: 2026-02-03 | B6: 沪电股份 | C6: 002463 | D6: 买入 | E6: 一买 | F6: 78.81 | G6: 300 | H6: 23643 | O6: 缠论日线一买(电子PCB) | V6: =IF($A6="","",IF(OR(D6="卖出",D6="分红"),IFERROR(INDEX($F$2:$F5,MATCH(2,1/($C$2:$C5=$C6))),""),"")) | W6: =IF($A6="","",IF(D6="买入",IF(AND(ISNUMBER(L6),L6>0),(F6-L6)*G6,0),0)) -> 0 | X6: 0 | Y6: 8.732053 | Z6: =IF($A6="","",IF(X6>0,IF(LEFT(Z5,1)="胜","胜"&VALUE(RIGHT(Z5,LEN(Z5)-1))+1,"胜1"),IF(X6<0,IF(LEFT(Z5,1)="亏","亏"&VALUE(RIGHT(Z5,LEN(Z5)-1))+1,"亏1"),"平"))) -> 平 | AA6: =IF($A6="","",MAX(0,(MAX($Y$2:Y6)-Y6)/MAX(1,MAX($Y$2:Y6)))) -> 0
A7: 2026-03-05 | B7: 沪电股份 | C7: 002463 | D7: 卖出 | E7: 做T | F7: 85 | G7: 300 | H7: 25500 | O7: 30min一卖做T | V7: =IF($A7="","",IF(OR(D7="卖出",D7="分红"),IFERROR(INDEX($F$2:$F6,MATCH(2,1/($C$2:$C6=$C7))),""),"")) | W7: =IF($A7="","",IF(D7="买入",IF(AND(ISNUMBER(L7),L7>0),(F7-L7)*G7,0),0)) -> 0 | X7: 1.570867 | Y7: 10.30292 | Z7: =IF($A7="","",IF(X7>0,IF(LEFT(Z6,1)="胜","胜"&VALUE(RIGHT(Z6,LEN(Z6)-1))+1,"胜1"),IF(X7<0,IF(LEFT(Z6,1)="亏","亏"&VALUE(RIGHT(Z6,LEN(Z6)-1))+1,"亏1"),"平"))) -> 胜1 | AA7: =IF($A7="","",MAX(0,(MAX($Y$2:Y7)-Y7)/MAX(1,MAX($Y$2:Y7)))) -> 0
A8: 2026-03-05 | B8: 沪电股份 | C8: 002463 | D8: 买入 | E8: 做T | F8: 83 | G8: 300 | H8: 24900 | O8: 5min一买回补 | V8: =IF($A8="","",IF(OR(D8="卖出",D8="分红"),IFERROR(INDEX($F$2:$F7,MATCH(2,1/($C$2:$C7=$C8))),""),"")) | W8: =IF($A8="","",IF(D8="买入",IF(AND(ISNUMBER(L8),L8>0),(F8-L8)*G8,0),0)) -> 0 | X8: 0 | Y8: 10.30292 | Z8: =IF($A8="","",IF(X8>0,IF(LEFT(Z7,1)="胜","胜"&VALUE(RIGHT(Z7,LEN(Z7)-1))+1,"胜1"),IF(X8<0,IF(LEFT(Z7,1)="亏","亏"&VALUE(RIGHT(Z7,LEN(Z7)-1))+1,"亏1"),"平"))) -> 平 | AA8: =IF($A8="","",MAX(0,(MAX($Y$2:Y8)-Y8)/MAX(1,MAX($Y$2:Y8)))) -> 0
A9: 2026-03-18 | B9: 沪电股份 | C9: 002463 | D9: 卖出 | E9: 做T | F9: 95 | G9: 300 | H9: 28500 | O9: 30min一卖做T | V9: =IF($A9="","",IF(OR(D9="卖出",D9="分红"),IFERROR(INDEX($F$2:$F8,MATCH(2,1/($C$2:$C8=$C9))),""),"")) | W9: =IF($A9="","",IF(D9="买入",IF(AND(ISNUMBER(L9),L9>0),(F9-L9)*G9,0),0)) -> 0 | X9: 2.891566 | Y9: 13.194486 | Z9: =IF($A9="","",IF(X9>0,IF(LEFT(Z8,1)="胜","胜"&VALUE(RIGHT(Z8,LEN(Z8)-1))+1,"胜1"),IF(X9<0,IF(LEFT(Z8,1)="亏","亏"&VALUE(RIGHT(Z8,LEN(Z8)-1))+1,"亏1"),"平"))) -> 胜1 | AA9: =IF($A9="","",MAX(0,(MAX($Y$2:Y9)-Y9)/MAX(1,MAX($Y$2:Y9)))) -> 0
A10: 2026-03-18 | B10: 沪电股份 | C10: 002463 | D10: 买入 | E10: 做T | F10: 93 | G10: 300 | H10: 27900 | O10: 5min一买回补 | V10: =IF($A10="","",IF(OR(D10="卖出",D10="分红"),IFERROR(INDEX($F$2:$F9,MATCH(2,1/($C$2:$C9=$C10))),""),"")) | W10: =IF($A10="","",IF(D10="买入",IF(AND(ISNUMBER(L10),L10>0),(F10-L10)*G10,0),0)) -> 0 | X10: 0 | Y10: 13.194486 | Z10: =IF($A10="","",IF(X10>0,IF(LEFT(Z9,1)="胜","胜"&VALUE(RIGHT(Z9,LEN(Z9)-1))+1,"胜1"),IF(X10<0,IF(LEFT(Z9,1)="亏","亏"&VALUE(RIGHT(Z9,LEN(Z9)-1))+1,"亏1"),"平"))) -> 平 | AA10: =IF($A10="","",MAX(0,(MAX($Y$2:Y10)-Y10)/MAX(1,MAX($Y$2:Y10)))) -> 0
A11: 2026-04-08 | B11: 沪电股份 | C11: 002463 | D11: 卖出 | E11: 一卖 | F11: 101.947 | G11: 300 | H11: 30584.1 | O11: 缠论日线一卖/止盈+29% | V11: =IF($A11="","",IF(OR(D11="卖出",D11="分红"),IFERROR(INDEX($F$2:$F10,MATCH(2,1/($C$2:$C10=$C11))),""),"")) -> 93 | W11: =IF($A11="","",IF(D11="买入",IF(AND(ISNUMBER(L11),L11>0),(F11-L11)*G11,0),0)) -> 0 | X11: 1.924086 | Y11: 15.118572 | Z11: =IF($A11="","",IF(X11>0,IF(LEFT(Z10,1)="胜","胜"&VALUE(RIGHT(Z10,LEN(Z10)-1))+1,"胜1"),IF(X11<0,IF(LEFT(Z10,1)="亏","亏"&VALUE(RIGHT(Z10,LEN(Z10)-1))+1,"亏1"),"平"))) -> 胜1 | AA11: =IF($A11="","",MAX(0,(MAX($Y$2:Y11)-Y11)/MAX(1,MAX($Y$2:Y11)))) -> 0
A12: 2026-04-15 | B12: 长江电力 | C12: 600900 | D12: 买入 | E12: 一买 | F12: 27.983 | G12: 300 | H12: 8394.9 | O12: 缠论日线一买(电力公用) | V12: =IF($A12="","",IF(OR(D12="卖出",D12="分红"),IFERROR(INDEX($F$2:$F11,MATCH(2,1/($C$2:$C11=$C12))),""),"")) | W12: =IF($A12="","",IF(D12="买入",IF(AND(ISNUMBER(L12),L12>0),(F12-L12)*G12,0),0)) -> 0 | X12: 0 | Y12: 15.118572 | Z12: =IF($A12="","",IF(X12>0,IF(LEFT(Z11,1)="胜","胜"&VALUE(RIGHT(Z11,LEN(Z11)-1))+1,"胜1"),IF(X12<0,IF(LEFT(Z11,1)="亏","亏"&VALUE(RIGHT(Z11,LEN(Z11)-1))+1,"亏1"),"平"))) -> 平 | AA12: =IF($A12="","",MAX(0,(MAX($Y$2:Y12)-Y12)/MAX(1,MAX($Y$2:Y12)))) -> 0
A13: 2026-04-22 | B13: 东风股份 | C13: 600006 | D13: 买入 | E13: 一买 | F13: 5.327 | G13: 600 | H13: 3196.2 | O13: 缠论30min一买 | V13: =IF($A13="","",IF(OR(D13="卖出",D13="分红"),IFERROR(INDEX($F$2:$F12,MATCH(2,1/($C$2:$C12=$C13))),""),"")) | W13: =IF($A13="","",IF(D13="买入",IF(AND(ISNUMBER(L13),L13>0),(F13-L13)*G13,0),0)) -> 0 | X13: 0 | Y13: 15.118572 | Z13: =IF($A13="","",IF(X13>0,IF(LEFT(Z12,1)="胜","胜"&VALUE(RIGHT(Z12,LEN(Z12)-1))+1,"胜1"),IF(X13<0,IF(LEFT(Z12,1)="亏","亏"&VALUE(RIGHT(Z12,LEN(Z12)-1))+1,"亏1"),"平"))) -> 平 | AA13: =IF($A13="","",MAX(0,(MAX($Y$2:Y13)-Y13)/MAX(1,MAX($Y$2:Y13)))) -> 0
A14: 2026-05-20 | B14: 东风股份 | C14: 600006 | D14: 卖出 | E14: 一卖 | F14: 5.22 | G14: 600 | H14: 3132 | O14: 缠论30min一卖/止损-2% | V14: =IF($A14="","",IF(OR(D14="卖出",D14="分红"),IFERROR(INDEX($F$2:$F13,MATCH(2,1/($C$2:$C13=$C14))),""),"")) | W14: =IF($A14="","",IF(D14="买入",IF(AND(ISNUMBER(L14),L14>0),(F14-L14)*G14,0),0)) -> 0 | X14: -0.401727 | Y14: 14.716845 | Z14: =IF($A14="","",IF(X14>0,IF(LEFT(Z13,1)="胜","胜"&VALUE(RIGHT(Z13,LEN(Z13)-1))+1,"胜1"),IF(X14<0,IF(LEFT(Z13,1)="亏","亏"&VALUE(RIGHT(Z13,LEN(Z13)-1))+1,"亏1"),"平"))) -> 亏1 | AA14: =IF($A14="","",MAX(0,(MAX($Y$2:Y14)-Y14)/MAX(1,MAX($Y$2:Y14)))) -> 0.026571756
... A17: 2026-07-18 | B17: 万华化学 | C17: 600309 | D17: 买入 | E17: 加仓 | F17: 71.09 | G17: 100 | H17: 7109 | O17: 30min一买加仓 | V17: =IF($A17="","",IF(OR(D17="卖出",D17="分红"),IFERROR(INDEX($F$2:$F16,MATCH(2,1/($C$2:$C16=$C17))),""),"")) | W17: =IF($A17="","",IF(D17="买入",IF(AND(ISNUMBER(L17),L17>0),(F17-L17)*G17,0),0)) -> 0 | X17: 0 | Y17: 15.002733 | Z17: =IF($A17="","",IF(X17>0,IF(LEFT(Z16,1)="胜","胜"&VALUE(RIGHT(Z16,LEN(Z16)-1))+1,"胜1"),IF(X17<0,IF(LEFT(Z16,1)="亏","亏"&VALUE(RIGHT(Z16,LEN(Z16)-1))+1,"亏1"),"平"))) -> 平 | AA17: =IF($A17="","",MAX(0,(MAX($Y$2:Y17)-Y17)/MAX(1,MAX($Y$2:Y17)))) -> 0.0076620332
A18: 2026-07-19 | B18: 隆基绿能 | C18: 601012 | D18: 买入 | E18: 一买 | F18: 11.843 | G18: 400 | H18: 4737.2 | L18: 11.4 | O18: 缠论日+30min共振一买 | V18: =IF($A18="","",IF(OR(D18="卖出",D18="分红"),IFERROR(INDEX($F$2:$F17,MATCH(2,1/($C$2:$C17=$C18))),""),"")) | W18: =IF($A18="","",IF(D18="买入",IF(AND(ISNUMBER(L18),L18>0),(F18-L18)*G18,0),0)) -> 177.2 | X18: 0 | Y18: 15.002733 | Z18: =IF($A18="","",IF(X18>0,IF(LEFT(Z17,1)="胜","胜"&VALUE(RIGHT(Z17,LEN(Z17)-1))+1,"胜1"),IF(X18<0,IF(LEFT(Z17,1)="亏","亏"&VALUE(RIGHT(Z17,LEN(Z17)-1))+1,"亏1"),"平"))) -> 平 | AA18: =IF($A18="","",MAX(0,(MAX($Y$2:Y18)-Y18)/MAX(1,MAX($Y$2:Y18)))) -> 0.0076620332
A19: 2026-03-20 | B19: 沪电股份 | C19: 002463 | D19: 分红 | H19: 50 | O19: 现金分红 | V19: =IF($A19="","",IF(OR(D19="卖出",D19="分红"),IFERROR(INDEX($F$2:$F18,MATCH(2,1/($C$2:$C18=$C19))),""),"")) -> 101.947 | W19: =IF($A19="","",IF(D19="买入",IF(AND(ISNUMBER(L19),L19>0),(F19-L19)*G19,0),0)) -> 0 | X19: 0 | Y19: 15.002733 | Z19: =IF($A19="","",IF(X19>0,IF(LEFT(Z18,1)="胜","胜"&VALUE(RIGHT(Z18,LEN(Z18)-1))+1,"胜1"),IF(X19<0,IF(LEFT(Z18,1)="亏","亏"&VALUE(RIGHT(Z18,LEN(Z18)-1))+1,"亏1"),"平"))) -> 平 | AA19: =IF($A19="","",MAX(0,(MAX($Y$2:Y19)-Y19)/MAX(1,MAX($Y$2:Y19)))) -> 0.0076620332
V20: =IF($A20="","",IF(OR(D20="卖出",D20="分红"),IFERROR(INDEX($F$2:$F19,MATCH(2,1/($C$2:$C19=$C20))),""),"")) | W20: =IF($A20="","",IF(D20="买入",IF(AND(ISNUMBER(L20),L20>0),(F20-L20)*G20,F20*0.08*G20),IF(AND(ISNUMBER(V20),V20>0),IF(AND(ISNUMBER(L20),L20>0),(V20-L20)*G20,V20*0.08*G20),0))) | X20: =IF($A20="","",IF(D20="买入",0,IFERROR(IF(W20<>0,(H20-IFERROR(INDEX($H$2:$H19,MATCH(2,1/($C$2:$C19=$C20))),0))/W20,0),0))) | Y20: =IF($A20="","",Y19+X20) | Z20: =IF($A20="","",IF(X20>0,IF(LEFT(Z19,1)="胜","胜"&VALUE(RIGHT(Z19,LEN(Z19)-1))+1,"胜1"),IF(X20<0,IF(LEFT(Z19,1)="亏","亏"&VALUE(RIGHT(Z19,LEN(Z19)-1))+1,"亏1"),"平"))) | AA20: =IF($A20="","",MAX(0,(MAX($Y$2:Y20)-Y20)/MAX(1,MAX($Y$2:Y20))))
V21: =IF($A21="","",IF(OR(D21="卖出",D21="分红"),IFERROR(INDEX($F$2:$F20,MATCH(2,1/($C$2:$C20=$C21))),""),"")) | W21: =IF($A21="","",IF(D21="买入",IF(AND(ISNUMBER(L21),L21>0),(F21-L21)*G21,F21*0.08*G21),IF(AND(ISNUMBER(V21),V21>0),IF(AND(ISNUMBER(L21),L21>0),(V21-L21)*G21,V21*0.08*G21),0))) | X21: =IF($A21="","",IF(D21="买入",0,IFERROR(IF(W21<>0,(H21-IFERROR(INDEX($H$2:$H20,MATCH(2,1/($C$2:$C20=$C21))),0))/W21,0),0))) | Y21: =IF($A21="","",Y20+X21) | Z21: =IF($A21="","",IF(X21>0,IF(LEFT(Z20,1)="胜","胜"&VALUE(RIGHT(Z20,LEN(Z20)-1))+1,"胜1"),IF(X21<0,IF(LEFT(Z20,1)="亏","亏"&VALUE(RIGHT(Z20,LEN(Z20)-1))+1,"亏1"),"平"))) | AA21: =IF($A21="","",MAX(0,(MAX($Y$2:Y21)-Y21)/MAX(1,MAX($Y$2:Y21))))
V22: =IF($A22="","",IF(OR(D22="卖出",D22="分红"),IFERROR(INDEX($F$2:$F21,MATCH(2,1/($C$2:$C21=$C22))),""),"")) | W22: =IF($A22="","",IF(D22="买入",IF(AND(ISNUMBER(L22),L22>0),(F22-L22)*G22,F22*0.08*G22),IF(AND(ISNUMBER(V22),V22>0),IF(AND(ISNUMBER(L22),L22>0),(V22-L22)*G22,V22*0.08*G22),0))) | X22: =IF($A22="","",IF(D22="买入",0,IFERROR(IF(W22<>0,(H22-IFERROR(INDEX($H$2:$H21,MATCH(2,1/($C$2:$C21=$C22))),0))/W22,0),0))) | Y22: =IF($A22="","",Y21+X22) | Z22: =IF($A22="","",IF(X22>0,IF(LEFT(Z21,1)="胜","胜"&VALUE(RIGHT(Z21,LEN(Z21)-1))+1,"胜1"),IF(X22<0,IF(LEFT(Z21,1)="亏","亏"&VALUE(RIGHT(Z21,LEN(Z21)-1))+1,"亏1"),"平"))) | AA22: =IF($A22="","",MAX(0,(MAX($Y$2:Y22)-Y22)/MAX(1,MAX($Y$2:Y22))))
V23: =IF($A23="","",IF(OR(D23="卖出",D23="分红"),IFERROR(INDEX($F$2:$F22,MATCH(2,1/($C$2:$C22=$C23))),""),"")) | W23: =IF($A23="","",IF(D23="买入",IF(AND(ISNUMBER(L23),L23>0),(F23-L23)*G23,F23*0.08*G23),IF(AND(ISNUMBER(V23),V23>0),IF(AND(ISNUMBER(L23),L23>0),(V23-L23)*G23,V23*0.08*G23),0))) | X23: =IF($A23="","",IF(D23="买入",0,IFERROR(IF(W23<>0,(H23-IFERROR(INDEX($H$2:$H22,MATCH(2,1/($C$2:$C22=$C23))),0))/W23,0),0))) | Y23: =IF($A23="","",Y22+X23) | Z23: =IF($A23="","",IF(X23>0,IF(LEFT(Z22,1)="胜","胜"&VALUE(RIGHT(Z22,LEN(Z22)-1))+1,"胜1"),IF(X23<0,IF(LEFT(Z22,1)="亏","亏"&VALUE(RIGHT(Z22,LEN(Z22)-1))+1,"亏1"),"平"))) | AA23: =IF($A23="","",MAX(0,(MAX($Y$2:Y23)-Y23)/MAX(1,MAX($Y$2:Y23))))
V24: =IF($A24="","",IF(OR(D24="卖出",D24="分红"),IFERROR(INDEX($F$2:$F23,MATCH(2,1/($C$2:$C23=$C24))),""),"")) | W24: =IF($A24="","",IF(D24="买入",IF(AND(ISNUMBER(L24),L24>0),(F24-L24)*G24,F24*0.08*G24),IF(AND(ISNUMBER(V24),V24>0),IF(AND(ISNUMBER(L24),L24>0),(V24-L24)*G24,V24*0.08*G24),0))) | X24: =IF($A24="","",IF(D24="买入",0,IFERROR(IF(W24<>0,(H24-IFERROR(INDEX($H$2:$H23,MATCH(2,1/($C$2:$C23=$C24))),0))/W24,0),0))) | Y24: =IF($A24="","",Y23+X24) | Z24: =IF($A24="","",IF(X24>0,IF(LEFT(Z23,1)="胜","胜"&VALUE(RIGHT(Z23,LEN(Z23)-1))+1,"胜1"),IF(X24<0,IF(LEFT(Z23,1)="亏","亏"&VALUE(RIGHT(Z23,LEN(Z23)-1))+1,"亏1"),"平"))) | AA24: =IF($A24="","",MAX(0,(MAX($Y$2:Y24)-Y24)/MAX(1,MAX($Y$2:Y24))))
V25: =IF($A25="","",IF(OR(D25="卖出",D25="分红"),IFERROR(INDEX($F$2:$F24,MATCH(2,1/($C$2:$C24=$C25))),""),"")) | W25: =IF($A25="","",IF(D25="买入",IF(AND(ISNUMBER(L25),L25>0),(F25-L25)*G25,F25*0.08*G25),IF(AND(ISNUMBER(V25),V25>0),IF(AND(ISNUMBER(L25),L25>0),(V25-L25)*G25,V25*0.08*G25),0))) | X25: =IF($A25="","",IF(D25="买入",0,IFERROR(IF(W25<>0,(H25-IFERROR(INDEX($H$2:$H24,MATCH(2,1/($C$2:$C24=$C25))),0))/W25,0),0))) | Y25: =IF($A25="","",Y24+X25) | Z25: =IF($A25="","",IF(X25>0,IF(LEFT(Z24,1)="胜","胜"&VALUE(RIGHT(Z24,LEN(Z24)-1))+1,"胜1"),IF(X25<0,IF(LEFT(Z24,1)="亏","亏"&VALUE(RIGHT(Z24,LEN(Z24)-1))+1,"亏1"),"平"))) | AA25: =IF($A25="","",MAX(0,(MAX($Y$2:Y25)-Y25)/MAX(1,MAX($Y$2:Y25))))
V26: =IF($A26="","",IF(OR(D26="卖出",D26="分红"),IFERROR(INDEX($F$2:$F25,MATCH(2,1/($C$2:$C25=$C26))),""),"")) | W26: =IF($A26="","",IF(D26="买入",IF(AND(ISNUMBER(L26),L26>0),(F26-L26)*G26,F26*0.08*G26),IF(AND(ISNUMBER(V26),V26>0),IF(AND(ISNUMBER(L26),L26>0),(V26-L26)*G26,V26*0.08*G26),0))) | X26: =IF($A26="","",IF(D26="买入",0,IFERROR(IF(W26<>0,(H26-IFERROR(INDEX($H$2:$H25,MATCH(2,1/($C$2:$C25=$C26))),0))/W26,0),0))) | Y26: =IF($A26="","",Y25+X26) | Z26: =IF($A26="","",IF(X26>0,IF(LEFT(Z25,1)="胜","胜"&VALUE(RIGHT(Z25,LEN(Z25)-1))+1,"胜1"),IF(X26<0,IF(LEFT(Z25,1)="亏","亏"&VALUE(RIGHT(Z25,LEN(Z25)-1))+1,"亏1"),"平"))) | AA26: =IF($A26="","",MAX(0,(MAX($Y$2:Y26)-Y26)/MAX(1,MAX($Y$2:Y26))))
V27: =IF($A27="","",IF(OR(D27="卖出",D27="分红"),IFERROR(INDEX($F$2:$F26,MATCH(2,1/($C$2:$C26=$C27))),""),"")) | W27: =IF($A27="","",IF(D27="买入",IF(AND(ISNUMBER(L27),L27>0),(F27-L27)*G27,F27*0.08*G27),IF(AND(ISNUMBER(V27),V27>0),IF(AND(ISNUMBER(L27),L27>0),(V27-L27)*G27,V27*0.08*G27),0))) | X27: =IF($A27="","",IF(D27="买入",0,IFERROR(IF(W27<>0,(H27-IFERROR(INDEX($H$2:$H26,MATCH(2,1/($C$2:$C26=$C27))),0))/W27,0),0))) | Y27: =IF($A27="","",Y26+X27) | Z27: =IF($A27="","",IF(X27>0,IF(LEFT(Z26,1)="胜","胜"&VALUE(RIGHT(Z26,LEN(Z26)-1))+1,"胜1"),IF(X27<0,IF(LEFT(Z26,1)="亏","亏"&VALUE(RIGHT(Z26,LEN(Z26)-1))+1,"亏1"),"平"))) | AA27: =IF($A27="","",MAX(0,(MAX($Y$2:Y27)-Y27)/MAX(1,MAX($Y$2:Y27))))
V28: =IF($A28="","",IF(OR(D28="卖出",D28="分红"),IFERROR(INDEX($F$2:$F27,MATCH(2,1/($C$2:$C27=$C28))),""),"")) | W28: =IF($A28="","",IF(D28="买入",IF(AND(ISNUMBER(L28),L28>0),(F28-L28)*G28,F28*0.08*G28),IF(AND(ISNUMBER(V28),V28>0),IF(AND(ISNUMBER(L28),L28>0),(V28-L28)*G28,V28*0.08*G28),0))) | X28: =IF($A28="","",IF(D28="买入",0,IFERROR(IF(W28<>0,(H28-IFERROR(INDEX($H$2:$H27,MATCH(2,1/($C$2:$C27=$C28))),0))/W28,0),0))) | Y28: =IF($A28="","",Y27+X28) | Z28: =IF($A28="","",IF(X28>0,IF(LEFT(Z27,1)="胜","胜"&VALUE(RIGHT(Z27,LEN(Z27)-1))+1,"胜1"),IF(X28<0,IF(LEFT(Z27,1)="亏","亏"&VALUE(RIGHT(Z27,LEN(Z27)-1))+1,"亏1"),"平"))) | AA28: =IF($A28="","",MAX(0,(MAX($Y$2:Y28)-Y28)/MAX(1,MAX($Y$2:Y28))))
V29: =IF($A29="","",IF(OR(D29="卖出",D29="分红"),IFERROR(INDEX($F$2:$F28,MATCH(2,1/($C$2:$C28=$C29))),""),"")) | W29: =IF($A29="","",IF(D29="买入",IF(AND(ISNUMBER(L29),L29>0),(F29-L29)*G29,F29*0.08*G29),IF(AND(ISNUMBER(V29),V29>0),IF(AND(ISNUMBER(L29),L29>0),(V29-L29)*G29,V29*0.08*G29),0))) | X29: =IF($A29="","",IF(D29="买入",0,IFERROR(IF(W29<>0,(H29-IFERROR(INDEX($H$2:$H28,MATCH(2,1/($C$2:$C28=$C29))),0))/W29,0),0))) | Y29: =IF($A29="","",Y28+X29) | Z29: =IF($A29="","",IF(X29>0,IF(LEFT(Z28,1)="胜","胜"&VALUE(RIGHT(Z28,LEN(Z28)-1))+1,"胜1"),IF(X29<0,IF(LEFT(Z28,1)="亏","亏"&VALUE(RIGHT(Z28,LEN(Z28)-1))+1,"亏1"),"平"))) | AA29: =IF($A29="","",MAX(0,(MAX($Y$2:Y29)-Y29)/MAX(1,MAX($Y$2:Y29))))
V30: =IF($A30="","",IF(OR(D30="卖出",D30="分红"),IFERROR(INDEX($F$2:$F29,MATCH(2,1/($C$2:$C29=$C30))),""),"")) | W30: =IF($A30="","",IF(D30="买入",IF(AND(ISNUMBER(L30),L30>0),(F30-L30)*G30,F30*0.08*G30),IF(AND(ISNUMBER(V30),V30>0),IF(AND(ISNUMBER(L30),L30>0),(V30-L30)*G30,V30*0.08*G30),0))) | X30: =IF($A30="","",IF(D30="买入",0,IFERROR(IF(W30<>0,(H30-IFERROR(INDEX($H$2:$H29,MATCH(2,1/($C$2:$C29=$C30))),0))/W30,0),0))) | Y30: =IF($A30="","",Y29+X30) | Z30: =IF($A30="","",IF(X30>0,IF(LEFT(Z29,1)="胜","胜"&VALUE(RIGHT(Z29,LEN(Z29)-1))+1,"胜1"),IF(X30<0,IF(LEFT(Z29,1)="亏","亏"&VALUE(RIGHT(Z29,LEN(Z29)-1))+1,"亏1"),"平"))) | AA30: =IF($A30="","",MAX(0,(MAX($Y$2:Y30)-Y30)/MAX(1,MAX($Y$2:Y30))))
V31: =IF($A31="","",IF(OR(D31="卖出",D31="分红"),IFERROR(INDEX($F$2:$F30,MATCH(2,1/($C$2:$C30=$C31))),""),"")) | W31: =IF($A31="","",IF(D31="买入",IF(AND(ISNUMBER(L31),L31>0),(F31-L31)*G31,F31*0.08*G31),IF(AND(ISNUMBER(V31),V31>0),IF(AND(ISNUMBER(L31),L31>0),(V31-L31)*G31,V31*0.08*G31),0))) | X31: =IF($A31="","",IF(D31="买入",0,IFERROR(IF(W31<>0,(H31-IFERROR(INDEX($H$2:$H30,MATCH(2,1/($C$2:$C30=$C31))),0))/W31,0),0))) | Y31: =IF($A31="","",Y30+X31) | Z31: =IF($A31="","",IF(X31>0,IF(LEFT(Z30,1)="胜","胜"&VALUE(RIGHT(Z30,LEN(Z30)-1))+1,"胜1"),IF(X31<0,IF(LEFT(Z30,1)="亏","亏"&VALUE(RIGHT(Z30,LEN(Z30)-1))+1,"亏1"),"平"))) | AA31: =IF($A31="","",MAX(0,(MAX($Y$2:Y31)-Y31)/MAX(1,MAX($Y$2:Y31))))
... V201: =IF($A201="","",IF(OR(D201="卖出",D201="分红"),IFERROR(INDEX($F$2:$F200,MATCH(2,1/($C$2:$C200=$C201))),""),"")) | W201: =IF($A201="","",IF(D201="买入",IF(AND(ISNUMBER(L201),L201>0),(F201-L201)*G201,F201*0.08*G201),IF(AND(ISNUMBER(V201),V201>0),IF(AND(ISNUMBER(L201),L201>0),(V201-L201)*G201,V201*0.08*G201),0))) | X201: =IF($A201="","",IF(D201="买入",0,IFERROR(IF(W201<>0,(H201-IFERROR(INDEX($H$2:$H200,MATCH(2,1/($C$2:$C200=$C201))),0))/W201,0),0))) | Y201: =IF($A201="","",Y200+X201) | Z201: =IF($A201="","",IF(X201>0,IF(LEFT(Z200,1)="胜","胜"&VALUE(RIGHT(Z200,LEN(Z200)-1))+1,"胜1"),IF(X201<0,IF(LEFT(Z200,1)="亏","亏"&VALUE(RIGHT(Z200,LEN(Z200)-1))+1,"亏1"),"平"))) | AA201: =IF($A201="","",MAX(0,(MAX($Y$2:Y201)-Y201)/MAX(1,MAX($Y$2:Y201))))
A203: 系统健康度仪表盘
A204: 总交易次数(不含分红) | B204: =COUNTIFS(A2:A200,"<>",D2:D200,"<>") -> 18
A205: 卖出次数 | B205: =COUNTIF(D2:D200,"卖出") -> 7
A206: 盈利次数(R>0) | B206: =COUNTIFS(X2:X200,">0") -> 5
A207: 亏损次数(R<0) | B207: =COUNTIFS(X2:X200,"<0") -> 2
A208: 胜率 | B208: =IFERROR(B206/B205,0) -> 0.71428571
A209: 平均R倍数 | B209: 2.143248
A210: 总R倍数 | B210: 15.002733
A211: 最大单笔R | B211: 9.082391
A212: 最大单笔亏损R | B212: -0.401727
A213: 最大连续盈利(笔) | B213: "见Z列(连胜/连亏)"
A214: 最大连续亏损(笔) | B214: "见Z列(连胜/连亏)"
A215: 累计R最大回撤 | B215: 0
A216: 盈亏比 | B216: 8.379487
A217: 系统状态 | B217: 正期望系统 ✅
A219: 46227 | B219: 万华化学 | C219: 600309 | D219: 卖出 | E219: 减仓降超限 | F219: 74.56 | G219: 100 | H219: 7456 | I219: 5 | J219: 0 | K219: 20842.32 | N219: 合规 | O219: 30min卖点+仓位37%超限 | P219: 盈利+774元
A220: 46227 | B220: 方盛制药 | C220: 603998 | D220: 买入 | E220: 日线一买确认 | F220: 9.45 | G220: 100 | H220: 945 | I220: 1.5 | J220: 100 | K220: 20842.32 | L220: 8.9775 | M220: 破止损 | N220: 合规 | O220: 日线ratio=3.7% DL_P=0.70 valid | P220: 持仓中
A221: 46227 | B221: 建研院 | C221: 603183 | D221: 买入 | E221: 日线一买确认 | F221: 4.07 | G221: 200 | H221: 814 | I221: 1.5 | J221: 200 | K221: 20842.32 | L221: 3.8665 | M221: 破止损 | N221: 合规 | O221: 日线ratio=5.7% DL_P=0.70 valid | P221: 持仓中
A222: 46227 | B222: 曲美家居 | C222: 603818 | D222: 买入 | E222: 日线一买确认 | F222: 3.2 | G222: 500 | H222: 1600 | I222: 2.4 | J222: 500 | K222: 20842.32 | L222: 3.04 | M222: 破止损 | N222: 合规(已减量) | O222: 日线ratio=9.7% 原挂2100股减至500股 | P222: 持仓中
A223: 46227 | B223: 创力集团 | C223: 603012 | D223: 买入 | E223: 日线一买确认 | F223: 8.021 | G223: 100 | H223: 802 | I223: 1.5 | J223: 100 | K223: 20842.32 | L223: 7.61995 | M223: 破止损 | N223: 合规 | O223: 日线ratio=2.7% DL_P=0.70 全买点 | P223: 持仓中
A224: 46227 | B224: 新五丰 | C224: 600975 | D224: 买入 | E224: 日线一买确认 | F224: 4.804 | G224: 300 | H224: 1441 | I224: 2.2 | J224: 300 | K224: 20842.32 | L224: 4.5638 | M224: 破止损 | N224: 合规 | O224: 日线ratio=12.1% 三级全买点 | P224: 持仓中
A225: 46225 | B225: 万华化学 | C225: 600309 | D225: 卖出 | E225: 一卖 | F225: 73 | G225: 300 | H225: 21900 | I225: 0 | J225: 0 | K225: 0
A226: 46225 | B226: 隆基绿能 | C226: 601012 | D226: 卖出 | E226: 一卖 | F226: 12 | G226: 200 | H226: 2400 | I226: 0 | J226: 200 | K226: 0.12
A227: 2026-07-29 | B227: ⚠️ 合规审查 | D227: 违规标注 | E227: 沃华医药买入+三力士卖出 均建议撤单
A228: 2026-07-29 | B228: 沃华医药 | C228: 002107 | D228: ⚠️违规买入 | E228: 不在候选池内, 未经系统筛选 | F228: 6 | G228: 200 | H228: 1200 | I228: 建议撤单
A229: 2026-07-29 | B229: 三力士 | C229: 002224 | D229: ⚠️违规卖出 | E229: 计划持有但挂全仓卖出单 | F229: 3.38 | G229: 300 | H229: 1014 | I229: 建议撤单, 除非有日线卖点信号
A230: 46233.485 | B230: 松芝股份 | C230: 002454 | D230: 卖出 | E230: 去弱留强 | F230: 4.87 | G230: 300 | H230: 1461 | O230: 去弱留强减仓，保留100股 | T230: 否
A231: 46233.485 | B231: 三力士 | C231: 002224 | D231: 卖出 | E231: 去弱留强 | F231: 3.46 | G231: 200 | H231: 692 | O231: 去弱留强减仓，保留100股 | T231: 否
A232: 46233.485 | B232: 拱东医疗 | C232: 605369 | D232: 卖出 | E232: 去弱留强 | F232: 15.94 | G232: 100 | H232: 1594 | O232: 去弱留强减仓，保留100股 | T232: 否
A233: 46233.595 | B233: 沃华医药 | C233: 002107 | D233: 买入 | E233: 二买信号 | F233: 5.95 | G233: 200 | H233: 1190 | J233: 400 | N233: 合规 | O233: 二买信号确认加仓(30min EP=0.60 DL_P=0.93) | T233: 否
A234: 46233.618 | B234: 三力士 | C234: 002224 | D234: 卖出 | E234: 一卖信号 | F234: 3.42 | G234: 100 | H234: 342 | J234: 0 | N234: 合规 | O234: 30min一卖信号确认，清仓剩余100股 | T234: 否
A235: 46233.618 | B235: 拱东医疗 | C235: 605369 | D235: 卖出 | E235: 去弱留强 | F235: 15.94 | G235: 100 | H235: 1594 | J235: 0 | N235: 合规 | O235: DL_P弱信号，清仓剩余100股 | T235: 否
A236: 46233.618 | B236: 贵绳股份 | C236: 600992 | D236: 买入 | E236: 二买信号 | F236: 8.94 | G236: 100 | H236: 894 | J236: 300 | N236: 合规 | O236: 二买确认加仓100股 | T236: 否
A237: 2026-07-31 04:08 | B237: 三力士 | C237: 002224 | D237: 卖出 | E237: 100 | F237: 3.42 | G237: 300 | H237: 1026 | I237: 5 | O237: P0清仓-破一买低
A238: 2026-07-31 04:08 | B238: 拱东医疗 | C238: 605369 | D238: 卖出 | E238: 100 | F238: 15.94 | G238: 100 | H238: 1594 | I238: 5 | O238: P0清仓-破一买低

Sheet 心态日志
A1: 日期 | B1: 非工作流看盘次数 | C1: 是否追价操作 | D1: 是否按系统执行 | E1: 情绪状态(1-5) | F1: 是否有止损外操作 | G1: 当日交易次数 | H1: 当日系统判定(全部合规) | I1: 焦虑事件描述 | J1: 今日心态感悟 | K1: 心态得分 | L1: 轻态化达标 | M1: 本周平均心态得分 | N1: 本周达标天数 | O1: 连续达标天数 | P1: 心态趋势
A2: 46225 | B2: 5 | C2: 0 | D2: 5 | E2: 3 | F2: 0 | G2: 0 | H2: 全部合规 | K2: 70 | L2: 未达标 | M2: =IF($A2="","",IFERROR(AVERAGEIFS(K$2:K2,WEEKNUM(A$2:A2,2),WEEKNUM(A2,2)),K2)) -> 70 | N2: =IF($A2="","",IFERROR(COUNTIFS(A$2:A2,"<>",L$2:L2,"达标",WEEKNUM(A$2:A2,2),WEEKNUM(A2,2)),0)) -> 0 | O2: =IF($A2="","",IF(L2="达标",IF(ROW()=2,1,IF(O2="",1,O2+1)),0)) -> 0 | P2: =IF($A2="","",IF(ROW()<=8,"基准周",IF(K2>75,"改善",IF(K2<60,"恶化","持平")))) -> 基准周
A3: 46226 | B3: 3 | C3: 0 | D3: 4 | E3: 3 | F3: 0 | G3: 1 | H3: 全部合规 | K3: 70 | L3: 未达标 | M3: =IF($A3="","",IFERROR(AVERAGEIFS(K$2:K3,WEEKNUM(A$2:A3,2),WEEKNUM(A3,2)),K3)) -> 70 | N3: =IF($A3="","",IFERROR(COUNTIFS(A$2:A3,"<>",L$2:L3,"达标",WEEKNUM(A$2:A3,2),WEEKNUM(A3,2)),0)) -> 0 | O3: =IF($A3="","",IF(L3="达标",IF(ROW()=2,1,IF(O3="",1,O3+1)),0)) -> 0 | P3: =IF($A3="","",IF(ROW()<=8,"基准周",IF(K3>75,"改善",IF(K3<60,"恶化","持平")))) -> 基准周
A4: 46227 | B4: 4 | C4: 0 | D4: 4 | E4: 3 | F4: 0 | G4: 6 | H4: 全部合规 | I4: 曲美家居原挂2100股(33%仓位)超限,减至500股后合规 | J4: 普跌日执行6笔交易,卖超限万华回收资金,建仓4只多级别买点标的。大盘1min买点ratio=55%未确认,属正常回调。严格执行仓位管理,未追涨未恐慌卖出。 | K4: =IF($A4="","",IF(B4=0,20,IF(B4=1,15,IF(B4=2,10,IF(B4=3,5,0))))+IF(C4="否",20,0)+IF(D4="是",20,0)+IF(E4=1,20,IF(E4=2,15,IF(E4=3,10,IF(E4=4,5,0))))+IF(F4="否",20,0)) -> 10 | L4: =IF($A4="","",IF(K4>=80,"达标","未达标")) -> 未达标 | M4: =IF($A4="","",IFERROR(AVERAGEIFS(K$2:K4,WEEKNUM(A$2:A4,2),WEEKNUM(A4,2)),K4)) -> 10 | N4: =IF($A4="","",IFERROR(COUNTIFS(A$2:A4,"<>",L$2:L4,"达标",WEEKNUM(A$2:A4,2),WEEKNUM(A4,2)),0)) -> 0 | O4: =IF($A4="","",IF(L4="达标",IF(ROW()=2,1,IF(O4="",1,O4+1)),0)) -> 0 | P4: =IF($A4="","",IF(ROW()<=8,"基准周",IF(K4>75,"改善",IF(K4<60,"恶化","持平")))) -> 基准周
K5: =IF($A5="","",IF(B5=0,20,IF(B5=1,15,IF(B5=2,10,IF(B5=3,5,0))))+IF(C5="否",20,0)+IF(D5="是",20,0)+IF(E5=1,20,IF(E5=2,15,IF(E5=3,10,IF(E5=4,5,0))))+IF(F5="否",20,0)) | L5: =IF($A5="","",IF(K5>=80,"达标","未达标")) | M5: =IF($A5="","",IFERROR(AVERAGEIFS(K$2:K5,WEEKNUM(A$2:A5,2),WEEKNUM(A5,2)),K5)) | N5: =IF($A5="","",IFERROR(COUNTIFS(A$2:A5,"<>",L$2:L5,"达标",WEEKNUM(A$2:A5,2),WEEKNUM(A5,2)),0)) | O5: =IF($A5="","",IF(L5="达标",IF(ROW()=2,1,IF(O4="",1,O4+1)),0)) | P5: =IF($A5="","",IF(ROW()<=8,"基准周",IF(K5>75,"改善",IF(K5<60,"恶化","持平"))))
K6: =IF($A6="","",IF(B6=0,20,IF(B6=1,15,IF(B6=2,10,IF(B6=3,5,0))))+IF(C6="否",20,0)+IF(D6="是",20,0)+IF(E6=1,20,IF(E6=2,15,IF(E6=3,10,IF(E6=4,5,0))))+IF(F6="否",20,0)) | L6: =IF($A6="","",IF(K6>=80,"达标","未达标")) | M6: =IF($A6="","",IFERROR(AVERAGEIFS(K$2:K6,WEEKNUM(A$2:A6,2),WEEKNUM(A6,2)),K6)) | N6: =IF($A6="","",IFERROR(COUNTIFS(A$2:A6,"<>",L$2:L6,"达标",WEEKNUM(A$2:A6,2),WEEKNUM(A6,2)),0)) | O6: =IF($A6="","",IF(L6="达标",IF(ROW()=2,1,IF(O5="",1,O5+1)),0)) | P6: =IF($A6="","",IF(ROW()<=8,"基准周",IF(K6>75,"改善",IF(K6<60,"恶化","持平"))))
K7: =IF($A7="","",IF(B7=0,20,IF(B7=1,15,IF(B7=2,10,IF(B7=3,5,0))))+IF(C7="否",20,0)+IF(D7="是",20,0)+IF(E7=1,20,IF(E7=2,15,IF(E7=3,10,IF(E7=4,5,0))))+IF(F7="否",20,0)) | L7: =IF($A7="","",IF(K7>=80,"达标","未达标")) | M7: =IF($A7="","",IFERROR(AVERAGEIFS(K$2:K7,WEEKNUM(A$2:A7,2),WEEKNUM(A7,2)),K7)) | N7: =IF($A7="","",IFERROR(COUNTIFS(A$2:A7,"<>",L$2:L7,"达标",WEEKNUM(A$2:A7,2),WEEKNUM(A7,2)),0)) | O7: =IF($A7="","",IF(L7="达标",IF(ROW()=2,1,IF(O6="",1,O6+1)),0)) | P7: =IF($A7="","",IF(ROW()<=8,"基准周",IF(K7>75,"改善",IF(K7<60,"恶化","持平"))))
K8: =IF($A8="","",IF(B8=0,20,IF(B8=1,15,IF(B8=2,10,IF(B8=3,5,0))))+IF(C8="否",20,0)+IF(D8="是",20,0)+IF(E8=1,20,IF(E8=2,15,IF(E8=3,10,IF(E8=4,5,0))))+IF(F8="否",20,0)) | L8: =IF($A8="","",IF(K8>=80,"达标","未达标")) | M8: =IF($A8="","",IFERROR(AVERAGEIFS(K$2:K8,WEEKNUM(A$2:A8,2),WEEKNUM(A8,2)),K8)) | N8: =IF($A8="","",IFERROR(COUNTIFS(A$2:A8,"<>",L$2:L8,"达标",WEEKNUM(A$2:A8,2),WEEKNUM(A8,2)),0)) | O8: =IF($A8="","",IF(L8="达标",IF(ROW()=2,1,IF(O7="",1,O7+1)),0)) | P8: =IF($A8="","",IF(ROW()<=8,"基准周",IF(K8>75,"改善",IF(K8<60,"恶化","持平"))))
K9: =IF($A9="","",IF(B9=0,20,IF(B9=1,15,IF(B9=2,10,IF(B9=3,5,0))))+IF(C9="否",20,0)+IF(D9="是",20,0)+IF(E9=1,20,IF(E9=2,15,IF(E9=3,10,IF(E9=4,5,0))))+IF(F9="否",20,0)) | L9: =IF($A9="","",IF(K9>=80,"达标","未达标")) | M9: =IF($A9="","",IFERROR(AVERAGEIFS(K$2:K9,WEEKNUM(A$2:A9,2),WEEKNUM(A9,2)),K9)) | N9: =IF($A9="","",IFERROR(COUNTIFS(A$2:A9,"<>",L$2:L9,"达标",WEEKNUM(A$2:A9,2),WEEKNUM(A9,2)),0)) | O9: =IF($A9="","",IF(L9="达标",IF(ROW()=2,1,IF(O8="",1,O8+1)),0)) | P9: =IF($A9="","",IF(ROW()<=8,"基准周",IF(K9>75,"改善",IF(K9<60,"恶化","持平"))))
K10: =IF($A10="","",IF(B10=0,20,IF(B10=1,15,IF(B10=2,10,IF(B10=3,5,0))))+IF(C10="否",20,0)+IF(D10="是",20,0)+IF(E10=1,20,IF(E10=2,15,IF(E10=3,10,IF(E10=4,5,0))))+IF(F10="否",20,0)) | L10: =IF($A10="","",IF(K10>=80,"达标","未达标")) | M10: =IF($A10="","",IFERROR(AVERAGEIFS(K$2:K10,WEEKNUM(A$2:A10,2),WEEKNUM(A10,2)),K10)) | N10: =IF($A10="","",IFERROR(COUNTIFS(A$2:A10,"<>",L$2:L10,"达标",WEEKNUM(A$2:A10,2),WEEKNUM(A10,2)),0)) | O10: =IF($A10="","",IF(L10="达标",IF(ROW()=2,1,IF(O9="",1,O9+1)),0)) | P10: =IF($A10="","",IF(ROW()<=8,"基准周",IF(K10>75,"改善",IF(K10<60,"恶化","持平"))))
K11: =IF($A11="","",IF(B11=0,20,IF(B11=1,15,IF(B11=2,10,IF(B11=3,5,0))))+IF(C11="否",20,0)+IF(D11="是",20,0)+IF(E11=1,20,IF(E11=2,15,IF(E11=3,10,IF(E11=4,5,0))))+IF(F11="否",20,0)) | L11: =IF($A11="","",IF(K11>=80,"达标","未达标")) | M11: =IF($A11="","",IFERROR(AVERAGEIFS(K$2:K11,WEEKNUM(A$2:A11,2),WEEKNUM(A11,2)),K11)) | N11: =IF($A11="","",IFERROR(COUNTIFS(A$2:A11,"<>",L$2:L11,"达标",WEEKNUM(A$2:A11,2),WEEKNUM(A11,2)),0)) | O11: =IF($A11="","",IF(L11="达标",IF(ROW()=2,1,IF(O10="",1,O10+1)),0)) | P11: =IF($A11="","",IF(ROW()<=8,"基准周",IF(K11>75,"改善",IF(K11<60,"恶化","持平"))))
K12: =IF($A12="","",IF(B12=0,20,IF(B12=1,15,IF(B12=2,10,IF(B12=3,5,0))))+IF(C12="否",20,0)+IF(D12="是",20,0)+IF(E12=1,20,IF(E12=2,15,IF(E12=3,10,IF(E12=4,5,0))))+IF(F12="否",20,0)) | L12: =IF($A12="","",IF(K12>=80,"达标","未达标")) | M12: =IF($A12="","",IFERROR(AVERAGEIFS(K$2:K12,WEEKNUM(A$2:A12,2),WEEKNUM(A12,2)),K12)) | N12: =IF($A12="","",IFERROR(COUNTIFS(A$2:A12,"<>",L$2:L12,"达标",WEEKNUM(A$2:A12,2),WEEKNUM(A12,2)),0)) | O12: =IF($A12="","",IF(L12="达标",IF(ROW()=2,1,IF(O11="",1,O11+1)),0)) | P12: =IF($A12="","",IF(ROW()<=8,"基准周",IF(K12>75,"改善",IF(K12<60,"恶化","持平"))))
K13: =IF($A13="","",IF(B13=0,20,IF(B13=1,15,IF(B13=2,10,IF(B13=3,5,0))))+IF(C13="否",20,0)+IF(D13="是",20,0)+IF(E13=1,20,IF(E13=2,15,IF(E13=3,10,IF(E13=4,5,0))))+IF(F13="否",20,0)) | L13: =IF($A13="","",IF(K13>=80,"达标","未达标")) | M13: =IF($A13="","",IFERROR(AVERAGEIFS(K$2:K13,WEEKNUM(A$2:A13,2),WEEKNUM(A13,2)),K13)) | N13: =IF($A13="","",IFERROR(COUNTIFS(A$2:A13,"<>",L$2:L13,"达标",WEEKNUM(A$2:A13,2),WEEKNUM(A13,2)),0)) | O13: =IF($A13="","",IF(L13="达标",IF(ROW()=2,1,IF(O12="",1,O12+1)),0)) | P13: =IF($A13="","",IF(ROW()<=8,"基准周",IF(K13>75,"改善",IF(K13<60,"恶化","持平"))))
K14: =IF($A14="","",IF(B14=0,20,IF(B14=1,15,IF(B14=2,10,IF(B14=3,5,0))))+IF(C14="否",20,0)+IF(D14="是",20,0)+IF(E14=1,20,IF(E14=2,15,IF(E14=3,10,IF(E14=4,5,0))))+IF(F14="否",20,0)) | L14: =IF($A14="","",IF(K14>=80,"达标","未达标")) | M14: =IF($A14="","",IFERROR(AVERAGEIFS(K$2:K14,WEEKNUM(A$2:A14,2),WEEKNUM(A14,2)),K14)) | N14: =IF($A14="","",IFERROR(COUNTIFS(A$2:A14,"<>",L$2:L14,"达标",WEEKNUM(A$2:A14,2),WEEKNUM(A14,2)),0)) | O14: =IF($A14="","",IF(L14="达标",IF(ROW()=2,1,IF(O13="",1,O13+1)),0)) | P14: =IF($A14="","",IF(ROW()<=8,"基准周",IF(K14>75,"改善",IF(K14<60,"恶化","持平"))))
K15: =IF($A15="","",IF(B15=0,20,IF(B15=1,15,IF(B15=2,10,IF(B15=3,5,0))))+IF(C15="否",20,0)+IF(D15="是",20,0)+IF(E15=1,20,IF(E15=2,15,IF(E15=3,10,IF(E15=4,5,0))))+IF(F15="否",20,0)) | L15: =IF($A15="","",IF(K15>=80,"达标","未达标")) | M15: =IF($A15="","",IFERROR(AVERAGEIFS(K$2:K15,WEEKNUM(A$2:A15,2),WEEKNUM(A15,2)),K15)) | N15: =IF($A15="","",IFERROR(COUNTIFS(A$2:A15,"<>",L$2:L15,"达标",WEEKNUM(A$2:A15,2),WEEKNUM(A15,2)),0)) | O15: =IF($A15="","",IF(L15="达标",IF(ROW()=2,1,IF(O14="",1,O14+1)),0)) | P15: =IF($A15="","",IF(ROW()<=8,"基准周",IF(K15>75,"改善",IF(K15<60,"恶化","持平"))))
K16: =IF($A16="","",IF(B16=0,20,IF(B16=1,15,IF(B16=2,10,IF(B16=3,5,0))))+IF(C16="否",20,0)+IF(D16="是",20,0)+IF(E16=1,20,IF(E16=2,15,IF(E16=3,10,IF(E16=4,5,0))))+IF(F16="否",20,0)) | L16: =IF($A16="","",IF(K16>=80,"达标","未达标")) | M16: =IF($A16="","",IFERROR(AVERAGEIFS(K$2:K16,WEEKNUM(A$2:A16,2),WEEKNUM(A16,2)),K16)) | N16: =IF($A16="","",IFERROR(COUNTIFS(A$2:A16,"<>",L$2:L16,"达标",WEEKNUM(A$2:A16,2),WEEKNUM(A16,2)),0)) | O16: =IF($A16="","",IF(L16="达标",IF(ROW()=2,1,IF(O15="",1,O15+1)),0)) | P16: =IF($A16="","",IF(ROW()<=8,"基准周",IF(K16>75,"改善",IF(K16<60,"恶化","持平"))))
... K59: =IF($A59="","",IF(B59=0,20,IF(B59=1,15,IF(B59=2,10,IF(B59=3,5,0))))+IF(C59="否",20,0)+IF(D59="是",20,0)+IF(E59=1,20,IF(E59=2,15,IF(E59=3,10,IF(E59=4,5,0))))+IF(F59="否",20,0)) | L59: =IF($A59="","",IF(K59>=80,"达标","未达标")) | M59: =IF($A59="","",IFERROR(AVERAGEIFS(K$2:K59,WEEKNUM(A$2:A59,2),WEEKNUM(A59,2)),K59)) | N59: =IF($A59="","",IFERROR(COUNTIFS(A$2:A59,"<>",L$2:L59,"达标",WEEKNUM(A$2:A59,2),WEEKNUM(A59,2)),0)) | O59: =IF($A59="","",IF(L59="达标",IF(ROW()=2,1,IF(O58="",1,O58+1)),0)) | P59: =IF($A59="","",IF(ROW()<=8,"基准周",IF(K59>75,"改善",IF(K59<60,"恶化","持平"))))
K60: =IF($A60="","",IF(B60=0,20,IF(B60=1,15,IF(B60=2,10,IF(B60=3,5,0))))+IF(C60="否",20,0)+IF(D60="是",20,0)+IF(E60=1,20,IF(E60=2,15,IF(E60=3,10,IF(E60=4,5,0))))+IF(F60="否",20,0)) | L60: =IF($A60="","",IF(K60>=80,"达标","未达标")) | M60: =IF($A60="","",IFERROR(AVERAGEIFS(K$2:K60,WEEKNUM(A$2:A60,2),WEEKNUM(A60,2)),K60)) | N60: =IF($A60="","",IFERROR(COUNTIFS(A$2:A60,"<>",L$2:L60,"达标",WEEKNUM(A$2:A60,2),WEEKNUM(A60,2)),0)) | O60: =IF($A60="","",IF(L60="达标",IF(ROW()=2,1,IF(O59="",1,O59+1)),0)) | P60: =IF($A60="","",IF(ROW()<=8,"基准周",IF(K60>K53,"改善",IF(K60<K53,"恶化","持平"))))
K61: =IF($A61="","",IF(B61=0,20,IF(B61=1,15,IF(B61=2,10,IF(B61=3,5,0))))+IF(C61="否",20,0)+IF(D61="是",20,0)+IF(E61=1,20,IF(E61=2,15,IF(E61=3,10,IF(E61=4,5,0))))+IF(F61="否",20,0)) | L61: =IF($A61="","",IF(K61>=80,"达标","未达标")) | M61: =IF($A61="","",IFERROR(AVERAGEIFS(K$2:K61,WEEKNUM(A$2:A61,2),WEEKNUM(A61,2)),K61)) | N61: =IF($A61="","",IFERROR(COUNTIFS(A$2:A61,"<>",L$2:L61,"达标",WEEKNUM(A$2:A61,2),WEEKNUM(A61,2)),0)) | O61: =IF($A61="","",IF(L61="达标",IF(ROW()=2,1,IF(O60="",1,O60+1)),0)) | P61: =IF($A61="","",IF(ROW()<=8,"基准周",IF(K61>75,"改善",IF(K61<60,"恶化","持平"))))
K62: =IF($A62="","",IF(B62=0,20,IF(B62=1,15,IF(B62=2,10,IF(B62=3,5,0))))+IF(C62="否",20,0)+IF(D62="是",20,0)+IF(E62=1,20,IF(E62=2,15,IF(E62=3,10,IF(E62=4,5,0))))+IF(F62="否",20,0)) | L62: =IF($A62="","",IF(K62>=80,"达标","未达标")) | M62: =IF($A62="","",IFERROR(AVERAGEIFS(K$2:K62,WEEKNUM(A$2:A62,2),WEEKNUM(A62,2)),K62)) | N62: =IF($A62="","",IFERROR(COUNTIFS(A$2:A62,"<>",L$2:L62,"达标",WEEKNUM(A$2:A62,2),WEEKNUM(A62,2)),0)) | O62: =IF($A62="","",IF(L62="达标",IF(ROW()=2,1,IF(O61="",1,O61+1)),0)) | P62: =IF($A62="","",IF(ROW()<=8,"基准周",IF(K62>75,"改善",IF(K62<60,"恶化","持平"))))
K63: =IF($A63="","",IF(B63=0,20,IF(B63=1,15,IF(B63=2,10,IF(B63=3,5,0))))+IF(C63="否",20,0)+IF(D63="是",20,0)+IF(E63=1,20,IF(E63=2,15,IF(E63=3,10,IF(E63=4,5,0))))+IF(F63="否",20,0)) | L63: =IF($A63="","",IF(K63>=80,"达标","未达标")) | M63: =IF($A63="","",IFERROR(AVERAGEIFS(K$2:K63,WEEKNUM(A$2:A63,2),WEEKNUM(A63,2)),K63)) | N63: =IF($A63="","",IFERROR(COUNTIFS(A$2:A63,"<>",L$2:L63,"达标",WEEKNUM(A$2:A63,2),WEEKNUM(A63,2)),0)) | O63: =IF($A63="","",IF(L63="达标",IF(ROW()=2,1,IF(O62="",1,O62+1)),0)) | P63: =IF($A63="","",IF(ROW()<=8,"基准周",IF(K63>75,"改善",IF(K63<60,"恶化","持平"))))
K64: =IF($A64="","",IF(B64=0,20,IF(B64=1,15,IF(B64=2,10,IF(B64=3,5,0))))+IF(C64="否",20,0)+IF(D64="是",20,0)+IF(E64=1,20,IF(E64=2,15,IF(E64=3,10,IF(E64=4,5,0))))+IF(F64="否",20,0)) | L64: =IF($A64="","",IF(K64>=80,"达标","未达标")) | M64: =IF($A64="","",IFERROR(AVERAGEIFS(K$2:K64,WEEKNUM(A$2:A64,2),WEEKNUM(A64,2)),K64)) | N64: =IF($A64="","",IFERROR(COUNTIFS(A$2:A64,"<>",L$2:L64,"达标",WEEKNUM(A$2:A64,2),WEEKNUM(A64,2)),0)) | O64: =IF($A64="","",IF(L64="达标",IF(ROW()=2,1,IF(O63="",1,O63+1)),0)) | P64: =IF($A64="","",IF(ROW()<=8,"基准周",IF(K64>75,"改善",IF(K64<60,"恶化","持平"))))
K65: =IF($A65="","",IF(B65=0,20,IF(B65=1,15,IF(B65=2,10,IF(B65=3,5,0))))+IF(C65="否",20,0)+IF(D65="是",20,0)+IF(E65=1,20,IF(E65=2,15,IF(E65=3,10,IF(E65=4,5,0))))+IF(F65="否",20,0)) | L65: =IF($A65="","",IF(K65>=80,"达标","未达标")) | M65: =IF($A65="","",IFERROR(AVERAGEIFS(K$2:K65,WEEKNUM(A$2:A65,2),WEEKNUM(A65,2)),K65)) | N65: =IF($A65="","",IFERROR(COUNTIFS(A$2:A65,"<>",L$2:L65,"达标",WEEKNUM(A$2:A65,2),WEEKNUM(A65,2)),0)) | O65: =IF($A65="","",IF(L65="达标",IF(ROW()=2,1,IF(O64="",1,O64+1)),0)) | P65: =IF($A65="","",IF(ROW()<=8,"基准周",IF(K65>75,"改善",IF(K65<60,"恶化","持平"))))
K66: =IF($A66="","",IF(B66=0,20,IF(B66=1,15,IF(B66=2,10,IF(B66=3,5,0))))+IF(C66="否",20,0)+IF(D66="是",20,0)+IF(E66=1,20,IF(E66=2,15,IF(E66=3,10,IF(E66=4,5,0))))+IF(F66="否",20,0)) | L66: =IF($A66="","",IF(K66>=80,"达标","未达标")) | M66: =IF($A66="","",IFERROR(AVERAGEIFS(K$2:K66,WEEKNUM(A$2:A66,2),WEEKNUM(A66,2)),K66)) | N66: =IF($A66="","",IFERROR(COUNTIFS(A$2:A66,"<>",L$2:L66,"达标",WEEKNUM(A$2:A66,2),WEEKNUM(A66,2)),0)) | O66: =IF($A66="","",IF(L66="达标",IF(ROW()=2,1,IF(O65="",1,O65+1)),0)) | P66: =IF($A66="","",IF(ROW()<=8,"基准周",IF(K66>75,"改善",IF(K66<60,"恶化","持平"))))
K67: =IF($A67="","",IF(B67=0,20,IF(B67=1,15,IF(B67=2,10,IF(B67=3,5,0))))+IF(C67="否",20,0)+IF(D67="是",20,0)+IF(E67=1,20,IF(E67=2,15,IF(E67=3,10,IF(E67=4,5,0))))+IF(F67="否",20,0)) | L67: =IF($A67="","",IF(K67>=80,"达标","未达标")) | M67: =IF($A67="","",IFERROR(AVERAGEIFS(K$2:K67,WEEKNUM(A$2:A67,2),WEEKNUM(A67,2)),K67)) | N67: =IF($A67="","",IFERROR(COUNTIFS(A$2:A67,"<>",L$2:L67,"达标",WEEKNUM(A$2:A67,2),WEEKNUM(A67,2)),0)) | O67: =IF($A67="","",IF(L67="达标",IF(ROW()=2,1,IF(O66="",1,O66+1)),0)) | P67: =IF($A67="","",IF(ROW()<=8,"基准周",IF(K67>K60,"改善",IF(K67<K60,"恶化","持平"))))
K68: =IF($A68="","",IF(B68=0,20,IF(B68=1,15,IF(B68=2,10,IF(B68=3,5,0))))+IF(C68="否",20,0)+IF(D68="是",20,0)+IF(E68=1,20,IF(E68=2,15,IF(E68=3,10,IF(E68=4,5,0))))+IF(F68="否",20,0)) | L68: =IF($A68="","",IF(K68>=80,"达标","未达标")) | M68: =IF($A68="","",IFERROR(AVERAGEIFS(K$2:K68,WEEKNUM(A$2:A68,2),WEEKNUM(A68,2)),K68)) | N68: =IF($A68="","",IFERROR(COUNTIFS(A$2:A68,"<>",L$2:L68,"达标",WEEKNUM(A$2:A68,2),WEEKNUM(A68,2)),0)) | O68: =IF($A68="","",IF(L68="达标",IF(ROW()=2,1,IF(O67="",1,O67+1)),0)) | P68: =IF($A68="","",IF(ROW()<=8,"基准周",IF(K68>75,"改善",IF(K68<60,"恶化","持平"))))
K69: =IF($A69="","",IF(B69=0,20,IF(B69=1,15,IF(B69=2,10,IF(B69=3,5,0))))+IF(C69="否",20,0)+IF(D69="是",20,0)+IF(E69=1,20,IF(E69=2,15,IF(E69=3,10,IF(E69=4,5,0))))+IF(F69="否",20,0)) | L69: =IF($A69="","",IF(K69>=80,"达标","未达标")) | M69: =IF($A69="","",IFERROR(AVERAGEIFS(K$2:K69,WEEKNUM(A$2:A69,2),WEEKNUM(A69,2)),K69)) | N69: =IF($A69="","",IFERROR(COUNTIFS(A$2:A69,"<>",L$2:L69,"达标",WEEKNUM(A$2:A69,2),WEEKNUM(A69,2)),0)) | O69: =IF($A69="","",IF(L69="达标",IF(ROW()=2,1,IF(O68="",1,O68+1)),0)) | P69: =IF($A69="","",IF(ROW()<=8,"基准周",IF(K69>75,"改善",IF(K69<60,"恶化","持平"))))
K70: =IF($A70="","",IF(B70=0,20,IF(B70=1,15,IF(B70=2,10,IF(B70=3,5,0))))+IF(C70="否",20,0)+IF(D70="是",20,0)+IF(E70=1,20,IF(E70=2,15,IF(E70=3,10,IF(E70=4,5,0))))+IF(F70="否",20,0)) | L70: =IF($A70="","",IF(K70>=80,"达标","未达标")) | M70: =IF($A70="","",IFERROR(AVERAGEIFS(K$2:K70,WEEKNUM(A$2:A70,2),WEEKNUM(A70,2)),K70)) | N70: =IF($A70="","",IFERROR(COUNTIFS(A$2:A70,"<>",L$2:L70,"达标",WEEKNUM(A$2:A70,2),WEEKNUM(A70,2)),0)) | O70: =IF($A70="","",IF(L70="达标",IF(ROW()=2,1,IF(O69="",1,O69+1)),0)) | P70: =IF($A70="","",IF(ROW()<=8,"基准周",IF(K70>75,"改善",IF(K70<60,"恶化","持平"))))
K71: =IF($A71="","",IF(B71=0,20,IF(B71=1,15,IF(B71=2,10,IF(B71=3,5,0))))+IF(C71="否",20,0)+IF(D71="是",20,0)+IF(E71=1,20,IF(E71=2,15,IF(E71=3,10,IF(E71=4,5,0))))+IF(F71="否",20,0)) | L71: =IF($A71="","",IF(K71>=80,"达标","未达标")) | M71: =IF($A71="","",IFERROR(AVERAGEIFS(K$2:K71,WEEKNUM(A$2:A71,2),WEEKNUM(A71,2)),K71)) | N71: =IF($A71="","",IFERROR(COUNTIFS(A$2:A71,"<>",L$2:L71,"达标",WEEKNUM(A$2:A71,2),WEEKNUM(A71,2)),0)) | O71: =IF($A71="","",IF(L71="达标",IF(ROW()=2,1,IF(O70="",1,O70+1)),0)) | P71: =IF($A71="","",IF(ROW()<=8,"基准周",IF(K71>75,"改善",IF(K71<60,"恶化","持平"))))
K72: =IF($A72="","",IF(B72=0,20,IF(B72=1,15,IF(B72=2,10,IF(B72=3,5,0))))+IF(C72="否",20,0)+IF(D72="是",20,0)+IF(E72=1,20,IF(E72=2,15,IF(E72=3,10,IF(E72=4,5,0))))+IF(F72="否",20,0)) | L72: =IF($A72="","",IF(K72>=80,"达标","未达标")) | M72: =IF($A72="","",IFERROR(AVERAGEIFS(K$2:K72,WEEKNUM(A$2:A72,2),WEEKNUM(A72,2)),K72)) | N72: =IF($A72="","",IFERROR(COUNTIFS(A$2:A72,"<>",L$2:L72,"达标",WEEKNUM(A$2:A72,2),WEEKNUM(A72,2)),0)) | O72: =IF($A72="","",IF(L72="达标",IF(ROW()=2,1,IF(O71="",1,O71+1)),0)) | P72: =IF($A72="","",IF(ROW()<=8,"基准周",IF(K72>75,"改善",IF(K72<60,"恶化","持平"))))
K73: =IF($A73="","",IF(B73=0,20,IF(B73=1,15,IF(B73=2,10,IF(B73=3,5,0))))+IF(C73="否",20,0)+IF(D73="是",20,0)+IF(E73=1,20,IF(E73=2,15,IF(E73=3,10,IF(E73=4,5,0))))+IF(F73="否",20,0)) | L73: =IF($A73="","",IF(K73>=80,"达标","未达标")) | M73: =IF($A73="","",IFERROR(AVERAGEIFS(K$2:K73,WEEKNUM(A$2:A73,2),WEEKNUM(A73,2)),K73)) | N73: =IF($A73="","",IFERROR(COUNTIFS(A$2:A73,"<>",L$2:L73,"达标",WEEKNUM(A$2:A73,2),WEEKNUM(A73,2)),0)) | O73: =IF($A73="","",IF(L73="达标",IF(ROW()=2,1,IF(O72="",1,O72+1)),0)) | P73: =IF($A73="","",IF(ROW()<=8,"基准周",IF(K73>75,"改善",IF(K73<60,"恶化","持平"))))
K74: =IF($A74="","",IF(B74=0,20,IF(B74=1,15,IF(B74=2,10,IF(B74=3,5,0))))+IF(C74="否",20,0)+IF(D74="是",20,0)+IF(E74=1,20,IF(E74=2,15,IF(E74=3,10,IF(E74=4,5,0))))+IF(F74="否",20,0)) | L74: =IF($A74="","",IF(K74>=80,"达标","未达标")) | M74: =IF($A74="","",IFERROR(AVERAGEIFS(K$2:K74,WEEKNUM(A$2:A74,2),WEEKNUM(A74,2)),K74)) | N74: =IF($A74="","",IFERROR(COUNTIFS(A$2:A74,"<>",L$2:L74,"达标",WEEKNUM(A$2:A74,2),WEEKNUM(A74,2)),0)) | O74: =IF($A74="","",IF(L74="达标",IF(ROW()=2,1,IF(O73="",1,O73+1)),0)) | P74: =IF($A74="","",IF(ROW()<=8,"基准周",IF(K74>75,"改善",IF(K74<60,"恶化","持平"))))
K75: =IF($A75="","",IF(B75=0,20,IF(B75=1,15,IF(B75=2,10,IF(B75=3,5,0))))+IF(C75="否",20,0)+IF(D75="是",20,0)+IF(E75=1,20,IF(E75=2,15,IF(E75=3,10,IF(E75=4,5,0))))+IF(F75="否",20,0)) | L75: =IF($A75="","",IF(K75>=80,"达标","未达标")) | M75: =IF($A75="","",IFERROR(AVERAGEIFS(K$2:K75,WEEKNUM(A$2:A75,2),WEEKNUM(A75,2)),K75)) | N75: =IF($A75="","",IFERROR(COUNTIFS(A$2:A75,"<>",L$2:L75,"达标",WEEKNUM(A$2:A75,2),WEEKNUM(A75,2)),0)) | O75: =IF($A75="","",IF(L75="达标",IF(ROW()=2,1,IF(O74="",1,O74+1)),0)) | P75: =IF($A75="","",IF(ROW()<=8,"基准周",IF(K75>K68,"改善",IF(K75<K68,"恶化","持平"))))
K76: =IF($A76="","",IF(B76=0,20,IF(B76=1,15,IF(B76=2,10,IF(B76=3,5,0))))+IF(C76="否",20,0)+IF(D76="是",20,0)+IF(E76=1,20,IF(E76=2,15,IF(E76=3,10,IF(E76=4,5,0))))+IF(F76="否",20,0)) | L76: =IF($A76="","",IF(K76>=80,"达标","未达标")) | M76: =IF($A76="","",IFERROR(AVERAGEIFS(K$2:K76,WEEKNUM(A$2:A76,2),WEEKNUM(A76,2)),K76)) | N76: =IF($A76="","",IFERROR(COUNTIFS(A$2:A76,"<>",L$2:L76,"达标",WEEKNUM(A$2:A76,2),WEEKNUM(A76,2)),0)) | O76: =IF($A76="","",IF(L76="达标",IF(ROW()=2,1,IF(O75="",1,O75+1)),0)) | P76: =IF($A76="","",IF(ROW()<=8,"基准周",IF(K76>75,"改善",IF(K76<60,"恶化","持平"))))
K77: =IF($A77="","",IF(B77=0,20,IF(B77=1,15,IF(B77=2,10,IF(B77=3,5,0))))+IF(C77="否",20,0)+IF(D77="是",20,0)+IF(E77=1,20,IF(E77=2,15,IF(E77=3,10,IF(E77=4,5,0))))+IF(F77="否",20,0)) | L77: =IF($A77="","",IF(K77>=80,"达标","未达标")) | M77: =IF($A77="","",IFERROR(AVERAGEIFS(K$2:K77,WEEKNUM(A$2:A77,2),WEEKNUM(A77,2)),K77)) | N77: =IF($A77="","",IFERROR(COUNTIFS(A$2:A77,"<>",L$2:L77,"达标",WEEKNUM(A$2:A77,2),WEEKNUM(A77,2)),0)) | O77: =IF($A77="","",IF(L77="达标",IF(ROW()=2,1,IF(O76="",1,O76+1)),0)) | P77: =IF($A77="","",IF(ROW()<=8,"基准周",IF(K77>75,"改善",IF(K77<60,"恶化","持平"))))
K78: =IF($A78="","",IF(B78=0,20,IF(B78=1,15,IF(B78=2,10,IF(B78=3,5,0))))+IF(C78="否",20,0)+IF(D78="是",20,0)+IF(E78=1,20,IF(E78=2,15,IF(E78=3,10,IF(E78=4,5,0))))+IF(F78="否",20,0)) | L78: =IF($A78="","",IF(K78>=80,"达标","未达标")) | M78: =IF($A78="","",IFERROR(AVERAGEIFS(K$2:K78,WEEKNUM(A$2:A78,2),WEEKNUM(A78,2)),K78)) | N78: =IF($A78="","",IFERROR(COUNTIFS(A$2:A78,"<>",L$2:L78,"达标",WEEKNUM(A$2:A78,2),WEEKNUM(A78,2)),0)) | O78: =IF($A78="","",IF(L78="达标",IF(ROW()=2,1,IF(O77="",1,O77+1)),0)) | P78: =IF($A78="","",IF(ROW()<=8,"基准周",IF(K78>75,"改善",IF(K78<60,"恶化","持平"))))
K79: =IF($A79="","",IF(B79=0,20,IF(B79=1,15,IF(B79=2,10,IF(B79=3,5,0))))+IF(C79="否",20,0)+IF(D79="是",20,0)+IF(E79=1,20,IF(E79=2,15,IF(E79=3,10,IF(E79=4,5,0))))+IF(F79="否",20,0)) | L79: =IF($A79="","",IF(K79>=80,"达标","未达标")) | M79: =IF($A79="","",IFERROR(AVERAGEIFS(K$2:K79,WEEKNUM(A$2:A79,2),WEEKNUM(A79,2)),K79)) | N79: =IF($A79="","",IFERROR(COUNTIFS(A$2:A79,"<>",L$2:L79,"达标",WEEKNUM(A$2:A79,2),WEEKNUM(A79,2)),0)) | O79: =IF($A79="","",IF(L79="达标",IF(ROW()=2,1,IF(O78="",1,O78+1)),0)) | P79: =IF($A79="","",IF(ROW()<=8,"基准周",IF(K79>75,"改善",IF(K79<60,"恶化","持平"))))
K80: =IF($A80="","",IF(B80=0,20,IF(B80=1,15,IF(B80=2,10,IF(B80=3,5,0))))+IF(C80="否",20,0)+IF(D80="是",20,0)+IF(E80=1,20,IF(E80=2,15,IF(E80=3,10,IF(E80=4,5,0))))+IF(F80="否",20,0)) | L80: =IF($A80="","",IF(K80>=80,"达标","未达标")) | M80: =IF($A80="","",IFERROR(AVERAGEIFS(K$2:K80,WEEKNUM(A$2:A80,2),WEEKNUM(A80,2)),K80)) | N80: =IF($A80="","",IFERROR(COUNTIFS(A$2:A80,"<>",L$2:L80,"达标",WEEKNUM(A$2:A80,2),WEEKNUM(A80,2)),0)) | O80: =IF($A80="","",IF(L80="达标",IF(ROW()=2,1,IF(O79="",1,O79+1)),0)) | P80: =IF($A80="","",IF(ROW()<=8,"基准周",IF(K80>75,"改善",IF(K80<60,"恶化","持平"))))
K81: =IF($A81="","",IF(B81=0,20,IF(B81=1,15,IF(B81=2,10,IF(B81=3,5,0))))+IF(C81="否",20,0)+IF(D81="是",20,0)+IF(E81=1,20,IF(E81=2,15,IF(E81=3,10,IF(E81=4,5,0))))+IF(F81="否",20,0)) | L81: =IF($A81="","",IF(K81>=80,"达标","未达标")) | M81: =IF($A81="","",IFERROR(AVERAGEIFS(K$2:K81,WEEKNUM(A$2:A81,2),WEEKNUM(A81,2)),K81)) | N81: =IF($A81="","",IFERROR(COUNTIFS(A$2:A81,"<>",L$2:L81,"达标",WEEKNUM(A$2:A81,2),WEEKNUM(A81,2)),0)) | O81: =IF($A81="","",IF(L81="达标",IF(ROW()=2,1,IF(O80="",1,O80+1)),0)) | P81: =IF($A81="","",IF(ROW()<=8,"基准周",IF(K81>75,"改善",IF(K81<60,"恶化","持平"))))
K82: =IF($A82="","",IF(B82=0,20,IF(B82=1,15,IF(B82=2,10,IF(B82=3,5,0))))+IF(C82="否",20,0)+IF(D82="是",20,0)+IF(E82=1,20,IF(E82=2,15,IF(E82=3,10,IF(E82=4,5,0))))+IF(F82="否",20,0)) | L82: =IF($A82="","",IF(K82>=80,"达标","未达标")) | M82: =IF($A82="","",IFERROR(AVERAGEIFS(K$2:K82,WEEKNUM(A$2:A82,2),WEEKNUM(A82,2)),K82)) | N82: =IF($A82="","",IFERROR(COUNTIFS(A$2:A82,"<>",L$2:L82,"达标",WEEKNUM(A$2:A82,2),WEEKNUM(A82,2)),0)) | O82: =IF($A82="","",IF(L82="达标",IF(ROW()=2,1,IF(O81="",1,O81+1)),0)) | P82: =IF($A82="","",IF(ROW()<=8,"基准周",IF(K82>K75,"改善",IF(K82<K75,"恶化","持平"))))
K83: =IF($A83="","",IF(B83=0,20,IF(B83=1,15,IF(B83=2,10,IF(B83=3,5,0))))+IF(C83="否",20,0)+IF(D83="是",20,0)+IF(E83=1,20,IF(E83=2,15,IF(E83=3,10,IF(E83=4,5,0))))+IF(F83="否",20,0)) | L83: =IF($A83="","",IF(K83>=80,"达标","未达标")) | M83: =IF($A83="","",IFERROR(AVERAGEIFS(K$2:K83,WEEKNUM(A$2:A83,2),WEEKNUM(A83,2)),K83)) | N83: =IF($A83="","",IFERROR(COUNTIFS(A$2:A83,"<>",L$2:L83,"达标",WEEKNUM(A$2:A83,2),WEEKNUM(A83,2)),0)) | O83: =IF($A83="","",IF(L83="达标",IF(ROW()=2,1,IF(O82="",1,O82+1)),0)) | P83: =IF($A83="","",IF(ROW()<=8,"基准周",IF(K83>75,"改善",IF(K83<60,"恶化","持平"))))
K84: =IF($A84="","",IF(B84=0,20,IF(B84=1,15,IF(B84=2,10,IF(B84=3,5,0))))+IF(C84="否",20,0)+IF(D84="是",20,0)+IF(E84=1,20,IF(E84=2,15,IF(E84=3,10,IF(E84=4,5,0))))+IF(F84="否",20,0)) | L84: =IF($A84="","",IF(K84>=80,"达标","未达标")) | M84: =IF($A84="","",IFERROR(AVERAGEIFS(K$2:K84,WEEKNUM(A$2:A84,2),WEEKNUM(A84,2)),K84)) | N84: =IF($A84="","",IFERROR(COUNTIFS(A$2:A84,"<>",L$2:L84,"达标",WEEKNUM(A$2:A84,2),WEEKNUM(A84,2)),0)) | O84: =IF($A84="","",IF(L84="达标",IF(ROW()=2,1,IF(O83="",1,O83+1)),0)) | P84: =IF($A84="","",IF(ROW()<=8,"基准周",IF(K84>75,"改善",IF(K84<60,"恶化","持平"))))
K85: =IF($A85="","",IF(B85=0,20,IF(B85=1,15,IF(B85=2,10,IF(B85=3,5,0))))+IF(C85="否",20,0)+IF(D85="是",20,0)+IF(E85=1,20,IF(E85=2,15,IF(E85=3,10,IF(E85=4,5,0))))+IF(F85="否",20,0)) | L85: =IF($A85="","",IF(K85>=80,"达标","未达标")) | M85: =IF($A85="","",IFERROR(AVERAGEIFS(K$2:K85,WEEKNUM(A$2:A85,2),WEEKNUM(A85,2)),K85)) | N85: =IF($A85="","",IFERROR(COUNTIFS(A$2:A85,"<>",L$2:L85,"达标",WEEKNUM(A$2:A85,2),WEEKNUM(A85,2)),0)) | O85: =IF($A85="","",IF(L85="达标",IF(ROW()=2,1,IF(O84="",1,O84+1)),0)) | P85: =IF($A85="","",IF(ROW()<=8,"基准周",IF(K85>75,"改善",IF(K85<60,"恶化","持平"))))
K86: =IF($A86="","",IF(B86=0,20,IF(B86=1,15,IF(B86=2,10,IF(B86=3,5,0))))+IF(C86="否",20,0)+IF(D86="是",20,0)+IF(E86=1,20,IF(E86=2,15,IF(E86=3,10,IF(E86=4,5,0))))+IF(F86="否",20,0)) | L86: =IF($A86="","",IF(K86>=80,"达标","未达标")) | M86: =IF($A86="","",IFERROR(AVERAGEIFS(K$2:K86,WEEKNUM(A$2:A86,2),WEEKNUM(A86,2)),K86)) | N86: =IF($A86="","",IFERROR(COUNTIFS(A$2:A86,"<>",L$2:L86,"达标",WEEKNUM(A$2:A86,2),WEEKNUM(A86,2)),0)) | O86: =IF($A86="","",IF(L86="达标",IF(ROW()=2,1,IF(O85="",1,O85+1)),0)) | P86: =IF($A86="","",IF(ROW()<=8,"基准周",IF(K86>75,"改善",IF(K86<60,"恶化","持平"))))
K87: =IF($A87="","",IF(B87=0,20,IF(B87=1,15,IF(B87=2,10,IF(B87=3,5,0))))+IF(C87="否",20,0)+IF(D87="是",20,0)+IF(E87=1,20,IF(E87=2,15,IF(E87=3,10,IF(E87=4,5,0))))+IF(F87="否",20,0)) | L87: =IF($A87="","",IF(K87>=80,"达标","未达标")) | M87: =IF($A87="","",IFERROR(AVERAGEIFS(K$2:K87,WEEKNUM(A$2:A87,2),WEEKNUM(A87,2)),K87)) | N87: =IF($A87="","",IFERROR(COUNTIFS(A$2:A87,"<>",L$2:L87,"达标",WEEKNUM(A$2:A87,2),WEEKNUM(A87,2)),0)) | O87: =IF($A87="","",IF(L87="达标",IF(ROW()=2,1,IF(O86="",1,O86+1)),0)) | P87: =IF($A87="","",IF(ROW()<=8,"基准周",IF(K87>75,"改善",IF(K87<60,"恶化","持平"))))
K88: =IF($A88="","",IF(B88=0,20,IF(B88=1,15,IF(B88=2,10,IF(B88=3,5,0))))+IF(C88="否",20,0)+IF(D88="是",20,0)+IF(E88=1,20,IF(E88=2,15,IF(E88=3,10,IF(E88=4,5,0))))+IF(F88="否",20,0)) | L88: =IF($A88="","",IF(K88>=80,"达标","未达标")) | M88: =IF($A88="","",IFERROR(AVERAGEIFS(K$2:K88,WEEKNUM(A$2:A88,2),WEEKNUM(A88,2)),K88)) | N88: =IF($A88="","",IFERROR(COUNTIFS(A$2:A88,"<>",L$2:L88,"达标",WEEKNUM(A$2:A88,2),WEEKNUM(A88,2)),0)) | O88: =IF($A88="","",IF(L88="达标",IF(ROW()=2,1,IF(O87="",1,O87+1)),0)) | P88: =IF($A88="","",IF(ROW()<=8,"基准周",IF(K88>75,"改善",IF(K88<60,"恶化","持平"))))
K89: =IF($A89="","",IF(B89=0,20,IF(B89=1,15,IF(B89=2,10,IF(B89=3,5,0))))+IF(C89="否",20,0)+IF(D89="是",20,0)+IF(E89=1,20,IF(E89=2,15,IF(E89=3,10,IF(E89=4,5,0))))+IF(F89="否",20,0)) | L89: =IF($A89="","",IF(K89>=80,"达标","未达标")) | M89: =IF($A89="","",IFERROR(AVERAGEIFS(K$2:K89,WEEKNUM(A$2:A89,2),WEEKNUM(A89,2)),K89)) | N89: =IF($A89="","",IFERROR(COUNTIFS(A$2:A89,"<>",L$2:L89,"达标",WEEKNUM(A$2:A89,2),WEEKNUM(A89,2)),0)) | O89: =IF($A89="","",IF(L89="达标",IF(ROW()=2,1,IF(O88="",1,O88+1)),0)) | P89: =IF($A89="","",IF(ROW()<=8,"基准周",IF(K89>75,"改善",IF(K89<60,"恶化","持平"))))
K90: =IF($A90="","",IF(B90=0,20,IF(B90=1,15,IF(B90=2,10,IF(B90=3,5,0))))+IF(C90="否",20,0)+IF(D90="是",20,0)+IF(E90=1,20,IF(E90=2,15,IF(E90=3,10,IF(E90=4,5,0))))+IF(F90="否",20,0)) | L90: =IF($A90="","",IF(K90>=80,"达标","未达标")) | M90: =IF($A90="","",IFERROR(AVERAGEIFS(K$2:K90,WEEKNUM(A$2:A90,2),WEEKNUM(A90,2)),K90)) | N90: =IF($A90="","",IFERROR(COUNTIFS(A$2:A90,"<>",L$2:L90,"达标",WEEKNUM(A$2:A90,2),WEEKNUM(A90,2)),0)) | O90: =IF($A90="","",IF(L90="达标",IF(ROW()=2,1,IF(O89="",1,O89+1)),0)) | P90: =IF($A90="","",IF(ROW()<=8,"基准周",IF(K90>75,"改善",IF(K90<60,"恶化","持平"))))
K91: =IF($A91="","",IF(B91=0,20,IF(B91=1,15,IF(B91=2,10,IF(B91=3,5,0))))+IF(C91="否",20,0)+IF(D91="是",20,0)+IF(E91=1,20,IF(E91=2,15,IF(E91=3,10,IF(E91=4,5,0))))+IF(F91="否",20,0)) | L91: =IF($A91="","",IF(K91>=80,"达标","未达标")) | M91: =IF($A91="","",IFERROR(AVERAGEIFS(K$2:K91,WEEKNUM(A$2:A91,2),WEEKNUM(A91,2)),K91)) | N91: =IF($A91="","",IFERROR(COUNTIFS(A$2:A91,"<>",L$2:L91,"达标",WEEKNUM(A$2:A91,2),WEEKNUM(A91,2)),0)) | O91: =IF($A91="","",IF(L91="达标",IF(ROW()=2,1,IF(O90="",1,O90+1)),0)) | P91: =IF($A91="","",IF(ROW()<=8,"基准周",IF(K91>75,"改善",IF(K91<60,"恶化","持平"))))
