Workbook

Sheet 执行清单
A1: 流程 | B1: 检查项 | C1: 判断依据 | D1: 自动结论 | E1: 手动确认 | F1: 不通过动作 | G1: 备注
A2: 周末 | B2: 赚钱效应分数已更新 | C2: 账户总表!赚钱效应分数 | F2: 未更新则不生成下周买入计划
A3: 周末 | B3: 亏钱效应分数已更新 | C3: 账户总表!亏钱效应分数 | F3: 未更新则默认按警戒处理
A4: 周末 | B4: 候选池已生成 | C4: ratio / DL_P / valid / SignalType | F4: 没有候选池则周一不新开仓
A5: 周一盘前 | B5: 账户状态不是防守 | C5: 当前状态 <> 防守 | D5: =IFERROR(IF(LOOKUP(2,1/(账户总表!$A:$A<>""),账户总表!$T:$T)<>"防守","是","否"),"否") -> 是 | F5: 防守状态只处理持仓风险
A6: 周一盘前 | B6: 允许新开仓 | C6: 账户总表!是否允许新开仓 | D6: =IFERROR(LOOKUP(2,1/(账户总表!$A:$A<>""),账户总表!$V:$V),"否") -> 否 | F6: 不允许则取消新增买入
A7: 周一盘前 | B7: 未暂停买入 | C7: 账户总表!是否暂停买入 = 否 | D7: =IFERROR(IF(LOOKUP(2,1/(账户总表!$A:$A<>""),账户总表!$W:$W)="否","是","否"),"否") -> 是 | F7: 暂停买入时只允许卖出/减仓
A8: 周一盘前 | B8: 总仓位未超上限 | C8: 总仓位 <= 总仓位上限 | D8: =IFERROR(IF(LOOKUP(2,1/(账户总表!$A:$A<>""),账户总表!$E:$E)<=LOOKUP(2,1/(账户总表!$A:$A<>""),账户总表!$N:$N),"是","否"),"否") -> 否 | F8: 超限先减仓，不新买
A9: 周一盘前 | B9: 有效持仓数未超上限 | C9: 有效持仓数 <= 有效持仓上限 | D9: =IFERROR(IF(LOOKUP(2,1/(账户总表!$A:$A<>""),账户总表!$R:$R)<=LOOKUP(2,1/(账户总表!$A:$A<>""),账户总表!$S:$S),"是","否"),"否") -> 否 | F9: 超限则不新增标的
A10: 周一盘前 | B10: 亏钱效应可控 | C10: 亏钱效应分数 <= 2 | D10: =IFERROR(IF(LOOKUP(2,1/(账户总表!$A:$A<>""),账户总表!$M:$M)<=2,"是","否"),"否") -> 是 | F10: 亏钱效应偏高则暂停转入/新开
A11: 周一盘前 | B11: 存在最终可买候选 | C11: 候选池!最终是否可买 = 是 | D11: =IFERROR(IF(COUNTIFS(候选池!$A:$A,LOOKUP(2,1/(账户总表!$A:$A<>""),账户总表!$A:$A),候选池!$AC:$AC,"是")>0,"是","否"),"否") -> 否 | F11: 没有可买候选则不下单
A12: 盘中买入 | B12: 只买最终可买=是的标的 | C12: 候选池!最终是否可买 | F12: 任一条件为否则不买
A13: 盘中买入 | B13: 止损价和失效条件已写 | C13: StopPrice > 0 且 InvalidationCondition 非空 | F13: 没写清楚不下单
A14: 盘中买入 | B14: 不是追价情绪单 | C14: Price <= SignalPrice * 1.02 或回踩确认 | F14: 追价则取消委托
A15: 持仓处理 | B15: 没有必须卖出的持仓 | C15: 执行结论不含立即卖出/次日卖出 | D15: =IFERROR(IF(COUNTIFS(持仓表!$A:$A,LOOKUP(2,1/(账户总表!$A:$A<>""),账户总表!$A:$A),持仓表!$AB:$AB,"立即卖出")+COUNTIFS(持仓表!$A:$A,LOOKUP(2,1/(账户总表!$A:$A<>""),账户总表!$A:$A),持仓表!$AB:$AB,"次日卖出")=0,"是","否"),"否") -> 是 | F15: 先卖出，再考虑新买
A16: 持仓处理 | B16: RiskWatch 已复核 | C16: RiskWatch = 是的持仓逐只检查 | F16: 观察股不加仓，重点看止损
A17: 转入转出 | B17: 转入只服务合规缺口 | C17: 是否允许转入=是 且 候选池提示缺口 | D17: =IFERROR(IF(AND(LOOKUP(2,1/(账户总表!$A:$A<>""),账户总表!$U:$U)="是",maxifs(候选池!$AB:$AB,候选池!$A:$A,LOOKUP(2,1/(账户总表!$A:$A<>""),账户总表!$A:$A))>0),"是","不适用"),"不适用") -> 不适用 | F17: 先有合规候选，再转入
A18: 转入转出 | B18: 防守转出已检查 | C18: 账户计划转出金额 | D18: =IFERROR(IF(LOOKUP(2,1/(账户总表!$A:$A<>""),账户总表!$Y:$Y)>0,"是","不适用"),"不适用") -> 不适用 | F18: 防守/利润转出分开处理
A19: 收盘后 | B19: 交易记录已补全 | C19: 成交价/股数/金额/止损/原因 | F19: 不记录则次日不新增交易
A20: 收盘后 | B20: 持仓表已更新 | C20: Close / ratio / DL_P / valid | F20: 未更新则不依赖次日公式结论
A21: 周复盘 | B21: 本周最大问题只写一条 | C21: 周复盘!本周最大问题 | F21: 只修最主要的执行偏差
A22: 每日 | B22: 心态日志已填写 | C22: 盘中看盘/情绪/执行 | F22: 未填写则心态得分缺失
A23: 每日 | B23: 盘中看盘次数<=1 | C23: 心态日志!盘中看盘次数 | F23: 超1次需说明原因
A24: 每日 | B24: 无止损外操作 | C24: 心态日志!是否有止损外操作 | F24: 偏离系统=心态偏离
A25: 每周 | B25: 心态趋势已复盘 | C25: 心态日志!心态趋势 | F25: 连续恶化需调整策略
A26: 每周 | B26: 连续达标天数>=3 | C26: 心态日志!连续达标天数 | F26: 低于3天需加强纪律

Sheet 关键变量表
A1: 类型 | B1: 变量名 | C1: Excel字段 | D1: 计算方式 | E1: 触发阈值 | F1: 影响动作 | G1: 复盘频率 | H1: 备注
A2: 生存变量 | B2: MaxDrawdown | C2: 账户总表!最大回撤 | D2: (TotalAsset-PeakAsset)/PeakAsset | E2: <=-10%, <=-15% | F2: 降总仓位/禁止新买入 | G2: 每日+周复盘 | H2: 决定系统是否降速
A3: 生存变量 | B3: 单笔止损 | C3: 持仓表!止损价 | D3: max(BuyPointLow*0.98, EntryPrice*0.92) | E3: Price<=StopPrice | F3: 次日卖出或立即卖出 | G3: 每日 | H3: 买前必须定义
A4: 生存变量 | B4: 连续亏损 | C4: 交易记录!结果分类 | D4: 近5笔亏损数 | E4: >=3笔 | F4: 暂停新开仓5个交易日 | G4: 每次成交后 | H4: 后续可扩展公式
A5: 扩张变量 | B5: 赚钱效应分数 | C5: 账户总表!赚钱效应分数 | D5: 0-5分 | E5: >=3 | F5: 允许转入/扩大执行 | G5: 周末 | H5: 强时按系数放大转入
A6: 扩张变量 | B6: 合规候选数量 | C6: 候选池!最终是否可买 | D6: COUNTIF(...,"是") | E6: >=1 | F6: 准备买入计划 | G6: 周末+盘前 | H6: 只统计规则通过标的
A7: 收缩变量 | B7: 亏钱效应分数 | C7: 账户总表!亏钱效应分数 | D7: 0-6分 | E7: >=3警戒, >=4防守 | F7: 暂停转入/提高现金 | G7: 每日+周末 | H7: 优先级高于赚钱效应
A8: 收缩变量 | B8: RiskWatch | C8: 持仓表!RiskWatch | D8: Close<EntryPrice AND DL_P<0.8 | E8: True | F8: 重点盯防 | G8: 每日 | H8: 观察不等于立即卖出
A9: 仓位变量 | B9: TotalPositionCap | C9: 账户总表!总仓位上限 | D9: 市场状态+信号等级+回撤保护 | E9: 最高70% | F9: 限制新增买入 | G9: 周一盘前 | H9: 硬性仓位上限
A10: 仓位变量 | B10: SingleStockCap | C10: 账户总表!单股上限 | D10: 按总资产分档 | E10: 20%-35% | F10: 限制单票暴露 | G10: 每日 | H10: 非WAIVED适用
A11: 仓位变量 | B11: MaxShares/MinShares | C11: 候选池!最大/最小可买股数 | D11: 100股整数约束 | E11: Max>=Min | F11: 决定是否可落地交易 | G11: 盘前 | H11: A股最小单位适配
A12: 执行变量 | B12: NotChasing | C12: 候选池!是否未追价 | D12: Price<=SignalPrice*1.02 | E12: 是 | F12: 禁止情绪追价 | G12: 盘前+盘中 | H12: 高开无回踩不买
... A22: 心态变量 | B22: 盘中看盘次数 | C22: 心态日志!盘中看盘次数 | D22: 每日看盘次数 | E22: 0次=满分 | F22: 目标逐步降至0次 | G22: 每日 | H22: 信息节食核心指标

Sheet 账户总表
A1: 日期 | B1: 总资产 TotalAsset | C1: 可用现金 CashAvailable | D1: 持仓市值 | E1: 总仓位 TotalPositionRatio | F1: 净入金 NetDeposit | G1: 阶段高点资产 PeakAsset | H1: 账户收益率 AccountReturn | I1: 最大回撤 MaxDrawdown | J1: 当前市场状态 MarketState | K1: 本周最高信号等级 | L1: 赚钱效应分数 | M1: 亏钱效应分数 | N1: 总仓位上限 TotalPositionCap | O1: 单股上限 SingleStockCap | P1: 总持仓数 | Q1: WAIVED数 | R1: 有效持仓数 | S1: 有效持仓上限 | T1: 当前状态 | U1: 是否允许转入 | V1: 是否允许新开仓 | W1: 是否暂停买入 | X1: 本周计划转入金额 | Y1: 本周计划转出金额 | Z1: 备注 | AA1: 初始本金 Principal | AB1: 目标年化收益率 TargetAnnualReturn | AC1: 运行月数 MonthsRunning | AD1: 目标资产 TargetAsset | AE1: 复利偏离度 CompoundDeviation | AF1: 交易股票数 TradeCount | AG1: 账户阶段 | AH1: 平均仓位 AvgPosition | AI1: 平均持仓天数 AvgHoldDays | AJ1: 交易成功率 SuccessRate | AK1: 资金周转率 CapitalTurnover | AL1: 做T次数 T0Count | AM1: 做T成功率 T0SuccessRate | AN1: 重仓行业 HeavySector | AO1: 投资风格 Style | AP1: 跑赢上证 BeatIndex | AQ1: 净入金后累计盈利 RealPnL
A2: 2026-01-31 | B2: 6683.54 | C2: 0 | D2: =IF($A2="","",SUMIFS(持仓表!$J:$J,持仓表!$A:$A,$A2)) -> 0 | E2: =IFERROR(D2/B2,0) -> 0 | F2: 2700 | G2: =IF($B2="","",MAX($B$2:B2)) -> 6683.54 | H2: =IFERROR((B2-F2)/F2,0) -> 1.4753852 | I2: =IFERROR((B2-G2)/G2,0) -> 0 | J2: 中性 | K2: B | L2: 2 | M2: 2 | N2: =IF($B2="","",MIN(70%,IF($I2<=-15%,10%,IF($I2<=-10%,30%,IF($M2>=4,10%,IF($M2>=3,30%,IF($J2="强",IF($K2="A",70%,IF($K2="B",60%,40%)),IF($J2="中性",IF($K2="A",50%,IF($K2="B",40%,25%)),IF($K2="A",30%,IF($K2="B",20%,10%)))))))))) -> 0.4 | O2: =IF($B2="","",IF(B2<30000,35%,IF(B2<50000,30%,IF(B2<100000,25%,20%)))) -> 0.35 | P2: =IF($A2="","",COUNTIFS(持仓表!$A:$A,$A2,持仓表!$G:$G,">0")) -> 0 | Q2: =IF($A2="","",COUNTIFS(持仓表!$A:$A,$A2,持仓表!$D:$D,"是",持仓表!$G:$G,">0")) -> 0 | R2: =IF($A2="","",MAX(0,P2-Q2)) -> 0 | S2: =IF($B2="","",IF(B2<50000,3,IF(B2<100000,4,5))) -> 3 | T2: =IF($A2="","",IF(OR(M2>=4,I2<=-8%),"防守",IF(OR(M2>=2,I2<=-5%),"警戒","正常"))) -> 警戒 | U2: =IF($A2="","",IF(AND(L2>=3,M2<=2,T2<>"防守"),"是","否")) -> 否 | V2: =IF($A2="","",IF(AND(E2<N2,R2<S2,M2<=2,I2>-15%),"是","否")) -> 是 | W2: =IF($A2="","",IF(OR(M2>=3,I2<=-15%),"是","否")) -> 否 | X2: =IF($A2="","",IFERROR(maxifs(候选池!$AB:$AB,候选池!$A:$A,$A2),0)) -> 0 | Y2: =IF($A2="","",IF(OR(M2>=4,I2<=-8%),MAX(0,B2*60%-C2),IF(AND(ISNUMBER(AD2),B2>AD2),IF(B2<30000,0,IF(B2<100000,MAX(0,(B2-AD2)*0.2),MAX(0,(B2-AD2)*0.3))),0))) -> 0 | AA2: 6683.54 | AB2: =IF($A2="","",IF(B2<30000,0.03,IF(B2<100000,0.02,0.015))) -> 0.03 | AC2: =IF($A2="","",IFERROR(DATEDIF($A$2,$A2,"m"),0)) -> 0 | AD2: =IF($A2="","",IF(OR(AA2="",AB2="",AC2=""),"",AA2*POWER(1+AB2,AC2))) -> 6683.54 | AE2: =IF($A2="","",IF(OR(AD2="",AD2=0),"",B2/AD2-1)) -> 0 | AF2: 2 | AG2: =IF($A2="","",IF(B2<30000,"婴儿",IF(B2<100000,"成长","成熟"))) -> 婴儿 | AH2: 0.7073 | AI2: 38 | AJ2: 1 | AK2: 0.0002 | AL2: 0 | AM2: 0 | AN2: 汽车 | AO2: 小盘 | AP2: 否 | AQ2: =IF($A2="","",B2-$AA$2-SUM($F$2:F2)) -> -2700
A3: 2026-02-28 | B3: 9520.45 | C3: 0 | D3: =IF($A3="","",SUMIFS(持仓表!$J:$J,持仓表!$A:$A,$A3)) -> 0 | E3: =IFERROR(D3/B3,0) -> 0 | F3: 0 | G3: =IF($B3="","",MAX($B$2:B3)) -> 9520.45 | H3: =IFERROR((B3-F3)/F3,0) -> 0 | I3: =IFERROR((B3-G3)/G3,0) -> 0 | J3: 强 | K3: A | L3: 3 | M3: 1 | N3: =IF($B3="","",MIN(70%,IF($I3<=-15%,10%,IF($I3<=-10%,30%,IF($M3>=4,10%,IF($M3>=3,30%,IF($J3="强",IF($K3="A",70%,IF($K3="B",60%,40%)),IF($J3="中性",IF($K3="A",50%,IF($K3="B",40%,25%)),IF($K3="A",30%,IF($K3="B",20%,10%)))))))))) -> 0.7 | O3: =IF($B3="","",IF(B3<30000,35%,IF(B3<50000,30%,IF(B3<100000,25%,20%)))) -> 0.35 | P3: =IF($A3="","",COUNTIFS(持仓表!$A:$A,$A3,持仓表!$G:$G,">0")) -> 0 | Q3: =IF($A3="","",COUNTIFS(持仓表!$A:$A,$A3,持仓表!$D:$D,"是",持仓表!$G:$G,">0")) -> 0 | R3: =IF($A3="","",MAX(0,P3-Q3)) -> 0 | S3: =IF($B3="","",IF(B3<50000,3,IF(B3<100000,4,5))) -> 3 | T3: =IF($A3="","",IF(OR(M3>=4,I3<=-8%),"防守",IF(OR(M3>=2,I3<=-5%),"警戒","正常"))) -> 正常 | U3: =IF($A3="","",IF(AND(L3>=3,M3<=2,T3<>"防守"),"是","否")) -> 是 | V3: =IF($A3="","",IF(AND(E3<N3,R3<S3,M3<=2,I3>-15%),"是","否")) -> 是 | W3: =IF($A3="","",IF(OR(M3>=3,I3<=-15%),"是","否")) -> 否 | X3: =IF($A3="","",IFERROR(maxifs(候选池!$AB:$AB,候选池!$A:$A,$A3),0)) -> 0 | Y3: =IF($A3="","",IF(OR(M3>=4,I3<=-8%),MAX(0,B3*60%-C3),IF(AND(ISNUMBER(AD3),B3>AD3),IF(B3<30000,0,IF(B3<100000,MAX(0,(B3-AD3)*0.2),MAX(0,(B3-AD3)*0.3))),0))) -> 0 | AA3: =IF($A3="","",IF($AA$2<>"",$AA$2,"")) -> 6683.54 | AB3: =IF($A3="","",IF(B3<30000,0.03,IF(B3<100000,0.02,0.015))) -> 0.03 | AC3: =IF($A3="","",IFERROR(DATEDIF($A$2,$A3,"m"),0)) -> 0 | AD3: =IF($A3="","",IF(OR(AA3="",AB3="",AC3=""),"",AA3*POWER(1+AB3,AC3))) -> 6683.54 | AE3: =IF($A3="","",IF(OR(AD3="",AD3=0),"",B3/AD3-1)) -> 0.42446219 | AF3: 1 | AG3: =IF($A3="","",IF(B3<30000,"婴儿",IF(B3<100000,"成长","成熟"))) -> 婴儿 | AH3: 0.5625 | AI3: 62 | AJ3: 1 | AK3: 0.2272 | AL3: 0 | AM3: 0 | AN3: 电子 | AO3: 中盘成长 | AP3: 是 | AQ3: =IF($A3="","",B3-$AA$2-SUM($F$2:F3)) -> 136.91
A4: 2026-03-31 | B4: 11454.37 | C4: 0 | D4: =IF($A4="","",SUMIFS(持仓表!$J:$J,持仓表!$A:$A,$A4)) -> 0 | E4: =IFERROR(D4/B4,0) -> 0 | F4: 0 | G4: =IF($B4="","",MAX($B$2:B4)) -> 11454.37 | H4: =IFERROR((B4-F4)/F4,0) -> 0 | I4: =IFERROR((B4-G4)/G4,0) -> 0 | J4: 弱 | K4: C | L4: 1 | M4: 3 | N4: =IF($B4="","",MIN(70%,IF($I4<=-15%,10%,IF($I4<=-10%,30%,IF($M4>=4,10%,IF($M4>=3,30%,IF($J4="强",IF($K4="A",70%,IF($K4="B",60%,40%)),IF($J4="中性",IF($K4="A",50%,IF($K4="B",40%,25%)),IF($K4="A",30%,IF($K4="B",20%,10%)))))))))) -> 0.3 | O4: =IF($B4="","",IF(B4<30000,35%,IF(B4<50000,30%,IF(B4<100000,25%,20%)))) -> 0.35 | P4: =IF($A4="","",COUNTIFS(持仓表!$A:$A,$A4,持仓表!$G:$G,">0")) -> 0 | Q4: =IF($A4="","",COUNTIFS(持仓表!$A:$A,$A4,持仓表!$D:$D,"是",持仓表!$G:$G,">0")) -> 0 | R4: =IF($A4="","",MAX(0,P4-Q4)) -> 0 | S4: =IF($B4="","",IF(B4<50000,3,IF(B4<100000,4,5))) -> 3 | T4: =IF($A4="","",IF(OR(M4>=4,I4<=-8%),"防守",IF(OR(M4>=2,I4<=-5%),"警戒","正常"))) -> 警戒 | U4: =IF($A4="","",IF(AND(L4>=3,M4<=2,T4<>"防守"),"是","否")) -> 否 | V4: =IF($A4="","",IF(AND(E4<N4,R4<S4,M4<=2,I4>-15%),"是","否")) -> 否 | W4: =IF($A4="","",IF(OR(M4>=3,I4<=-15%),"是","否")) -> 是 | X4: =IF($A4="","",IFERROR(maxifs(候选池!$AB:$AB,候选池!$A:$A,$A4),0)) -> 0 | Y4: =IF($A4="","",IF(OR(M4>=4,I4<=-8%),MAX(0,B4*60%-C4),IF(AND(ISNUMBER(AD4),B4>AD4),IF(B4<30000,0,IF(B4<100000,MAX(0,(B4-AD4)*0.2),MAX(0,(B4-AD4)*0.3))),0))) -> 0 | AA4: =IF($A4="","",IF($AA$2<>"",$AA$2,"")) -> 6683.54 | AB4: =IF($A4="","",IF(B4<30000,0.03,IF(B4<100000,0.02,0.015))) -> 0.03 | AC4: =IF($A4="","",IFERROR(DATEDIF($A$2,$A4,"m"),0)) -> 2 | AD4: =IF($A4="","",IF(OR(AA4="",AB4="",AC4=""),"",AA4*POWER(1+AB4,AC4))) -> 7090.5676 | AE4: =IF($A4="","",IF(OR(AD4="",AD4=0),"",B4/AD4-1)) -> 0.61543767 | AF4: 0 | AG4: =IF($A4="","",IF(B4<30000,"婴儿",IF(B4<100000,"成长","成熟"))) -> 婴儿 | AH4: 0.7306 | AI4: 0 | AJ4: 0 | AK4: 0 | AL4: 2 | AM4: 1 | AN4: 电子 | AO4: 中盘成长 | AP4: 是 | AQ4: =IF($A4="","",B4-$AA$2-SUM($F$2:F4)) -> 2070.83
A5: 2026-04-30 | B5: 14148.37 | C5: 0 | D5: =IF($A5="","",SUMIFS(持仓表!$J:$J,持仓表!$A:$A,$A5)) -> 0 | E5: =IFERROR(D5/B5,0) -> 0 | F5: 0 | G5: =IF($B5="","",MAX($B$2:B5)) -> 14148.37 | H5: =IFERROR((B5-F5)/F5,0) -> 0 | I5: =IFERROR((B5-G5)/G5,0) -> 0 | J5: 强 | K5: A | L5: 4 | M5: 1 | N5: =IF($B5="","",MIN(70%,IF($I5<=-15%,10%,IF($I5<=-10%,30%,IF($M5>=4,10%,IF($M5>=3,30%,IF($J5="强",IF($K5="A",70%,IF($K5="B",60%,40%)),IF($J5="中性",IF($K5="A",50%,IF($K5="B",40%,25%)),IF($K5="A",30%,IF($K5="B",20%,10%)))))))))) -> 0.7 | O5: =IF($B5="","",IF(B5<30000,35%,IF(B5<50000,30%,IF(B5<100000,25%,20%)))) -> 0.35 | P5: =IF($A5="","",COUNTIFS(持仓表!$A:$A,$A5,持仓表!$G:$G,">0")) -> 0 | Q5: =IF($A5="","",COUNTIFS(持仓表!$A:$A,$A5,持仓表!$D:$D,"是",持仓表!$G:$G,">0")) -> 0 | R5: =IF($A5="","",MAX(0,P5-Q5)) -> 0 | S5: =IF($B5="","",IF(B5<50000,3,IF(B5<100000,4,5))) -> 3 | T5: =IF($A5="","",IF(OR(M5>=4,I5<=-8%),"防守",IF(OR(M5>=2,I5<=-5%),"警戒","正常"))) -> 正常 | U5: =IF($A5="","",IF(AND(L5>=3,M5<=2,T5<>"防守"),"是","否")) -> 是 | V5: =IF($A5="","",IF(AND(E5<N5,R5<S5,M5<=2,I5>-15%),"是","否")) -> 是 | W5: =IF($A5="","",IF(OR(M5>=3,I5<=-15%),"是","否")) -> 否 | X5: =IF($A5="","",IFERROR(maxifs(候选池!$AB:$AB,候选池!$A:$A,$A5),0)) -> 0 | Y5: =IF($A5="","",IF(OR(M5>=4,I5<=-8%),MAX(0,B5*60%-C5),IF(AND(ISNUMBER(AD5),B5>AD5),IF(B5<30000,0,IF(B5<100000,MAX(0,(B5-AD5)*0.2),MAX(0,(B5-AD5)*0.3))),0))) -> 0 | AA5: =IF($A5="","",IF($AA$2<>"",$AA$2,"")) -> 6683.54 | AB5: =IF($A5="","",IF(B5<30000,0.03,IF(B5<100000,0.02,0.015))) -> 0.03 | AC5: =IF($A5="","",IFERROR(DATEDIF($A$2,$A5,"m"),0)) -> 2 | AD5: =IF($A5="","",IF(OR(AA5="",AB5="",AC5=""),"",AA5*POWER(1+AB5,AC5))) -> 7090.5676 | AE5: =IF($A5="","",IF(OR(AD5="",AD5=0),"",B5/AD5-1)) -> 0.99537905 | AF5: 2 | AG5: =IF($A5="","",IF(B5<30000,"婴儿",IF(B5<100000,"成长","成熟"))) -> 婴儿 | AH5: 0.7543 | AI5: 0 | AJ5: 0 | AK5: 0 | AL5: 0 | AM5: 0 | AN5: 电子 | AO5: 中盘成长 | AP5: 是 | AQ5: =IF($A5="","",B5-$AA$2-SUM($F$2:F5)) -> 4764.83
A6: 2026-05-31 | B6: 17086.37 | C6: 0 | D6: =IF($A6="","",SUMIFS(持仓表!$J:$J,持仓表!$A:$A,$A6)) -> 0 | E6: =IFERROR(D6/B6,0) -> 0 | F6: 0 | G6: =IF($B6="","",MAX($B$2:B6)) -> 17086.37 | H6: =IFERROR((B6-F6)/F6,0) -> 0 | I6: =IFERROR((B6-G6)/G6,0) -> 0 | J6: 强 | K6: A | L6: 4 | M6: 1 | N6: =IF($B6="","",MIN(70%,IF($I6<=-15%,10%,IF($I6<=-10%,30%,IF($M6>=4,10%,IF($M6>=3,30%,IF($J6="强",IF($K6="A",70%,IF($K6="B",60%,40%)),IF($J6="中性",IF($K6="A",50%,IF($K6="B",40%,25%)),IF($K6="A",30%,IF($K6="B",20%,10%)))))))))) -> 0.7 | O6: =IF($B6="","",IF(B6<30000,35%,IF(B6<50000,30%,IF(B6<100000,25%,20%)))) -> 0.35 | P6: =IF($A6="","",COUNTIFS(持仓表!$A:$A,$A6,持仓表!$G:$G,">0")) -> 0 | Q6: =IF($A6="","",COUNTIFS(持仓表!$A:$A,$A6,持仓表!$D:$D,"是",持仓表!$G:$G,">0")) -> 0 | R6: =IF($A6="","",MAX(0,P6-Q6)) -> 0 | S6: =IF($B6="","",IF(B6<50000,3,IF(B6<100000,4,5))) -> 3 | T6: =IF($A6="","",IF(OR(M6>=4,I6<=-8%),"防守",IF(OR(M6>=2,I6<=-5%),"警戒","正常"))) -> 正常 | U6: =IF($A6="","",IF(AND(L6>=3,M6<=2,T6<>"防守"),"是","否")) -> 是 | V6: =IF($A6="","",IF(AND(E6<N6,R6<S6,M6<=2,I6>-15%),"是","否")) -> 是 | W6: =IF($A6="","",IF(OR(M6>=3,I6<=-15%),"是","否")) -> 否 | X6: =IF($A6="","",IFERROR(maxifs(候选池!$AB:$AB,候选池!$A:$A,$A6),0)) -> 0 | Y6: =IF($A6="","",IF(OR(M6>=4,I6<=-8%),MAX(0,B6*60%-C6),IF(AND(ISNUMBER(AD6),B6>AD6),IF(B6<30000,0,IF(B6<100000,MAX(0,(B6-AD6)*0.2),MAX(0,(B6-AD6)*0.3))),0))) -> 0 | AA6: =IF($A6="","",IF($AA$2<>"",$AA$2,"")) -> 6683.54 | AB6: =IF($A6="","",IF(B6<30000,0.03,IF(B6<100000,0.02,0.015))) -> 0.03 | AC6: =IF($A6="","",IFERROR(DATEDIF($A$2,$A6,"m"),0)) -> 4 | AD6: =IF($A6="","",IF(OR(AA6="",AB6="",AC6=""),"",AA6*POWER(1+AB6,AC6))) -> 7522.3832 | AE6: =IF($A6="","",IF(OR(AD6="",AD6=0),"",B6/AD6-1)) -> 1.2714038 | AF6: 1 | AG6: =IF($A6="","",IF(B6<30000,"婴儿",IF(B6<100000,"成长","成熟"))) -> 婴儿 | AH6: 0.7849 | AI6: 0 | AJ6: 0 | AK6: 0 | AL6: 0 | AM6: 0 | AN6: 电力 | AO6: 中盘价值 | AP6: 是 | AQ6: =IF($A6="","",B6-$AA$2-SUM($F$2:F6)) -> 7702.83
A7: 2026-06-30 | B7: 18504 | C7: 0 | D7: =IF($A7="","",SUMIFS(持仓表!$J:$J,持仓表!$A:$A,$A7)) -> 0 | E7: =IFERROR(D7/B7,0) -> 0 | F7: 0 | G7: =IF($B7="","",MAX($B$2:B7)) -> 18504 | H7: =IFERROR((B7-F7)/F7,0) -> 0 | I7: =IFERROR((B7-G7)/G7,0) -> 0 | J7: 中性 | K7: B | L7: 3 | M7: 2 | N7: =IF($B7="","",MIN(70%,IF($I7<=-15%,10%,IF($I7<=-10%,30%,IF($M7>=4,10%,IF($M7>=3,30%,IF($J7="强",IF($K7="A",70%,IF($K7="B",60%,40%)),IF($J7="中性",IF($K7="A",50%,IF($K7="B",40%,25%)),IF($K7="A",30%,IF($K7="B",20%,10%)))))))))) -> 0.4 | O7: =IF($B7="","",IF(B7<30000,35%,IF(B7<50000,30%,IF(B7<100000,25%,20%)))) -> 0.35 | P7: =IF($A7="","",COUNTIFS(持仓表!$A:$A,$A7,持仓表!$G:$G,">0")) -> 0 | Q7: =IF($A7="","",COUNTIFS(持仓表!$A:$A,$A7,持仓表!$D:$D,"是",持仓表!$G:$G,">0")) -> 0 | R7: =IF($A7="","",MAX(0,P7-Q7)) -> 0 | S7: =IF($B7="","",IF(B7<50000,3,IF(B7<100000,4,5))) -> 3 | T7: =IF($A7="","",IF(OR(M7>=4,I7<=-8%),"防守",IF(OR(M7>=2,I7<=-5%),"警戒","正常"))) -> 警戒 | U7: =IF($A7="","",IF(AND(L7>=3,M7<=2,T7<>"防守"),"是","否")) -> 是 | V7: =IF($A7="","",IF(AND(E7<N7,R7<S7,M7<=2,I7>-15%),"是","否")) -> 是 | W7: =IF($A7="","",IF(OR(M7>=3,I7<=-15%),"是","否")) -> 否 | X7: =IF($A7="","",IFERROR(maxifs(候选池!$AB:$AB,候选池!$A:$A,$A7),0)) -> 0 | Y7: =IF($A7="","",IF(OR(M7>=4,I7<=-8%),MAX(0,B7*60%-C7),IF(AND(ISNUMBER(AD7),B7>AD7),IF(B7<30000,0,IF(B7<100000,MAX(0,(B7-AD7)*0.2),MAX(0,(B7-AD7)*0.3))),0))) -> 0 | AA7: =IF($A7="","",IF($AA$2<>"",$AA$2,"")) -> 6683.54 | AB7: =IF($A7="","",IF(B7<30000,0.03,IF(B7<100000,0.02,0.015))) -> 0.03 | AC7: =IF($A7="","",IFERROR(DATEDIF($A$2,$A7,"m"),0)) -> 4 | AD7: =IF($A7="","",IF(OR(AA7="",AB7="",AC7=""),"",AA7*POWER(1+AB7,AC7))) -> 7522.3832 | AE7: =IF($A7="","",IF(OR(AD7="",AD7=0),"",B7/AD7-1)) -> 1.4598587 | AF7: 2 | AG7: =IF($A7="","",IF(B7<30000,"婴儿",IF(B7<100000,"成长","成熟"))) -> 婴儿 | AH7: 0.7012 | AI7: 80 | AJ7: 1 | AK7: 0.3937 | AL7: 0 | AM7: 0 | AN7: 电力 | AO7: 中盘价值 | AP7: 是 | AQ7: =IF($A7="","",B7-$AA$2-SUM($F$2:F7)) -> 9120.46
A8: 46224 | B8: 20326.12 | C8: 7847.12 | D8: =IF($A8="","",SUMIFS(持仓表!$J:$J,持仓表!$A:$A,$A8)) -> 10642 | E8: =IFERROR(D8/B8,0) -> 0.52356279 | F8: 1309 | G8: =IF($B8="","",MAX($B$2:B8)) -> 20326.12 | H8: =IFERROR((B8-F8)/F8,0) -> 14.527976 | I8: =IFERROR((B8-G8)/G8,0) -> 0 | J8: 中性 | K8: B | L8: 3 | M8: 2 | N8: =IF($B8="","",MIN(70%,IF($I8<=-15%,10%,IF($I8<=-10%,30%,IF($M8>=4,10%,IF($M8>=3,30%,IF($J8="强",IF($K8="A",70%,IF($K8="B",60%,40%)),IF($J8="中性",IF($K8="A",50%,IF($K8="B",40%,25%)),IF($K8="A",30%,IF($K8="B",20%,10%)))))))))) -> 0.4 | O8: =IF($B8="","",IF(B8<30000,35%,IF(B8<50000,30%,IF(B8<100000,25%,20%)))) -> 0.35 | P8: =IF($A8="","",COUNTIFS(持仓表!$A:$A,$A8,持仓表!$G:$G,">0")) -> 3 | Q8: =IF($A8="","",COUNTIFS(持仓表!$A:$A,$A8,持仓表!$D:$D,"是",持仓表!$G:$G,">0")) -> 1 | R8: =IF($A8="","",MAX(0,P8-Q8)) -> 2 | S8: =IF($B8="","",IF(B8<50000,3,IF(B8<100000,4,5))) -> 3 | T8: =IF($A8="","",IF(OR(M8>=4,I8<=-8%),"防守",IF(OR(M8>=2,I8<=-5%),"警戒","正常"))) -> 警戒 | U8: =IF($A8="","",IF(AND(L8>=3,M8<=2,T8<>"防守"),"是","否")) -> 是 | V8: =IF($A8="","",IF(AND(E8<N8,R8<S8,M8<=2,I8>-15%),"是","否")) -> 否 | W8: =IF($A8="","",IF(OR(M8>=3,I8<=-15%),"是","否")) -> 否 | X8: =IF($A8="","",IFERROR(maxifs(候选池!$AB:$AB,候选池!$A:$A,$A8),0)) -> 0 | Y8: =IF($A8="","",IF(OR(M8>=4,I8<=-8%),MAX(0,B8*60%-C8),IF(AND(ISNUMBER(AD8),B8>AD8),IF(B8<30000,0,IF(B8<100000,MAX(0,(B8-AD8)*0.2),MAX(0,(B8-AD8)*0.3))),0))) -> 0 | Z8: 12:36录入,当日盈亏-143元 | AA8: =IF($A8="","",IF($AA$2<>"",$AA$2,"")) -> 6683.54 | AB8: =IF($A8="","",IF(B8<30000,0.03,IF(B8<100000,0.02,0.015))) -> 0.03 | AC8: =IF($A8="","",IFERROR(DATEDIF($A$2,$A8,"m"),0)) -> 5 | AD8: =IF($A8="","",IF(OR(AA8="",AB8="",AC8=""),"",AA8*POWER(1+AB8,AC8))) -> 7748.0546 | AE8: =IF($A8="","",IF(OR(AD8="",AD8=0),"",B8/AD8-1)) -> 1.6233837 | AF8: 2 | AG8: =IF($A8="","",IF(B8<30000,"婴儿",IF(B8<100000,"成长","成熟"))) -> 婴儿 | AH8: 0.3423 | AI8: 5 | AJ8: 1 | AK8: 0.0058 | AL8: 1 | AM8: 0 | AN8: 化工 | AO8: 大盘价值 | AP8: 是 | AQ8: =IF($A8="","",B8-$AA$2-SUM($F$2:F8)) -> 9633.58
A9: 46225 | B9: 20798.12 | C9: 7847.12 | D9: =IF($A9="","",SUMIFS(持仓表!$J:$J,持仓表!$A:$A,$A9)) -> 0 | E9: =IFERROR(D9/B9,0) -> 0 | G9: =IF($B9="","",MAX($B$2:B9)) -> 20798.12 | H9: =IFERROR((B9-F9)/F9,0) -> 0 | I9: =IFERROR((B9-G9)/G9,0) -> 0 | N9: =IF($B9="","",MIN(70%,IF($I9<=-15%,10%,IF($I9<=-10%,30%,IF($M9>=4,10%,IF($M9>=3,30%,IF($J9="强",IF($K9="A",70%,IF($K9="B",60%,40%)),IF($J9="中性",IF($K9="A",50%,IF($K9="B",40%,25%)),IF($K9="A",30%,IF($K9="B",20%,10%)))))))))) -> 0.1 | O9: =IF($B9="","",IF(B9<30000,35%,IF(B9<50000,30%,IF(B9<100000,25%,20%)))) -> 0.35 | P9: =IF($A9="","",COUNTIFS(持仓表!$A:$A,$A9,持仓表!$G:$G,">0")) -> 0 | Q9: =IF($A9="","",COUNTIFS(持仓表!$A:$A,$A9,持仓表!$D:$D,"是",持仓表!$G:$G,">0")) -> 0 | R9: =IF($A9="","",MAX(0,P9-Q9)) -> 0 | S9: =IF($B9="","",IF(B9<50000,3,IF(B9<100000,4,5))) -> 3 | T9: =IF($A9="","",IF(OR(M9>=4,I9<=-8%),"防守",IF(OR(M9>=2,I9<=-5%),"警戒","正常"))) -> 正常 | U9: =IF($A9="","",IF(AND(L9>=3,M9<=2,T9<>"防守"),"是","否")) -> 否 | V9: =IF($A9="","",IF(AND(E9<N9,R9<S9,M9<=2,I9>-15%),"是","否")) -> 是 | W9: =IF($A9="","",IF(OR(M9>=3,I9<=-15%),"是","否")) -> 否 | X9: =IF($A9="","",IFERROR(maxifs(候选池!$AB:$AB,候选池!$A:$A,$A9),0)) -> 0 | Y9: =IF($A9="","",IF(OR(M9>=4,I9<=-8%),MAX(0,B9*60%-C9),IF(AND(ISNUMBER(AD9),B9>AD9),IF(B9<30000,0,IF(B9<100000,MAX(0,(B9-AD9)*0.2),MAX(0,(B9-AD9)*0.3))),0))) -> 0 | AA9: =IF($A9="","",IF($AA$2<>"",$AA$2,"")) -> 6683.54 | AB9: =IF($A9="","",IF(B9<30000,0.03,IF(B9<100000,0.02,0.015))) -> 0.03 | AC9: =IF($A9="","",IFERROR(DATEDIF($A$2,$A9,"m"),0)) -> 5 | AD9: =IF($A9="","",IF(OR(AA9="",AB9="",AC9=""),"",AA9*POWER(1+AB9,AC9))) -> 7748.0546 | AE9: =IF($A9="","",IF(OR(AD9="",AD9=0),"",B9/AD9-1)) -> 1.6843022 | AG9: =IF($A9="","",IF(B9<30000,"婴儿",IF(B9<100000,"成长","成熟"))) -> 婴儿 | AQ9: =IF($A9="","",B9-$AA$2-SUM($F$2:F9)) -> 10105.58
A10: 46226 | B10: 20959.73 | C10: 10362.73 | D10: =IF($A10="","",SUMIFS(持仓表!$J:$J,持仓表!$A:$A,$A10)) -> 0 | E10: =IFERROR(D10/B10,0) -> 0 | G10: =IF($B10="","",MAX($B$2:B10)) -> 20959.73 | H10: =IFERROR((B10-F10)/F10,0) -> 0 | I10: =IFERROR((B10-G10)/G10,0) -> 0 | N10: =IF($B10="","",MIN(70%,IF($I10<=-15%,10%,IF($I10<=-10%,30%,IF($M10>=4,10%,IF($M10>=3,30%,IF($J10="强",IF($K10="A",70%,IF($K10="B",60%,40%)),IF($J10="中性",IF($K10="A",50%,IF($K10="B",40%,25%)),IF($K10="A",30%,IF($K10="B",20%,10%)))))))))) -> 0.1 | O10: =IF($B10="","",IF(B10<30000,35%,IF(B10<50000,30%,IF(B10<100000,25%,20%)))) -> 0.35 | P10: =IF($A10="","",COUNTIFS(持仓表!$A:$A,$A10,持仓表!$G:$G,">0")) -> 0 | Q10: =IF($A10="","",COUNTIFS(持仓表!$A:$A,$A10,持仓表!$D:$D,"是",持仓表!$G:$G,">0")) -> 0 | R10: =IF($A10="","",MAX(0,P10-Q10)) -> 0 | S10: =IF($B10="","",IF(B10<50000,3,IF(B10<100000,4,5))) -> 3 | T10: =IF($A10="","",IF(OR(M10>=4,I10<=-8%),"防守",IF(OR(M10>=2,I10<=-5%),"警戒","正常"))) -> 正常 | U10: =IF($A10="","",IF(AND(L10>=3,M10<=2,T10<>"防守"),"是","否")) -> 否 | V10: =IF($A10="","",IF(AND(E10<N10,R10<S10,M10<=2,I10>-15%),"是","否")) -> 是 | W10: =IF($A10="","",IF(OR(M10>=3,I10<=-15%),"是","否")) -> 否 | X10: =IF($A10="","",IFERROR(maxifs(候选池!$AB:$AB,候选池!$A:$A,$A10),0)) -> 0 | Y10: =IF($A10="","",IF(OR(M10>=4,I10<=-8%),MAX(0,B10*60%-C10),IF(AND(ISNUMBER(AD10),B10>AD10),IF(B10<30000,0,IF(B10<100000,MAX(0,(B10-AD10)*0.2),MAX(0,(B10-AD10)*0.3))),0))) -> 0 | AA10: =IF($A10="","",IF($AA$2<>"",$AA$2,"")) -> 6683.54 | AB10: =IF($A10="","",IF(B10<30000,0.03,IF(B10<100000,0.02,0.015))) -> 0.03 | AC10: =IF($A10="","",IFERROR(DATEDIF($A$2,$A10,"m"),0)) -> 5 | AD10: =IF($A10="","",IF(OR(AA10="",AB10="",AC10=""),"",AA10*POWER(1+AB10,AC10))) -> 7748.0546 | AE10: =IF($A10="","",IF(OR(AD10="",AD10=0),"",B10/AD10-1)) -> 1.7051603 | AG10: =IF($A10="","",IF(B10<30000,"婴儿",IF(B10<100000,"成长","成熟"))) -> 婴儿 | AQ10: =IF($A10="","",B10-$AA$2-SUM($F$2:F10)) -> 10267.19
A11: 46226 | B11: 21004.83 | C11: 10362.83 | D11: =IF($A11="","",SUMIFS(持仓表!$J:$J,持仓表!$A:$A,$A11)) -> 0 | E11: =IFERROR(D11/B11,0) -> 0 | G11: =IF($B11="","",MAX($B$2:B11)) -> 21004.83 | H11: =IFERROR((B11-F11)/F11,0) -> 0 | I11: =IFERROR((B11-G11)/G11,0) -> 0 | N11: =IF($B11="","",MIN(70%,IF($I11<=-15%,10%,IF($I11<=-10%,30%,IF($M11>=4,10%,IF($M11>=3,30%,IF($J11="强",IF($K11="A",70%,IF($K11="B",60%,40%)),IF($J11="中性",IF($K11="A",50%,IF($K11="B",40%,25%)),IF($K11="A",30%,IF($K11="B",20%,10%)))))))))) -> 0.1 | O11: =IF($B11="","",IF(B11<30000,35%,IF(B11<50000,30%,IF(B11<100000,25%,20%)))) -> 0.35 | P11: =IF($A11="","",COUNTIFS(持仓表!$A:$A,$A11,持仓表!$G:$G,">0")) -> 0 | Q11: =IF($A11="","",COUNTIFS(持仓表!$A:$A,$A11,持仓表!$D:$D,"是",持仓表!$G:$G,">0")) -> 0 | R11: =IF($A11="","",MAX(0,P11-Q11)) -> 0 | S11: =IF($B11="","",IF(B11<50000,3,IF(B11<100000,4,5))) -> 3 | T11: =IF($A11="","",IF(OR(M11>=4,I11<=-8%),"防守",IF(OR(M11>=2,I11<=-5%),"警戒","正常"))) -> 正常 | U11: =IF($A11="","",IF(AND(L11>=3,M11<=2,T11<>"防守"),"是","否")) -> 否 | V11: =IF($A11="","",IF(AND(E11<N11,R11<S11,M11<=2,I11>-15%),"是","否")) -> 是 | W11: =IF($A11="","",IF(OR(M11>=3,I11<=-15%),"是","否")) -> 否 | X11: =IF($A11="","",IFERROR(maxifs(候选池!$AB:$AB,候选池!$A:$A,$A11),0)) -> 0 | Y11: =IF($A11="","",IF(OR(M11>=4,I11<=-8%),MAX(0,B11*60%-C11),IF(AND(ISNUMBER(AD11),B11>AD11),IF(B11<30000,0,IF(B11<100000,MAX(0,(B11-AD11)*0.2),MAX(0,(B11-AD11)*0.3))),0))) -> 0 | AA11: =IF($A11="","",IF($AA$2<>"",$AA$2,"")) -> 6683.54 | AB11: =IF($A11="","",IF(B11<30000,0.03,IF(B11<100000,0.02,0.015))) -> 0.03 | AC11: =IF($A11="","",IFERROR(DATEDIF($A$2,$A11,"m"),0)) -> 5 | AD11: =IF($A11="","",IF(OR(AA11="",AB11="",AC11=""),"",AA11*POWER(1+AB11,AC11))) -> 7748.0546 | AE11: =IF($A11="","",IF(OR(AD11="",AD11=0),"",B11/AD11-1)) -> 1.7109811 | AG11: =IF($A11="","",IF(B11<30000,"婴儿",IF(B11<100000,"成长","成熟"))) -> 婴儿 | AQ11: =IF($A11="","",B11-$AA$2-SUM($F$2:F11)) -> 10312.29
A12: 46227 | B12: 20842.32 | C12: 12358.32 | D12: =IF($A12="","",SUMIFS(持仓表!$J:$J,持仓表!$A:$A,$A12)) -> 8484 | E12: =IFERROR(D12/B12,0) -> 0.40705641 | F12: 0 | G12: =IF($B12="","",MAX($B$2:B12)) -> 21004.83 | H12: =IFERROR((B12-F12)/F12,0) -> 0 | I12: =IFERROR((B12-G12)/G12,0) -> -0.007736792 | N12: =IF($B12="","",MIN(70%,IF($I12<=-15%,10%,IF($I12<=-10%,30%,IF($M12>=4,10%,IF($M12>=3,30%,IF($J12="强",IF($K12="A",70%,IF($K12="B",60%,40%)),IF($J12="中性",IF($K12="A",50%,IF($K12="B",40%,25%)),IF($K12="A",30%,IF($K12="B",20%,10%)))))))))) -> 0.1 | O12: =IF($B12="","",IF(B12<30000,35%,IF(B12<50000,30%,IF(B12<100000,25%,20%)))) -> 0.35 | P12: =IF($A12="","",COUNTIFS(持仓表!$A:$A,$A12,持仓表!$G:$G,">0")) -> 7 | Q12: =IF($A12="","",COUNTIFS(持仓表!$A:$A,$A12,持仓表!$D:$D,"是",持仓表!$G:$G,">0")) -> 1 | R12: =IF($A12="","",MAX(0,P12-Q12)) -> 6 | S12: =IF($B12="","",IF(B12<50000,3,IF(B12<100000,4,5))) -> 3 | T12: =IF($A12="","",IF(OR(M12>=4,I12<=-8%),"防守",IF(OR(M12>=2,I12<=-5%),"警戒","正常"))) -> 正常 | U12: =IF($A12="","",IF(AND(L12>=3,M12<=2,T12<>"防守"),"是","否")) -> 否 | V12: =IF($A12="","",IF(AND(E12<N12,R12<S12,M12<=2,I12>-15%),"是","否")) -> 否 | W12: =IF($A12="","",IF(OR(M12>=3,I12<=-15%),"是","否")) -> 否 | X12: =IF($A12="","",IFERROR(maxifs(候选池!$AB:$AB,候选池!$A:$A,$A12),0)) -> 0 | Y12: =IF($A12="","",IF(OR(M12>=4,I12<=-8%),MAX(0,B12*60%-C12),IF(AND(ISNUMBER(AD12),B12>AD12),IF(B12<30000,0,IF(B12<100000,MAX(0,(B12-AD12)*0.2),MAX(0,(B12-AD12)*0.3))),0))) -> 0 | AA12: =IF($A12="","",IF($AA$2<>"",$AA$2,"")) -> 6683.54 | AB12: =IF($A12="","",IF(B12<30000,0.03,IF(B12<100000,0.02,0.015))) -> 0.03 | AC12: =IF($A12="","",IFERROR(DATEDIF($A$2,$A12,"m"),0)) -> 5 | AD12: =IF($A12="","",IF(OR(AA12="",AB12="",AC12=""),"",AA12*POWER(1+AB12,AC12))) -> 7748.0546 | AE12: =IF($A12="","",IF(OR(AD12="",AD12=0),"",B12/AD12-1)) -> 1.6900068 | AG12: =IF($A12="","",IF(B12<30000,"婴儿",IF(B12<100000,"成长","成熟"))) -> 婴儿 | AQ12: =IF($A12="","",B12-$AA$2-SUM($F$2:F12)) -> 10149.78
D13: =IF($A13="","",SUMIFS(持仓表!$J:$J,持仓表!$A:$A,$A13)) | E13: =IFERROR(D13/B13,0) -> 0 | G13: =IF($B13="","",MAX($B$2:B13)) | H13: =IFERROR((B13-F13)/F13,0) -> 0 | I13: =IFERROR((B13-G13)/G13,0) -> 0 | N13: =IF($B13="","",MIN(70%,IF($I13<=-15%,10%,IF($I13<=-10%,30%,IF($M13>=4,10%,IF($M13>=3,30%,IF($J13="强",IF($K13="A",70%,IF($K13="B",60%,40%)),IF($J13="中性",IF($K13="A",50%,IF($K13="B",40%,25%)),IF($K13="A",30%,IF($K13="B",20%,10%)))))))))) | O13: =IF($B13="","",IF(B13<30000,35%,IF(B13<50000,30%,IF(B13<100000,25%,20%)))) | P13: =IF($A13="","",COUNTIFS(持仓表!$A:$A,$A13,持仓表!$G:$G,">0")) | Q13: =IF($A13="","",COUNTIFS(持仓表!$A:$A,$A13,持仓表!$D:$D,"是",持仓表!$G:$G,">0")) | R13: =IF($A13="","",MAX(0,P13-Q13)) | S13: =IF($B13="","",IF(B13<50000,3,IF(B13<100000,4,5))) | T13: =IF($A13="","",IF(OR(M13>=4,I13<=-8%),"防守",IF(OR(M13>=2,I13<=-5%),"警戒","正常"))) | U13: =IF($A13="","",IF(AND(L13>=3,M13<=2,T13<>"防守"),"是","否")) | V13: =IF($A13="","",IF(AND(E13<N13,R13<S13,M13<=2,I13>-15%),"是","否")) | W13: =IF($A13="","",IF(OR(M13>=3,I13<=-15%),"是","否")) | X13: =IF($A13="","",IFERROR(maxifs(候选池!$AB:$AB,候选池!$A:$A,$A13),0)) | Y13: =IF($A13="","",IF(OR(M13>=4,I13<=-8%),MAX(0,B13*60%-C13),IF(AND(ISNUMBER(AD13),B13>AD13),IF(B13<30000,0,IF(B13<100000,MAX(0,(B13-AD13)*0.2),MAX(0,(B13-AD13)*0.3))),0))) | AA13: =IF($A13="","",IF($AA$2<>"",$AA$2,"")) | AB13: =IF($A13="","",IF(B13<30000,0.03,IF(B13<100000,0.02,0.015))) | AC13: =IF($A13="","",IFERROR(DATEDIF($A$2,$A13,"m"),0)) | AD13: =IF($A13="","",IF(OR(AA13="",AB13="",AC13=""),"",AA13*POWER(1+AB13,AC13))) | AE13: =IF($A13="","",IF(OR(AD13="",AD13=0),"",B13/AD13-1)) | AG13: =IF($A13="","",IF(B13<30000,"婴儿",IF(B13<100000,"成长","成熟"))) | AQ13: =IF($A13="","",B13-$AA$2-SUM($F$2:F13))
D14: =IF($A14="","",SUMIFS(持仓表!$J:$J,持仓表!$A:$A,$A14)) | E14: =IFERROR(D14/B14,0) -> 0 | G14: =IF($B14="","",MAX($B$2:B14)) | H14: =IFERROR((B14-F14)/F14,0) -> 0 | I14: =IFERROR((B14-G14)/G14,0) -> 0 | N14: =IF($B14="","",MIN(70%,IF($I14<=-15%,10%,IF($I14<=-10%,30%,IF($M14>=4,10%,IF($M14>=3,30%,IF($J14="强",IF($K14="A",70%,IF($K14="B",60%,40%)),IF($J14="中性",IF($K14="A",50%,IF($K14="B",40%,25%)),IF($K14="A",30%,IF($K14="B",20%,10%)))))))))) | O14: =IF($B14="","",IF(B14<30000,35%,IF(B14<50000,30%,IF(B14<100000,25%,20%)))) | P14: =IF($A14="","",COUNTIFS(持仓表!$A:$A,$A14,持仓表!$G:$G,">0")) | Q14: =IF($A14="","",COUNTIFS(持仓表!$A:$A,$A14,持仓表!$D:$D,"是",持仓表!$G:$G,">0")) | R14: =IF($A14="","",MAX(0,P14-Q14)) | S14: =IF($B14="","",IF(B14<50000,3,IF(B14<100000,4,5))) | T14: =IF($A14="","",IF(OR(M14>=4,I14<=-8%),"防守",IF(OR(M14>=2,I14<=-5%),"警戒","正常"))) | U14: =IF($A14="","",IF(AND(L14>=3,M14<=2,T14<>"防守"),"是","否")) | V14: =IF($A14="","",IF(AND(E14<N14,R14<S14,M14<=2,I14>-15%),"是","否")) | W14: =IF($A14="","",IF(OR(M14>=3,I14<=-15%),"是","否")) | X14: =IF($A14="","",IFERROR(maxifs(候选池!$AB:$AB,候选池!$A:$A,$A14),0)) | Y14: =IF($A14="","",IF(OR(M14>=4,I14<=-8%),MAX(0,B14*60%-C14),IF(AND(ISNUMBER(AD14),B14>AD14),IF(B14<30000,0,IF(B14<100000,MAX(0,(B14-AD14)*0.2),MAX(0,(B14-AD14)*0.3))),0))) | AA14: =IF($A14="","",IF($AA$2<>"",$AA$2,"")) | AB14: =IF($A14="","",IF(B14<30000,0.03,IF(B14<100000,0.02,0.015))) | AC14: =IF($A14="","",IFERROR(DATEDIF($A$2,$A14,"m"),0)) | AD14: =IF($A14="","",IF(OR(AA14="",AB14="",AC14=""),"",AA14*POWER(1+AB14,AC14))) | AE14: =IF($A14="","",IF(OR(AD14="",AD14=0),"",B14/AD14-1)) | AG14: =IF($A14="","",IF(B14<30000,"婴儿",IF(B14<100000,"成长","成熟"))) | AQ14: =IF($A14="","",B14-$AA$2-SUM($F$2:F14))
D15: =IF($A15="","",SUMIFS(持仓表!$J:$J,持仓表!$A:$A,$A15)) | E15: =IFERROR(D15/B15,0) -> 0 | G15: =IF($B15="","",MAX($B$2:B15)) | H15: =IFERROR((B15-F15)/F15,0) -> 0 | I15: =IFERROR((B15-G15)/G15,0) -> 0 | N15: =IF($B15="","",MIN(70%,IF($I15<=-15%,10%,IF($I15<=-10%,30%,IF($M15>=4,10%,IF($M15>=3,30%,IF($J15="强",IF($K15="A",70%,IF($K15="B",60%,40%)),IF($J15="中性",IF($K15="A",50%,IF($K15="B",40%,25%)),IF($K15="A",30%,IF($K15="B",20%,10%)))))))))) | O15: =IF($B15="","",IF(B15<30000,35%,IF(B15<50000,30%,IF(B15<100000,25%,20%)))) | P15: =IF($A15="","",COUNTIFS(持仓表!$A:$A,$A15,持仓表!$G:$G,">0")) | Q15: =IF($A15="","",COUNTIFS(持仓表!$A:$A,$A15,持仓表!$D:$D,"是",持仓表!$G:$G,">0")) | R15: =IF($A15="","",MAX(0,P15-Q15)) | S15: =IF($B15="","",IF(B15<50000,3,IF(B15<100000,4,5))) | T15: =IF($A15="","",IF(OR(M15>=4,I15<=-8%),"防守",IF(OR(M15>=2,I15<=-5%),"警戒","正常"))) | U15: =IF($A15="","",IF(AND(L15>=3,M15<=2,T15<>"防守"),"是","否")) | V15: =IF($A15="","",IF(AND(E15<N15,R15<S15,M15<=2,I15>-15%),"是","否")) | W15: =IF($A15="","",IF(OR(M15>=3,I15<=-15%),"是","否")) | X15: =IF($A15="","",IFERROR(maxifs(候选池!$AB:$AB,候选池!$A:$A,$A15),0)) | Y15: =IF($A15="","",IF(OR(M15>=4,I15<=-8%),MAX(0,B15*60%-C15),IF(AND(ISNUMBER(AD15),B15>AD15),IF(B15<30000,0,IF(B15<100000,MAX(0,(B15-AD15)*0.2),MAX(0,(B15-AD15)*0.3))),0))) | AA15: =IF($A15="","",IF($AA$2<>"",$AA$2,"")) | AB15: =IF($A15="","",IF(B15<30000,0.03,IF(B15<100000,0.02,0.015))) | AC15: =IF($A15="","",IFERROR(DATEDIF($A$2,$A15,"m"),0)) | AD15: =IF($A15="","",IF(OR(AA15="",AB15="",AC15=""),"",AA15*POWER(1+AB15,AC15))) | AE15: =IF($A15="","",IF(OR(AD15="",AD15=0),"",B15/AD15-1)) | AG15: =IF($A15="","",IF(B15<30000,"婴儿",IF(B15<100000,"成长","成熟"))) | AQ15: =IF($A15="","",B15-$AA$2-SUM($F$2:F15))
D16: =IF($A16="","",SUMIFS(持仓表!$J:$J,持仓表!$A:$A,$A16)) | E16: =IFERROR(D16/B16,0) -> 0 | G16: =IF($B16="","",MAX($B$2:B16)) | H16: =IFERROR((B16-F16)/F16,0) -> 0 | I16: =IFERROR((B16-G16)/G16,0) -> 0 | N16: =IF($B16="","",MIN(70%,IF($I16<=-15%,10%,IF($I16<=-10%,30%,IF($M16>=4,10%,IF($M16>=3,30%,IF($J16="强",IF($K16="A",70%,IF($K16="B",60%,40%)),IF($J16="中性",IF($K16="A",50%,IF($K16="B",40%,25%)),IF($K16="A",30%,IF($K16="B",20%,10%)))))))))) | O16: =IF($B16="","",IF(B16<30000,35%,IF(B16<50000,30%,IF(B16<100000,25%,20%)))) | P16: =IF($A16="","",COUNTIFS(持仓表!$A:$A,$A16,持仓表!$G:$G,">0")) | Q16: =IF($A16="","",COUNTIFS(持仓表!$A:$A,$A16,持仓表!$D:$D,"是",持仓表!$G:$G,">0")) | R16: =IF($A16="","",MAX(0,P16-Q16)) | S16: =IF($B16="","",IF(B16<50000,3,IF(B16<100000,4,5))) | T16: =IF($A16="","",IF(OR(M16>=4,I16<=-8%),"防守",IF(OR(M16>=2,I16<=-5%),"警戒","正常"))) | U16: =IF($A16="","",IF(AND(L16>=3,M16<=2,T16<>"防守"),"是","否")) | V16: =IF($A16="","",IF(AND(E16<N16,R16<S16,M16<=2,I16>-15%),"是","否")) | W16: =IF($A16="","",IF(OR(M16>=3,I16<=-15%),"是","否")) | X16: =IF($A16="","",IFERROR(maxifs(候选池!$AB:$AB,候选池!$A:$A,$A16),0)) | Y16: =IF($A16="","",IF(OR(M16>=4,I16<=-8%),MAX(0,B16*60%-C16),IF(AND(ISNUMBER(AD16),B16>AD16),IF(B16<30000,0,IF(B16<100000,MAX(0,(B16-AD16)*0.2),MAX(0,(B16-AD16)*0.3))),0))) | AA16: =IF($A16="","",IF($AA$2<>"",$AA$2,"")) | AB16: =IF($A16="","",IF(B16<30000,0.03,IF(B16<100000,0.02,0.015))) | AC16: =IF($A16="","",IFERROR(DATEDIF($A$2,$A16,"m"),0)) | AD16: =IF($A16="","",IF(OR(AA16="",AB16="",AC16=""),"",AA16*POWER(1+AB16,AC16))) | AE16: =IF($A16="","",IF(OR(AD16="",AD16=0),"",B16/AD16-1)) | AG16: =IF($A16="","",IF(B16<30000,"婴儿",IF(B16<100000,"成长","成熟"))) | AQ16: =IF($A16="","",B16-$AA$2-SUM($F$2:F16))
D17: =IF($A17="","",SUMIFS(持仓表!$J:$J,持仓表!$A:$A,$A17)) | E17: =IFERROR(D17/B17,0) -> 0 | G17: =IF($B17="","",MAX($B$2:B17)) | H17: =IFERROR((B17-F17)/F17,0) -> 0 | I17: =IFERROR((B17-G17)/G17,0) -> 0 | N17: =IF($B17="","",MIN(70%,IF($I17<=-15%,10%,IF($I17<=-10%,30%,IF($M17>=4,10%,IF($M17>=3,30%,IF($J17="强",IF($K17="A",70%,IF($K17="B",60%,40%)),IF($J17="中性",IF($K17="A",50%,IF($K17="B",40%,25%)),IF($K17="A",30%,IF($K17="B",20%,10%)))))))))) | O17: =IF($B17="","",IF(B17<30000,35%,IF(B17<50000,30%,IF(B17<100000,25%,20%)))) | P17: =IF($A17="","",COUNTIFS(持仓表!$A:$A,$A17,持仓表!$G:$G,">0")) | Q17: =IF($A17="","",COUNTIFS(持仓表!$A:$A,$A17,持仓表!$D:$D,"是",持仓表!$G:$G,">0")) | R17: =IF($A17="","",MAX(0,P17-Q17)) | S17: =IF($B17="","",IF(B17<50000,3,IF(B17<100000,4,5))) | T17: =IF($A17="","",IF(OR(M17>=4,I17<=-8%),"防守",IF(OR(M17>=2,I17<=-5%),"警戒","正常"))) | U17: =IF($A17="","",IF(AND(L17>=3,M17<=2,T17<>"防守"),"是","否")) | V17: =IF($A17="","",IF(AND(E17<N17,R17<S17,M17<=2,I17>-15%),"是","否")) | W17: =IF($A17="","",IF(OR(M17>=3,I17<=-15%),"是","否")) | X17: =IF($A17="","",IFERROR(maxifs(候选池!$AB:$AB,候选池!$A:$A,$A17),0)) | Y17: =IF($A17="","",IF(OR(M17>=4,I17<=-8%),MAX(0,B17*60%-C17),IF(AND(ISNUMBER(AD17),B17>AD17),IF(B17<30000,0,IF(B17<100000,MAX(0,(B17-AD17)*0.2),MAX(0,(B17-AD17)*0.3))),0))) | AA17: =IF($A17="","",IF($AA$2<>"",$AA$2,"")) | AB17: =IF($A17="","",IF(B17<30000,0.03,IF(B17<100000,0.02,0.015))) | AC17: =IF($A17="","",IFERROR(DATEDIF($A$2,$A17,"m"),0)) | AD17: =IF($A17="","",IF(OR(AA17="",AB17="",AC17=""),"",AA17*POWER(1+AB17,AC17))) | AE17: =IF($A17="","",IF(OR(AD17="",AD17=0),"",B17/AD17-1)) | AG17: =IF($A17="","",IF(B17<30000,"婴儿",IF(B17<100000,"成长","成熟"))) | AQ17: =IF($A17="","",B17-$AA$2-SUM($F$2:F17))
D18: =IF($A18="","",SUMIFS(持仓表!$J:$J,持仓表!$A:$A,$A18)) | E18: =IFERROR(D18/B18,0) -> 0 | G18: =IF($B18="","",MAX($B$2:B18)) | H18: =IFERROR((B18-F18)/F18,0) -> 0 | I18: =IFERROR((B18-G18)/G18,0) -> 0 | N18: =IF($B18="","",MIN(70%,IF($I18<=-15%,10%,IF($I18<=-10%,30%,IF($M18>=4,10%,IF($M18>=3,30%,IF($J18="强",IF($K18="A",70%,IF($K18="B",60%,40%)),IF($J18="中性",IF($K18="A",50%,IF($K18="B",40%,25%)),IF($K18="A",30%,IF($K18="B",20%,10%)))))))))) | O18: =IF($B18="","",IF(B18<30000,35%,IF(B18<50000,30%,IF(B18<100000,25%,20%)))) | P18: =IF($A18="","",COUNTIFS(持仓表!$A:$A,$A18,持仓表!$G:$G,">0")) | Q18: =IF($A18="","",COUNTIFS(持仓表!$A:$A,$A18,持仓表!$D:$D,"是",持仓表!$G:$G,">0")) | R18: =IF($A18="","",MAX(0,P18-Q18)) | S18: =IF($B18="","",IF(B18<50000,3,IF(B18<100000,4,5))) | T18: =IF($A18="","",IF(OR(M18>=4,I18<=-8%),"防守",IF(OR(M18>=2,I18<=-5%),"警戒","正常"))) | U18: =IF($A18="","",IF(AND(L18>=3,M18<=2,T18<>"防守"),"是","否")) | V18: =IF($A18="","",IF(AND(E18<N18,R18<S18,M18<=2,I18>-15%),"是","否")) | W18: =IF($A18="","",IF(OR(M18>=3,I18<=-15%),"是","否")) | X18: =IF($A18="","",IFERROR(maxifs(候选池!$AB:$AB,候选池!$A:$A,$A18),0)) | Y18: =IF($A18="","",IF(OR(M18>=4,I18<=-8%),MAX(0,B18*60%-C18),IF(AND(ISNUMBER(AD18),B18>AD18),IF(B18<30000,0,IF(B18<100000,MAX(0,(B18-AD18)*0.2),MAX(0,(B18-AD18)*0.3))),0))) | AA18: =IF($A18="","",IF($AA$2<>"",$AA$2,"")) | AB18: =IF($A18="","",IF(B18<30000,0.03,IF(B18<100000,0.02,0.015))) | AC18: =IF($A18="","",IFERROR(DATEDIF($A$2,$A18,"m"),0)) | AD18: =IF($A18="","",IF(OR(AA18="",AB18="",AC18=""),"",AA18*POWER(1+AB18,AC18))) | AE18: =IF($A18="","",IF(OR(AD18="",AD18=0),"",B18/AD18-1)) | AG18: =IF($A18="","",IF(B18<30000,"婴儿",IF(B18<100000,"成长","成熟"))) | AQ18: =IF($A18="","",B18-$AA$2-SUM($F$2:F18))
D19: =IF($A19="","",SUMIFS(持仓表!$J:$J,持仓表!$A:$A,$A19)) | E19: =IFERROR(D19/B19,0) -> 0 | G19: =IF($B19="","",MAX($B$2:B19)) | H19: =IFERROR((B19-F19)/F19,0) -> 0 | I19: =IFERROR((B19-G19)/G19,0) -> 0 | N19: =IF($B19="","",MIN(70%,IF($I19<=-15%,10%,IF($I19<=-10%,30%,IF($M19>=4,10%,IF($M19>=3,30%,IF($J19="强",IF($K19="A",70%,IF($K19="B",60%,40%)),IF($J19="中性",IF($K19="A",50%,IF($K19="B",40%,25%)),IF($K19="A",30%,IF($K19="B",20%,10%)))))))))) | O19: =IF($B19="","",IF(B19<30000,35%,IF(B19<50000,30%,IF(B19<100000,25%,20%)))) | P19: =IF($A19="","",COUNTIFS(持仓表!$A:$A,$A19,持仓表!$G:$G,">0")) | Q19: =IF($A19="","",COUNTIFS(持仓表!$A:$A,$A19,持仓表!$D:$D,"是",持仓表!$G:$G,">0")) | R19: =IF($A19="","",MAX(0,P19-Q19)) | S19: =IF($B19="","",IF(B19<50000,3,IF(B19<100000,4,5))) | T19: =IF($A19="","",IF(OR(M19>=4,I19<=-8%),"防守",IF(OR(M19>=2,I19<=-5%),"警戒","正常"))) | U19: =IF($A19="","",IF(AND(L19>=3,M19<=2,T19<>"防守"),"是","否")) | V19: =IF($A19="","",IF(AND(E19<N19,R19<S19,M19<=2,I19>-15%),"是","否")) | W19: =IF($A19="","",IF(OR(M19>=3,I19<=-15%),"是","否")) | X19: =IF($A19="","",IFERROR(maxifs(候选池!$AB:$AB,候选池!$A:$A,$A19),0)) | Y19: =IF($A19="","",IF(OR(M19>=4,I19<=-8%),MAX(0,B19*60%-C19),IF(AND(ISNUMBER(AD19),B19>AD19),IF(B19<30000,0,IF(B19<100000,MAX(0,(B19-AD19)*0.2),MAX(0,(B19-AD19)*0.3))),0))) | AA19: =IF($A19="","",IF($AA$2<>"",$AA$2,"")) | AB19: =IF($A19="","",IF(B19<30000,0.03,IF(B19<100000,0.02,0.015))) | AC19: =IF($A19="","",IFERROR(DATEDIF($A$2,$A19,"m"),0)) | AD19: =IF($A19="","",IF(OR(AA19="",AB19="",AC19=""),"",AA19*POWER(1+AB19,AC19))) | AE19: =IF($A19="","",IF(OR(AD19="",AD19=0),"",B19/AD19-1)) | AG19: =IF($A19="","",IF(B19<30000,"婴儿",IF(B19<100000,"成长","成熟"))) | AQ19: =IF($A19="","",B19-$AA$2-SUM($F$2:F19))
D20: =IF($A20="","",SUMIFS(持仓表!$J:$J,持仓表!$A:$A,$A20)) | E20: =IFERROR(D20/B20,0) -> 0 | G20: =IF($B20="","",MAX($B$2:B20)) | H20: =IFERROR((B20-F20)/F20,0) -> 0 | I20: =IFERROR((B20-G20)/G20,0) -> 0 | N20: =IF($B20="","",MIN(70%,IF($I20<=-15%,10%,IF($I20<=-10%,30%,IF($M20>=4,10%,IF($M20>=3,30%,IF($J20="强",IF($K20="A",70%,IF($K20="B",60%,40%)),IF($J20="中性",IF($K20="A",50%,IF($K20="B",40%,25%)),IF($K20="A",30%,IF($K20="B",20%,10%)))))))))) | O20: =IF($B20="","",IF(B20<30000,35%,IF(B20<50000,30%,IF(B20<100000,25%,20%)))) | P20: =IF($A20="","",COUNTIFS(持仓表!$A:$A,$A20,持仓表!$G:$G,">0")) | Q20: =IF($A20="","",COUNTIFS(持仓表!$A:$A,$A20,持仓表!$D:$D,"是",持仓表!$G:$G,">0")) | R20: =IF($A20="","",MAX(0,P20-Q20)) | S20: =IF($B20="","",IF(B20<50000,3,IF(B20<100000,4,5))) | T20: =IF($A20="","",IF(OR(M20>=4,I20<=-8%),"防守",IF(OR(M20>=2,I20<=-5%),"警戒","正常"))) | U20: =IF($A20="","",IF(AND(L20>=3,M20<=2,T20<>"防守"),"是","否")) | V20: =IF($A20="","",IF(AND(E20<N20,R20<S20,M20<=2,I20>-15%),"是","否")) | W20: =IF($A20="","",IF(OR(M20>=3,I20<=-15%),"是","否")) | X20: =IF($A20="","",IFERROR(maxifs(候选池!$AB:$AB,候选池!$A:$A,$A20),0)) | Y20: =IF($A20="","",IF(OR(M20>=4,I20<=-8%),MAX(0,B20*60%-C20),IF(AND(ISNUMBER(AD20),B20>AD20),IF(B20<30000,0,IF(B20<100000,MAX(0,(B20-AD20)*0.2),MAX(0,(B20-AD20)*0.3))),0))) | AA20: =IF($A20="","",IF($AA$2<>"",$AA$2,"")) | AB20: =IF($A20="","",IF(B20<30000,0.03,IF(B20<100000,0.02,0.015))) | AC20: =IF($A20="","",IFERROR(DATEDIF($A$2,$A20,"m"),0)) | AD20: =IF($A20="","",IF(OR(AA20="",AB20="",AC20=""),"",AA20*POWER(1+AB20,AC20))) | AE20: =IF($A20="","",IF(OR(AD20="",AD20=0),"",B20/AD20-1)) | AG20: =IF($A20="","",IF(B20<30000,"婴儿",IF(B20<100000,"成长","成熟"))) | AQ20: =IF($A20="","",B20-$AA$2-SUM($F$2:F20))
D21: =IF($A21="","",SUMIFS(持仓表!$J:$J,持仓表!$A:$A,$A21)) | E21: =IFERROR(D21/B21,0) -> 0 | G21: =IF($B21="","",MAX($B$2:B21)) | H21: =IFERROR((B21-F21)/F21,0) -> 0 | I21: =IFERROR((B21-G21)/G21,0) -> 0 | N21: =IF($B21="","",MIN(70%,IF($I21<=-15%,10%,IF($I21<=-10%,30%,IF($M21>=4,10%,IF($M21>=3,30%,IF($J21="强",IF($K21="A",70%,IF($K21="B",60%,40%)),IF($J21="中性",IF($K21="A",50%,IF($K21="B",40%,25%)),IF($K21="A",30%,IF($K21="B",20%,10%)))))))))) | O21: =IF($B21="","",IF(B21<30000,35%,IF(B21<50000,30%,IF(B21<100000,25%,20%)))) | P21: =IF($A21="","",COUNTIFS(持仓表!$A:$A,$A21,持仓表!$G:$G,">0")) | Q21: =IF($A21="","",COUNTIFS(持仓表!$A:$A,$A21,持仓表!$D:$D,"是",持仓表!$G:$G,">0")) | R21: =IF($A21="","",MAX(0,P21-Q21)) | S21: =IF($B21="","",IF(B21<50000,3,IF(B21<100000,4,5))) | T21: =IF($A21="","",IF(OR(M21>=4,I21<=-8%),"防守",IF(OR(M21>=2,I21<=-5%),"警戒","正常"))) | U21: =IF($A21="","",IF(AND(L21>=3,M21<=2,T21<>"防守"),"是","否")) | V21: =IF($A21="","",IF(AND(E21<N21,R21<S21,M21<=2,I21>-15%),"是","否")) | W21: =IF($A21="","",IF(OR(M21>=3,I21<=-15%),"是","否")) | X21: =IF($A21="","",IFERROR(maxifs(候选池!$AB:$AB,候选池!$A:$A,$A21),0)) | Y21: =IF($A21="","",IF(OR(M21>=4,I21<=-8%),MAX(0,B21*60%-C21),IF(AND(ISNUMBER(AD21),B21>AD21),IF(B21<30000,0,IF(B21<100000,MAX(0,(B21-AD21)*0.2),MAX(0,(B21-AD21)*0.3))),0))) | AA21: =IF($A21="","",IF($AA$2<>"",$AA$2,"")) | AB21: =IF($A21="","",IF(B21<30000,0.03,IF(B21<100000,0.02,0.015))) | AC21: =IF($A21="","",IFERROR(DATEDIF($A$2,$A21,"m"),0)) | AD21: =IF($A21="","",IF(OR(AA21="",AB21="",AC21=""),"",AA21*POWER(1+AB21,AC21))) | AE21: =IF($A21="","",IF(OR(AD21="",AD21=0),"",B21/AD21-1)) | AG21: =IF($A21="","",IF(B21<30000,"婴儿",IF(B21<100000,"成长","成熟"))) | AQ21: =IF($A21="","",B21-$AA$2-SUM($F$2:F21))
D22: =IF($A22="","",SUMIFS(持仓表!$J:$J,持仓表!$A:$A,$A22)) | E22: =IFERROR(D22/B22,0) -> 0 | G22: =IF($B22="","",MAX($B$2:B22)) | H22: =IFERROR((B22-F22)/F22,0) -> 0 | I22: =IFERROR((B22-G22)/G22,0) -> 0 | N22: =IF($B22="","",MIN(70%,IF($I22<=-15%,10%,IF($I22<=-10%,30%,IF($M22>=4,10%,IF($M22>=3,30%,IF($J22="强",IF($K22="A",70%,IF($K22="B",60%,40%)),IF($J22="中性",IF($K22="A",50%,IF($K22="B",40%,25%)),IF($K22="A",30%,IF($K22="B",20%,10%)))))))))) | O22: =IF($B22="","",IF(B22<30000,35%,IF(B22<50000,30%,IF(B22<100000,25%,20%)))) | P22: =IF($A22="","",COUNTIFS(持仓表!$A:$A,$A22,持仓表!$G:$G,">0")) | Q22: =IF($A22="","",COUNTIFS(持仓表!$A:$A,$A22,持仓表!$D:$D,"是",持仓表!$G:$G,">0")) | R22: =IF($A22="","",MAX(0,P22-Q22)) | S22: =IF($B22="","",IF(B22<50000,3,IF(B22<100000,4,5))) | T22: =IF($A22="","",IF(OR(M22>=4,I22<=-8%),"防守",IF(OR(M22>=2,I22<=-5%),"警戒","正常"))) | U22: =IF($A22="","",IF(AND(L22>=3,M22<=2,T22<>"防守"),"是","否")) | V22: =IF($A22="","",IF(AND(E22<N22,R22<S22,M22<=2,I22>-15%),"是","否")) | W22: =IF($A22="","",IF(OR(M22>=3,I22<=-15%),"是","否")) | X22: =IF($A22="","",IFERROR(maxifs(候选池!$AB:$AB,候选池!$A:$A,$A22),0)) | Y22: =IF($A22="","",IF(OR(M22>=4,I22<=-8%),MAX(0,B22*60%-C22),IF(AND(ISNUMBER(AD22),B22>AD22),IF(B22<30000,0,IF(B22<100000,MAX(0,(B22-AD22)*0.2),MAX(0,(B22-AD22)*0.3))),0))) | AA22: =IF($A22="","",IF($AA$2<>"",$AA$2,"")) | AB22: =IF($A22="","",IF(B22<30000,0.03,IF(B22<100000,0.02,0.015))) | AC22: =IF($A22="","",IFERROR(DATEDIF($A$2,$A22,"m"),0)) | AD22: =IF($A22="","",IF(OR(AA22="",AB22="",AC22=""),"",AA22*POWER(1+AB22,AC22))) | AE22: =IF($A22="","",IF(OR(AD22="",AD22=0),"",B22/AD22-1)) | AG22: =IF($A22="","",IF(B22<30000,"婴儿",IF(B22<100000,"成长","成熟"))) | AQ22: =IF($A22="","",B22-$AA$2-SUM($F$2:F22))
D23: =IF($A23="","",SUMIFS(持仓表!$J:$J,持仓表!$A:$A,$A23)) | E23: =IFERROR(D23/B23,0) -> 0 | G23: =IF($B23="","",MAX($B$2:B23)) | H23: =IFERROR((B23-F23)/F23,0) -> 0 | I23: =IFERROR((B23-G23)/G23,0) -> 0 | N23: =IF($B23="","",MIN(70%,IF($I23<=-15%,10%,IF($I23<=-10%,30%,IF($M23>=4,10%,IF($M23>=3,30%,IF($J23="强",IF($K23="A",70%,IF($K23="B",60%,40%)),IF($J23="中性",IF($K23="A",50%,IF($K23="B",40%,25%)),IF($K23="A",30%,IF($K23="B",20%,10%)))))))))) | O23: =IF($B23="","",IF(B23<30000,35%,IF(B23<50000,30%,IF(B23<100000,25%,20%)))) | P23: =IF($A23="","",COUNTIFS(持仓表!$A:$A,$A23,持仓表!$G:$G,">0")) | Q23: =IF($A23="","",COUNTIFS(持仓表!$A:$A,$A23,持仓表!$D:$D,"是",持仓表!$G:$G,">0")) | R23: =IF($A23="","",MAX(0,P23-Q23)) | S23: =IF($B23="","",IF(B23<50000,3,IF(B23<100000,4,5))) | T23: =IF($A23="","",IF(OR(M23>=4,I23<=-8%),"防守",IF(OR(M23>=2,I23<=-5%),"警戒","正常"))) | U23: =IF($A23="","",IF(AND(L23>=3,M23<=2,T23<>"防守"),"是","否")) | V23: =IF($A23="","",IF(AND(E23<N23,R23<S23,M23<=2,I23>-15%),"是","否")) | W23: =IF($A23="","",IF(OR(M23>=3,I23<=-15%),"是","否")) | X23: =IF($A23="","",IFERROR(maxifs(候选池!$AB:$AB,候选池!$A:$A,$A23),0)) | Y23: =IF($A23="","",IF(OR(M23>=4,I23<=-8%),MAX(0,B23*60%-C23),IF(AND(ISNUMBER(AD23),B23>AD23),IF(B23<30000,0,IF(B23<100000,MAX(0,(B23-AD23)*0.2),MAX(0,(B23-AD23)*0.3))),0))) | AA23: =IF($A23="","",IF($AA$2<>"",$AA$2,"")) | AB23: =IF($A23="","",IF(B23<30000,0.03,IF(B23<100000,0.02,0.015))) | AC23: =IF($A23="","",IFERROR(DATEDIF($A$2,$A23,"m"),0)) | AD23: =IF($A23="","",IF(OR(AA23="",AB23="",AC23=""),"",AA23*POWER(1+AB23,AC23))) | AE23: =IF($A23="","",IF(OR(AD23="",AD23=0),"",B23/AD23-1)) | AG23: =IF($A23="","",IF(B23<30000,"婴儿",IF(B23<100000,"成长","成熟"))) | AQ23: =IF($A23="","",B23-$AA$2-SUM($F$2:F23))
D24: =IF($A24="","",SUMIFS(持仓表!$J:$J,持仓表!$A:$A,$A24)) | E24: =IFERROR(D24/B24,0) -> 0 | G24: =IF($B24="","",MAX($B$2:B24)) | H24: =IFERROR((B24-F24)/F24,0) -> 0 | I24: =IFERROR((B24-G24)/G24,0) -> 0 | N24: =IF($B24="","",MIN(70%,IF($I24<=-15%,10%,IF($I24<=-10%,30%,IF($M24>=4,10%,IF($M24>=3,30%,IF($J24="强",IF($K24="A",70%,IF($K24="B",60%,40%)),IF($J24="中性",IF($K24="A",50%,IF($K24="B",40%,25%)),IF($K24="A",30%,IF($K24="B",20%,10%)))))))))) | O24: =IF($B24="","",IF(B24<30000,35%,IF(B24<50000,30%,IF(B24<100000,25%,20%)))) | P24: =IF($A24="","",COUNTIFS(持仓表!$A:$A,$A24,持仓表!$G:$G,">0")) | Q24: =IF($A24="","",COUNTIFS(持仓表!$A:$A,$A24,持仓表!$D:$D,"是",持仓表!$G:$G,">0")) | R24: =IF($A24="","",MAX(0,P24-Q24)) | S24: =IF($B24="","",IF(B24<50000,3,IF(B24<100000,4,5))) | T24: =IF($A24="","",IF(OR(M24>=4,I24<=-8%),"防守",IF(OR(M24>=2,I24<=-5%),"警戒","正常"))) | U24: =IF($A24="","",IF(AND(L24>=3,M24<=2,T24<>"防守"),"是","否")) | V24: =IF($A24="","",IF(AND(E24<N24,R24<S24,M24<=2,I24>-15%),"是","否")) | W24: =IF($A24="","",IF(OR(M24>=3,I24<=-15%),"是","否")) | X24: =IF($A24="","",IFERROR(maxifs(候选池!$AB:$AB,候选池!$A:$A,$A24),0)) | Y24: =IF($A24="","",IF(OR(M24>=4,I24<=-8%),MAX(0,B24*60%-C24),IF(AND(ISNUMBER(AD24),B24>AD24),IF(B24<30000,0,IF(B24<100000,MAX(0,(B24-AD24)*0.2),MAX(0,(B24-AD24)*0.3))),0))) | AA24: =IF($A24="","",IF($AA$2<>"",$AA$2,"")) | AB24: =IF($A24="","",IF(B24<30000,0.03,IF(B24<100000,0.02,0.015))) | AC24: =IF($A24="","",IFERROR(DATEDIF($A$2,$A24,"m"),0)) | AD24: =IF($A24="","",IF(OR(AA24="",AB24="",AC24=""),"",AA24*POWER(1+AB24,AC24))) | AE24: =IF($A24="","",IF(OR(AD24="",AD24=0),"",B24/AD24-1)) | AG24: =IF($A24="","",IF(B24<30000,"婴儿",IF(B24<100000,"成长","成熟"))) | AQ24: =IF($A24="","",B24-$AA$2-SUM($F$2:F24))
... D201: =IF($A201="","",SUMIFS(持仓表!$J:$J,持仓表!$A:$A,$A201)) | E201: =IFERROR(D201/B201,0) -> 0 | G201: =IF($B201="","",MAX($B$2:B201)) | H201: =IFERROR((B201-F201)/F201,0) -> 0 | I201: =IFERROR((B201-G201)/G201,0) -> 0 | N201: =IF($B201="","",MIN(70%,IF($I201<=-15%,10%,IF($I201<=-10%,30%,IF($M201>=4,10%,IF($M201>=3,30%,IF($J201="强",IF($K201="A",70%,IF($K201="B",60%,40%)),IF($J201="中性",IF($K201="A",50%,IF($K201="B",40%,25%)),IF($K201="A",30%,IF($K201="B",20%,10%)))))))))) | O201: =IF($B201="","",IF(B201<30000,35%,IF(B201<50000,30%,IF(B201<100000,25%,20%)))) | P201: =IF($A201="","",COUNTIFS(持仓表!$A:$A,$A201,持仓表!$G:$G,">0")) | Q201: =IF($A201="","",COUNTIFS(持仓表!$A:$A,$A201,持仓表!$D:$D,"是",持仓表!$G:$G,">0")) | R201: =IF($A201="","",MAX(0,P201-Q201)) | S201: =IF($B201="","",IF(B201<50000,3,IF(B201<100000,4,5))) | T201: =IF($A201="","",IF(OR(M201>=4,I201<=-8%),"防守",IF(OR(M201>=2,I201<=-5%),"警戒","正常"))) | U201: =IF($A201="","",IF(AND(L201>=3,M201<=2,T201<>"防守"),"是","否")) | V201: =IF($A201="","",IF(AND(E201<N201,R201<S201,M201<=2,I201>-15%),"是","否")) | W201: =IF($A201="","",IF(OR(M201>=3,I201<=-15%),"是","否")) | X201: =IF($A201="","",IFERROR(maxifs(候选池!$AB:$AB,候选池!$A:$A,$A201),0)) | Y201: =IF($A201="","",IF(OR(M201>=4,I201<=-8%),MAX(0,B201*60%-C201),IF(AND(ISNUMBER(AD201),B201>AD201),IF(B201<30000,0,IF(B201<100000,MAX(0,(B201-AD201)*0.2),MAX(0,(B201-AD201)*0.3))),0))) | AA201: =IF($A201="","",IF($AA$2<>"",$AA$2,"")) | AB201: =IF($A201="","",IF(B201<30000,0.03,IF(B201<100000,0.02,0.015))) | AC201: =IF($A201="","",IFERROR(DATEDIF($A$2,$A201,"m"),0)) | AD201: =IF($A201="","",IF(OR(AA201="",AB201="",AC201=""),"",AA201*POWER(1+AB201,AC201))) | AE201: =IF($A201="","",IF(OR(AD201="",AD201=0),"",B201/AD201-1)) | AG201: =IF($A201="","",IF(B201<30000,"婴儿",IF(B201<100000,"成长","成熟"))) | AQ201: =IF($A201="","",B201-$AA$2-SUM($F$2:F201))

Sheet 持仓表
A1: 日期 | B1: 股票名称 | C1: 代码 | D1: 是否WAIVED | E1: WAIVED基准价 | F1: 买入日期 | G1: 持股数量 Shares | H1: 持仓均价 EntryPrice | I1: 当前价 Close | J1: 持仓市值 | K1: 成本金额 | L1: 浮盈亏金额 | M1: 浮盈亏比 ProfitRatio | N1: 持仓占比 PositionRatio | O1: 买点低点 BuyPointLow | P1: 止损价 StopPrice | Q1: 是否破止损 | R1: ratio | S1: DL_P | T1: valid | U1: SignalType | V1: SignalInvalid | W1: RiskWatch | X1: 是否确认一卖 | Y1: 是否超单股上限 | Z1: 盈亏状态 | AA1: 处置动作 | AB1: 执行结论 | AC1: 处置原因 | AD1: 备注
A2: 46224 | B2: 东风股份 | C2: 600006 | D2: 是 | E2: 5.24 | F2: 45971 | G2: 100 | H2: 8.711 | I2: 5.33 | J2: =IFERROR(G2*I2,0) -> 533 | K2: =IFERROR(G2*H2,0) -> 871.1 | L2: =IFERROR(J2-K2,0) -> -338.1 | M2: =IFERROR((I2-H2)/H2,0) -> -0.38812995 | N2: =IFERROR(J2/INDEX(账户总表!$B:$B,MATCH($A2,账户总表!$A:$A,0)),0) -> 0.026222417 | O2: 5.24 | P2: =IF($A2="","",IF($D2="是",IF(E2>0,E2*0.92,MAX(O2*0.98,H2*0.92)),MAX(O2*0.98,H2*0.92))) -> 4.8208 | Q2: =IF($A2="","",IF(AND(I2>0,P2>0,I2<=P2),"是","否")) -> 否 | V2: =IF($A2="","",IF(OR(AND(O2>0,I2<O2),AND(T2="False",S2<0.8)),"是","否")) -> 否 | W2: =IF($A2="","",IF(AND(I2<H2,S2<0.8),"是","否")) -> 是 | X2: =IF($A2="","",IF(AND(R2<60%,S2>0.8,T2="True",U2="一卖"),"是","否")) -> 否 | Y2: =IF($A2="","",IF(D2="是","否",IF(N2>LOOKUP(2,1/(账户总表!$A:$A<>""),账户总表!$O:$O),"是","否"))) -> 否 | Z2: =IF($A2="","",IF(M2>=0,"盈利","亏损")) -> 亏损 | AA2: =IF($A2="","",IF(OR(Q2="是",M2<=-8%,V2="是",X2="是"),"卖出",IF(Y2="是","减仓",IF(W2="是","观察","持有")))) -> 卖出 | AB2: =IF($A2="","",IF(D2="是",IF(I2<=E2*0.92,"立即卖出(WAIVED止损)","继续持有(WAIVED)"),IF(OR(M2<=-10%,Q2="是"),"立即卖出",IF(OR(AA2="卖出",V2="是",X2="是"),"次日卖出",IF(AND(Y2="是",NOT(OR(Q2="是",M2<=-8%,V2="是",X2="是"))),"减仓至上限",IF(W2="是","观察","继续持有")))))) -> 继续持有(WAIVED) | AC2: =IF($A2="","",IF(Q2="是","触发止损",IF(M2<=-8%,"固定止损",IF(V2="是","信号失效",IF(X2="是","确认一卖",IF(Y2="是","单股超限",IF(W2="是","DL_P弱化","规则内持有"))))))) -> 固定止损
A3: 46224 | B3: 万华化学 | C3: 600309 | D3: 否 | F3: 46217 | G3: 100 | H3: 67.558 | I3: 75.49 | J3: =IFERROR(G3*I3,0) -> 7549 | K3: =IFERROR(G3*H3,0) -> 6755.8 | L3: =IFERROR(J3-K3,0) -> 793.2 | M3: =IFERROR((I3-H3)/H3,0) -> 0.11741023 | N3: =IFERROR(J3/INDEX(账户总表!$B:$B,MATCH($A3,账户总表!$A:$A,0)),0) -> 0.37139405 | O3: 70.4 | P3: =IF($A3="","",IF($D3="是",IF(E3>0,E3*0.92,MAX(O3*0.98,H3*0.92)),MAX(O3*0.98,H3*0.92))) -> 68.992 | Q3: =IF($A3="","",IF(AND(I3>0,P3>0,I3<=P3),"是","否")) -> 否 | V3: =IF($A3="","",IF(OR(AND(O3>0,I3<O3),AND(T3="False",S3<0.8)),"是","否")) -> 否 | W3: =IF($A3="","",IF(AND(I3<H3,S3<0.8),"是","否")) -> 否 | X3: =IF($A3="","",IF(AND(R3<60%,S3>0.8,T3="True",U3="一卖"),"是","否")) -> 否 | Y3: =IF($A3="","",IF(D3="是","否",IF(N3>LOOKUP(2,1/(账户总表!$A:$A<>""),账户总表!$O:$O),"是","否"))) -> 是 | Z3: =IF($A3="","",IF(M3>=0,"盈利","亏损")) -> 盈利 | AA3: =IF($A3="","",IF(OR(Q3="是",M3<=-8%,V3="是",X3="是"),"卖出",IF(Y3="是","减仓",IF(W3="是","观察","持有")))) -> 减仓 | AB3: =IF($A3="","",IF(D3="是",IF(I3<=E3*0.92,"立即卖出(WAIVED止损)","继续持有(WAIVED)"),IF(OR(M3<=-10%,Q3="是"),"立即卖出",IF(OR(AA3="卖出",V3="是",X3="是"),"次日卖出",IF(AND(Y3="是",NOT(OR(Q3="是",M3<=-8%,V3="是",X3="是"))),"减仓至上限",IF(W3="是","观察","继续持有")))))) -> 减仓至上限 | AC3: =IF($A3="","",IF(Q3="是","触发止损",IF(M3<=-8%,"固定止损",IF(V3="是","信号失效",IF(X3="是","确认一卖",IF(Y3="是","单股超限",IF(W3="是","DL_P弱化","规则内持有"))))))) -> 单股超限
A4: 46224 | B4: 隆基绿能 | C4: 601012 | D4: 否 | F4: 46221 | G4: 200 | H4: 11.107 | I4: 12.8 | J4: =IFERROR(G4*I4,0) -> 2560 | K4: =IFERROR(G4*H4,0) -> 2221.4 | L4: =IFERROR(J4-K4,0) -> 338.6 | M4: =IFERROR((I4-H4)/H4,0) -> 0.1524264 | N4: =IFERROR(J4/INDEX(账户总表!$B:$B,MATCH($A4,账户总表!$A:$A,0)),0) -> 0.12594632 | O4: 11.63 | P4: =IF($A4="","",IF($D4="是",IF(E4>0,E4*0.92,MAX(O4*0.98,H4*0.92)),MAX(O4*0.98,H4*0.92))) -> 11.3974 | Q4: =IF($A4="","",IF(AND(I4>0,P4>0,I4<=P4),"是","否")) -> 否 | V4: =IF($A4="","",IF(OR(AND(O4>0,I4<O4),AND(T4="False",S4<0.8)),"是","否")) -> 否 | W4: =IF($A4="","",IF(AND(I4<H4,S4<0.8),"是","否")) -> 否 | X4: =IF($A4="","",IF(AND(R4<60%,S4>0.8,T4="True",U4="一卖"),"是","否")) -> 否 | Y4: =IF($A4="","",IF(D4="是","否",IF(N4>LOOKUP(2,1/(账户总表!$A:$A<>""),账户总表!$O:$O),"是","否"))) -> 否 | Z4: =IF($A4="","",IF(M4>=0,"盈利","亏损")) -> 盈利 | AA4: =IF($A4="","",IF(OR(Q4="是",M4<=-8%,V4="是",X4="是"),"卖出",IF(Y4="是","减仓",IF(W4="是","观察","持有")))) -> 持有 | AB4: =IF($A4="","",IF(D4="是",IF(I4<=E4*0.92,"立即卖出(WAIVED止损)","继续持有(WAIVED)"),IF(OR(M4<=-10%,Q4="是"),"立即卖出",IF(OR(AA4="卖出",V4="是",X4="是"),"次日卖出",IF(AND(Y4="是",NOT(OR(Q4="是",M4<=-8%,V4="是",X4="是"))),"减仓至上限",IF(W4="是","观察","继续持有")))))) -> 继续持有 | AC4: =IF($A4="","",IF(Q4="是","触发止损",IF(M4<=-8%,"固定止损",IF(V4="是","信号失效",IF(X4="是","确认一卖",IF(Y4="是","单股超限",IF(W4="是","DL_P弱化","规则内持有"))))))) -> 规则内持有
A5: 46227 | B5: 创力集团 | C5: 603012 | D5: 否 | F5: 2026-07-24 | G5: 100 | H5: 8.021 | I5: 8.03 | J5: =IF(A5="","",G5*I5) -> 803 | K5: =IF(A5="","",G5*H5) -> 802.1 | L5: =IF(A5="","",J5-K5) -> 0.9 | M5: =IFERROR((I5-H5)/H5,0) -> 0.0011220546 | N5: =IFERROR(J5/INDEX(账户总表!$B:$B,MATCH($A5,账户总表!$A:$A,0)),0) -> 0.038527381 | P5: 7.61995 | Q5: =IF($A5="","",IF(AND(I5>0,P5>0,I5<=P5),"是","否")) -> 否 | V5: =IF($A5="","",IF(OR(AND(O5>0,I5<O5),AND(T5="False",S5<0.8)),"是","否")) -> 否 | W5: =IF($A5="","",IF(AND(I5<H5,S5<0.8),"是","否")) -> 否 | X5: =IF($A5="","",IF(AND(R5<60%,S5>0.8,T5="True",U5="一卖"),"是","否")) -> 否 | Y5: =IF($A5="","",IF(D5="是","否",IF(N5>LOOKUP(2,1/(账户总表!$A:$A<>""),账户总表!$O:$O),"是","否"))) -> 否 | Z5: =IF($A5="","",IF(M5>=0,"盈利","亏损")) -> 盈利 | AA5: =IF($A5="","",IF(OR(Q5="是",M5<=-8%,V5="是",X5="是"),"卖出",IF(Y5="是","减仓",IF(W5="是","观察","持有")))) -> 持有 | AB5: =IF($A5="","",IF(D5="是",IF(I5<=E5*0.92,"立即卖出(WAIVED止损)","继续持有(WAIVED)"),IF(OR(M5<=-10%,Q5="是"),"立即卖出",IF(OR(AA5="卖出",V5="是",X5="是"),"次日卖出",IF(AND(Y5="是",NOT(OR(Q5="是",M5<=-8%,V5="是",X5="是"))),"减仓至上限",IF(W5="是","观察","继续持有")))))) -> 继续持有 | AC5: =IF($A5="","",IF(Q5="是","触发止损",IF(M5<=-8%,"固定止损",IF(V5="是","信号失效",IF(X5="是","确认一卖",IF(Y5="是","单股超限",IF(W5="是","DL_P弱化","规则内持有"))))))) -> 规则内持有
A6: 46227 | B6: 新五丰 | C6: 600975 | D6: 否 | F6: 2026-07-24 | G6: 300 | H6: 4.804 | I6: 4.73 | J6: =IF(A6="","",G6*I6) -> 1419 | K6: =IF(A6="","",G6*H6) -> 1441.2 | L6: =IF(A6="","",J6-K6) -> -22.2 | M6: =IFERROR((I6-H6)/H6,0) -> -0.01540383 | N6: =IFERROR(J6/INDEX(账户总表!$B:$B,MATCH($A6,账户总表!$A:$A,0)),0) -> 0.068082632 | P6: 4.5638 | Q6: =IF($A6="","",IF(AND(I6>0,P6>0,I6<=P6),"是","否")) -> 否 | V6: =IF($A6="","",IF(OR(AND(O6>0,I6<O6),AND(T6="False",S6<0.8)),"是","否")) -> 否 | W6: =IF($A6="","",IF(AND(I6<H6,S6<0.8),"是","否")) -> 是 | X6: =IF($A6="","",IF(AND(R6<60%,S6>0.8,T6="True",U6="一卖"),"是","否")) -> 否 | Y6: =IF($A6="","",IF(D6="是","否",IF(N6>LOOKUP(2,1/(账户总表!$A:$A<>""),账户总表!$O:$O),"是","否"))) -> 否 | Z6: =IF($A6="","",IF(M6>=0,"盈利","亏损")) -> 亏损 | AA6: =IF($A6="","",IF(OR(Q6="是",M6<=-8%,V6="是",X6="是"),"卖出",IF(Y6="是","减仓",IF(W6="是","观察","持有")))) -> 观察 | AB6: =IF($A6="","",IF(D6="是",IF(I6<=E6*0.92,"立即卖出(WAIVED止损)","继续持有(WAIVED)"),IF(OR(M6<=-10%,Q6="是"),"立即卖出",IF(OR(AA6="卖出",V6="是",X6="是"),"次日卖出",IF(AND(Y6="是",NOT(OR(Q6="是",M6<=-8%,V6="是",X6="是"))),"减仓至上限",IF(W6="是","观察","继续持有")))))) -> 观察 | AC6: =IF($A6="","",IF(Q6="是","触发止损",IF(M6<=-8%,"固定止损",IF(V6="是","信号失效",IF(X6="是","确认一卖",IF(Y6="是","单股超限",IF(W6="是","DL_P弱化","规则内持有"))))))) -> DL_P弱化
A7: 46227 | B7: 方盛制药 | C7: 603998 | D7: 否 | F7: 2026-07-24 | G7: 100 | H7: 9.271 | I7: 8.96 | J7: =IF(A7="","",G7*I7) -> 896 | K7: =IF(A7="","",G7*H7) -> 927.1 | L7: =IF(A7="","",J7-K7) -> -31.1 | M7: =IFERROR((I7-H7)/H7,0) -> -0.033545464 | N7: =IFERROR(J7/INDEX(账户总表!$B:$B,MATCH($A7,账户总表!$A:$A,0)),0) -> 0.042989456 | P7: 8.80745 | Q7: =IF($A7="","",IF(AND(I7>0,P7>0,I7<=P7),"是","否")) -> 否 | V7: =IF($A7="","",IF(OR(AND(O7>0,I7<O7),AND(T7="False",S7<0.8)),"是","否")) -> 否 | W7: =IF($A7="","",IF(AND(I7<H7,S7<0.8),"是","否")) -> 是 | X7: =IF($A7="","",IF(AND(R7<60%,S7>0.8,T7="True",U7="一卖"),"是","否")) -> 否 | Y7: =IF($A7="","",IF(D7="是","否",IF(N7>LOOKUP(2,1/(账户总表!$A:$A<>""),账户总表!$O:$O),"是","否"))) -> 否 | Z7: =IF($A7="","",IF(M7>=0,"盈利","亏损")) -> 亏损 | AA7: =IF($A7="","",IF(OR(Q7="是",M7<=-8%,V7="是",X7="是"),"卖出",IF(Y7="是","减仓",IF(W7="是","观察","持有")))) -> 观察 | AB7: =IF($A7="","",IF(D7="是",IF(I7<=E7*0.92,"立即卖出(WAIVED止损)","继续持有(WAIVED)"),IF(OR(M7<=-10%,Q7="是"),"立即卖出",IF(OR(AA7="卖出",V7="是",X7="是"),"次日卖出",IF(AND(Y7="是",NOT(OR(Q7="是",M7<=-8%,V7="是",X7="是"))),"减仓至上限",IF(W7="是","观察","继续持有")))))) -> 观察 | AC7: =IF($A7="","",IF(Q7="是","触发止损",IF(M7<=-8%,"固定止损",IF(V7="是","信号失效",IF(X7="是","确认一卖",IF(Y7="是","单股超限",IF(W7="是","DL_P弱化","规则内持有"))))))) -> DL_P弱化
A8: 46227 | B8: 建研院 | C8: 603183 | D8: 否 | F8: 2026-07-24 | G8: 200 | H8: 3.966 | I8: 4.02 | J8: =IF(A8="","",G8*I8) -> 804 | K8: =IF(A8="","",G8*H8) -> 793.2 | L8: =IF(A8="","",J8-K8) -> 10.8 | M8: =IFERROR((I8-H8)/H8,0) -> 0.013615734 | N8: =IFERROR(J8/INDEX(账户总表!$B:$B,MATCH($A8,账户总表!$A:$A,0)),0) -> 0.03857536 | P8: 3.7677 | Q8: =IF($A8="","",IF(AND(I8>0,P8>0,I8<=P8),"是","否")) -> 否 | V8: =IF($A8="","",IF(OR(AND(O8>0,I8<O8),AND(T8="False",S8<0.8)),"是","否")) -> 否 | W8: =IF($A8="","",IF(AND(I8<H8,S8<0.8),"是","否")) -> 否 | X8: =IF($A8="","",IF(AND(R8<60%,S8>0.8,T8="True",U8="一卖"),"是","否")) -> 否 | Y8: =IF($A8="","",IF(D8="是","否",IF(N8>LOOKUP(2,1/(账户总表!$A:$A<>""),账户总表!$O:$O),"是","否"))) -> 否 | Z8: =IF($A8="","",IF(M8>=0,"盈利","亏损")) -> 盈利 | AA8: =IF($A8="","",IF(OR(Q8="是",M8<=-8%,V8="是",X8="是"),"卖出",IF(Y8="是","减仓",IF(W8="是","观察","持有")))) -> 持有 | AB8: =IF($A8="","",IF(D8="是",IF(I8<=E8*0.92,"立即卖出(WAIVED止损)","继续持有(WAIVED)"),IF(OR(M8<=-10%,Q8="是"),"立即卖出",IF(OR(AA8="卖出",V8="是",X8="是"),"次日卖出",IF(AND(Y8="是",NOT(OR(Q8="是",M8<=-8%,V8="是",X8="是"))),"减仓至上限",IF(W8="是","观察","继续持有")))))) -> 继续持有 | AC8: =IF($A8="","",IF(Q8="是","触发止损",IF(M8<=-8%,"固定止损",IF(V8="是","信号失效",IF(X8="是","确认一卖",IF(Y8="是","单股超限",IF(W8="是","DL_P弱化","规则内持有"))))))) -> 规则内持有
A9: 46227 | B9: 曲美家居 | C9: 603818 | D9: 否 | F9: 2026-07-24 | G9: 500 | H9: 3.142 | I9: 3.09 | J9: =IF(A9="","",G9*I9) -> 1545 | K9: =IF(A9="","",G9*H9) -> 1571 | L9: =IF(A9="","",J9-K9) -> -26 | M9: =IFERROR((I9-H9)/H9,0) -> -0.016549968 | N9: =IFERROR(J9/INDEX(账户总表!$B:$B,MATCH($A9,账户总表!$A:$A,0)),0) -> 0.074128024 | P9: 2.9849 | Q9: =IF($A9="","",IF(AND(I9>0,P9>0,I9<=P9),"是","否")) -> 否 | V9: =IF($A9="","",IF(OR(AND(O9>0,I9<O9),AND(T9="False",S9<0.8)),"是","否")) -> 否 | W9: =IF($A9="","",IF(AND(I9<H9,S9<0.8),"是","否")) -> 是 | X9: =IF($A9="","",IF(AND(R9<60%,S9>0.8,T9="True",U9="一卖"),"是","否")) -> 否 | Y9: =IF($A9="","",IF(D9="是","否",IF(N9>LOOKUP(2,1/(账户总表!$A:$A<>""),账户总表!$O:$O),"是","否"))) -> 否 | Z9: =IF($A9="","",IF(M9>=0,"盈利","亏损")) -> 亏损 | AA9: =IF($A9="","",IF(OR(Q9="是",M9<=-8%,V9="是",X9="是"),"卖出",IF(Y9="是","减仓",IF(W9="是","观察","持有")))) -> 观察 | AB9: =IF($A9="","",IF(D9="是",IF(I9<=E9*0.92,"立即卖出(WAIVED止损)","继续持有(WAIVED)"),IF(OR(M9<=-10%,Q9="是"),"立即卖出",IF(OR(AA9="卖出",V9="是",X9="是"),"次日卖出",IF(AND(Y9="是",NOT(OR(Q9="是",M9<=-8%,V9="是",X9="是"))),"减仓至上限",IF(W9="是","观察","继续持有")))))) -> 观察 | AC9: =IF($A9="","",IF(Q9="是","触发止损",IF(M9<=-8%,"固定止损",IF(V9="是","信号失效",IF(X9="是","确认一卖",IF(Y9="是","单股超限",IF(W9="是","DL_P弱化","规则内持有"))))))) -> DL_P弱化
A10: 46227 | B10: 东风股份 | C10: 600006 | D10: 是 | F10: 2026-07-24 | G10: 100 | H10: 8.711 | I10: 5.33 | J10: =IF(A10="","",G10*I10) -> 533 | K10: =IF(A10="","",G10*H10) -> 871.1 | L10: =IF(A10="","",J10-K10) -> -338.1 | M10: =IFERROR((I10-H10)/H10,0) -> -0.38812995 | N10: =IFERROR(J10/INDEX(账户总表!$B:$B,MATCH($A10,账户总表!$A:$A,0)),0) -> 0.025572969 | P10: 5.2234 | Q10: =IF($A10="","",IF(AND(I10>0,P10>0,I10<=P10),"是","否")) -> 否 | V10: =IF($A10="","",IF(OR(AND(O10>0,I10<O10),AND(T10="False",S10<0.8)),"是","否")) -> 否 | W10: =IF($A10="","",IF(AND(I10<H10,S10<0.8),"是","否")) -> 是 | X10: =IF($A10="","",IF(AND(R10<60%,S10>0.8,T10="True",U10="一卖"),"是","否")) -> 否 | Y10: =IF($A10="","",IF(D10="是","否",IF(N10>LOOKUP(2,1/(账户总表!$A:$A<>""),账户总表!$O:$O),"是","否"))) -> 否 | Z10: =IF($A10="","",IF(M10>=0,"盈利","亏损")) -> 亏损 | AA10: =IF($A10="","",IF(OR(Q10="是",M10<=-8%,V10="是",X10="是"),"卖出",IF(Y10="是","减仓",IF(W10="是","观察","持有")))) -> 卖出 | AB10: =IF($A10="","",IF(D10="是",IF(I10<=E10*0.92,"立即卖出(WAIVED止损)","继续持有(WAIVED)"),IF(OR(M10<=-10%,Q10="是"),"立即卖出",IF(OR(AA10="卖出",V10="是",X10="是"),"次日卖出",IF(AND(Y10="是",NOT(OR(Q10="是",M10<=-8%,V10="是",X10="是"))),"减仓至上限",IF(W10="是","观察","继续持有")))))) -> 继续持有(WAIVED) | AC10: =IF($A10="","",IF(Q10="是","触发止损",IF(M10<=-8%,"固定止损",IF(V10="是","信号失效",IF(X10="是","确认一卖",IF(Y10="是","单股超限",IF(W10="是","DL_P弱化","规则内持有"))))))) -> 固定止损
A11: 46227 | B11: 万华化学 | C11: 600309 | D11: 否 | F11: 2026-07-24 | G11: 0 | H11: 67.607 | I11: 73.75 | J11: =IF(A11="","",G11*I11) -> 0 | K11: =IF(A11="","",G11*H11) -> 0 | L11: =IF(A11="","",J11-K11) -> 0 | M11: =IFERROR((I11-H11)/H11,0) -> 0.090863372 | N11: =IFERROR(J11/INDEX(账户总表!$B:$B,MATCH($A11,账户总表!$A:$A,0)),0) -> 0 | P11: =IF($A11="","",IF($D11="是",IF(E11>0,E11*0.92,MAX(O11*0.98,H11*0.92)),MAX(O11*0.98,H11*0.92))) -> 62.19844 | Q11: =IF($A11="","",IF(AND(I11>0,P11>0,I11<=P11),"是","否")) -> 否 | V11: =IF($A11="","",IF(OR(AND(O11>0,I11<O11),AND(T11="False",S11<0.8)),"是","否")) -> 否 | W11: =IF($A11="","",IF(AND(I11<H11,S11<0.8),"是","否")) -> 否 | X11: =IF($A11="","",IF(AND(R11<60%,S11>0.8,T11="True",U11="一卖"),"是","否")) -> 否 | Y11: =IF($A11="","",IF(D11="是","否",IF(N11>LOOKUP(2,1/(账户总表!$A:$A<>""),账户总表!$O:$O),"是","否"))) -> 否 | Z11: =IF($A11="","",IF(M11>=0,"盈利","亏损")) -> 盈利 | AA11: =IF($A11="","",IF(OR(Q11="是",M11<=-8%,V11="是",X11="是"),"卖出",IF(Y11="是","减仓",IF(W11="是","观察","持有")))) -> 持有 | AB11: =IF($A11="","",IF(D11="是",IF(I11<=E11*0.92,"立即卖出(WAIVED止损)","继续持有(WAIVED)"),IF(OR(M11<=-10%,Q11="是"),"立即卖出",IF(OR(AA11="卖出",V11="是",X11="是"),"次日卖出",IF(AND(Y11="是",NOT(OR(Q11="是",M11<=-8%,V11="是",X11="是"))),"减仓至上限",IF(W11="是","观察","继续持有")))))) -> 继续持有 | AC11: =IF($A11="","",IF(Q11="是","触发止损",IF(M11<=-8%,"固定止损",IF(V11="是","信号失效",IF(X11="是","确认一卖",IF(Y11="是","单股超限",IF(W11="是","DL_P弱化","规则内持有"))))))) -> 规则内持有
A12: 46227 | B12: 隆基绿能 | C12: 601012 | D12: 否 | F12: 2026-07-24 | G12: 200 | H12: 11.107 | I12: 12.42 | J12: =IF(A12="","",G12*I12) -> 2484 | K12: =IF(A12="","",G12*H12) -> 2221.4 | L12: =IF(A12="","",J12-K12) -> 262.6 | M12: =IFERROR((I12-H12)/H12,0) -> 0.11821374 | N12: =IFERROR(J12/INDEX(账户总表!$B:$B,MATCH($A12,账户总表!$A:$A,0)),0) -> 0.11918059 | P12: 10.55165 | Q12: =IF($A12="","",IF(AND(I12>0,P12>0,I12<=P12),"是","否")) -> 否 | V12: =IF($A12="","",IF(OR(AND(O12>0,I12<O12),AND(T12="False",S12<0.8)),"是","否")) -> 否 | W12: =IF($A12="","",IF(AND(I12<H12,S12<0.8),"是","否")) -> 否 | X12: =IF($A12="","",IF(AND(R12<60%,S12>0.8,T12="True",U12="一卖"),"是","否")) -> 否 | Y12: =IF($A12="","",IF(D12="是","否",IF(N12>LOOKUP(2,1/(账户总表!$A:$A<>""),账户总表!$O:$O),"是","否"))) -> 否 | Z12: =IF($A12="","",IF(M12>=0,"盈利","亏损")) -> 盈利 | AA12: =IF($A12="","",IF(OR(Q12="是",M12<=-8%,V12="是",X12="是"),"卖出",IF(Y12="是","减仓",IF(W12="是","观察","持有")))) -> 持有 | AB12: =IF($A12="","",IF(D12="是",IF(I12<=E12*0.92,"立即卖出(WAIVED止损)","继续持有(WAIVED)"),IF(OR(M12<=-10%,Q12="是"),"立即卖出",IF(OR(AA12="卖出",V12="是",X12="是"),"次日卖出",IF(AND(Y12="是",NOT(OR(Q12="是",M12<=-8%,V12="是",X12="是"))),"减仓至上限",IF(W12="是","观察","继续持有")))))) -> 继续持有 | AC12: =IF($A12="","",IF(Q12="是","触发止损",IF(M12<=-8%,"固定止损",IF(V12="是","信号失效",IF(X12="是","确认一卖",IF(Y12="是","单股超限",IF(W12="是","DL_P弱化","规则内持有"))))))) -> 规则内持有
J13: =IFERROR(G13*I13,0) -> 0 | K13: =IFERROR(G13*H13,0) -> 0 | L13: =IFERROR(J13-K13,0) -> 0 | M13: =IFERROR((I13-H13)/H13,0) -> 0 | N13: =IFERROR(J13/INDEX(账户总表!$B:$B,MATCH($A13,账户总表!$A:$A,0)),0) -> 0 | P13: =IF($A13="","",IF($D13="是",IF(E13>0,E13*0.92,MAX(O13*0.98,H13*0.92)),MAX(O13*0.98,H13*0.92))) | Q13: =IF($A13="","",IF(AND(I13>0,P13>0,I13<=P13),"是","否")) | V13: =IF($A13="","",IF(OR(AND(O13>0,I13<O13),AND(T13="False",S13<0.8)),"是","否")) | W13: =IF($A13="","",IF(AND(I13<H13,S13<0.8),"是","否")) | X13: =IF($A13="","",IF(AND(R13<60%,S13>0.8,T13="True",U13="一卖"),"是","否")) | Y13: =IF($A13="","",IF(D13="是","否",IF(N13>LOOKUP(2,1/(账户总表!$A:$A<>""),账户总表!$O:$O),"是","否"))) | Z13: =IF($A13="","",IF(M13>=0,"盈利","亏损")) | AA13: =IF($A13="","",IF(OR(Q13="是",M13<=-8%,V13="是",X13="是"),"卖出",IF(Y13="是","减仓",IF(W13="是","观察","持有")))) | AB13: =IF($A13="","",IF(D13="是",IF(I13<=E13*0.92,"立即卖出(WAIVED止损)","继续持有(WAIVED)"),IF(OR(M13<=-10%,Q13="是"),"立即卖出",IF(OR(AA13="卖出",V13="是",X13="是"),"次日卖出",IF(AND(Y13="是",NOT(OR(Q13="是",M13<=-8%,V13="是",X13="是"))),"减仓至上限",IF(W13="是","观察","继续持有")))))) | AC13: =IF($A13="","",IF(Q13="是","触发止损",IF(M13<=-8%,"固定止损",IF(V13="是","信号失效",IF(X13="是","确认一卖",IF(Y13="是","单股超限",IF(W13="是","DL_P弱化","规则内持有")))))))
J14: =IFERROR(G14*I14,0) -> 0 | K14: =IFERROR(G14*H14,0) -> 0 | L14: =IFERROR(J14-K14,0) -> 0 | M14: =IFERROR((I14-H14)/H14,0) -> 0 | N14: =IFERROR(J14/INDEX(账户总表!$B:$B,MATCH($A14,账户总表!$A:$A,0)),0) -> 0 | P14: =IF($A14="","",IF($D14="是",IF(E14>0,E14*0.92,MAX(O14*0.98,H14*0.92)),MAX(O14*0.98,H14*0.92))) | Q14: =IF($A14="","",IF(AND(I14>0,P14>0,I14<=P14),"是","否")) | V14: =IF($A14="","",IF(OR(AND(O14>0,I14<O14),AND(T14="False",S14<0.8)),"是","否")) | W14: =IF($A14="","",IF(AND(I14<H14,S14<0.8),"是","否")) | X14: =IF($A14="","",IF(AND(R14<60%,S14>0.8,T14="True",U14="一卖"),"是","否")) | Y14: =IF($A14="","",IF(D14="是","否",IF(N14>LOOKUP(2,1/(账户总表!$A:$A<>""),账户总表!$O:$O),"是","否"))) | Z14: =IF($A14="","",IF(M14>=0,"盈利","亏损")) | AA14: =IF($A14="","",IF(OR(Q14="是",M14<=-8%,V14="是",X14="是"),"卖出",IF(Y14="是","减仓",IF(W14="是","观察","持有")))) | AB14: =IF($A14="","",IF(D14="是",IF(I14<=E14*0.92,"立即卖出(WAIVED止损)","继续持有(WAIVED)"),IF(OR(M14<=-10%,Q14="是"),"立即卖出",IF(OR(AA14="卖出",V14="是",X14="是"),"次日卖出",IF(AND(Y14="是",NOT(OR(Q14="是",M14<=-8%,V14="是",X14="是"))),"减仓至上限",IF(W14="是","观察","继续持有")))))) | AC14: =IF($A14="","",IF(Q14="是","触发止损",IF(M14<=-8%,"固定止损",IF(V14="是","信号失效",IF(X14="是","确认一卖",IF(Y14="是","单股超限",IF(W14="是","DL_P弱化","规则内持有")))))))
J15: =IFERROR(G15*I15,0) -> 0 | K15: =IFERROR(G15*H15,0) -> 0 | L15: =IFERROR(J15-K15,0) -> 0 | M15: =IFERROR((I15-H15)/H15,0) -> 0 | N15: =IFERROR(J15/INDEX(账户总表!$B:$B,MATCH($A15,账户总表!$A:$A,0)),0) -> 0 | P15: =IF($A15="","",IF($D15="是",IF(E15>0,E15*0.92,MAX(O15*0.98,H15*0.92)),MAX(O15*0.98,H15*0.92))) | Q15: =IF($A15="","",IF(AND(I15>0,P15>0,I15<=P15),"是","否")) | V15: =IF($A15="","",IF(OR(AND(O15>0,I15<O15),AND(T15="False",S15<0.8)),"是","否")) | W15: =IF($A15="","",IF(AND(I15<H15,S15<0.8),"是","否")) | X15: =IF($A15="","",IF(AND(R15<60%,S15>0.8,T15="True",U15="一卖"),"是","否")) | Y15: =IF($A15="","",IF(D15="是","否",IF(N15>LOOKUP(2,1/(账户总表!$A:$A<>""),账户总表!$O:$O),"是","否"))) | Z15: =IF($A15="","",IF(M15>=0,"盈利","亏损")) | AA15: =IF($A15="","",IF(OR(Q15="是",M15<=-8%,V15="是",X15="是"),"卖出",IF(Y15="是","减仓",IF(W15="是","观察","持有")))) | AB15: =IF($A15="","",IF(D15="是",IF(I15<=E15*0.92,"立即卖出(WAIVED止损)","继续持有(WAIVED)"),IF(OR(M15<=-10%,Q15="是"),"立即卖出",IF(OR(AA15="卖出",V15="是",X15="是"),"次日卖出",IF(AND(Y15="是",NOT(OR(Q15="是",M15<=-8%,V15="是",X15="是"))),"减仓至上限",IF(W15="是","观察","继续持有")))))) | AC15: =IF($A15="","",IF(Q15="是","触发止损",IF(M15<=-8%,"固定止损",IF(V15="是","信号失效",IF(X15="是","确认一卖",IF(Y15="是","单股超限",IF(W15="是","DL_P弱化","规则内持有")))))))
J16: =IFERROR(G16*I16,0) -> 0 | K16: =IFERROR(G16*H16,0) -> 0 | L16: =IFERROR(J16-K16,0) -> 0 | M16: =IFERROR((I16-H16)/H16,0) -> 0 | N16: =IFERROR(J16/INDEX(账户总表!$B:$B,MATCH($A16,账户总表!$A:$A,0)),0) -> 0 | P16: =IF($A16="","",IF($D16="是",IF(E16>0,E16*0.92,MAX(O16*0.98,H16*0.92)),MAX(O16*0.98,H16*0.92))) | Q16: =IF($A16="","",IF(AND(I16>0,P16>0,I16<=P16),"是","否")) | V16: =IF($A16="","",IF(OR(AND(O16>0,I16<O16),AND(T16="False",S16<0.8)),"是","否")) | W16: =IF($A16="","",IF(AND(I16<H16,S16<0.8),"是","否")) | X16: =IF($A16="","",IF(AND(R16<60%,S16>0.8,T16="True",U16="一卖"),"是","否")) | Y16: =IF($A16="","",IF(D16="是","否",IF(N16>LOOKUP(2,1/(账户总表!$A:$A<>""),账户总表!$O:$O),"是","否"))) | Z16: =IF($A16="","",IF(M16>=0,"盈利","亏损")) | AA16: =IF($A16="","",IF(OR(Q16="是",M16<=-8%,V16="是",X16="是"),"卖出",IF(Y16="是","减仓",IF(W16="是","观察","持有")))) | AB16: =IF($A16="","",IF(D16="是",IF(I16<=E16*0.92,"立即卖出(WAIVED止损)","继续持有(WAIVED)"),IF(OR(M16<=-10%,Q16="是"),"立即卖出",IF(OR(AA16="卖出",V16="是",X16="是"),"次日卖出",IF(AND(Y16="是",NOT(OR(Q16="是",M16<=-8%,V16="是",X16="是"))),"减仓至上限",IF(W16="是","观察","继续持有")))))) | AC16: =IF($A16="","",IF(Q16="是","触发止损",IF(M16<=-8%,"固定止损",IF(V16="是","信号失效",IF(X16="是","确认一卖",IF(Y16="是","单股超限",IF(W16="是","DL_P弱化","规则内持有")))))))
J17: =IFERROR(G17*I17,0) -> 0 | K17: =IFERROR(G17*H17,0) -> 0 | L17: =IFERROR(J17-K17,0) -> 0 | M17: =IFERROR((I17-H17)/H17,0) -> 0 | N17: =IFERROR(J17/INDEX(账户总表!$B:$B,MATCH($A17,账户总表!$A:$A,0)),0) -> 0 | P17: =IF($A17="","",IF($D17="是",IF(E17>0,E17*0.92,MAX(O17*0.98,H17*0.92)),MAX(O17*0.98,H17*0.92))) | Q17: =IF($A17="","",IF(AND(I17>0,P17>0,I17<=P17),"是","否")) | V17: =IF($A17="","",IF(OR(AND(O17>0,I17<O17),AND(T17="False",S17<0.8)),"是","否")) | W17: =IF($A17="","",IF(AND(I17<H17,S17<0.8),"是","否")) | X17: =IF($A17="","",IF(AND(R17<60%,S17>0.8,T17="True",U17="一卖"),"是","否")) | Y17: =IF($A17="","",IF(D17="是","否",IF(N17>LOOKUP(2,1/(账户总表!$A:$A<>""),账户总表!$O:$O),"是","否"))) | Z17: =IF($A17="","",IF(M17>=0,"盈利","亏损")) | AA17: =IF($A17="","",IF(OR(Q17="是",M17<=-8%,V17="是",X17="是"),"卖出",IF(Y17="是","减仓",IF(W17="是","观察","持有")))) | AB17: =IF($A17="","",IF(D17="是",IF(I17<=E17*0.92,"立即卖出(WAIVED止损)","继续持有(WAIVED)"),IF(OR(M17<=-10%,Q17="是"),"立即卖出",IF(OR(AA17="卖出",V17="是",X17="是"),"次日卖出",IF(AND(Y17="是",NOT(OR(Q17="是",M17<=-8%,V17="是",X17="是"))),"减仓至上限",IF(W17="是","观察","继续持有")))))) | AC17: =IF($A17="","",IF(Q17="是","触发止损",IF(M17<=-8%,"固定止损",IF(V17="是","信号失效",IF(X17="是","确认一卖",IF(Y17="是","单股超限",IF(W17="是","DL_P弱化","规则内持有")))))))
J18: =IFERROR(G18*I18,0) -> 0 | K18: =IFERROR(G18*H18,0) -> 0 | L18: =IFERROR(J18-K18,0) -> 0 | M18: =IFERROR((I18-H18)/H18,0) -> 0 | N18: =IFERROR(J18/INDEX(账户总表!$B:$B,MATCH($A18,账户总表!$A:$A,0)),0) -> 0 | P18: =IF($A18="","",IF($D18="是",IF(E18>0,E18*0.92,MAX(O18*0.98,H18*0.92)),MAX(O18*0.98,H18*0.92))) | Q18: =IF($A18="","",IF(AND(I18>0,P18>0,I18<=P18),"是","否")) | V18: =IF($A18="","",IF(OR(AND(O18>0,I18<O18),AND(T18="False",S18<0.8)),"是","否")) | W18: =IF($A18="","",IF(AND(I18<H18,S18<0.8),"是","否")) | X18: =IF($A18="","",IF(AND(R18<60%,S18>0.8,T18="True",U18="一卖"),"是","否")) | Y18: =IF($A18="","",IF(D18="是","否",IF(N18>LOOKUP(2,1/(账户总表!$A:$A<>""),账户总表!$O:$O),"是","否"))) | Z18: =IF($A18="","",IF(M18>=0,"盈利","亏损")) | AA18: =IF($A18="","",IF(OR(Q18="是",M18<=-8%,V18="是",X18="是"),"卖出",IF(Y18="是","减仓",IF(W18="是","观察","持有")))) | AB18: =IF($A18="","",IF(D18="是",IF(I18<=E18*0.92,"立即卖出(WAIVED止损)","继续持有(WAIVED)"),IF(OR(M18<=-10%,Q18="是"),"立即卖出",IF(OR(AA18="卖出",V18="是",X18="是"),"次日卖出",IF(AND(Y18="是",NOT(OR(Q18="是",M18<=-8%,V18="是",X18="是"))),"减仓至上限",IF(W18="是","观察","继续持有")))))) | AC18: =IF($A18="","",IF(Q18="是","触发止损",IF(M18<=-8%,"固定止损",IF(V18="是","信号失效",IF(X18="是","确认一卖",IF(Y18="是","单股超限",IF(W18="是","DL_P弱化","规则内持有")))))))
J19: =IFERROR(G19*I19,0) -> 0 | K19: =IFERROR(G19*H19,0) -> 0 | L19: =IFERROR(J19-K19,0) -> 0 | M19: =IFERROR((I19-H19)/H19,0) -> 0 | N19: =IFERROR(J19/INDEX(账户总表!$B:$B,MATCH($A19,账户总表!$A:$A,0)),0) -> 0 | P19: =IF($A19="","",IF($D19="是",IF(E19>0,E19*0.92,MAX(O19*0.98,H19*0.92)),MAX(O19*0.98,H19*0.92))) | Q19: =IF($A19="","",IF(AND(I19>0,P19>0,I19<=P19),"是","否")) | V19: =IF($A19="","",IF(OR(AND(O19>0,I19<O19),AND(T19="False",S19<0.8)),"是","否")) | W19: =IF($A19="","",IF(AND(I19<H19,S19<0.8),"是","否")) | X19: =IF($A19="","",IF(AND(R19<60%,S19>0.8,T19="True",U19="一卖"),"是","否")) | Y19: =IF($A19="","",IF(D19="是","否",IF(N19>LOOKUP(2,1/(账户总表!$A:$A<>""),账户总表!$O:$O),"是","否"))) | Z19: =IF($A19="","",IF(M19>=0,"盈利","亏损")) | AA19: =IF($A19="","",IF(OR(Q19="是",M19<=-8%,V19="是",X19="是"),"卖出",IF(Y19="是","减仓",IF(W19="是","观察","持有")))) | AB19: =IF($A19="","",IF(D19="是",IF(I19<=E19*0.92,"立即卖出(WAIVED止损)","继续持有(WAIVED)"),IF(OR(M19<=-10%,Q19="是"),"立即卖出",IF(OR(AA19="卖出",V19="是",X19="是"),"次日卖出",IF(AND(Y19="是",NOT(OR(Q19="是",M19<=-8%,V19="是",X19="是"))),"减仓至上限",IF(W19="是","观察","继续持有")))))) | AC19: =IF($A19="","",IF(Q19="是","触发止损",IF(M19<=-8%,"固定止损",IF(V19="是","信号失效",IF(X19="是","确认一卖",IF(Y19="是","单股超限",IF(W19="是","DL_P弱化","规则内持有")))))))
J20: =IFERROR(G20*I20,0) -> 0 | K20: =IFERROR(G20*H20,0) -> 0 | L20: =IFERROR(J20-K20,0) -> 0 | M20: =IFERROR((I20-H20)/H20,0) -> 0 | N20: =IFERROR(J20/INDEX(账户总表!$B:$B,MATCH($A20,账户总表!$A:$A,0)),0) -> 0 | P20: =IF($A20="","",IF($D20="是",IF(E20>0,E20*0.92,MAX(O20*0.98,H20*0.92)),MAX(O20*0.98,H20*0.92))) | Q20: =IF($A20="","",IF(AND(I20>0,P20>0,I20<=P20),"是","否")) | V20: =IF($A20="","",IF(OR(AND(O20>0,I20<O20),AND(T20="False",S20<0.8)),"是","否")) | W20: =IF($A20="","",IF(AND(I20<H20,S20<0.8),"是","否")) | X20: =IF($A20="","",IF(AND(R20<60%,S20>0.8,T20="True",U20="一卖"),"是","否")) | Y20: =IF($A20="","",IF(D20="是","否",IF(N20>LOOKUP(2,1/(账户总表!$A:$A<>""),账户总表!$O:$O),"是","否"))) | Z20: =IF($A20="","",IF(M20>=0,"盈利","亏损")) | AA20: =IF($A20="","",IF(OR(Q20="是",M20<=-8%,V20="是",X20="是"),"卖出",IF(Y20="是","减仓",IF(W20="是","观察","持有")))) | AB20: =IF($A20="","",IF(D20="是",IF(I20<=E20*0.92,"立即卖出(WAIVED止损)","继续持有(WAIVED)"),IF(OR(M20<=-10%,Q20="是"),"立即卖出",IF(OR(AA20="卖出",V20="是",X20="是"),"次日卖出",IF(AND(Y20="是",NOT(OR(Q20="是",M20<=-8%,V20="是",X20="是"))),"减仓至上限",IF(W20="是","观察","继续持有")))))) | AC20: =IF($A20="","",IF(Q20="是","触发止损",IF(M20<=-8%,"固定止损",IF(V20="是","信号失效",IF(X20="是","确认一卖",IF(Y20="是","单股超限",IF(W20="是","DL_P弱化","规则内持有")))))))
J21: =IFERROR(G21*I21,0) -> 0 | K21: =IFERROR(G21*H21,0) -> 0 | L21: =IFERROR(J21-K21,0) -> 0 | M21: =IFERROR((I21-H21)/H21,0) -> 0 | N21: =IFERROR(J21/INDEX(账户总表!$B:$B,MATCH($A21,账户总表!$A:$A,0)),0) -> 0 | P21: =IF($A21="","",IF($D21="是",IF(E21>0,E21*0.92,MAX(O21*0.98,H21*0.92)),MAX(O21*0.98,H21*0.92))) | Q21: =IF($A21="","",IF(AND(I21>0,P21>0,I21<=P21),"是","否")) | V21: =IF($A21="","",IF(OR(AND(O21>0,I21<O21),AND(T21="False",S21<0.8)),"是","否")) | W21: =IF($A21="","",IF(AND(I21<H21,S21<0.8),"是","否")) | X21: =IF($A21="","",IF(AND(R21<60%,S21>0.8,T21="True",U21="一卖"),"是","否")) | Y21: =IF($A21="","",IF(D21="是","否",IF(N21>LOOKUP(2,1/(账户总表!$A:$A<>""),账户总表!$O:$O),"是","否"))) | Z21: =IF($A21="","",IF(M21>=0,"盈利","亏损")) | AA21: =IF($A21="","",IF(OR(Q21="是",M21<=-8%,V21="是",X21="是"),"卖出",IF(Y21="是","减仓",IF(W21="是","观察","持有")))) | AB21: =IF($A21="","",IF(D21="是",IF(I21<=E21*0.92,"立即卖出(WAIVED止损)","继续持有(WAIVED)"),IF(OR(M21<=-10%,Q21="是"),"立即卖出",IF(OR(AA21="卖出",V21="是",X21="是"),"次日卖出",IF(AND(Y21="是",NOT(OR(Q21="是",M21<=-8%,V21="是",X21="是"))),"减仓至上限",IF(W21="是","观察","继续持有")))))) | AC21: =IF($A21="","",IF(Q21="是","触发止损",IF(M21<=-8%,"固定止损",IF(V21="是","信号失效",IF(X21="是","确认一卖",IF(Y21="是","单股超限",IF(W21="是","DL_P弱化","规则内持有")))))))
J22: =IFERROR(G22*I22,0) -> 0 | K22: =IFERROR(G22*H22,0) -> 0 | L22: =IFERROR(J22-K22,0) -> 0 | M22: =IFERROR((I22-H22)/H22,0) -> 0 | N22: =IFERROR(J22/INDEX(账户总表!$B:$B,MATCH($A22,账户总表!$A:$A,0)),0) -> 0 | P22: =IF($A22="","",IF($D22="是",IF(E22>0,E22*0.92,MAX(O22*0.98,H22*0.92)),MAX(O22*0.98,H22*0.92))) | Q22: =IF($A22="","",IF(AND(I22>0,P22>0,I22<=P22),"是","否")) | V22: =IF($A22="","",IF(OR(AND(O22>0,I22<O22),AND(T22="False",S22<0.8)),"是","否")) | W22: =IF($A22="","",IF(AND(I22<H22,S22<0.8),"是","否")) | X22: =IF($A22="","",IF(AND(R22<60%,S22>0.8,T22="True",U22="一卖"),"是","否")) | Y22: =IF($A22="","",IF(D22="是","否",IF(N22>LOOKUP(2,1/(账户总表!$A:$A<>""),账户总表!$O:$O),"是","否"))) | Z22: =IF($A22="","",IF(M22>=0,"盈利","亏损")) | AA22: =IF($A22="","",IF(OR(Q22="是",M22<=-8%,V22="是",X22="是"),"卖出",IF(Y22="是","减仓",IF(W22="是","观察","持有")))) | AB22: =IF($A22="","",IF(D22="是",IF(I22<=E22*0.92,"立即卖出(WAIVED止损)","继续持有(WAIVED)"),IF(OR(M22<=-10%,Q22="是"),"立即卖出",IF(OR(AA22="卖出",V22="是",X22="是"),"次日卖出",IF(AND(Y22="是",NOT(OR(Q22="是",M22<=-8%,V22="是",X22="是"))),"减仓至上限",IF(W22="是","观察","继续持有")))))) | AC22: =IF($A22="","",IF(Q22="是","触发止损",IF(M22<=-8%,"固定止损",IF(V22="是","信号失效",IF(X22="是","确认一卖",IF(Y22="是","单股超限",IF(W22="是","DL_P弱化","规则内持有")))))))
J23: =IFERROR(G23*I23,0) -> 0 | K23: =IFERROR(G23*H23,0) -> 0 | L23: =IFERROR(J23-K23,0) -> 0 | M23: =IFERROR((I23-H23)/H23,0) -> 0 | N23: =IFERROR(J23/INDEX(账户总表!$B:$B,MATCH($A23,账户总表!$A:$A,0)),0) -> 0 | P23: =IF($A23="","",IF($D23="是",IF(E23>0,E23*0.92,MAX(O23*0.98,H23*0.92)),MAX(O23*0.98,H23*0.92))) | Q23: =IF($A23="","",IF(AND(I23>0,P23>0,I23<=P23),"是","否")) | V23: =IF($A23="","",IF(OR(AND(O23>0,I23<O23),AND(T23="False",S23<0.8)),"是","否")) | W23: =IF($A23="","",IF(AND(I23<H23,S23<0.8),"是","否")) | X23: =IF($A23="","",IF(AND(R23<60%,S23>0.8,T23="True",U23="一卖"),"是","否")) | Y23: =IF($A23="","",IF(D23="是","否",IF(N23>LOOKUP(2,1/(账户总表!$A:$A<>""),账户总表!$O:$O),"是","否"))) | Z23: =IF($A23="","",IF(M23>=0,"盈利","亏损")) | AA23: =IF($A23="","",IF(OR(Q23="是",M23<=-8%,V23="是",X23="是"),"卖出",IF(Y23="是","减仓",IF(W23="是","观察","持有")))) | AB23: =IF($A23="","",IF(D23="是",IF(I23<=E23*0.92,"立即卖出(WAIVED止损)","继续持有(WAIVED)"),IF(OR(M23<=-10%,Q23="是"),"立即卖出",IF(OR(AA23="卖出",V23="是",X23="是"),"次日卖出",IF(AND(Y23="是",NOT(OR(Q23="是",M23<=-8%,V23="是",X23="是"))),"减仓至上限",IF(W23="是","观察","继续持有")))))) | AC23: =IF($A23="","",IF(Q23="是","触发止损",IF(M23<=-8%,"固定止损",IF(V23="是","信号失效",IF(X23="是","确认一卖",IF(Y23="是","单股超限",IF(W23="是","DL_P弱化","规则内持有")))))))
J24: =IFERROR(G24*I24,0) -> 0 | K24: =IFERROR(G24*H24,0) -> 0 | L24: =IFERROR(J24-K24,0) -> 0 | M24: =IFERROR((I24-H24)/H24,0) -> 0 | N24: =IFERROR(J24/INDEX(账户总表!$B:$B,MATCH($A24,账户总表!$A:$A,0)),0) -> 0 | P24: =IF($A24="","",IF($D24="是",IF(E24>0,E24*0.92,MAX(O24*0.98,H24*0.92)),MAX(O24*0.98,H24*0.92))) | Q24: =IF($A24="","",IF(AND(I24>0,P24>0,I24<=P24),"是","否")) | V24: =IF($A24="","",IF(OR(AND(O24>0,I24<O24),AND(T24="False",S24<0.8)),"是","否")) | W24: =IF($A24="","",IF(AND(I24<H24,S24<0.8),"是","否")) | X24: =IF($A24="","",IF(AND(R24<60%,S24>0.8,T24="True",U24="一卖"),"是","否")) | Y24: =IF($A24="","",IF(D24="是","否",IF(N24>LOOKUP(2,1/(账户总表!$A:$A<>""),账户总表!$O:$O),"是","否"))) | Z24: =IF($A24="","",IF(M24>=0,"盈利","亏损")) | AA24: =IF($A24="","",IF(OR(Q24="是",M24<=-8%,V24="是",X24="是"),"卖出",IF(Y24="是","减仓",IF(W24="是","观察","持有")))) | AB24: =IF($A24="","",IF(D24="是",IF(I24<=E24*0.92,"立即卖出(WAIVED止损)","继续持有(WAIVED)"),IF(OR(M24<=-10%,Q24="是"),"立即卖出",IF(OR(AA24="卖出",V24="是",X24="是"),"次日卖出",IF(AND(Y24="是",NOT(OR(Q24="是",M24<=-8%,V24="是",X24="是"))),"减仓至上限",IF(W24="是","观察","继续持有")))))) | AC24: =IF($A24="","",IF(Q24="是","触发止损",IF(M24<=-8%,"固定止损",IF(V24="是","信号失效",IF(X24="是","确认一卖",IF(Y24="是","单股超限",IF(W24="是","DL_P弱化","规则内持有")))))))
... J201: =IFERROR(G201*I201,0) -> 0 | K201: =IFERROR(G201*H201,0) -> 0 | L201: =IFERROR(J201-K201,0) -> 0 | M201: =IFERROR((I201-H201)/H201,0) -> 0 | N201: =IFERROR(J201/INDEX(账户总表!$B:$B,MATCH($A201,账户总表!$A:$A,0)),0) -> 0 | P201: =IF($A201="","",IF($D201="是",IF(E201>0,E201*0.92,MAX(O201*0.98,H201*0.92)),MAX(O201*0.98,H201*0.92))) | Q201: =IF($A201="","",IF(AND(I201>0,P201>0,I201<=P201),"是","否")) | V201: =IF($A201="","",IF(OR(AND(O201>0,I201<O201),AND(T201="False",S201<0.8)),"是","否")) | W201: =IF($A201="","",IF(AND(I201<H201,S201<0.8),"是","否")) | X201: =IF($A201="","",IF(AND(R201<60%,S201>0.8,T201="True",U201="一卖"),"是","否")) | Y201: =IF($A201="","",IF(D201="是","否",IF(N201>LOOKUP(2,1/(账户总表!$A:$A<>""),账户总表!$O:$O),"是","否"))) | Z201: =IF($A201="","",IF(M201>=0,"盈利","亏损")) | AA201: =IF($A201="","",IF(OR(Q201="是",M201<=-8%,V201="是",X201="是"),"卖出",IF(Y201="是","减仓",IF(W201="是","观察","持有")))) | AB201: =IF($A201="","",IF(D201="是",IF(I201<=E201*0.92,"立即卖出(WAIVED止损)","继续持有(WAIVED)"),IF(OR(M201<=-10%,Q201="是"),"立即卖出",IF(OR(AA201="卖出",V201="是",X201="是"),"次日卖出",IF(AND(Y201="是",NOT(OR(Q201="是",M201<=-8%,V201="是",X201="是"))),"减仓至上限",IF(W201="是","观察","继续持有")))))) | AC201: =IF($A201="","",IF(Q201="是","触发止损",IF(M201<=-8%,"固定止损",IF(V201="是","信号失效",IF(X201="是","确认一卖",IF(Y201="是","单股超限",IF(W201="是","DL_P弱化","规则内持有")))))))

Sheet 候选池
A1: 日期 | B1: 股票名称 | C1: 代码 | D1: 当前价 Price | E1: 信号价 SignalPrice | F1: 买点低点 BuyPointLow | G1: ratio | H1: DL_P | I1: valid | J1: SignalType | K1: 信号等级 | L1: 是否确认信号 ConfirmedSignal | M1: 是否未追价 NotChasing | N1: 单股上限 SingleStockCap | O1: 最大持仓金额 MaxPositionValue | P1: 理论最大股数 RawShares | Q1: 最大可买股数 MaxShares | R1: 最小可买股数 MinShares | S1: 计划买入股数 BuyShares | T1: 计划买入金额 | U1: 新增仓位占比 | V1: 买入后总仓位 | W1: 是否满足总仓位上限 | X1: 止损价 StopPrice | Y1: 失效条件 InvalidationCondition | Z1: 是否需要转入 | AA1: 最低转入金额 | AB1: 建议转入金额 | AC1: 最终是否可买 Buy | AD1: 不可买原因 | AE1: 备注
A2: 46228 | B2: 开滦股份 | C2: 600997 | D2: 5.21 | E2: 5.21 | F2: 4.95 | G2: 0.02034495 | H2: 0.67402107 | I2: True | J2: 一买 | K2: =IF($A2="","",IF(AND(G2<45%,H2>=0.9),"A",IF(AND(G2<60%,H2>0.8),"B","C"))) -> C | L2: =IF($A2="","",IF(AND(G2<60%,H2>0.8,I2="True"),"是","否")) -> 否 | M2: =IF($A2="","",IF(AND(D2>0,E2>0,D2<=E2*1.02),"是","否")) -> 是 | N2: =IFERROR(INDEX(账户总表!$O:$O,MATCH($A2,账户总表!$A:$A,0)),0) -> 0 | O2: =IFERROR(INDEX(账户总表!$B:$B,MATCH($A2,账户总表!$A:$A,0))*N2,0) -> 0 | P2: =IFERROR(O2/D2,0) -> 0 | Q2: =IFERROR(FLOOR(P2,100),0) -> 0 | R2: =IFERROR(CEILING(800/(100*D2),1)*100,0) -> 200 | T2: =IFERROR(S2*D2,0) -> 0 | U2: =IFERROR(T2/INDEX(账户总表!$B:$B,MATCH($A2,账户总表!$A:$A,0)),0) -> 0 | V2: =IFERROR(INDEX(账户总表!$E:$E,MATCH($A2,账户总表!$A:$A,0))+U2,0) -> 0 | W2: =IF($A2="","",IFERROR(IF(V2<=INDEX(账户总表!$N:$N,MATCH($A2,账户总表!$A:$A,0)),"是","否"),"否")) -> 否 | X2: =IF($A2="","",MAX(F2*0.98,D2*0.92)) -> 4.851 | Z2: =IF($A2="","",IFERROR(IF(AND(T2>INDEX(账户总表!$C:$C,MATCH($A2,账户总表!$A:$A,0)),L2="是"),"是","否"),"否")) -> 否 | AA2: =IF($A2="","",IFERROR(IF(Z2="是",MAX(0,T2-INDEX(账户总表!$C:$C,MATCH($A2,账户总表!$A:$A,0)),IF(N2>0,T2/N2-INDEX(账户总表!$B:$B,MATCH($A2,账户总表!$A:$A,0)),0)),0),0)) -> 0 | AB2: =IF($A2="","",IF(AND(Z2="是",INDEX(账户总表!$U:$U,MATCH($A2,账户总表!$A:$A,0))="是"),IF(INDEX(账户总表!$L:$L,MATCH($A2,账户总表!$A:$A,0))>=4,AA2*1.5,AA2),0)) -> #N/A | AC2: =IF($A2="","",IF(AND(L2="是",Q2>=R2,S2<=Q2,S2>=R2,W2="是",X2>0,M2="是",INDEX(账户总表!$M:$M,MATCH($A2,账户总表!$A:$A,0))<=2,INDEX(账户总表!$V:$V,MATCH($A2,账户总表!$A:$A,0))="是",OR(T2<=INDEX(账户总表!$C:$C,MATCH($A2,账户总表!$A:$A,0)),AND(Z2="是",INDEX(账户总表!$U:$U,MATCH($A2,账户总表!$A:$A,0))="是",AB2>0))),"是","否")) -> #N/A | AD2: =IF($A2="","",IF(L2<>"是","信号未确认",IF(X2<=0,"止损价未定义",IF(Q2<R2,"100股约束不满足",IF(S2>Q2,"计划股数超单股上限",IF(S2<R2,"计划股数低于最小门槛",IF(W2<>"是","总仓位超限",IF(M2<>"是","追价",IF(INDEX(账户总表!$M:$M,MATCH($A2,账户总表!$A:$A,0))>2,"亏钱效应偏高",IF(INDEX(账户总表!$V:$V,MATCH($A2,账户总表!$A:$A,0))<>"是","账户不允许新开仓",IF(AND(T2>INDEX(账户总表!$C:$C,MATCH($A2,账户总表!$A:$A,0)),INDEX(账户总表!$U:$U,MATCH($A2,账户总表!$A:$A,0))<>"是"),"现金不足且不允许转入",IF(AND(Z2="是",AB2<=0),"转入金额未满足","")))))))))))) -> 信号未确认 | AE2: 接近确认,缺:DL_P=0.67
A3: 46228 | B3: 汇嘉时代 | C3: 603101 | D3: 6.86 | E3: 6.86 | F3: 6.52 | G3: 0.029657537 | H3: 0.73486272 | I3: True | J3: 一买 | K3: =IF($A3="","",IF(AND(G3<45%,H3>=0.9),"A",IF(AND(G3<60%,H3>0.8),"B","C"))) -> C | L3: =IF($A3="","",IF(AND(G3<60%,H3>0.8,I3="True"),"是","否")) -> 否 | M3: =IF($A3="","",IF(AND(D3>0,E3>0,D3<=E3*1.02),"是","否")) -> 是 | N3: =IFERROR(INDEX(账户总表!$O:$O,MATCH($A3,账户总表!$A:$A,0)),0) -> 0 | O3: =IFERROR(INDEX(账户总表!$B:$B,MATCH($A3,账户总表!$A:$A,0))*N3,0) -> 0 | P3: =IFERROR(O3/D3,0) -> 0 | Q3: =IFERROR(FLOOR(P3,100),0) -> 0 | R3: =IFERROR(CEILING(800/(100*D3),1)*100,0) -> 200 | T3: =IFERROR(S3*D3,0) -> 0 | U3: =IFERROR(T3/INDEX(账户总表!$B:$B,MATCH($A3,账户总表!$A:$A,0)),0) -> 0 | V3: =IFERROR(INDEX(账户总表!$E:$E,MATCH($A3,账户总表!$A:$A,0))+U3,0) -> 0 | W3: =IF($A3="","",IFERROR(IF(V3<=INDEX(账户总表!$N:$N,MATCH($A3,账户总表!$A:$A,0)),"是","否"),"否")) -> 否 | X3: =IF($A3="","",MAX(F3*0.98,D3*0.92)) -> 6.3896 | Z3: =IF($A3="","",IFERROR(IF(AND(T3>INDEX(账户总表!$C:$C,MATCH($A3,账户总表!$A:$A,0)),L3="是"),"是","否"),"否")) -> 否 | AA3: =IF($A3="","",IFERROR(IF(Z3="是",MAX(0,T3-INDEX(账户总表!$C:$C,MATCH($A3,账户总表!$A:$A,0)),IF(N3>0,T3/N3-INDEX(账户总表!$B:$B,MATCH($A3,账户总表!$A:$A,0)),0)),0),0)) -> 0 | AB3: =IF($A3="","",IF(AND(Z3="是",INDEX(账户总表!$U:$U,MATCH($A3,账户总表!$A:$A,0))="是"),IF(INDEX(账户总表!$L:$L,MATCH($A3,账户总表!$A:$A,0))>=4,AA3*1.5,AA3),0)) -> #N/A | AC3: =IF($A3="","",IF(AND(L3="是",Q3>=R3,S3<=Q3,S3>=R3,W3="是",X3>0,M3="是",INDEX(账户总表!$M:$M,MATCH($A3,账户总表!$A:$A,0))<=2,INDEX(账户总表!$V:$V,MATCH($A3,账户总表!$A:$A,0))="是",OR(T3<=INDEX(账户总表!$C:$C,MATCH($A3,账户总表!$A:$A,0)),AND(Z3="是",INDEX(账户总表!$U:$U,MATCH($A3,账户总表!$A:$A,0))="是",AB3>0))),"是","否")) -> #N/A | AD3: =IF($A3="","",IF(L3<>"是","信号未确认",IF(X3<=0,"止损价未定义",IF(Q3<R3,"100股约束不满足",IF(S3>Q3,"计划股数超单股上限",IF(S3<R3,"计划股数低于最小门槛",IF(W3<>"是","总仓位超限",IF(M3<>"是","追价",IF(INDEX(账户总表!$M:$M,MATCH($A3,账户总表!$A:$A,0))>2,"亏钱效应偏高",IF(INDEX(账户总表!$V:$V,MATCH($A3,账户总表!$A:$A,0))<>"是","账户不允许新开仓",IF(AND(T3>INDEX(账户总表!$C:$C,MATCH($A3,账户总表!$A:$A,0)),INDEX(账户总表!$U:$U,MATCH($A3,账户总表!$A:$A,0))<>"是"),"现金不足且不允许转入",IF(AND(Z3="是",AB3<=0),"转入金额未满足","")))))))))))) -> 信号未确认 | AE3: 接近确认,缺:DL_P=0.73
A4: 46228 | B4: 宝钢包装 | C4: 601968 | D4: 4.13 | E4: 4.13 | F4: 3.92 | G4: 0.035091332 | H4: 0.71034935 | I4: True | J4: 一买 | K4: =IF($A4="","",IF(AND(G4<45%,H4>=0.9),"A",IF(AND(G4<60%,H4>0.8),"B","C"))) -> C | L4: =IF($A4="","",IF(AND(G4<60%,H4>0.8,I4="True"),"是","否")) -> 否 | M4: =IF($A4="","",IF(AND(D4>0,E4>0,D4<=E4*1.02),"是","否")) -> 是 | N4: =IFERROR(INDEX(账户总表!$O:$O,MATCH($A4,账户总表!$A:$A,0)),0) -> 0 | O4: =IFERROR(INDEX(账户总表!$B:$B,MATCH($A4,账户总表!$A:$A,0))*N4,0) -> 0 | P4: =IFERROR(O4/D4,0) -> 0 | Q4: =IFERROR(FLOOR(P4,100),0) -> 0 | R4: =IFERROR(CEILING(800/(100*D4),1)*100,0) -> 200 | T4: =IFERROR(S4*D4,0) -> 0 | U4: =IFERROR(T4/INDEX(账户总表!$B:$B,MATCH($A4,账户总表!$A:$A,0)),0) -> 0 | V4: =IFERROR(INDEX(账户总表!$E:$E,MATCH($A4,账户总表!$A:$A,0))+U4,0) -> 0 | W4: =IF($A4="","",IFERROR(IF(V4<=INDEX(账户总表!$N:$N,MATCH($A4,账户总表!$A:$A,0)),"是","否"),"否")) -> 否 | X4: =IF($A4="","",MAX(F4*0.98,D4*0.92)) -> 3.8416 | Z4: =IF($A4="","",IFERROR(IF(AND(T4>INDEX(账户总表!$C:$C,MATCH($A4,账户总表!$A:$A,0)),L4="是"),"是","否"),"否")) -> 否 | AA4: =IF($A4="","",IFERROR(IF(Z4="是",MAX(0,T4-INDEX(账户总表!$C:$C,MATCH($A4,账户总表!$A:$A,0)),IF(N4>0,T4/N4-INDEX(账户总表!$B:$B,MATCH($A4,账户总表!$A:$A,0)),0)),0),0)) -> 0 | AB4: =IF($A4="","",IF(AND(Z4="是",INDEX(账户总表!$U:$U,MATCH($A4,账户总表!$A:$A,0))="是"),IF(INDEX(账户总表!$L:$L,MATCH($A4,账户总表!$A:$A,0))>=4,AA4*1.5,AA4),0)) -> #N/A | AC4: =IF($A4="","",IF(AND(L4="是",Q4>=R4,S4<=Q4,S4>=R4,W4="是",X4>0,M4="是",INDEX(账户总表!$M:$M,MATCH($A4,账户总表!$A:$A,0))<=2,INDEX(账户总表!$V:$V,MATCH($A4,账户总表!$A:$A,0))="是",OR(T4<=INDEX(账户总表!$C:$C,MATCH($A4,账户总表!$A:$A,0)),AND(Z4="是",INDEX(账户总表!$U:$U,MATCH($A4,账户总表!$A:$A,0))="是",AB4>0))),"是","否")) -> #N/A | AD4: =IF($A4="","",IF(L4<>"是","信号未确认",IF(X4<=0,"止损价未定义",IF(Q4<R4,"100股约束不满足",IF(S4>Q4,"计划股数超单股上限",IF(S4<R4,"计划股数低于最小门槛",IF(W4<>"是","总仓位超限",IF(M4<>"是","追价",IF(INDEX(账户总表!$M:$M,MATCH($A4,账户总表!$A:$A,0))>2,"亏钱效应偏高",IF(INDEX(账户总表!$V:$V,MATCH($A4,账户总表!$A:$A,0))<>"是","账户不允许新开仓",IF(AND(T4>INDEX(账户总表!$C:$C,MATCH($A4,账户总表!$A:$A,0)),INDEX(账户总表!$U:$U,MATCH($A4,账户总表!$A:$A,0))<>"是"),"现金不足且不允许转入",IF(AND(Z4="是",AB4<=0),"转入金额未满足","")))))))))))) -> 信号未确认 | AE4: 接近确认,缺:DL_P=0.71
A5: 46228 | B5: 家家悦 | C5: 603708 | D5: 8.98 | E5: 8.98 | F5: 8.53 | G5: 0.039394085 | H5: 0.62768013 | I5: True | J5: 一买 | K5: =IF($A5="","",IF(AND(G5<45%,H5>=0.9),"A",IF(AND(G5<60%,H5>0.8),"B","C"))) -> C | L5: =IF($A5="","",IF(AND(G5<60%,H5>0.8,I5="True"),"是","否")) -> 否 | M5: =IF($A5="","",IF(AND(D5>0,E5>0,D5<=E5*1.02),"是","否")) -> 是 | N5: =IFERROR(INDEX(账户总表!$O:$O,MATCH($A5,账户总表!$A:$A,0)),0) -> 0 | O5: =IFERROR(INDEX(账户总表!$B:$B,MATCH($A5,账户总表!$A:$A,0))*N5,0) -> 0 | P5: =IFERROR(O5/D5,0) -> 0 | Q5: =IFERROR(FLOOR(P5,100),0) -> 0 | R5: =IFERROR(CEILING(800/(100*D5),1)*100,0) -> 100 | T5: =IFERROR(S5*D5,0) -> 0 | U5: =IFERROR(T5/INDEX(账户总表!$B:$B,MATCH($A5,账户总表!$A:$A,0)),0) -> 0 | V5: =IFERROR(INDEX(账户总表!$E:$E,MATCH($A5,账户总表!$A:$A,0))+U5,0) -> 0 | W5: =IF($A5="","",IFERROR(IF(V5<=INDEX(账户总表!$N:$N,MATCH($A5,账户总表!$A:$A,0)),"是","否"),"否")) -> 否 | X5: =IF($A5="","",MAX(F5*0.98,D5*0.92)) -> 8.3594 | Z5: =IF($A5="","",IFERROR(IF(AND(T5>INDEX(账户总表!$C:$C,MATCH($A5,账户总表!$A:$A,0)),L5="是"),"是","否"),"否")) -> 否 | AA5: =IF($A5="","",IFERROR(IF(Z5="是",MAX(0,T5-INDEX(账户总表!$C:$C,MATCH($A5,账户总表!$A:$A,0)),IF(N5>0,T5/N5-INDEX(账户总表!$B:$B,MATCH($A5,账户总表!$A:$A,0)),0)),0),0)) -> 0 | AB5: =IF($A5="","",IF(AND(Z5="是",INDEX(账户总表!$U:$U,MATCH($A5,账户总表!$A:$A,0))="是"),IF(INDEX(账户总表!$L:$L,MATCH($A5,账户总表!$A:$A,0))>=4,AA5*1.5,AA5),0)) -> #N/A | AC5: =IF($A5="","",IF(AND(L5="是",Q5>=R5,S5<=Q5,S5>=R5,W5="是",X5>0,M5="是",INDEX(账户总表!$M:$M,MATCH($A5,账户总表!$A:$A,0))<=2,INDEX(账户总表!$V:$V,MATCH($A5,账户总表!$A:$A,0))="是",OR(T5<=INDEX(账户总表!$C:$C,MATCH($A5,账户总表!$A:$A,0)),AND(Z5="是",INDEX(账户总表!$U:$U,MATCH($A5,账户总表!$A:$A,0))="是",AB5>0))),"是","否")) -> #N/A | AD5: =IF($A5="","",IF(L5<>"是","信号未确认",IF(X5<=0,"止损价未定义",IF(Q5<R5,"100股约束不满足",IF(S5>Q5,"计划股数超单股上限",IF(S5<R5,"计划股数低于最小门槛",IF(W5<>"是","总仓位超限",IF(M5<>"是","追价",IF(INDEX(账户总表!$M:$M,MATCH($A5,账户总表!$A:$A,0))>2,"亏钱效应偏高",IF(INDEX(账户总表!$V:$V,MATCH($A5,账户总表!$A:$A,0))<>"是","账户不允许新开仓",IF(AND(T5>INDEX(账户总表!$C:$C,MATCH($A5,账户总表!$A:$A,0)),INDEX(账户总表!$U:$U,MATCH($A5,账户总表!$A:$A,0))<>"是"),"现金不足且不允许转入",IF(AND(Z5="是",AB5<=0),"转入金额未满足","")))))))))))) -> 信号未确认 | AE5: 接近确认,缺:DL_P=0.63
A6: 46228 | B6: 一鸣食品 | C6: 605179 | D6: 13 | E6: 13 | F6: 12.35 | G6: 0.045241052 | H6: 0.71619043 | I6: True | J6: 一买 | K6: =IF($A6="","",IF(AND(G6<45%,H6>=0.9),"A",IF(AND(G6<60%,H6>0.8),"B","C"))) -> C | L6: =IF($A6="","",IF(AND(G6<60%,H6>0.8,I6="True"),"是","否")) -> 否 | M6: =IF($A6="","",IF(AND(D6>0,E6>0,D6<=E6*1.02),"是","否")) -> 是 | N6: =IFERROR(INDEX(账户总表!$O:$O,MATCH($A6,账户总表!$A:$A,0)),0) -> 0 | O6: =IFERROR(INDEX(账户总表!$B:$B,MATCH($A6,账户总表!$A:$A,0))*N6,0) -> 0 | P6: =IFERROR(O6/D6,0) -> 0 | Q6: =IFERROR(FLOOR(P6,100),0) -> 0 | R6: =IFERROR(CEILING(800/(100*D6),1)*100,0) -> 100 | T6: =IFERROR(S6*D6,0) -> 0 | U6: =IFERROR(T6/INDEX(账户总表!$B:$B,MATCH($A6,账户总表!$A:$A,0)),0) -> 0 | V6: =IFERROR(INDEX(账户总表!$E:$E,MATCH($A6,账户总表!$A:$A,0))+U6,0) -> 0 | W6: =IF($A6="","",IFERROR(IF(V6<=INDEX(账户总表!$N:$N,MATCH($A6,账户总表!$A:$A,0)),"是","否"),"否")) -> 否 | X6: =IF($A6="","",MAX(F6*0.98,D6*0.92)) -> 12.103 | Z6: =IF($A6="","",IFERROR(IF(AND(T6>INDEX(账户总表!$C:$C,MATCH($A6,账户总表!$A:$A,0)),L6="是"),"是","否"),"否")) -> 否 | AA6: =IF($A6="","",IFERROR(IF(Z6="是",MAX(0,T6-INDEX(账户总表!$C:$C,MATCH($A6,账户总表!$A:$A,0)),IF(N6>0,T6/N6-INDEX(账户总表!$B:$B,MATCH($A6,账户总表!$A:$A,0)),0)),0),0)) -> 0 | AB6: =IF($A6="","",IF(AND(Z6="是",INDEX(账户总表!$U:$U,MATCH($A6,账户总表!$A:$A,0))="是"),IF(INDEX(账户总表!$L:$L,MATCH($A6,账户总表!$A:$A,0))>=4,AA6*1.5,AA6),0)) -> #N/A | AC6: =IF($A6="","",IF(AND(L6="是",Q6>=R6,S6<=Q6,S6>=R6,W6="是",X6>0,M6="是",INDEX(账户总表!$M:$M,MATCH($A6,账户总表!$A:$A,0))<=2,INDEX(账户总表!$V:$V,MATCH($A6,账户总表!$A:$A,0))="是",OR(T6<=INDEX(账户总表!$C:$C,MATCH($A6,账户总表!$A:$A,0)),AND(Z6="是",INDEX(账户总表!$U:$U,MATCH($A6,账户总表!$A:$A,0))="是",AB6>0))),"是","否")) -> #N/A | AD6: =IF($A6="","",IF(L6<>"是","信号未确认",IF(X6<=0,"止损价未定义",IF(Q6<R6,"100股约束不满足",IF(S6>Q6,"计划股数超单股上限",IF(S6<R6,"计划股数低于最小门槛",IF(W6<>"是","总仓位超限",IF(M6<>"是","追价",IF(INDEX(账户总表!$M:$M,MATCH($A6,账户总表!$A:$A,0))>2,"亏钱效应偏高",IF(INDEX(账户总表!$V:$V,MATCH($A6,账户总表!$A:$A,0))<>"是","账户不允许新开仓",IF(AND(T6>INDEX(账户总表!$C:$C,MATCH($A6,账户总表!$A:$A,0)),INDEX(账户总表!$U:$U,MATCH($A6,账户总表!$A:$A,0))<>"是"),"现金不足且不允许转入",IF(AND(Z6="是",AB6<=0),"转入金额未满足","")))))))))))) -> 信号未确认 | AE6: 接近确认,缺:DL_P=0.72
A7: 46228 | B7: 南方传媒 | C7: 601900 | D7: 11.2 | E7: 11.2 | F7: 10.64 | G7: 0.051630912 | H7: 0.61712532 | I7: True | J7: 一买 | K7: =IF($A7="","",IF(AND(G7<45%,H7>=0.9),"A",IF(AND(G7<60%,H7>0.8),"B","C"))) -> C | L7: =IF($A7="","",IF(AND(G7<60%,H7>0.8,I7="True"),"是","否")) -> 否 | M7: =IF($A7="","",IF(AND(D7>0,E7>0,D7<=E7*1.02),"是","否")) -> 是 | N7: =IFERROR(INDEX(账户总表!$O:$O,MATCH($A7,账户总表!$A:$A,0)),0) -> 0 | O7: =IFERROR(INDEX(账户总表!$B:$B,MATCH($A7,账户总表!$A:$A,0))*N7,0) -> 0 | P7: =IFERROR(O7/D7,0) -> 0 | Q7: =IFERROR(FLOOR(P7,100),0) -> 0 | R7: =IFERROR(CEILING(800/(100*D7),1)*100,0) -> 100 | T7: =IFERROR(S7*D7,0) -> 0 | U7: =IFERROR(T7/INDEX(账户总表!$B:$B,MATCH($A7,账户总表!$A:$A,0)),0) -> 0 | V7: =IFERROR(INDEX(账户总表!$E:$E,MATCH($A7,账户总表!$A:$A,0))+U7,0) -> 0 | W7: =IF($A7="","",IFERROR(IF(V7<=INDEX(账户总表!$N:$N,MATCH($A7,账户总表!$A:$A,0)),"是","否"),"否")) -> 否 | X7: =IF($A7="","",MAX(F7*0.98,D7*0.92)) -> 10.4272 | Z7: =IF($A7="","",IFERROR(IF(AND(T7>INDEX(账户总表!$C:$C,MATCH($A7,账户总表!$A:$A,0)),L7="是"),"是","否"),"否")) -> 否 | AA7: =IF($A7="","",IFERROR(IF(Z7="是",MAX(0,T7-INDEX(账户总表!$C:$C,MATCH($A7,账户总表!$A:$A,0)),IF(N7>0,T7/N7-INDEX(账户总表!$B:$B,MATCH($A7,账户总表!$A:$A,0)),0)),0),0)) -> 0 | AB7: =IF($A7="","",IF(AND(Z7="是",INDEX(账户总表!$U:$U,MATCH($A7,账户总表!$A:$A,0))="是"),IF(INDEX(账户总表!$L:$L,MATCH($A7,账户总表!$A:$A,0))>=4,AA7*1.5,AA7),0)) -> #N/A | AC7: =IF($A7="","",IF(AND(L7="是",Q7>=R7,S7<=Q7,S7>=R7,W7="是",X7>0,M7="是",INDEX(账户总表!$M:$M,MATCH($A7,账户总表!$A:$A,0))<=2,INDEX(账户总表!$V:$V,MATCH($A7,账户总表!$A:$A,0))="是",OR(T7<=INDEX(账户总表!$C:$C,MATCH($A7,账户总表!$A:$A,0)),AND(Z7="是",INDEX(账户总表!$U:$U,MATCH($A7,账户总表!$A:$A,0))="是",AB7>0))),"是","否")) -> #N/A | AD7: =IF($A7="","",IF(L7<>"是","信号未确认",IF(X7<=0,"止损价未定义",IF(Q7<R7,"100股约束不满足",IF(S7>Q7,"计划股数超单股上限",IF(S7<R7,"计划股数低于最小门槛",IF(W7<>"是","总仓位超限",IF(M7<>"是","追价",IF(INDEX(账户总表!$M:$M,MATCH($A7,账户总表!$A:$A,0))>2,"亏钱效应偏高",IF(INDEX(账户总表!$V:$V,MATCH($A7,账户总表!$A:$A,0))<>"是","账户不允许新开仓",IF(AND(T7>INDEX(账户总表!$C:$C,MATCH($A7,账户总表!$A:$A,0)),INDEX(账户总表!$U:$U,MATCH($A7,账户总表!$A:$A,0))<>"是"),"现金不足且不允许转入",IF(AND(Z7="是",AB7<=0),"转入金额未满足","")))))))))))) -> 信号未确认 | AE7: 接近确认,缺:DL_P=0.62
A8: 46228 | B8: 东鹏饮料 | C8: 605499 | D8: 125.82 | E8: 125.82 | F8: 119.53 | G8: 0.057991952 | H8: 0.75566874 | I8: True | J8: 一买 | K8: =IF($A8="","",IF(AND(G8<45%,H8>=0.9),"A",IF(AND(G8<60%,H8>0.8),"B","C"))) -> C | L8: =IF($A8="","",IF(AND(G8<60%,H8>0.8,I8="True"),"是","否")) -> 否 | M8: =IF($A8="","",IF(AND(D8>0,E8>0,D8<=E8*1.02),"是","否")) -> 是 | N8: =IFERROR(INDEX(账户总表!$O:$O,MATCH($A8,账户总表!$A:$A,0)),0) -> 0 | O8: =IFERROR(INDEX(账户总表!$B:$B,MATCH($A8,账户总表!$A:$A,0))*N8,0) -> 0 | P8: =IFERROR(O8/D8,0) -> 0 | Q8: =IFERROR(FLOOR(P8,100),0) -> 0 | R8: =IFERROR(CEILING(800/(100*D8),1)*100,0) -> 100 | T8: =IFERROR(S8*D8,0) -> 0 | U8: =IFERROR(T8/INDEX(账户总表!$B:$B,MATCH($A8,账户总表!$A:$A,0)),0) -> 0 | V8: =IFERROR(INDEX(账户总表!$E:$E,MATCH($A8,账户总表!$A:$A,0))+U8,0) -> 0 | W8: =IF($A8="","",IFERROR(IF(V8<=INDEX(账户总表!$N:$N,MATCH($A8,账户总表!$A:$A,0)),"是","否"),"否")) -> 否 | X8: =IF($A8="","",MAX(F8*0.98,D8*0.92)) -> 117.1394 | Z8: =IF($A8="","",IFERROR(IF(AND(T8>INDEX(账户总表!$C:$C,MATCH($A8,账户总表!$A:$A,0)),L8="是"),"是","否"),"否")) -> 否 | AA8: =IF($A8="","",IFERROR(IF(Z8="是",MAX(0,T8-INDEX(账户总表!$C:$C,MATCH($A8,账户总表!$A:$A,0)),IF(N8>0,T8/N8-INDEX(账户总表!$B:$B,MATCH($A8,账户总表!$A:$A,0)),0)),0),0)) -> 0 | AB8: =IF($A8="","",IF(AND(Z8="是",INDEX(账户总表!$U:$U,MATCH($A8,账户总表!$A:$A,0))="是"),IF(INDEX(账户总表!$L:$L,MATCH($A8,账户总表!$A:$A,0))>=4,AA8*1.5,AA8),0)) -> #N/A | AC8: =IF($A8="","",IF(AND(L8="是",Q8>=R8,S8<=Q8,S8>=R8,W8="是",X8>0,M8="是",INDEX(账户总表!$M:$M,MATCH($A8,账户总表!$A:$A,0))<=2,INDEX(账户总表!$V:$V,MATCH($A8,账户总表!$A:$A,0))="是",OR(T8<=INDEX(账户总表!$C:$C,MATCH($A8,账户总表!$A:$A,0)),AND(Z8="是",INDEX(账户总表!$U:$U,MATCH($A8,账户总表!$A:$A,0))="是",AB8>0))),"是","否")) -> #N/A | AD8: =IF($A8="","",IF(L8<>"是","信号未确认",IF(X8<=0,"止损价未定义",IF(Q8<R8,"100股约束不满足",IF(S8>Q8,"计划股数超单股上限",IF(S8<R8,"计划股数低于最小门槛",IF(W8<>"是","总仓位超限",IF(M8<>"是","追价",IF(INDEX(账户总表!$M:$M,MATCH($A8,账户总表!$A:$A,0))>2,"亏钱效应偏高",IF(INDEX(账户总表!$V:$V,MATCH($A8,账户总表!$A:$A,0))<>"是","账户不允许新开仓",IF(AND(T8>INDEX(账户总表!$C:$C,MATCH($A8,账户总表!$A:$A,0)),INDEX(账户总表!$U:$U,MATCH($A8,账户总表!$A:$A,0))<>"是"),"现金不足且不允许转入",IF(AND(Z8="是",AB8<=0),"转入金额未满足","")))))))))))) -> 信号未确认 | AE8: 接近确认,缺:DL_P=0.76 | 需转入224元
A9: 46228 | B9: 健友股份 | C9: 603707 | D9: 7.55 | E9: 7.55 | F9: 7.17 | G9: 0.058907914 | H9: 0.63308093 | I9: True | J9: 一买 | K9: =IF($A9="","",IF(AND(G9<45%,H9>=0.9),"A",IF(AND(G9<60%,H9>0.8),"B","C"))) -> C | L9: =IF($A9="","",IF(AND(G9<60%,H9>0.8,I9="True"),"是","否")) -> 否 | M9: =IF($A9="","",IF(AND(D9>0,E9>0,D9<=E9*1.02),"是","否")) -> 是 | N9: =IFERROR(INDEX(账户总表!$O:$O,MATCH($A9,账户总表!$A:$A,0)),0) -> 0 | O9: =IFERROR(INDEX(账户总表!$B:$B,MATCH($A9,账户总表!$A:$A,0))*N9,0) -> 0 | P9: =IFERROR(O9/D9,0) -> 0 | Q9: =IFERROR(FLOOR(P9,100),0) -> 0 | R9: =IFERROR(CEILING(800/(100*D9),1)*100,0) -> 200 | T9: =IFERROR(S9*D9,0) -> 0 | U9: =IFERROR(T9/INDEX(账户总表!$B:$B,MATCH($A9,账户总表!$A:$A,0)),0) -> 0 | V9: =IFERROR(INDEX(账户总表!$E:$E,MATCH($A9,账户总表!$A:$A,0))+U9,0) -> 0 | W9: =IF($A9="","",IFERROR(IF(V9<=INDEX(账户总表!$N:$N,MATCH($A9,账户总表!$A:$A,0)),"是","否"),"否")) -> 否 | X9: =IF($A9="","",MAX(F9*0.98,D9*0.92)) -> 7.0266 | Z9: =IF($A9="","",IFERROR(IF(AND(T9>INDEX(账户总表!$C:$C,MATCH($A9,账户总表!$A:$A,0)),L9="是"),"是","否"),"否")) -> 否 | AA9: =IF($A9="","",IFERROR(IF(Z9="是",MAX(0,T9-INDEX(账户总表!$C:$C,MATCH($A9,账户总表!$A:$A,0)),IF(N9>0,T9/N9-INDEX(账户总表!$B:$B,MATCH($A9,账户总表!$A:$A,0)),0)),0),0)) -> 0 | AB9: =IF($A9="","",IF(AND(Z9="是",INDEX(账户总表!$U:$U,MATCH($A9,账户总表!$A:$A,0))="是"),IF(INDEX(账户总表!$L:$L,MATCH($A9,账户总表!$A:$A,0))>=4,AA9*1.5,AA9),0)) -> #N/A | AC9: =IF($A9="","",IF(AND(L9="是",Q9>=R9,S9<=Q9,S9>=R9,W9="是",X9>0,M9="是",INDEX(账户总表!$M:$M,MATCH($A9,账户总表!$A:$A,0))<=2,INDEX(账户总表!$V:$V,MATCH($A9,账户总表!$A:$A,0))="是",OR(T9<=INDEX(账户总表!$C:$C,MATCH($A9,账户总表!$A:$A,0)),AND(Z9="是",INDEX(账户总表!$U:$U,MATCH($A9,账户总表!$A:$A,0))="是",AB9>0))),"是","否")) -> #N/A | AD9: =IF($A9="","",IF(L9<>"是","信号未确认",IF(X9<=0,"止损价未定义",IF(Q9<R9,"100股约束不满足",IF(S9>Q9,"计划股数超单股上限",IF(S9<R9,"计划股数低于最小门槛",IF(W9<>"是","总仓位超限",IF(M9<>"是","追价",IF(INDEX(账户总表!$M:$M,MATCH($A9,账户总表!$A:$A,0))>2,"亏钱效应偏高",IF(INDEX(账户总表!$V:$V,MATCH($A9,账户总表!$A:$A,0))<>"是","账户不允许新开仓",IF(AND(T9>INDEX(账户总表!$C:$C,MATCH($A9,账户总表!$A:$A,0)),INDEX(账户总表!$U:$U,MATCH($A9,账户总表!$A:$A,0))<>"是"),"现金不足且不允许转入",IF(AND(Z9="是",AB9<=0),"转入金额未满足","")))))))))))) -> 信号未确认 | AE9: 接近确认,缺:DL_P=0.63
A10: 46228 | B10: 今世缘 | C10: 603369 | D10: 25.52 | E10: 25.52 | F10: 24.24 | G10: 0.063663124 | H10: 0.71022595 | I10: True | J10: 一买 | K10: =IF($A10="","",IF(AND(G10<45%,H10>=0.9),"A",IF(AND(G10<60%,H10>0.8),"B","C"))) -> C | L10: =IF($A10="","",IF(AND(G10<60%,H10>0.8,I10="True"),"是","否")) -> 否 | M10: =IF($A10="","",IF(AND(D10>0,E10>0,D10<=E10*1.02),"是","否")) -> 是 | N10: =IFERROR(INDEX(账户总表!$O:$O,MATCH($A10,账户总表!$A:$A,0)),0) -> 0 | O10: =IFERROR(INDEX(账户总表!$B:$B,MATCH($A10,账户总表!$A:$A,0))*N10,0) -> 0 | P10: =IFERROR(O10/D10,0) -> 0 | Q10: =IFERROR(FLOOR(P10,100),0) -> 0 | R10: =IFERROR(CEILING(800/(100*D10),1)*100,0) -> 100 | T10: =IFERROR(S10*D10,0) -> 0 | U10: =IFERROR(T10/INDEX(账户总表!$B:$B,MATCH($A10,账户总表!$A:$A,0)),0) -> 0 | V10: =IFERROR(INDEX(账户总表!$E:$E,MATCH($A10,账户总表!$A:$A,0))+U10,0) -> 0 | W10: =IF($A10="","",IFERROR(IF(V10<=INDEX(账户总表!$N:$N,MATCH($A10,账户总表!$A:$A,0)),"是","否"),"否")) -> 否 | X10: =IF($A10="","",MAX(F10*0.98,D10*0.92)) -> 23.7552 | Z10: =IF($A10="","",IFERROR(IF(AND(T10>INDEX(账户总表!$C:$C,MATCH($A10,账户总表!$A:$A,0)),L10="是"),"是","否"),"否")) -> 否 | AA10: =IF($A10="","",IFERROR(IF(Z10="是",MAX(0,T10-INDEX(账户总表!$C:$C,MATCH($A10,账户总表!$A:$A,0)),IF(N10>0,T10/N10-INDEX(账户总表!$B:$B,MATCH($A10,账户总表!$A:$A,0)),0)),0),0)) -> 0 | AB10: =IF($A10="","",IF(AND(Z10="是",INDEX(账户总表!$U:$U,MATCH($A10,账户总表!$A:$A,0))="是"),IF(INDEX(账户总表!$L:$L,MATCH($A10,账户总表!$A:$A,0))>=4,AA10*1.5,AA10),0)) -> #N/A | AC10: =IF($A10="","",IF(AND(L10="是",Q10>=R10,S10<=Q10,S10>=R10,W10="是",X10>0,M10="是",INDEX(账户总表!$M:$M,MATCH($A10,账户总表!$A:$A,0))<=2,INDEX(账户总表!$V:$V,MATCH($A10,账户总表!$A:$A,0))="是",OR(T10<=INDEX(账户总表!$C:$C,MATCH($A10,账户总表!$A:$A,0)),AND(Z10="是",INDEX(账户总表!$U:$U,MATCH($A10,账户总表!$A:$A,0))="是",AB10>0))),"是","否")) -> #N/A | AD10: =IF($A10="","",IF(L10<>"是","信号未确认",IF(X10<=0,"止损价未定义",IF(Q10<R10,"100股约束不满足",IF(S10>Q10,"计划股数超单股上限",IF(S10<R10,"计划股数低于最小门槛",IF(W10<>"是","总仓位超限",IF(M10<>"是","追价",IF(INDEX(账户总表!$M:$M,MATCH($A10,账户总表!$A:$A,0))>2,"亏钱效应偏高",IF(INDEX(账户总表!$V:$V,MATCH($A10,账户总表!$A:$A,0))<>"是","账户不允许新开仓",IF(AND(T10>INDEX(账户总表!$C:$C,MATCH($A10,账户总表!$A:$A,0)),INDEX(账户总表!$U:$U,MATCH($A10,账户总表!$A:$A,0))<>"是"),"现金不足且不允许转入",IF(AND(Z10="是",AB10<=0),"转入金额未满足","")))))))))))) -> 信号未确认 | AE10: 接近确认,缺:DL_P=0.71
A11: 46228 | B11: 新城控股 | C11: 601155 | D11: 10.98 | E11: 10.98 | F11: 10.43 | G11: 0.064564591 | H11: 0.66288842 | I11: True | J11: 一买 | K11: =IF($A11="","",IF(AND(G11<45%,H11>=0.9),"A",IF(AND(G11<60%,H11>0.8),"B","C"))) -> C | L11: =IF($A11="","",IF(AND(G11<60%,H11>0.8,I11="True"),"是","否")) -> 否 | M11: =IF($A11="","",IF(AND(D11>0,E11>0,D11<=E11*1.02),"是","否")) -> 是 | N11: =IFERROR(INDEX(账户总表!$O:$O,MATCH($A11,账户总表!$A:$A,0)),0) -> 0 | O11: =IFERROR(INDEX(账户总表!$B:$B,MATCH($A11,账户总表!$A:$A,0))*N11,0) -> 0 | P11: =IFERROR(O11/D11,0) -> 0 | Q11: =IFERROR(FLOOR(P11,100),0) -> 0 | R11: =IFERROR(CEILING(800/(100*D11),1)*100,0) -> 100 | T11: =IFERROR(S11*D11,0) -> 0 | U11: =IFERROR(T11/INDEX(账户总表!$B:$B,MATCH($A11,账户总表!$A:$A,0)),0) -> 0 | V11: =IFERROR(INDEX(账户总表!$E:$E,MATCH($A11,账户总表!$A:$A,0))+U11,0) -> 0 | W11: =IF($A11="","",IFERROR(IF(V11<=INDEX(账户总表!$N:$N,MATCH($A11,账户总表!$A:$A,0)),"是","否"),"否")) -> 否 | X11: =IF($A11="","",MAX(F11*0.98,D11*0.92)) -> 10.2214 | Z11: =IF($A11="","",IFERROR(IF(AND(T11>INDEX(账户总表!$C:$C,MATCH($A11,账户总表!$A:$A,0)),L11="是"),"是","否"),"否")) -> 否 | AA11: =IF($A11="","",IFERROR(IF(Z11="是",MAX(0,T11-INDEX(账户总表!$C:$C,MATCH($A11,账户总表!$A:$A,0)),IF(N11>0,T11/N11-INDEX(账户总表!$B:$B,MATCH($A11,账户总表!$A:$A,0)),0)),0),0)) -> 0 | AB11: =IF($A11="","",IF(AND(Z11="是",INDEX(账户总表!$U:$U,MATCH($A11,账户总表!$A:$A,0))="是"),IF(INDEX(账户总表!$L:$L,MATCH($A11,账户总表!$A:$A,0))>=4,AA11*1.5,AA11),0)) -> #N/A | AC11: =IF($A11="","",IF(AND(L11="是",Q11>=R11,S11<=Q11,S11>=R11,W11="是",X11>0,M11="是",INDEX(账户总表!$M:$M,MATCH($A11,账户总表!$A:$A,0))<=2,INDEX(账户总表!$V:$V,MATCH($A11,账户总表!$A:$A,0))="是",OR(T11<=INDEX(账户总表!$C:$C,MATCH($A11,账户总表!$A:$A,0)),AND(Z11="是",INDEX(账户总表!$U:$U,MATCH($A11,账户总表!$A:$A,0))="是",AB11>0))),"是","否")) -> #N/A | AD11: =IF($A11="","",IF(L11<>"是","信号未确认",IF(X11<=0,"止损价未定义",IF(Q11<R11,"100股约束不满足",IF(S11>Q11,"计划股数超单股上限",IF(S11<R11,"计划股数低于最小门槛",IF(W11<>"是","总仓位超限",IF(M11<>"是","追价",IF(INDEX(账户总表!$M:$M,MATCH($A11,账户总表!$A:$A,0))>2,"亏钱效应偏高",IF(INDEX(账户总表!$V:$V,MATCH($A11,账户总表!$A:$A,0))<>"是","账户不允许新开仓",IF(AND(T11>INDEX(账户总表!$C:$C,MATCH($A11,账户总表!$A:$A,0)),INDEX(账户总表!$U:$U,MATCH($A11,账户总表!$A:$A,0))<>"是"),"现金不足且不允许转入",IF(AND(Z11="是",AB11<=0),"转入金额未满足","")))))))))))) -> 信号未确认 | AE11: 接近确认,缺:DL_P=0.66
A12: 46228 | B12: 福然德 | C12: 605050 | D12: 10.22 | E12: 10.22 | F12: 9.71 | G12: 0.064721128 | H12: 0.64764779 | I12: True | J12: 一买 | K12: =IF($A12="","",IF(AND(G12<45%,H12>=0.9),"A",IF(AND(G12<60%,H12>0.8),"B","C"))) -> C | L12: =IF($A12="","",IF(AND(G12<60%,H12>0.8,I12="True"),"是","否")) -> 否 | M12: =IF($A12="","",IF(AND(D12>0,E12>0,D12<=E12*1.02),"是","否")) -> 是 | N12: =IFERROR(INDEX(账户总表!$O:$O,MATCH($A12,账户总表!$A:$A,0)),0) -> 0 | O12: =IFERROR(INDEX(账户总表!$B:$B,MATCH($A12,账户总表!$A:$A,0))*N12,0) -> 0 | P12: =IFERROR(O12/D12,0) -> 0 | Q12: =IFERROR(FLOOR(P12,100),0) -> 0 | R12: =IFERROR(CEILING(800/(100*D12),1)*100,0) -> 100 | T12: =IFERROR(S12*D12,0) -> 0 | U12: =IFERROR(T12/INDEX(账户总表!$B:$B,MATCH($A12,账户总表!$A:$A,0)),0) -> 0 | V12: =IFERROR(INDEX(账户总表!$E:$E,MATCH($A12,账户总表!$A:$A,0))+U12,0) -> 0 | W12: =IF($A12="","",IFERROR(IF(V12<=INDEX(账户总表!$N:$N,MATCH($A12,账户总表!$A:$A,0)),"是","否"),"否")) -> 否 | X12: =IF($A12="","",MAX(F12*0.98,D12*0.92)) -> 9.5158 | Z12: =IF($A12="","",IFERROR(IF(AND(T12>INDEX(账户总表!$C:$C,MATCH($A12,账户总表!$A:$A,0)),L12="是"),"是","否"),"否")) -> 否 | AA12: =IF($A12="","",IFERROR(IF(Z12="是",MAX(0,T12-INDEX(账户总表!$C:$C,MATCH($A12,账户总表!$A:$A,0)),IF(N12>0,T12/N12-INDEX(账户总表!$B:$B,MATCH($A12,账户总表!$A:$A,0)),0)),0),0)) -> 0 | AB12: =IF($A12="","",IF(AND(Z12="是",INDEX(账户总表!$U:$U,MATCH($A12,账户总表!$A:$A,0))="是"),IF(INDEX(账户总表!$L:$L,MATCH($A12,账户总表!$A:$A,0))>=4,AA12*1.5,AA12),0)) -> #N/A | AC12: =IF($A12="","",IF(AND(L12="是",Q12>=R12,S12<=Q12,S12>=R12,W12="是",X12>0,M12="是",INDEX(账户总表!$M:$M,MATCH($A12,账户总表!$A:$A,0))<=2,INDEX(账户总表!$V:$V,MATCH($A12,账户总表!$A:$A,0))="是",OR(T12<=INDEX(账户总表!$C:$C,MATCH($A12,账户总表!$A:$A,0)),AND(Z12="是",INDEX(账户总表!$U:$U,MATCH($A12,账户总表!$A:$A,0))="是",AB12>0))),"是","否")) -> #N/A | AD12: =IF($A12="","",IF(L12<>"是","信号未确认",IF(X12<=0,"止损价未定义",IF(Q12<R12,"100股约束不满足",IF(S12>Q12,"计划股数超单股上限",IF(S12<R12,"计划股数低于最小门槛",IF(W12<>"是","总仓位超限",IF(M12<>"是","追价",IF(INDEX(账户总表!$M:$M,MATCH($A12,账户总表!$A:$A,0))>2,"亏钱效应偏高",IF(INDEX(账户总表!$V:$V,MATCH($A12,账户总表!$A:$A,0))<>"是","账户不允许新开仓",IF(AND(T12>INDEX(账户总表!$C:$C,MATCH($A12,账户总表!$A:$A,0)),INDEX(账户总表!$U:$U,MATCH($A12,账户总表!$A:$A,0))<>"是"),"现金不足且不允许转入",IF(AND(Z12="是",AB12<=0),"转入金额未满足","")))))))))))) -> 信号未确认 | AE12: 接近确认,缺:DL_P=0.65
A13: 46228 | B13: 欧派家居 | C13: 603833 | D13: 30.99 | E13: 30.99 | F13: 29.44 | G13: 0.073269771 | H13: 0.73514296 | I13: True | J13: 一买 | K13: =IF($A13="","",IF(AND(G13<45%,H13>=0.9),"A",IF(AND(G13<60%,H13>0.8),"B","C"))) -> C | L13: =IF($A13="","",IF(AND(G13<60%,H13>0.8,I13="True"),"是","否")) -> 否 | M13: =IF($A13="","",IF(AND(D13>0,E13>0,D13<=E13*1.02),"是","否")) -> 是 | N13: =IFERROR(INDEX(账户总表!$O:$O,MATCH($A13,账户总表!$A:$A,0)),0) -> 0 | O13: =IFERROR(INDEX(账户总表!$B:$B,MATCH($A13,账户总表!$A:$A,0))*N13,0) -> 0 | P13: =IFERROR(O13/D13,0) -> 0 | Q13: =IFERROR(FLOOR(P13,100),0) -> 0 | R13: =IFERROR(CEILING(800/(100*D13),1)*100,0) -> 100 | T13: =IFERROR(S13*D13,0) -> 0 | U13: =IFERROR(T13/INDEX(账户总表!$B:$B,MATCH($A13,账户总表!$A:$A,0)),0) -> 0 | V13: =IFERROR(INDEX(账户总表!$E:$E,MATCH($A13,账户总表!$A:$A,0))+U13,0) -> 0 | W13: =IF($A13="","",IFERROR(IF(V13<=INDEX(账户总表!$N:$N,MATCH($A13,账户总表!$A:$A,0)),"是","否"),"否")) -> 否 | X13: =IF($A13="","",MAX(F13*0.98,D13*0.92)) -> 28.8512 | Z13: =IF($A13="","",IFERROR(IF(AND(T13>INDEX(账户总表!$C:$C,MATCH($A13,账户总表!$A:$A,0)),L13="是"),"是","否"),"否")) -> 否 | AA13: =IF($A13="","",IFERROR(IF(Z13="是",MAX(0,T13-INDEX(账户总表!$C:$C,MATCH($A13,账户总表!$A:$A,0)),IF(N13>0,T13/N13-INDEX(账户总表!$B:$B,MATCH($A13,账户总表!$A:$A,0)),0)),0),0)) -> 0 | AB13: =IF($A13="","",IF(AND(Z13="是",INDEX(账户总表!$U:$U,MATCH($A13,账户总表!$A:$A,0))="是"),IF(INDEX(账户总表!$L:$L,MATCH($A13,账户总表!$A:$A,0))>=4,AA13*1.5,AA13),0)) -> #N/A | AC13: =IF($A13="","",IF(AND(L13="是",Q13>=R13,S13<=Q13,S13>=R13,W13="是",X13>0,M13="是",INDEX(账户总表!$M:$M,MATCH($A13,账户总表!$A:$A,0))<=2,INDEX(账户总表!$V:$V,MATCH($A13,账户总表!$A:$A,0))="是",OR(T13<=INDEX(账户总表!$C:$C,MATCH($A13,账户总表!$A:$A,0)),AND(Z13="是",INDEX(账户总表!$U:$U,MATCH($A13,账户总表!$A:$A,0))="是",AB13>0))),"是","否")) -> #N/A | AD13: =IF($A13="","",IF(L13<>"是","信号未确认",IF(X13<=0,"止损价未定义",IF(Q13<R13,"100股约束不满足",IF(S13>Q13,"计划股数超单股上限",IF(S13<R13,"计划股数低于最小门槛",IF(W13<>"是","总仓位超限",IF(M13<>"是","追价",IF(INDEX(账户总表!$M:$M,MATCH($A13,账户总表!$A:$A,0))>2,"亏钱效应偏高",IF(INDEX(账户总表!$V:$V,MATCH($A13,账户总表!$A:$A,0))<>"是","账户不允许新开仓",IF(AND(T13>INDEX(账户总表!$C:$C,MATCH($A13,账户总表!$A:$A,0)),INDEX(账户总表!$U:$U,MATCH($A13,账户总表!$A:$A,0))<>"是"),"现金不足且不允许转入",IF(AND(Z13="是",AB13<=0),"转入金额未满足","")))))))))))) -> 信号未确认 | AE13: 接近确认,缺:DL_P=0.74
... A17: 46228 | B17: 山金国际 | C17: 000975 | D17: 21.8 | E17: 21.8 | F17: 20.71 | G17: 0.21990287 | H17: 0.76348679 | I17: True | J17: 一买 | K17: =IF($A17="","",IF(AND(G17<45%,H17>=0.9),"A",IF(AND(G17<60%,H17>0.8),"B","C"))) -> C | L17: =IF($A17="","",IF(AND(G17<60%,H17>0.8,I17="True"),"是","否")) -> 否 | M17: =IF($A17="","",IF(AND(D17>0,E17>0,D17<=E17*1.02),"是","否")) -> 是 | N17: =IFERROR(INDEX(账户总表!$O:$O,MATCH($A17,账户总表!$A:$A,0)),0) -> 0 | O17: =IFERROR(INDEX(账户总表!$B:$B,MATCH($A17,账户总表!$A:$A,0))*N17,0) -> 0 | P17: =IFERROR(O17/D17,0) -> 0 | Q17: =IFERROR(FLOOR(P17,100),0) -> 0 | R17: =IFERROR(CEILING(800/(100*D17),1)*100,0) -> 100 | T17: =IFERROR(S17*D17,0) -> 0 | U17: =IFERROR(T17/INDEX(账户总表!$B:$B,MATCH($A17,账户总表!$A:$A,0)),0) -> 0 | V17: =IFERROR(INDEX(账户总表!$E:$E,MATCH($A17,账户总表!$A:$A,0))+U17,0) -> 0 | W17: =IF($A17="","",IFERROR(IF(V17<=INDEX(账户总表!$N:$N,MATCH($A17,账户总表!$A:$A,0)),"是","否"),"否")) -> 否 | X17: =IF($A17="","",MAX(F17*0.98,D17*0.92)) -> 20.2958 | Z17: =IF($A17="","",IFERROR(IF(AND(T17>INDEX(账户总表!$C:$C,MATCH($A17,账户总表!$A:$A,0)),L17="是"),"是","否"),"否")) -> 否 | AA17: =IF($A17="","",IFERROR(IF(Z17="是",MAX(0,T17-INDEX(账户总表!$C:$C,MATCH($A17,账户总表!$A:$A,0)),IF(N17>0,T17/N17-INDEX(账户总表!$B:$B,MATCH($A17,账户总表!$A:$A,0)),0)),0),0)) -> 0 | AB17: =IF($A17="","",IF(AND(Z17="是",INDEX(账户总表!$U:$U,MATCH($A17,账户总表!$A:$A,0))="是"),IF(INDEX(账户总表!$L:$L,MATCH($A17,账户总表!$A:$A,0))>=4,AA17*1.5,AA17),0)) -> #N/A | AC17: =IF($A17="","",IF(AND(L17="是",Q17>=R17,S17<=Q17,S17>=R17,W17="是",X17>0,M17="是",INDEX(账户总表!$M:$M,MATCH($A17,账户总表!$A:$A,0))<=2,INDEX(账户总表!$V:$V,MATCH($A17,账户总表!$A:$A,0))="是",OR(T17<=INDEX(账户总表!$C:$C,MATCH($A17,账户总表!$A:$A,0)),AND(Z17="是",INDEX(账户总表!$U:$U,MATCH($A17,账户总表!$A:$A,0))="是",AB17>0))),"是","否")) -> #N/A | AD17: =IF($A17="","",IF(L17<>"是","信号未确认",IF(X17<=0,"止损价未定义",IF(Q17<R17,"100股约束不满足",IF(S17>Q17,"计划股数超单股上限",IF(S17<R17,"计划股数低于最小门槛",IF(W17<>"是","总仓位超限",IF(M17<>"是","追价",IF(INDEX(账户总表!$M:$M,MATCH($A17,账户总表!$A:$A,0))>2,"亏钱效应偏高",IF(INDEX(账户总表!$V:$V,MATCH($A17,账户总表!$A:$A,0))<>"是","账户不允许新开仓",IF(AND(T17>INDEX(账户总表!$C:$C,MATCH($A17,账户总表!$A:$A,0)),INDEX(账户总表!$U:$U,MATCH($A17,账户总表!$A:$A,0))<>"是"),"现金不足且不允许转入",IF(AND(Z17="是",AB17<=0),"转入金额未满足","")))))))))))) -> 信号未确认 | AE17: 接近确认,缺:DL_P=0.76
K18: =IF($A18="","",IF(AND(G18<45%,H18>=0.9),"A",IF(AND(G18<60%,H18>0.8),"B","C"))) | L18: =IF($A18="","",IF(AND(G18<60%,H18>0.8,I18="True"),"是","否")) | M18: =IF($A18="","",IF(AND(D18>0,E18>0,D18<=E18*1.02),"是","否")) | N18: =IFERROR(INDEX(账户总表!$O:$O,MATCH($A18,账户总表!$A:$A,0)),0) -> 0 | O18: =IFERROR(INDEX(账户总表!$B:$B,MATCH($A18,账户总表!$A:$A,0))*N18,0) -> 0 | P18: =IFERROR(O18/D18,0) -> 0 | Q18: =IFERROR(FLOOR(P18,100),0) -> 0 | R18: =IFERROR(CEILING(800/(100*D18),1)*100,0) -> 0 | T18: =IFERROR(S18*D18,0) -> 0 | U18: =IFERROR(T18/INDEX(账户总表!$B:$B,MATCH($A18,账户总表!$A:$A,0)),0) -> 0 | V18: =IFERROR(INDEX(账户总表!$E:$E,MATCH($A18,账户总表!$A:$A,0))+U18,0) -> 0 | W18: =IF($A18="","",IFERROR(IF(V18<=INDEX(账户总表!$N:$N,MATCH($A18,账户总表!$A:$A,0)),"是","否"),"否")) | X18: =IF($A18="","",MAX(F18*0.98,D18*0.92)) | Z18: =IF($A18="","",IFERROR(IF(AND(T18>INDEX(账户总表!$C:$C,MATCH($A18,账户总表!$A:$A,0)),L18="是"),"是","否"),"否")) | AA18: =IF($A18="","",IFERROR(IF(Z18="是",MAX(0,T18-INDEX(账户总表!$C:$C,MATCH($A18,账户总表!$A:$A,0)),IF(N18>0,T18/N18-INDEX(账户总表!$B:$B,MATCH($A18,账户总表!$A:$A,0)),0)),0),0)) | AB18: =IF($A18="","",IF(AND(Z18="是",INDEX(账户总表!$U:$U,MATCH($A18,账户总表!$A:$A,0))="是"),IF(INDEX(账户总表!$L:$L,MATCH($A18,账户总表!$A:$A,0))>=4,AA18*1.5,AA18),0)) | AC18: =IF($A18="","",IF(AND(L18="是",Q18>=R18,S18<=Q18,S18>=R18,W18="是",X18>0,M18="是",INDEX(账户总表!$M:$M,MATCH($A18,账户总表!$A:$A,0))<=2,INDEX(账户总表!$V:$V,MATCH($A18,账户总表!$A:$A,0))="是",OR(T18<=INDEX(账户总表!$C:$C,MATCH($A18,账户总表!$A:$A,0)),AND(Z18="是",INDEX(账户总表!$U:$U,MATCH($A18,账户总表!$A:$A,0))="是",AB18>0))),"是","否")) | AD18: =IF($A18="","",IF(L18<>"是","信号未确认",IF(X18<=0,"止损价未定义",IF(Q18<R18,"100股约束不满足",IF(S18>Q18,"计划股数超单股上限",IF(S18<R18,"计划股数低于最小门槛",IF(W18<>"是","总仓位超限",IF(M18<>"是","追价",IF(INDEX(账户总表!$M:$M,MATCH($A18,账户总表!$A:$A,0))>2,"亏钱效应偏高",IF(INDEX(账户总表!$V:$V,MATCH($A18,账户总表!$A:$A,0))<>"是","账户不允许新开仓",IF(AND(T18>INDEX(账户总表!$C:$C,MATCH($A18,账户总表!$A:$A,0)),INDEX(账户总表!$U:$U,MATCH($A18,账户总表!$A:$A,0))<>"是"),"现金不足且不允许转入",IF(AND(Z18="是",AB18<=0),"转入金额未满足",""))))))))))))
K19: =IF($A19="","",IF(AND(G19<45%,H19>=0.9),"A",IF(AND(G19<60%,H19>0.8),"B","C"))) | L19: =IF($A19="","",IF(AND(G19<60%,H19>0.8,I19="True"),"是","否")) | M19: =IF($A19="","",IF(AND(D19>0,E19>0,D19<=E19*1.02),"是","否")) | N19: =IFERROR(INDEX(账户总表!$O:$O,MATCH($A19,账户总表!$A:$A,0)),0) -> 0 | O19: =IFERROR(INDEX(账户总表!$B:$B,MATCH($A19,账户总表!$A:$A,0))*N19,0) -> 0 | P19: =IFERROR(O19/D19,0) -> 0 | Q19: =IFERROR(FLOOR(P19,100),0) -> 0 | R19: =IFERROR(CEILING(800/(100*D19),1)*100,0) -> 0 | T19: =IFERROR(S19*D19,0) -> 0 | U19: =IFERROR(T19/INDEX(账户总表!$B:$B,MATCH($A19,账户总表!$A:$A,0)),0) -> 0 | V19: =IFERROR(INDEX(账户总表!$E:$E,MATCH($A19,账户总表!$A:$A,0))+U19,0) -> 0 | W19: =IF($A19="","",IFERROR(IF(V19<=INDEX(账户总表!$N:$N,MATCH($A19,账户总表!$A:$A,0)),"是","否"),"否")) | X19: =IF($A19="","",MAX(F19*0.98,D19*0.92)) | Z19: =IF($A19="","",IFERROR(IF(AND(T19>INDEX(账户总表!$C:$C,MATCH($A19,账户总表!$A:$A,0)),L19="是"),"是","否"),"否")) | AA19: =IF($A19="","",IFERROR(IF(Z19="是",MAX(0,T19-INDEX(账户总表!$C:$C,MATCH($A19,账户总表!$A:$A,0)),IF(N19>0,T19/N19-INDEX(账户总表!$B:$B,MATCH($A19,账户总表!$A:$A,0)),0)),0),0)) | AB19: =IF($A19="","",IF(AND(Z19="是",INDEX(账户总表!$U:$U,MATCH($A19,账户总表!$A:$A,0))="是"),IF(INDEX(账户总表!$L:$L,MATCH($A19,账户总表!$A:$A,0))>=4,AA19*1.5,AA19),0)) | AC19: =IF($A19="","",IF(AND(L19="是",Q19>=R19,S19<=Q19,S19>=R19,W19="是",X19>0,M19="是",INDEX(账户总表!$M:$M,MATCH($A19,账户总表!$A:$A,0))<=2,INDEX(账户总表!$V:$V,MATCH($A19,账户总表!$A:$A,0))="是",OR(T19<=INDEX(账户总表!$C:$C,MATCH($A19,账户总表!$A:$A,0)),AND(Z19="是",INDEX(账户总表!$U:$U,MATCH($A19,账户总表!$A:$A,0))="是",AB19>0))),"是","否")) | AD19: =IF($A19="","",IF(L19<>"是","信号未确认",IF(X19<=0,"止损价未定义",IF(Q19<R19,"100股约束不满足",IF(S19>Q19,"计划股数超单股上限",IF(S19<R19,"计划股数低于最小门槛",IF(W19<>"是","总仓位超限",IF(M19<>"是","追价",IF(INDEX(账户总表!$M:$M,MATCH($A19,账户总表!$A:$A,0))>2,"亏钱效应偏高",IF(INDEX(账户总表!$V:$V,MATCH($A19,账户总表!$A:$A,0))<>"是","账户不允许新开仓",IF(AND(T19>INDEX(账户总表!$C:$C,MATCH($A19,账户总表!$A:$A,0)),INDEX(账户总表!$U:$U,MATCH($A19,账户总表!$A:$A,0))<>"是"),"现金不足且不允许转入",IF(AND(Z19="是",AB19<=0),"转入金额未满足",""))))))))))))
K20: =IF($A20="","",IF(AND(G20<45%,H20>=0.9),"A",IF(AND(G20<60%,H20>0.8),"B","C"))) | L20: =IF($A20="","",IF(AND(G20<60%,H20>0.8,I20="True"),"是","否")) | M20: =IF($A20="","",IF(AND(D20>0,E20>0,D20<=E20*1.02),"是","否")) | N20: =IFERROR(INDEX(账户总表!$O:$O,MATCH($A20,账户总表!$A:$A,0)),0) -> 0 | O20: =IFERROR(INDEX(账户总表!$B:$B,MATCH($A20,账户总表!$A:$A,0))*N20,0) -> 0 | P20: =IFERROR(O20/D20,0) -> 0 | Q20: =IFERROR(FLOOR(P20,100),0) -> 0 | R20: =IFERROR(CEILING(800/(100*D20),1)*100,0) -> 0 | T20: =IFERROR(S20*D20,0) -> 0 | U20: =IFERROR(T20/INDEX(账户总表!$B:$B,MATCH($A20,账户总表!$A:$A,0)),0) -> 0 | V20: =IFERROR(INDEX(账户总表!$E:$E,MATCH($A20,账户总表!$A:$A,0))+U20,0) -> 0 | W20: =IF($A20="","",IFERROR(IF(V20<=INDEX(账户总表!$N:$N,MATCH($A20,账户总表!$A:$A,0)),"是","否"),"否")) | X20: =IF($A20="","",MAX(F20*0.98,D20*0.92)) | Z20: =IF($A20="","",IFERROR(IF(AND(T20>INDEX(账户总表!$C:$C,MATCH($A20,账户总表!$A:$A,0)),L20="是"),"是","否"),"否")) | AA20: =IF($A20="","",IFERROR(IF(Z20="是",MAX(0,T20-INDEX(账户总表!$C:$C,MATCH($A20,账户总表!$A:$A,0)),IF(N20>0,T20/N20-INDEX(账户总表!$B:$B,MATCH($A20,账户总表!$A:$A,0)),0)),0),0)) | AB20: =IF($A20="","",IF(AND(Z20="是",INDEX(账户总表!$U:$U,MATCH($A20,账户总表!$A:$A,0))="是"),IF(INDEX(账户总表!$L:$L,MATCH($A20,账户总表!$A:$A,0))>=4,AA20*1.5,AA20),0)) | AC20: =IF($A20="","",IF(AND(L20="是",Q20>=R20,S20<=Q20,S20>=R20,W20="是",X20>0,M20="是",INDEX(账户总表!$M:$M,MATCH($A20,账户总表!$A:$A,0))<=2,INDEX(账户总表!$V:$V,MATCH($A20,账户总表!$A:$A,0))="是",OR(T20<=INDEX(账户总表!$C:$C,MATCH($A20,账户总表!$A:$A,0)),AND(Z20="是",INDEX(账户总表!$U:$U,MATCH($A20,账户总表!$A:$A,0))="是",AB20>0))),"是","否")) | AD20: =IF($A20="","",IF(L20<>"是","信号未确认",IF(X20<=0,"止损价未定义",IF(Q20<R20,"100股约束不满足",IF(S20>Q20,"计划股数超单股上限",IF(S20<R20,"计划股数低于最小门槛",IF(W20<>"是","总仓位超限",IF(M20<>"是","追价",IF(INDEX(账户总表!$M:$M,MATCH($A20,账户总表!$A:$A,0))>2,"亏钱效应偏高",IF(INDEX(账户总表!$V:$V,MATCH($A20,账户总表!$A:$A,0))<>"是","账户不允许新开仓",IF(AND(T20>INDEX(账户总表!$C:$C,MATCH($A20,账户总表!$A:$A,0)),INDEX(账户总表!$U:$U,MATCH($A20,账户总表!$A:$A,0))<>"是"),"现金不足且不允许转入",IF(AND(Z20="是",AB20<=0),"转入金额未满足",""))))))))))))
K21: =IF($A21="","",IF(AND(G21<45%,H21>=0.9),"A",IF(AND(G21<60%,H21>0.8),"B","C"))) | L21: =IF($A21="","",IF(AND(G21<60%,H21>0.8,I21="True"),"是","否")) | M21: =IF($A21="","",IF(AND(D21>0,E21>0,D21<=E21*1.02),"是","否")) | N21: =IFERROR(INDEX(账户总表!$O:$O,MATCH($A21,账户总表!$A:$A,0)),0) -> 0 | O21: =IFERROR(INDEX(账户总表!$B:$B,MATCH($A21,账户总表!$A:$A,0))*N21,0) -> 0 | P21: =IFERROR(O21/D21,0) -> 0 | Q21: =IFERROR(FLOOR(P21,100),0) -> 0 | R21: =IFERROR(CEILING(800/(100*D21),1)*100,0) -> 0 | T21: =IFERROR(S21*D21,0) -> 0 | U21: =IFERROR(T21/INDEX(账户总表!$B:$B,MATCH($A21,账户总表!$A:$A,0)),0) -> 0 | V21: =IFERROR(INDEX(账户总表!$E:$E,MATCH($A21,账户总表!$A:$A,0))+U21,0) -> 0 | W21: =IF($A21="","",IFERROR(IF(V21<=INDEX(账户总表!$N:$N,MATCH($A21,账户总表!$A:$A,0)),"是","否"),"否")) | X21: =IF($A21="","",MAX(F21*0.98,D21*0.92)) | Z21: =IF($A21="","",IFERROR(IF(AND(T21>INDEX(账户总表!$C:$C,MATCH($A21,账户总表!$A:$A,0)),L21="是"),"是","否"),"否")) | AA21: =IF($A21="","",IFERROR(IF(Z21="是",MAX(0,T21-INDEX(账户总表!$C:$C,MATCH($A21,账户总表!$A:$A,0)),IF(N21>0,T21/N21-INDEX(账户总表!$B:$B,MATCH($A21,账户总表!$A:$A,0)),0)),0),0)) | AB21: =IF($A21="","",IF(AND(Z21="是",INDEX(账户总表!$U:$U,MATCH($A21,账户总表!$A:$A,0))="是"),IF(INDEX(账户总表!$L:$L,MATCH($A21,账户总表!$A:$A,0))>=4,AA21*1.5,AA21),0)) | AC21: =IF($A21="","",IF(AND(L21="是",Q21>=R21,S21<=Q21,S21>=R21,W21="是",X21>0,M21="是",INDEX(账户总表!$M:$M,MATCH($A21,账户总表!$A:$A,0))<=2,INDEX(账户总表!$V:$V,MATCH($A21,账户总表!$A:$A,0))="是",OR(T21<=INDEX(账户总表!$C:$C,MATCH($A21,账户总表!$A:$A,0)),AND(Z21="是",INDEX(账户总表!$U:$U,MATCH($A21,账户总表!$A:$A,0))="是",AB21>0))),"是","否")) | AD21: =IF($A21="","",IF(L21<>"是","信号未确认",IF(X21<=0,"止损价未定义",IF(Q21<R21,"100股约束不满足",IF(S21>Q21,"计划股数超单股上限",IF(S21<R21,"计划股数低于最小门槛",IF(W21<>"是","总仓位超限",IF(M21<>"是","追价",IF(INDEX(账户总表!$M:$M,MATCH($A21,账户总表!$A:$A,0))>2,"亏钱效应偏高",IF(INDEX(账户总表!$V:$V,MATCH($A21,账户总表!$A:$A,0))<>"是","账户不允许新开仓",IF(AND(T21>INDEX(账户总表!$C:$C,MATCH($A21,账户总表!$A:$A,0)),INDEX(账户总表!$U:$U,MATCH($A21,账户总表!$A:$A,0))<>"是"),"现金不足且不允许转入",IF(AND(Z21="是",AB21<=0),"转入金额未满足",""))))))))))))
K22: =IF($A22="","",IF(AND(G22<45%,H22>=0.9),"A",IF(AND(G22<60%,H22>0.8),"B","C"))) | L22: =IF($A22="","",IF(AND(G22<60%,H22>0.8,I22="True"),"是","否")) | M22: =IF($A22="","",IF(AND(D22>0,E22>0,D22<=E22*1.02),"是","否")) | N22: =IFERROR(INDEX(账户总表!$O:$O,MATCH($A22,账户总表!$A:$A,0)),0) -> 0 | O22: =IFERROR(INDEX(账户总表!$B:$B,MATCH($A22,账户总表!$A:$A,0))*N22,0) -> 0 | P22: =IFERROR(O22/D22,0) -> 0 | Q22: =IFERROR(FLOOR(P22,100),0) -> 0 | R22: =IFERROR(CEILING(800/(100*D22),1)*100,0) -> 0 | T22: =IFERROR(S22*D22,0) -> 0 | U22: =IFERROR(T22/INDEX(账户总表!$B:$B,MATCH($A22,账户总表!$A:$A,0)),0) -> 0 | V22: =IFERROR(INDEX(账户总表!$E:$E,MATCH($A22,账户总表!$A:$A,0))+U22,0) -> 0 | W22: =IF($A22="","",IFERROR(IF(V22<=INDEX(账户总表!$N:$N,MATCH($A22,账户总表!$A:$A,0)),"是","否"),"否")) | X22: =IF($A22="","",MAX(F22*0.98,D22*0.92)) | Z22: =IF($A22="","",IFERROR(IF(AND(T22>INDEX(账户总表!$C:$C,MATCH($A22,账户总表!$A:$A,0)),L22="是"),"是","否"),"否")) | AA22: =IF($A22="","",IFERROR(IF(Z22="是",MAX(0,T22-INDEX(账户总表!$C:$C,MATCH($A22,账户总表!$A:$A,0)),IF(N22>0,T22/N22-INDEX(账户总表!$B:$B,MATCH($A22,账户总表!$A:$A,0)),0)),0),0)) | AB22: =IF($A22="","",IF(AND(Z22="是",INDEX(账户总表!$U:$U,MATCH($A22,账户总表!$A:$A,0))="是"),IF(INDEX(账户总表!$L:$L,MATCH($A22,账户总表!$A:$A,0))>=4,AA22*1.5,AA22),0)) | AC22: =IF($A22="","",IF(AND(L22="是",Q22>=R22,S22<=Q22,S22>=R22,W22="是",X22>0,M22="是",INDEX(账户总表!$M:$M,MATCH($A22,账户总表!$A:$A,0))<=2,INDEX(账户总表!$V:$V,MATCH($A22,账户总表!$A:$A,0))="是",OR(T22<=INDEX(账户总表!$C:$C,MATCH($A22,账户总表!$A:$A,0)),AND(Z22="是",INDEX(账户总表!$U:$U,MATCH($A22,账户总表!$A:$A,0))="是",AB22>0))),"是","否")) | AD22: =IF($A22="","",IF(L22<>"是","信号未确认",IF(X22<=0,"止损价未定义",IF(Q22<R22,"100股约束不满足",IF(S22>Q22,"计划股数超单股上限",IF(S22<R22,"计划股数低于最小门槛",IF(W22<>"是","总仓位超限",IF(M22<>"是","追价",IF(INDEX(账户总表!$M:$M,MATCH($A22,账户总表!$A:$A,0))>2,"亏钱效应偏高",IF(INDEX(账户总表!$V:$V,MATCH($A22,账户总表!$A:$A,0))<>"是","账户不允许新开仓",IF(AND(T22>INDEX(账户总表!$C:$C,MATCH($A22,账户总表!$A:$A,0)),INDEX(账户总表!$U:$U,MATCH($A22,账户总表!$A:$A,0))<>"是"),"现金不足且不允许转入",IF(AND(Z22="是",AB22<=0),"转入金额未满足",""))))))))))))
K23: =IF($A23="","",IF(AND(G23<45%,H23>=0.9),"A",IF(AND(G23<60%,H23>0.8),"B","C"))) | L23: =IF($A23="","",IF(AND(G23<60%,H23>0.8,I23="True"),"是","否")) | M23: =IF($A23="","",IF(AND(D23>0,E23>0,D23<=E23*1.02),"是","否")) | N23: =IFERROR(INDEX(账户总表!$O:$O,MATCH($A23,账户总表!$A:$A,0)),0) -> 0 | O23: =IFERROR(INDEX(账户总表!$B:$B,MATCH($A23,账户总表!$A:$A,0))*N23,0) -> 0 | P23: =IFERROR(O23/D23,0) -> 0 | Q23: =IFERROR(FLOOR(P23,100),0) -> 0 | R23: =IFERROR(CEILING(800/(100*D23),1)*100,0) -> 0 | T23: =IFERROR(S23*D23,0) -> 0 | U23: =IFERROR(T23/INDEX(账户总表!$B:$B,MATCH($A23,账户总表!$A:$A,0)),0) -> 0 | V23: =IFERROR(INDEX(账户总表!$E:$E,MATCH($A23,账户总表!$A:$A,0))+U23,0) -> 0 | W23: =IF($A23="","",IFERROR(IF(V23<=INDEX(账户总表!$N:$N,MATCH($A23,账户总表!$A:$A,0)),"是","否"),"否")) | X23: =IF($A23="","",MAX(F23*0.98,D23*0.92)) | Z23: =IF($A23="","",IFERROR(IF(AND(T23>INDEX(账户总表!$C:$C,MATCH($A23,账户总表!$A:$A,0)),L23="是"),"是","否"),"否")) | AA23: =IF($A23="","",IFERROR(IF(Z23="是",MAX(0,T23-INDEX(账户总表!$C:$C,MATCH($A23,账户总表!$A:$A,0)),IF(N23>0,T23/N23-INDEX(账户总表!$B:$B,MATCH($A23,账户总表!$A:$A,0)),0)),0),0)) | AB23: =IF($A23="","",IF(AND(Z23="是",INDEX(账户总表!$U:$U,MATCH($A23,账户总表!$A:$A,0))="是"),IF(INDEX(账户总表!$L:$L,MATCH($A23,账户总表!$A:$A,0))>=4,AA23*1.5,AA23),0)) | AC23: =IF($A23="","",IF(AND(L23="是",Q23>=R23,S23<=Q23,S23>=R23,W23="是",X23>0,M23="是",INDEX(账户总表!$M:$M,MATCH($A23,账户总表!$A:$A,0))<=2,INDEX(账户总表!$V:$V,MATCH($A23,账户总表!$A:$A,0))="是",OR(T23<=INDEX(账户总表!$C:$C,MATCH($A23,账户总表!$A:$A,0)),AND(Z23="是",INDEX(账户总表!$U:$U,MATCH($A23,账户总表!$A:$A,0))="是",AB23>0))),"是","否")) | AD23: =IF($A23="","",IF(L23<>"是","信号未确认",IF(X23<=0,"止损价未定义",IF(Q23<R23,"100股约束不满足",IF(S23>Q23,"计划股数超单股上限",IF(S23<R23,"计划股数低于最小门槛",IF(W23<>"是","总仓位超限",IF(M23<>"是","追价",IF(INDEX(账户总表!$M:$M,MATCH($A23,账户总表!$A:$A,0))>2,"亏钱效应偏高",IF(INDEX(账户总表!$V:$V,MATCH($A23,账户总表!$A:$A,0))<>"是","账户不允许新开仓",IF(AND(T23>INDEX(账户总表!$C:$C,MATCH($A23,账户总表!$A:$A,0)),INDEX(账户总表!$U:$U,MATCH($A23,账户总表!$A:$A,0))<>"是"),"现金不足且不允许转入",IF(AND(Z23="是",AB23<=0),"转入金额未满足",""))))))))))))
K24: =IF($A24="","",IF(AND(G24<45%,H24>=0.9),"A",IF(AND(G24<60%,H24>0.8),"B","C"))) | L24: =IF($A24="","",IF(AND(G24<60%,H24>0.8,I24="True"),"是","否")) | M24: =IF($A24="","",IF(AND(D24>0,E24>0,D24<=E24*1.02),"是","否")) | N24: =IFERROR(INDEX(账户总表!$O:$O,MATCH($A24,账户总表!$A:$A,0)),0) -> 0 | O24: =IFERROR(INDEX(账户总表!$B:$B,MATCH($A24,账户总表!$A:$A,0))*N24,0) -> 0 | P24: =IFERROR(O24/D24,0) -> 0 | Q24: =IFERROR(FLOOR(P24,100),0) -> 0 | R24: =IFERROR(CEILING(800/(100*D24),1)*100,0) -> 0 | T24: =IFERROR(S24*D24,0) -> 0 | U24: =IFERROR(T24/INDEX(账户总表!$B:$B,MATCH($A24,账户总表!$A:$A,0)),0) -> 0 | V24: =IFERROR(INDEX(账户总表!$E:$E,MATCH($A24,账户总表!$A:$A,0))+U24,0) -> 0 | W24: =IF($A24="","",IFERROR(IF(V24<=INDEX(账户总表!$N:$N,MATCH($A24,账户总表!$A:$A,0)),"是","否"),"否")) | X24: =IF($A24="","",MAX(F24*0.98,D24*0.92)) | Z24: =IF($A24="","",IFERROR(IF(AND(T24>INDEX(账户总表!$C:$C,MATCH($A24,账户总表!$A:$A,0)),L24="是"),"是","否"),"否")) | AA24: =IF($A24="","",IFERROR(IF(Z24="是",MAX(0,T24-INDEX(账户总表!$C:$C,MATCH($A24,账户总表!$A:$A,0)),IF(N24>0,T24/N24-INDEX(账户总表!$B:$B,MATCH($A24,账户总表!$A:$A,0)),0)),0),0)) | AB24: =IF($A24="","",IF(AND(Z24="是",INDEX(账户总表!$U:$U,MATCH($A24,账户总表!$A:$A,0))="是"),IF(INDEX(账户总表!$L:$L,MATCH($A24,账户总表!$A:$A,0))>=4,AA24*1.5,AA24),0)) | AC24: =IF($A24="","",IF(AND(L24="是",Q24>=R24,S24<=Q24,S24>=R24,W24="是",X24>0,M24="是",INDEX(账户总表!$M:$M,MATCH($A24,账户总表!$A:$A,0))<=2,INDEX(账户总表!$V:$V,MATCH($A24,账户总表!$A:$A,0))="是",OR(T24<=INDEX(账户总表!$C:$C,MATCH($A24,账户总表!$A:$A,0)),AND(Z24="是",INDEX(账户总表!$U:$U,MATCH($A24,账户总表!$A:$A,0))="是",AB24>0))),"是","否")) | AD24: =IF($A24="","",IF(L24<>"是","信号未确认",IF(X24<=0,"止损价未定义",IF(Q24<R24,"100股约束不满足",IF(S24>Q24,"计划股数超单股上限",IF(S24<R24,"计划股数低于最小门槛",IF(W24<>"是","总仓位超限",IF(M24<>"是","追价",IF(INDEX(账户总表!$M:$M,MATCH($A24,账户总表!$A:$A,0))>2,"亏钱效应偏高",IF(INDEX(账户总表!$V:$V,MATCH($A24,账户总表!$A:$A,0))<>"是","账户不允许新开仓",IF(AND(T24>INDEX(账户总表!$C:$C,MATCH($A24,账户总表!$A:$A,0)),INDEX(账户总表!$U:$U,MATCH($A24,账户总表!$A:$A,0))<>"是"),"现金不足且不允许转入",IF(AND(Z24="是",AB24<=0),"转入金额未满足",""))))))))))))
K25: =IF($A25="","",IF(AND(G25<45%,H25>=0.9),"A",IF(AND(G25<60%,H25>0.8),"B","C"))) | L25: =IF($A25="","",IF(AND(G25<60%,H25>0.8,I25="True"),"是","否")) | M25: =IF($A25="","",IF(AND(D25>0,E25>0,D25<=E25*1.02),"是","否")) | N25: =IFERROR(INDEX(账户总表!$O:$O,MATCH($A25,账户总表!$A:$A,0)),0) -> 0 | O25: =IFERROR(INDEX(账户总表!$B:$B,MATCH($A25,账户总表!$A:$A,0))*N25,0) -> 0 | P25: =IFERROR(O25/D25,0) -> 0 | Q25: =IFERROR(FLOOR(P25,100),0) -> 0 | R25: =IFERROR(CEILING(800/(100*D25),1)*100,0) -> 0 | T25: =IFERROR(S25*D25,0) -> 0 | U25: =IFERROR(T25/INDEX(账户总表!$B:$B,MATCH($A25,账户总表!$A:$A,0)),0) -> 0 | V25: =IFERROR(INDEX(账户总表!$E:$E,MATCH($A25,账户总表!$A:$A,0))+U25,0) -> 0 | W25: =IF($A25="","",IFERROR(IF(V25<=INDEX(账户总表!$N:$N,MATCH($A25,账户总表!$A:$A,0)),"是","否"),"否")) | X25: =IF($A25="","",MAX(F25*0.98,D25*0.92)) | Z25: =IF($A25="","",IFERROR(IF(AND(T25>INDEX(账户总表!$C:$C,MATCH($A25,账户总表!$A:$A,0)),L25="是"),"是","否"),"否")) | AA25: =IF($A25="","",IFERROR(IF(Z25="是",MAX(0,T25-INDEX(账户总表!$C:$C,MATCH($A25,账户总表!$A:$A,0)),IF(N25>0,T25/N25-INDEX(账户总表!$B:$B,MATCH($A25,账户总表!$A:$A,0)),0)),0),0)) | AB25: =IF($A25="","",IF(AND(Z25="是",INDEX(账户总表!$U:$U,MATCH($A25,账户总表!$A:$A,0))="是"),IF(INDEX(账户总表!$L:$L,MATCH($A25,账户总表!$A:$A,0))>=4,AA25*1.5,AA25),0)) | AC25: =IF($A25="","",IF(AND(L25="是",Q25>=R25,S25<=Q25,S25>=R25,W25="是",X25>0,M25="是",INDEX(账户总表!$M:$M,MATCH($A25,账户总表!$A:$A,0))<=2,INDEX(账户总表!$V:$V,MATCH($A25,账户总表!$A:$A,0))="是",OR(T25<=INDEX(账户总表!$C:$C,MATCH($A25,账户总表!$A:$A,0)),AND(Z25="是",INDEX(账户总表!$U:$U,MATCH($A25,账户总表!$A:$A,0))="是",AB25>0))),"是","否")) | AD25: =IF($A25="","",IF(L25<>"是","信号未确认",IF(X25<=0,"止损价未定义",IF(Q25<R25,"100股约束不满足",IF(S25>Q25,"计划股数超单股上限",IF(S25<R25,"计划股数低于最小门槛",IF(W25<>"是","总仓位超限",IF(M25<>"是","追价",IF(INDEX(账户总表!$M:$M,MATCH($A25,账户总表!$A:$A,0))>2,"亏钱效应偏高",IF(INDEX(账户总表!$V:$V,MATCH($A25,账户总表!$A:$A,0))<>"是","账户不允许新开仓",IF(AND(T25>INDEX(账户总表!$C:$C,MATCH($A25,账户总表!$A:$A,0)),INDEX(账户总表!$U:$U,MATCH($A25,账户总表!$A:$A,0))<>"是"),"现金不足且不允许转入",IF(AND(Z25="是",AB25<=0),"转入金额未满足",""))))))))))))
K26: =IF($A26="","",IF(AND(G26<45%,H26>=0.9),"A",IF(AND(G26<60%,H26>0.8),"B","C"))) | L26: =IF($A26="","",IF(AND(G26<60%,H26>0.8,I26="True"),"是","否")) | M26: =IF($A26="","",IF(AND(D26>0,E26>0,D26<=E26*1.02),"是","否")) | N26: =IFERROR(INDEX(账户总表!$O:$O,MATCH($A26,账户总表!$A:$A,0)),0) -> 0 | O26: =IFERROR(INDEX(账户总表!$B:$B,MATCH($A26,账户总表!$A:$A,0))*N26,0) -> 0 | P26: =IFERROR(O26/D26,0) -> 0 | Q26: =IFERROR(FLOOR(P26,100),0) -> 0 | R26: =IFERROR(CEILING(800/(100*D26),1)*100,0) -> 0 | T26: =IFERROR(S26*D26,0) -> 0 | U26: =IFERROR(T26/INDEX(账户总表!$B:$B,MATCH($A26,账户总表!$A:$A,0)),0) -> 0 | V26: =IFERROR(INDEX(账户总表!$E:$E,MATCH($A26,账户总表!$A:$A,0))+U26,0) -> 0 | W26: =IF($A26="","",IFERROR(IF(V26<=INDEX(账户总表!$N:$N,MATCH($A26,账户总表!$A:$A,0)),"是","否"),"否")) | X26: =IF($A26="","",MAX(F26*0.98,D26*0.92)) | Z26: =IF($A26="","",IFERROR(IF(AND(T26>INDEX(账户总表!$C:$C,MATCH($A26,账户总表!$A:$A,0)),L26="是"),"是","否"),"否")) | AA26: =IF($A26="","",IFERROR(IF(Z26="是",MAX(0,T26-INDEX(账户总表!$C:$C,MATCH($A26,账户总表!$A:$A,0)),IF(N26>0,T26/N26-INDEX(账户总表!$B:$B,MATCH($A26,账户总表!$A:$A,0)),0)),0),0)) | AB26: =IF($A26="","",IF(AND(Z26="是",INDEX(账户总表!$U:$U,MATCH($A26,账户总表!$A:$A,0))="是"),IF(INDEX(账户总表!$L:$L,MATCH($A26,账户总表!$A:$A,0))>=4,AA26*1.5,AA26),0)) | AC26: =IF($A26="","",IF(AND(L26="是",Q26>=R26,S26<=Q26,S26>=R26,W26="是",X26>0,M26="是",INDEX(账户总表!$M:$M,MATCH($A26,账户总表!$A:$A,0))<=2,INDEX(账户总表!$V:$V,MATCH($A26,账户总表!$A:$A,0))="是",OR(T26<=INDEX(账户总表!$C:$C,MATCH($A26,账户总表!$A:$A,0)),AND(Z26="是",INDEX(账户总表!$U:$U,MATCH($A26,账户总表!$A:$A,0))="是",AB26>0))),"是","否")) | AD26: =IF($A26="","",IF(L26<>"是","信号未确认",IF(X26<=0,"止损价未定义",IF(Q26<R26,"100股约束不满足",IF(S26>Q26,"计划股数超单股上限",IF(S26<R26,"计划股数低于最小门槛",IF(W26<>"是","总仓位超限",IF(M26<>"是","追价",IF(INDEX(账户总表!$M:$M,MATCH($A26,账户总表!$A:$A,0))>2,"亏钱效应偏高",IF(INDEX(账户总表!$V:$V,MATCH($A26,账户总表!$A:$A,0))<>"是","账户不允许新开仓",IF(AND(T26>INDEX(账户总表!$C:$C,MATCH($A26,账户总表!$A:$A,0)),INDEX(账户总表!$U:$U,MATCH($A26,账户总表!$A:$A,0))<>"是"),"现金不足且不允许转入",IF(AND(Z26="是",AB26<=0),"转入金额未满足",""))))))))))))
K27: =IF($A27="","",IF(AND(G27<45%,H27>=0.9),"A",IF(AND(G27<60%,H27>0.8),"B","C"))) | L27: =IF($A27="","",IF(AND(G27<60%,H27>0.8,I27="True"),"是","否")) | M27: =IF($A27="","",IF(AND(D27>0,E27>0,D27<=E27*1.02),"是","否")) | N27: =IFERROR(INDEX(账户总表!$O:$O,MATCH($A27,账户总表!$A:$A,0)),0) -> 0 | O27: =IFERROR(INDEX(账户总表!$B:$B,MATCH($A27,账户总表!$A:$A,0))*N27,0) -> 0 | P27: =IFERROR(O27/D27,0) -> 0 | Q27: =IFERROR(FLOOR(P27,100),0) -> 0 | R27: =IFERROR(CEILING(800/(100*D27),1)*100,0) -> 0 | T27: =IFERROR(S27*D27,0) -> 0 | U27: =IFERROR(T27/INDEX(账户总表!$B:$B,MATCH($A27,账户总表!$A:$A,0)),0) -> 0 | V27: =IFERROR(INDEX(账户总表!$E:$E,MATCH($A27,账户总表!$A:$A,0))+U27,0) -> 0 | W27: =IF($A27="","",IFERROR(IF(V27<=INDEX(账户总表!$N:$N,MATCH($A27,账户总表!$A:$A,0)),"是","否"),"否")) | X27: =IF($A27="","",MAX(F27*0.98,D27*0.92)) | Z27: =IF($A27="","",IFERROR(IF(AND(T27>INDEX(账户总表!$C:$C,MATCH($A27,账户总表!$A:$A,0)),L27="是"),"是","否"),"否")) | AA27: =IF($A27="","",IFERROR(IF(Z27="是",MAX(0,T27-INDEX(账户总表!$C:$C,MATCH($A27,账户总表!$A:$A,0)),IF(N27>0,T27/N27-INDEX(账户总表!$B:$B,MATCH($A27,账户总表!$A:$A,0)),0)),0),0)) | AB27: =IF($A27="","",IF(AND(Z27="是",INDEX(账户总表!$U:$U,MATCH($A27,账户总表!$A:$A,0))="是"),IF(INDEX(账户总表!$L:$L,MATCH($A27,账户总表!$A:$A,0))>=4,AA27*1.5,AA27),0)) | AC27: =IF($A27="","",IF(AND(L27="是",Q27>=R27,S27<=Q27,S27>=R27,W27="是",X27>0,M27="是",INDEX(账户总表!$M:$M,MATCH($A27,账户总表!$A:$A,0))<=2,INDEX(账户总表!$V:$V,MATCH($A27,账户总表!$A:$A,0))="是",OR(T27<=INDEX(账户总表!$C:$C,MATCH($A27,账户总表!$A:$A,0)),AND(Z27="是",INDEX(账户总表!$U:$U,MATCH($A27,账户总表!$A:$A,0))="是",AB27>0))),"是","否")) | AD27: =IF($A27="","",IF(L27<>"是","信号未确认",IF(X27<=0,"止损价未定义",IF(Q27<R27,"100股约束不满足",IF(S27>Q27,"计划股数超单股上限",IF(S27<R27,"计划股数低于最小门槛",IF(W27<>"是","总仓位超限",IF(M27<>"是","追价",IF(INDEX(账户总表!$M:$M,MATCH($A27,账户总表!$A:$A,0))>2,"亏钱效应偏高",IF(INDEX(账户总表!$V:$V,MATCH($A27,账户总表!$A:$A,0))<>"是","账户不允许新开仓",IF(AND(T27>INDEX(账户总表!$C:$C,MATCH($A27,账户总表!$A:$A,0)),INDEX(账户总表!$U:$U,MATCH($A27,账户总表!$A:$A,0))<>"是"),"现金不足且不允许转入",IF(AND(Z27="是",AB27<=0),"转入金额未满足",""))))))))))))
K28: =IF($A28="","",IF(AND(G28<45%,H28>=0.9),"A",IF(AND(G28<60%,H28>0.8),"B","C"))) | L28: =IF($A28="","",IF(AND(G28<60%,H28>0.8,I28="True"),"是","否")) | M28: =IF($A28="","",IF(AND(D28>0,E28>0,D28<=E28*1.02),"是","否")) | N28: =IFERROR(INDEX(账户总表!$O:$O,MATCH($A28,账户总表!$A:$A,0)),0) -> 0 | O28: =IFERROR(INDEX(账户总表!$B:$B,MATCH($A28,账户总表!$A:$A,0))*N28,0) -> 0 | P28: =IFERROR(O28/D28,0) -> 0 | Q28: =IFERROR(FLOOR(P28,100),0) -> 0 | R28: =IFERROR(CEILING(800/(100*D28),1)*100,0) -> 0 | T28: =IFERROR(S28*D28,0) -> 0 | U28: =IFERROR(T28/INDEX(账户总表!$B:$B,MATCH($A28,账户总表!$A:$A,0)),0) -> 0 | V28: =IFERROR(INDEX(账户总表!$E:$E,MATCH($A28,账户总表!$A:$A,0))+U28,0) -> 0 | W28: =IF($A28="","",IFERROR(IF(V28<=INDEX(账户总表!$N:$N,MATCH($A28,账户总表!$A:$A,0)),"是","否"),"否")) | X28: =IF($A28="","",MAX(F28*0.98,D28*0.92)) | Z28: =IF($A28="","",IFERROR(IF(AND(T28>INDEX(账户总表!$C:$C,MATCH($A28,账户总表!$A:$A,0)),L28="是"),"是","否"),"否")) | AA28: =IF($A28="","",IFERROR(IF(Z28="是",MAX(0,T28-INDEX(账户总表!$C:$C,MATCH($A28,账户总表!$A:$A,0)),IF(N28>0,T28/N28-INDEX(账户总表!$B:$B,MATCH($A28,账户总表!$A:$A,0)),0)),0),0)) | AB28: =IF($A28="","",IF(AND(Z28="是",INDEX(账户总表!$U:$U,MATCH($A28,账户总表!$A:$A,0))="是"),IF(INDEX(账户总表!$L:$L,MATCH($A28,账户总表!$A:$A,0))>=4,AA28*1.5,AA28),0)) | AC28: =IF($A28="","",IF(AND(L28="是",Q28>=R28,S28<=Q28,S28>=R28,W28="是",X28>0,M28="是",INDEX(账户总表!$M:$M,MATCH($A28,账户总表!$A:$A,0))<=2,INDEX(账户总表!$V:$V,MATCH($A28,账户总表!$A:$A,0))="是",OR(T28<=INDEX(账户总表!$C:$C,MATCH($A28,账户总表!$A:$A,0)),AND(Z28="是",INDEX(账户总表!$U:$U,MATCH($A28,账户总表!$A:$A,0))="是",AB28>0))),"是","否")) | AD28: =IF($A28="","",IF(L28<>"是","信号未确认",IF(X28<=0,"止损价未定义",IF(Q28<R28,"100股约束不满足",IF(S28>Q28,"计划股数超单股上限",IF(S28<R28,"计划股数低于最小门槛",IF(W28<>"是","总仓位超限",IF(M28<>"是","追价",IF(INDEX(账户总表!$M:$M,MATCH($A28,账户总表!$A:$A,0))>2,"亏钱效应偏高",IF(INDEX(账户总表!$V:$V,MATCH($A28,账户总表!$A:$A,0))<>"是","账户不允许新开仓",IF(AND(T28>INDEX(账户总表!$C:$C,MATCH($A28,账户总表!$A:$A,0)),INDEX(账户总表!$U:$U,MATCH($A28,账户总表!$A:$A,0))<>"是"),"现金不足且不允许转入",IF(AND(Z28="是",AB28<=0),"转入金额未满足",""))))))))))))
K29: =IF($A29="","",IF(AND(G29<45%,H29>=0.9),"A",IF(AND(G29<60%,H29>0.8),"B","C"))) | L29: =IF($A29="","",IF(AND(G29<60%,H29>0.8,I29="True"),"是","否")) | M29: =IF($A29="","",IF(AND(D29>0,E29>0,D29<=E29*1.02),"是","否")) | N29: =IFERROR(INDEX(账户总表!$O:$O,MATCH($A29,账户总表!$A:$A,0)),0) -> 0 | O29: =IFERROR(INDEX(账户总表!$B:$B,MATCH($A29,账户总表!$A:$A,0))*N29,0) -> 0 | P29: =IFERROR(O29/D29,0) -> 0 | Q29: =IFERROR(FLOOR(P29,100),0) -> 0 | R29: =IFERROR(CEILING(800/(100*D29),1)*100,0) -> 0 | T29: =IFERROR(S29*D29,0) -> 0 | U29: =IFERROR(T29/INDEX(账户总表!$B:$B,MATCH($A29,账户总表!$A:$A,0)),0) -> 0 | V29: =IFERROR(INDEX(账户总表!$E:$E,MATCH($A29,账户总表!$A:$A,0))+U29,0) -> 0 | W29: =IF($A29="","",IFERROR(IF(V29<=INDEX(账户总表!$N:$N,MATCH($A29,账户总表!$A:$A,0)),"是","否"),"否")) | X29: =IF($A29="","",MAX(F29*0.98,D29*0.92)) | Z29: =IF($A29="","",IFERROR(IF(AND(T29>INDEX(账户总表!$C:$C,MATCH($A29,账户总表!$A:$A,0)),L29="是"),"是","否"),"否")) | AA29: =IF($A29="","",IFERROR(IF(Z29="是",MAX(0,T29-INDEX(账户总表!$C:$C,MATCH($A29,账户总表!$A:$A,0)),IF(N29>0,T29/N29-INDEX(账户总表!$B:$B,MATCH($A29,账户总表!$A:$A,0)),0)),0),0)) | AB29: =IF($A29="","",IF(AND(Z29="是",INDEX(账户总表!$U:$U,MATCH($A29,账户总表!$A:$A,0))="是"),IF(INDEX(账户总表!$L:$L,MATCH($A29,账户总表!$A:$A,0))>=4,AA29*1.5,AA29),0)) | AC29: =IF($A29="","",IF(AND(L29="是",Q29>=R29,S29<=Q29,S29>=R29,W29="是",X29>0,M29="是",INDEX(账户总表!$M:$M,MATCH($A29,账户总表!$A:$A,0))<=2,INDEX(账户总表!$V:$V,MATCH($A29,账户总表!$A:$A,0))="是",OR(T29<=INDEX(账户总表!$C:$C,MATCH($A29,账户总表!$A:$A,0)),AND(Z29="是",INDEX(账户总表!$U:$U,MATCH($A29,账户总表!$A:$A,0))="是",AB29>0))),"是","否")) | AD29: =IF($A29="","",IF(L29<>"是","信号未确认",IF(X29<=0,"止损价未定义",IF(Q29<R29,"100股约束不满足",IF(S29>Q29,"计划股数超单股上限",IF(S29<R29,"计划股数低于最小门槛",IF(W29<>"是","总仓位超限",IF(M29<>"是","追价",IF(INDEX(账户总表!$M:$M,MATCH($A29,账户总表!$A:$A,0))>2,"亏钱效应偏高",IF(INDEX(账户总表!$V:$V,MATCH($A29,账户总表!$A:$A,0))<>"是","账户不允许新开仓",IF(AND(T29>INDEX(账户总表!$C:$C,MATCH($A29,账户总表!$A:$A,0)),INDEX(账户总表!$U:$U,MATCH($A29,账户总表!$A:$A,0))<>"是"),"现金不足且不允许转入",IF(AND(Z29="是",AB29<=0),"转入金额未满足",""))))))))))))
... K201: =IF($A201="","",IF(AND(G201<45%,H201>=0.9),"A",IF(AND(G201<60%,H201>0.8),"B","C"))) | L201: =IF($A201="","",IF(AND(G201<60%,H201>0.8,I201="True"),"是","否")) | M201: =IF($A201="","",IF(AND(D201>0,E201>0,D201<=E201*1.02),"是","否")) | N201: =IFERROR(INDEX(账户总表!$O:$O,MATCH($A201,账户总表!$A:$A,0)),0) -> 0 | O201: =IFERROR(INDEX(账户总表!$B:$B,MATCH($A201,账户总表!$A:$A,0))*N201,0) -> 0 | P201: =IFERROR(O201/D201,0) -> 0 | Q201: =IFERROR(FLOOR(P201,100),0) -> 0 | R201: =IFERROR(CEILING(800/(100*D201),1)*100,0) -> 0 | T201: =IFERROR(S201*D201,0) -> 0 | U201: =IFERROR(T201/INDEX(账户总表!$B:$B,MATCH($A201,账户总表!$A:$A,0)),0) -> 0 | V201: =IFERROR(INDEX(账户总表!$E:$E,MATCH($A201,账户总表!$A:$A,0))+U201,0) -> 0 | W201: =IF($A201="","",IFERROR(IF(V201<=INDEX(账户总表!$N:$N,MATCH($A201,账户总表!$A:$A,0)),"是","否"),"否")) | X201: =IF($A201="","",MAX(F201*0.98,D201*0.92)) | Z201: =IF($A201="","",IFERROR(IF(AND(T201>INDEX(账户总表!$C:$C,MATCH($A201,账户总表!$A:$A,0)),L201="是"),"是","否"),"否")) | AA201: =IF($A201="","",IFERROR(IF(Z201="是",MAX(0,T201-INDEX(账户总表!$C:$C,MATCH($A201,账户总表!$A:$A,0)),IF(N201>0,T201/N201-INDEX(账户总表!$B:$B,MATCH($A201,账户总表!$A:$A,0)),0)),0),0)) | AB201: =IF($A201="","",IF(AND(Z201="是",INDEX(账户总表!$U:$U,MATCH($A201,账户总表!$A:$A,0))="是"),IF(INDEX(账户总表!$L:$L,MATCH($A201,账户总表!$A:$A,0))>=4,AA201*1.5,AA201),0)) | AC201: =IF($A201="","",IF(AND(L201="是",Q201>=R201,S201<=Q201,S201>=R201,W201="是",X201>0,M201="是",INDEX(账户总表!$M:$M,MATCH($A201,账户总表!$A:$A,0))<=2,INDEX(账户总表!$V:$V,MATCH($A201,账户总表!$A:$A,0))="是",OR(T201<=INDEX(账户总表!$C:$C,MATCH($A201,账户总表!$A:$A,0)),AND(Z201="是",INDEX(账户总表!$U:$U,MATCH($A201,账户总表!$A:$A,0))="是",AB201>0))),"是","否")) | AD201: =IF($A201="","",IF(L201<>"是","信号未确认",IF(X201<=0,"止损价未定义",IF(Q201<R201,"100股约束不满足",IF(S201>Q201,"计划股数超单股上限",IF(S201<R201,"计划股数低于最小门槛",IF(W201<>"是","总仓位超限",IF(M201<>"是","追价",IF(INDEX(账户总表!$M:$M,MATCH($A201,账户总表!$A:$A,0))>2,"亏钱效应偏高",IF(INDEX(账户总表!$V:$V,MATCH($A201,账户总表!$A:$A,0))<>"是","账户不允许新开仓",IF(AND(T201>INDEX(账户总表!$C:$C,MATCH($A201,账户总表!$A:$A,0)),INDEX(账户总表!$U:$U,MATCH($A201,账户总表!$A:$A,0))<>"是"),"现金不足且不允许转入",IF(AND(Z201="是",AB201<=0),"转入金额未满足",""))))))))))))

Sheet 交易记录
A1: 交易日期 | B1: 股票名称 | C1: 代码 | D1: 买卖方向 | E1: 信号类型 | F1: 成交价格 | G1: 成交股数 | H1: 成交金额 | I1: 手续费 | J1: 成交后持仓股数 | K1: 成交后仓位占比 | L1: 止损价 | M1: 失效条件 | N1: 执行动作是否合规 | O1: 交易原因 | P1: 结果分类 | Q1: 平仓日期 | R1: 平仓收益率 | S1: 是否触发止损 | T1: 是否情绪化交易 | U1: 备注 | V1: 买入价 | W1: 止损风险额 | X1: R倍数 | Y1: 累计R | Z1: 连胜/连亏 | AA1: 最大回撤(%)
A2: 2026-01-05 | B2: 亚通精工 | C2: 603190 | D2: 买入 | E2: 一买 | F2: 26.66 | G2: 100 | H2: 2666 | O2: 缠论日线一买 | V2: =IF($A2="","",IF(OR(D2="卖出",D2="分红"),IFERROR(INDEX($F$2:$F1,MATCH(2,1/($C$2:$C1=$C2))),""),"")) | W2: =IF($A2="","",IF(D2="买入",IF(AND(ISNUMBER(L2),L2>0),(F2-L2)*G2,F2*0.08*G2),IF(AND(ISNUMBER(V2),V2>0),IF(AND(ISNUMBER(L2),L2>0),(V2-L2)*G2,V2*0.08*G2),0))) -> 213.28 | X2: =IF($A2="","",IF(D2="买入",0,IFERROR(IF(W2<>0,(H2-IFERROR(INDEX($H$2:$H1,MATCH(2,1/($C$2:$C1=$C2))),0))/W2,0),0))) -> 0 | Y2: =IF($A2="","",X2) -> 0 | Z2: =IF($A2="","",IF(X2>0,"胜1",IF(X2<0,"亏1","平"))) -> 平 | AA2: =IF($A2="","",0) -> 0
A3: 2026-01-12 | B3: 黄河旋风 | C3: 600172 | D3: 买入 | E3: 一买 | F3: 6.19 | G3: 800 | H3: 4952 | O3: 缠论日线一买 | V3: =IF($A3="","",IF(OR(D3="卖出",D3="分红"),IFERROR(INDEX($F$2:$F2,MATCH(2,1/($C$2:$C2=$C3))),""),"")) | W3: =IF($A3="","",IF(D3="买入",IF(AND(ISNUMBER(L3),L3>0),(F3-L3)*G3,F3*0.08*G3),IF(AND(ISNUMBER(V3),V3>0),IF(AND(ISNUMBER(L3),L3>0),(V3-L3)*G3,V3*0.08*G3),0))) -> 396.16 | X3: =IF($A3="","",IF(D3="买入",0,IFERROR(IF(W3<>0,(H3-IFERROR(INDEX($H$2:$H2,MATCH(2,1/($C$2:$C2=$C3))),0))/W3,0),0))) -> 0 | Y3: =IF($A3="","",Y2+X3) -> 0 | Z3: =IF($A3="","",IF(X3>0,IF(LEFT(Z2,1)="胜","胜"&VALUE(RIGHT(Z2,LEN(Z2)-1))+1,"胜1"),IF(X3<0,IF(LEFT(Z2,1)="亏","亏"&VALUE(RIGHT(Z2,LEN(Z2)-1))+1,"亏1"),"平"))) -> 平 | AA3: =IF($A3="","",MAX(0,(MAX($Y$2:Y3)-Y3)/MAX(1,MAX($Y$2:Y3)))) -> 0
A4: 2026-01-25 | B4: 亚通精工 | C4: 603190 | D4: 卖出 | E4: 一卖 | F4: 26.193 | G4: 100 | H4: 2619.3 | O4: 缠论30min一卖/止损 | V4: =IF($A4="","",IF(OR(D4="卖出",D4="分红"),IFERROR(INDEX($F$2:$F3,MATCH(2,1/($C$2:$C3=$C4))),""),"")) -> 26.66 | W4: =IF($A4="","",IF(D4="买入",IF(AND(ISNUMBER(L4),L4>0),(F4-L4)*G4,F4*0.08*G4),IF(AND(ISNUMBER(V4),V4>0),IF(AND(ISNUMBER(L4),L4>0),(V4-L4)*G4,V4*0.08*G4),0))) -> 213.28 | X4: =IF($A4="","",IF(D4="买入",0,IFERROR(IF(W4<>0,(H4-IFERROR(INDEX($H$2:$H3,MATCH(2,1/($C$2:$C3=$C4))),0))/W4,0),0))) -> -0.21896099 | Y4: =IF($A4="","",Y3+X4) -> -0.21896099 | Z4: =IF($A4="","",IF(X4>0,IF(LEFT(Z3,1)="胜","胜"&VALUE(RIGHT(Z3,LEN(Z3)-1))+1,"胜1"),IF(X4<0,IF(LEFT(Z3,1)="亏","亏"&VALUE(RIGHT(Z3,LEN(Z3)-1))+1,"亏1"),"平"))) -> 亏1 | AA4: =IF($A4="","",MAX(0,(MAX($Y$2:Y4)-Y4)/MAX(1,MAX($Y$2:Y4)))) -> 0.21896099
A5: 2026-01-28 | B5: 黄河旋风 | C5: 600172 | D5: 卖出 | E5: 一卖 | F5: 9.001 | G5: 800 | H5: 7200.8 | O5: 缠论日线一卖/止盈+45% | V5: =IF($A5="","",IF(OR(D5="卖出",D5="分红"),IFERROR(INDEX($F$2:$F4,MATCH(2,1/($C$2:$C4=$C5))),""),"")) -> 6.19 | W5: =IF($A5="","",IF(D5="买入",IF(AND(ISNUMBER(L5),L5>0),(F5-L5)*G5,F5*0.08*G5),IF(AND(ISNUMBER(V5),V5>0),IF(AND(ISNUMBER(L5),L5>0),(V5-L5)*G5,V5*0.08*G5),0))) -> 396.16 | X5: =IF($A5="","",IF(D5="买入",0,IFERROR(IF(W5<>0,(H5-IFERROR(INDEX($H$2:$H4,MATCH(2,1/($C$2:$C4=$C5))),0))/W5,0),0))) -> 5.6764943 | Y5: =IF($A5="","",Y4+X5) -> 5.4575334 | Z5: =IF($A5="","",IF(X5>0,IF(LEFT(Z4,1)="胜","胜"&VALUE(RIGHT(Z4,LEN(Z4)-1))+1,"胜1"),IF(X5<0,IF(LEFT(Z4,1)="亏","亏"&VALUE(RIGHT(Z4,LEN(Z4)-1))+1,"亏1"),"平"))) -> 胜1 | AA5: =IF($A5="","",MAX(0,(MAX($Y$2:Y5)-Y5)/MAX(1,MAX($Y$2:Y5)))) -> 0
A6: 2026-02-03 | B6: 沪电股份 | C6: 002463 | D6: 买入 | E6: 一买 | F6: 78.81 | G6: 300 | H6: 23643 | O6: 缠论日线一买(电子PCB) | V6: =IF($A6="","",IF(OR(D6="卖出",D6="分红"),IFERROR(INDEX($F$2:$F5,MATCH(2,1/($C$2:$C5=$C6))),""),"")) | W6: =IF($A6="","",IF(D6="买入",IF(AND(ISNUMBER(L6),L6>0),(F6-L6)*G6,F6*0.08*G6),IF(AND(ISNUMBER(V6),V6>0),IF(AND(ISNUMBER(L6),L6>0),(V6-L6)*G6,V6*0.08*G6),0))) -> 1891.44 | X6: =IF($A6="","",IF(D6="买入",0,IFERROR(IF(W6<>0,(H6-IFERROR(INDEX($H$2:$H5,MATCH(2,1/($C$2:$C5=$C6))),0))/W6,0),0))) -> 0 | Y6: =IF($A6="","",Y5+X6) -> 5.4575334 | Z6: =IF($A6="","",IF(X6>0,IF(LEFT(Z5,1)="胜","胜"&VALUE(RIGHT(Z5,LEN(Z5)-1))+1,"胜1"),IF(X6<0,IF(LEFT(Z5,1)="亏","亏"&VALUE(RIGHT(Z5,LEN(Z5)-1))+1,"亏1"),"平"))) -> 平 | AA6: =IF($A6="","",MAX(0,(MAX($Y$2:Y6)-Y6)/MAX(1,MAX($Y$2:Y6)))) -> 0
A7: 2026-03-05 | B7: 沪电股份 | C7: 002463 | D7: 卖出 | E7: 做T | F7: 85 | G7: 300 | H7: 25500 | O7: 30min一卖做T | V7: =IF($A7="","",IF(OR(D7="卖出",D7="分红"),IFERROR(INDEX($F$2:$F6,MATCH(2,1/($C$2:$C6=$C7))),""),"")) | W7: =IF($A7="","",IF(D7="买入",IF(AND(ISNUMBER(L7),L7>0),(F7-L7)*G7,F7*0.08*G7),IF(AND(ISNUMBER(V7),V7>0),IF(AND(ISNUMBER(L7),L7>0),(V7-L7)*G7,V7*0.08*G7),0))) -> 0 | X7: =IF($A7="","",IF(D7="买入",0,IFERROR(IF(W7<>0,(H7-IFERROR(INDEX($H$2:$H6,MATCH(2,1/($C$2:$C6=$C7))),0))/W7,0),0))) -> 0 | Y7: =IF($A7="","",Y6+X7) -> 5.4575334 | Z7: =IF($A7="","",IF(X7>0,IF(LEFT(Z6,1)="胜","胜"&VALUE(RIGHT(Z6,LEN(Z6)-1))+1,"胜1"),IF(X7<0,IF(LEFT(Z6,1)="亏","亏"&VALUE(RIGHT(Z6,LEN(Z6)-1))+1,"亏1"),"平"))) -> 平 | AA7: =IF($A7="","",MAX(0,(MAX($Y$2:Y7)-Y7)/MAX(1,MAX($Y$2:Y7)))) -> 0
A8: 2026-03-05 | B8: 沪电股份 | C8: 002463 | D8: 买入 | E8: 做T | F8: 83 | G8: 300 | H8: 24900 | O8: 5min一买回补 | V8: =IF($A8="","",IF(OR(D8="卖出",D8="分红"),IFERROR(INDEX($F$2:$F7,MATCH(2,1/($C$2:$C7=$C8))),""),"")) | W8: =IF($A8="","",IF(D8="买入",IF(AND(ISNUMBER(L8),L8>0),(F8-L8)*G8,F8*0.08*G8),IF(AND(ISNUMBER(V8),V8>0),IF(AND(ISNUMBER(L8),L8>0),(V8-L8)*G8,V8*0.08*G8),0))) -> 1992 | X8: =IF($A8="","",IF(D8="买入",0,IFERROR(IF(W8<>0,(H8-IFERROR(INDEX($H$2:$H7,MATCH(2,1/($C$2:$C7=$C8))),0))/W8,0),0))) -> 0 | Y8: =IF($A8="","",Y7+X8) -> 5.4575334 | Z8: =IF($A8="","",IF(X8>0,IF(LEFT(Z7,1)="胜","胜"&VALUE(RIGHT(Z7,LEN(Z7)-1))+1,"胜1"),IF(X8<0,IF(LEFT(Z7,1)="亏","亏"&VALUE(RIGHT(Z7,LEN(Z7)-1))+1,"亏1"),"平"))) -> 平 | AA8: =IF($A8="","",MAX(0,(MAX($Y$2:Y8)-Y8)/MAX(1,MAX($Y$2:Y8)))) -> 0
A9: 2026-03-18 | B9: 沪电股份 | C9: 002463 | D9: 卖出 | E9: 做T | F9: 95 | G9: 300 | H9: 28500 | O9: 30min一卖做T | V9: =IF($A9="","",IF(OR(D9="卖出",D9="分红"),IFERROR(INDEX($F$2:$F8,MATCH(2,1/($C$2:$C8=$C9))),""),"")) | W9: =IF($A9="","",IF(D9="买入",IF(AND(ISNUMBER(L9),L9>0),(F9-L9)*G9,F9*0.08*G9),IF(AND(ISNUMBER(V9),V9>0),IF(AND(ISNUMBER(L9),L9>0),(V9-L9)*G9,V9*0.08*G9),0))) -> 0 | X9: =IF($A9="","",IF(D9="买入",0,IFERROR(IF(W9<>0,(H9-IFERROR(INDEX($H$2:$H8,MATCH(2,1/($C$2:$C8=$C9))),0))/W9,0),0))) -> 0 | Y9: =IF($A9="","",Y8+X9) -> 5.4575334 | Z9: =IF($A9="","",IF(X9>0,IF(LEFT(Z8,1)="胜","胜"&VALUE(RIGHT(Z8,LEN(Z8)-1))+1,"胜1"),IF(X9<0,IF(LEFT(Z8,1)="亏","亏"&VALUE(RIGHT(Z8,LEN(Z8)-1))+1,"亏1"),"平"))) -> 平 | AA9: =IF($A9="","",MAX(0,(MAX($Y$2:Y9)-Y9)/MAX(1,MAX($Y$2:Y9)))) -> 0
A10: 2026-03-18 | B10: 沪电股份 | C10: 002463 | D10: 买入 | E10: 做T | F10: 93 | G10: 300 | H10: 27900 | O10: 5min一买回补 | V10: =IF($A10="","",IF(OR(D10="卖出",D10="分红"),IFERROR(INDEX($F$2:$F9,MATCH(2,1/($C$2:$C9=$C10))),""),"")) | W10: =IF($A10="","",IF(D10="买入",IF(AND(ISNUMBER(L10),L10>0),(F10-L10)*G10,F10*0.08*G10),IF(AND(ISNUMBER(V10),V10>0),IF(AND(ISNUMBER(L10),L10>0),(V10-L10)*G10,V10*0.08*G10),0))) -> 2232 | X10: =IF($A10="","",IF(D10="买入",0,IFERROR(IF(W10<>0,(H10-IFERROR(INDEX($H$2:$H9,MATCH(2,1/($C$2:$C9=$C10))),0))/W10,0),0))) -> 0 | Y10: =IF($A10="","",Y9+X10) -> 5.4575334 | Z10: =IF($A10="","",IF(X10>0,IF(LEFT(Z9,1)="胜","胜"&VALUE(RIGHT(Z9,LEN(Z9)-1))+1,"胜1"),IF(X10<0,IF(LEFT(Z9,1)="亏","亏"&VALUE(RIGHT(Z9,LEN(Z9)-1))+1,"亏1"),"平"))) -> 平 | AA10: =IF($A10="","",MAX(0,(MAX($Y$2:Y10)-Y10)/MAX(1,MAX($Y$2:Y10)))) -> 0
A11: 2026-04-08 | B11: 沪电股份 | C11: 002463 | D11: 卖出 | E11: 一卖 | F11: 101.947 | G11: 300 | H11: 30584.1 | O11: 缠论日线一卖/止盈+29% | V11: =IF($A11="","",IF(OR(D11="卖出",D11="分红"),IFERROR(INDEX($F$2:$F10,MATCH(2,1/($C$2:$C10=$C11))),""),"")) -> 93 | W11: =IF($A11="","",IF(D11="买入",IF(AND(ISNUMBER(L11),L11>0),(F11-L11)*G11,F11*0.08*G11),IF(AND(ISNUMBER(V11),V11>0),IF(AND(ISNUMBER(L11),L11>0),(V11-L11)*G11,V11*0.08*G11),0))) -> 2232 | X11: =IF($A11="","",IF(D11="买入",0,IFERROR(IF(W11<>0,(H11-IFERROR(INDEX($H$2:$H10,MATCH(2,1/($C$2:$C10=$C11))),0))/W11,0),0))) -> 1.2025538 | Y11: =IF($A11="","",Y10+X11) -> 6.6600871 | Z11: =IF($A11="","",IF(X11>0,IF(LEFT(Z10,1)="胜","胜"&VALUE(RIGHT(Z10,LEN(Z10)-1))+1,"胜1"),IF(X11<0,IF(LEFT(Z10,1)="亏","亏"&VALUE(RIGHT(Z10,LEN(Z10)-1))+1,"亏1"),"平"))) -> 胜1 | AA11: =IF($A11="","",MAX(0,(MAX($Y$2:Y11)-Y11)/MAX(1,MAX($Y$2:Y11)))) -> 0
A12: 2026-04-15 | B12: 长江电力 | C12: 600900 | D12: 买入 | E12: 一买 | F12: 27.983 | G12: 300 | H12: 8394.9 | O12: 缠论日线一买(电力公用) | V12: =IF($A12="","",IF(OR(D12="卖出",D12="分红"),IFERROR(INDEX($F$2:$F11,MATCH(2,1/($C$2:$C11=$C12))),""),"")) | W12: =IF($A12="","",IF(D12="买入",IF(AND(ISNUMBER(L12),L12>0),(F12-L12)*G12,F12*0.08*G12),IF(AND(ISNUMBER(V12),V12>0),IF(AND(ISNUMBER(L12),L12>0),(V12-L12)*G12,V12*0.08*G12),0))) -> 671.592 | X12: =IF($A12="","",IF(D12="买入",0,IFERROR(IF(W12<>0,(H12-IFERROR(INDEX($H$2:$H11,MATCH(2,1/($C$2:$C11=$C12))),0))/W12,0),0))) -> 0 | Y12: =IF($A12="","",Y11+X12) -> 6.6600871 | Z12: =IF($A12="","",IF(X12>0,IF(LEFT(Z11,1)="胜","胜"&VALUE(RIGHT(Z11,LEN(Z11)-1))+1,"胜1"),IF(X12<0,IF(LEFT(Z11,1)="亏","亏"&VALUE(RIGHT(Z11,LEN(Z11)-1))+1,"亏1"),"平"))) -> 平 | AA12: =IF($A12="","",MAX(0,(MAX($Y$2:Y12)-Y12)/MAX(1,MAX($Y$2:Y12)))) -> 0
A13: 2026-04-22 | B13: 东风股份 | C13: 600006 | D13: 买入 | E13: 一买 | F13: 5.327 | G13: 600 | H13: 3196.2 | O13: 缠论30min一买 | V13: =IF($A13="","",IF(OR(D13="卖出",D13="分红"),IFERROR(INDEX($F$2:$F12,MATCH(2,1/($C$2:$C12=$C13))),""),"")) | W13: =IF($A13="","",IF(D13="买入",IF(AND(ISNUMBER(L13),L13>0),(F13-L13)*G13,F13*0.08*G13),IF(AND(ISNUMBER(V13),V13>0),IF(AND(ISNUMBER(L13),L13>0),(V13-L13)*G13,V13*0.08*G13),0))) -> 255.696 | X13: =IF($A13="","",IF(D13="买入",0,IFERROR(IF(W13<>0,(H13-IFERROR(INDEX($H$2:$H12,MATCH(2,1/($C$2:$C12=$C13))),0))/W13,0),0))) -> 0 | Y13: =IF($A13="","",Y12+X13) -> 6.6600871 | Z13: =IF($A13="","",IF(X13>0,IF(LEFT(Z12,1)="胜","胜"&VALUE(RIGHT(Z12,LEN(Z12)-1))+1,"胜1"),IF(X13<0,IF(LEFT(Z12,1)="亏","亏"&VALUE(RIGHT(Z12,LEN(Z12)-1))+1,"亏1"),"平"))) -> 平 | AA13: =IF($A13="","",MAX(0,(MAX($Y$2:Y13)-Y13)/MAX(1,MAX($Y$2:Y13)))) -> 0
A14: 2026-05-20 | B14: 东风股份 | C14: 600006 | D14: 卖出 | E14: 一卖 | F14: 5.22 | G14: 600 | H14: 3132 | O14: 缠论30min一卖/止损-2% | V14: =IF($A14="","",IF(OR(D14="卖出",D14="分红"),IFERROR(INDEX($F$2:$F13,MATCH(2,1/($C$2:$C13=$C14))),""),"")) | W14: =IF($A14="","",IF(D14="买入",IF(AND(ISNUMBER(L14),L14>0),(F14-L14)*G14,F14*0.08*G14),IF(AND(ISNUMBER(V14),V14>0),IF(AND(ISNUMBER(L14),L14>0),(V14-L14)*G14,V14*0.08*G14),0))) -> 0 | X14: =IF($A14="","",IF(D14="买入",0,IFERROR(IF(W14<>0,(H14-IFERROR(INDEX($H$2:$H13,MATCH(2,1/($C$2:$C13=$C14))),0))/W14,0),0))) -> 0 | Y14: =IF($A14="","",Y13+X14) -> 6.6600871 | Z14: =IF($A14="","",IF(X14>0,IF(LEFT(Z13,1)="胜","胜"&VALUE(RIGHT(Z13,LEN(Z13)-1))+1,"胜1"),IF(X14<0,IF(LEFT(Z13,1)="亏","亏"&VALUE(RIGHT(Z13,LEN(Z13)-1))+1,"亏1"),"平"))) -> 平 | AA14: =IF($A14="","",MAX(0,(MAX($Y$2:Y14)-Y14)/MAX(1,MAX($Y$2:Y14)))) -> 0
... A17: 2026-07-18 | B17: 万华化学 | C17: 600309 | D17: 买入 | E17: 加仓 | F17: 71.09 | G17: 100 | H17: 7109 | O17: 30min一买加仓 | V17: =IF($A17="","",IF(OR(D17="卖出",D17="分红"),IFERROR(INDEX($F$2:$F16,MATCH(2,1/($C$2:$C16=$C17))),""),"")) | W17: =IF($A17="","",IF(D17="买入",IF(AND(ISNUMBER(L17),L17>0),(F17-L17)*G17,F17*0.08*G17),IF(AND(ISNUMBER(V17),V17>0),IF(AND(ISNUMBER(L17),L17>0),(V17-L17)*G17,V17*0.08*G17),0))) -> 568.72 | X17: =IF($A17="","",IF(D17="买入",0,IFERROR(IF(W17<>0,(H17-IFERROR(INDEX($H$2:$H16,MATCH(2,1/($C$2:$C16=$C17))),0))/W17,0),0))) -> 0 | Y17: =IF($A17="","",Y16+X17) -> 6.6600871 | Z17: =IF($A17="","",IF(X17>0,IF(LEFT(Z16,1)="胜","胜"&VALUE(RIGHT(Z16,LEN(Z16)-1))+1,"胜1"),IF(X17<0,IF(LEFT(Z16,1)="亏","亏"&VALUE(RIGHT(Z16,LEN(Z16)-1))+1,"亏1"),"平"))) -> 平 | AA17: =IF($A17="","",MAX(0,(MAX($Y$2:Y17)-Y17)/MAX(1,MAX($Y$2:Y17)))) -> 0
A18: 2026-07-19 | B18: 隆基绿能 | C18: 601012 | D18: 买入 | E18: 一买 | F18: 11.843 | G18: 400 | H18: 4737.2 | L18: 11.4 | O18: 缠论日+30min共振一买 | V18: =IF($A18="","",IF(OR(D18="卖出",D18="分红"),IFERROR(INDEX($F$2:$F17,MATCH(2,1/($C$2:$C17=$C18))),""),"")) | W18: =IF($A18="","",IF(D18="买入",IF(AND(ISNUMBER(L18),L18>0),(F18-L18)*G18,F18*0.08*G18),IF(AND(ISNUMBER(V18),V18>0),IF(AND(ISNUMBER(L18),L18>0),(V18-L18)*G18,V18*0.08*G18),0))) -> 177.2 | X18: =IF($A18="","",IF(D18="买入",0,IFERROR(IF(W18<>0,(H18-IFERROR(INDEX($H$2:$H17,MATCH(2,1/($C$2:$C17=$C18))),0))/W18,0),0))) -> 0 | Y18: =IF($A18="","",Y17+X18) -> 6.6600871 | Z18: =IF($A18="","",IF(X18>0,IF(LEFT(Z17,1)="胜","胜"&VALUE(RIGHT(Z17,LEN(Z17)-1))+1,"胜1"),IF(X18<0,IF(LEFT(Z17,1)="亏","亏"&VALUE(RIGHT(Z17,LEN(Z17)-1))+1,"亏1"),"平"))) -> 平 | AA18: =IF($A18="","",MAX(0,(MAX($Y$2:Y18)-Y18)/MAX(1,MAX($Y$2:Y18)))) -> 0
A19: 2026-03-20 | B19: 沪电股份 | C19: 002463 | D19: 分红 | H19: 50 | O19: 现金分红 | V19: =IF($A19="","",IF(OR(D19="卖出",D19="分红"),IFERROR(INDEX($F$2:$F18,MATCH(2,1/($C$2:$C18=$C19))),""),"")) -> 101.947 | W19: =IF($A19="","",IF(D19="买入",IF(AND(ISNUMBER(L19),L19>0),(F19-L19)*G19,F19*0.08*G19),IF(AND(ISNUMBER(V19),V19>0),IF(AND(ISNUMBER(L19),L19>0),(V19-L19)*G19,V19*0.08*G19),0))) -> 0 | X19: =IF($A19="","",IF(D19="买入",0,IFERROR(IF(W19<>0,(H19-IFERROR(INDEX($H$2:$H18,MATCH(2,1/($C$2:$C18=$C19))),0))/W19,0),0))) -> 0 | Y19: =IF($A19="","",Y18+X19) -> 6.6600871 | Z19: =IF($A19="","",IF(X19>0,IF(LEFT(Z18,1)="胜","胜"&VALUE(RIGHT(Z18,LEN(Z18)-1))+1,"胜1"),IF(X19<0,IF(LEFT(Z18,1)="亏","亏"&VALUE(RIGHT(Z18,LEN(Z18)-1))+1,"亏1"),"平"))) -> 平 | AA19: =IF($A19="","",MAX(0,(MAX($Y$2:Y19)-Y19)/MAX(1,MAX($Y$2:Y19)))) -> 0
V20: =IF($A20="","",IF(OR(D20="卖出",D20="分红"),IFERROR(INDEX($F$2:$F19,MATCH(2,1/($C$2:$C19=$C20))),""),"")) | W20: =IF($A20="","",IF(D20="买入",IF(AND(ISNUMBER(L20),L20>0),(F20-L20)*G20,F20*0.08*G20),IF(AND(ISNUMBER(V20),V20>0),IF(AND(ISNUMBER(L20),L20>0),(V20-L20)*G20,V20*0.08*G20),0))) | X20: =IF($A20="","",IF(D20="买入",0,IFERROR(IF(W20<>0,(H20-IFERROR(INDEX($H$2:$H19,MATCH(2,1/($C$2:$C19=$C20))),0))/W20,0),0))) | Y20: =IF($A20="","",Y19+X20) | Z20: =IF($A20="","",IF(X20>0,IF(LEFT(Z19,1)="胜","胜"&VALUE(RIGHT(Z19,LEN(Z19)-1))+1,"胜1"),IF(X20<0,IF(LEFT(Z19,1)="亏","亏"&VALUE(RIGHT(Z19,LEN(Z19)-1))+1,"亏1"),"平"))) | AA20: =IF($A20="","",MAX(0,(MAX($Y$2:Y20)-Y20)/MAX(1,MAX($Y$2:Y20))))
V21: =IF($A21="","",IF(OR(D21="卖出",D21="分红"),IFERROR(INDEX($F$2:$F20,MATCH(2,1/($C$2:$C20=$C21))),""),"")) | W21: =IF($A21="","",IF(D21="买入",IF(AND(ISNUMBER(L21),L21>0),(F21-L21)*G21,F21*0.08*G21),IF(AND(ISNUMBER(V21),V21>0),IF(AND(ISNUMBER(L21),L21>0),(V21-L21)*G21,V21*0.08*G21),0))) | X21: =IF($A21="","",IF(D21="买入",0,IFERROR(IF(W21<>0,(H21-IFERROR(INDEX($H$2:$H20,MATCH(2,1/($C$2:$C20=$C21))),0))/W21,0),0))) | Y21: =IF($A21="","",Y20+X21) | Z21: =IF($A21="","",IF(X21>0,IF(LEFT(Z20,1)="胜","胜"&VALUE(RIGHT(Z20,LEN(Z20)-1))+1,"胜1"),IF(X21<0,IF(LEFT(Z20,1)="亏","亏"&VALUE(RIGHT(Z20,LEN(Z20)-1))+1,"亏1"),"平"))) | AA21: =IF($A21="","",MAX(0,(MAX($Y$2:Y21)-Y21)/MAX(1,MAX($Y$2:Y21))))
V22: =IF($A22="","",IF(OR(D22="卖出",D22="分红"),IFERROR(INDEX($F$2:$F21,MATCH(2,1/($C$2:$C21=$C22))),""),"")) | W22: =IF($A22="","",IF(D22="买入",IF(AND(ISNUMBER(L22),L22>0),(F22-L22)*G22,F22*0.08*G22),IF(AND(ISNUMBER(V22),V22>0),IF(AND(ISNUMBER(L22),L22>0),(V22-L22)*G22,V22*0.08*G22),0))) | X22: =IF($A22="","",IF(D22="买入",0,IFERROR(IF(W22<>0,(H22-IFERROR(INDEX($H$2:$H21,MATCH(2,1/($C$2:$C21=$C22))),0))/W22,0),0))) | Y22: =IF($A22="","",Y21+X22) | Z22: =IF($A22="","",IF(X22>0,IF(LEFT(Z21,1)="胜","胜"&VALUE(RIGHT(Z21,LEN(Z21)-1))+1,"胜1"),IF(X22<0,IF(LEFT(Z21,1)="亏","亏"&VALUE(RIGHT(Z21,LEN(Z21)-1))+1,"亏1"),"平"))) | AA22: =IF($A22="","",MAX(0,(MAX($Y$2:Y22)-Y22)/MAX(1,MAX($Y$2:Y22))))
V23: =IF($A23="","",IF(OR(D23="卖出",D23="分红"),IFERROR(INDEX($F$2:$F22,MATCH(2,1/($C$2:$C22=$C23))),""),"")) | W23: =IF($A23="","",IF(D23="买入",IF(AND(ISNUMBER(L23),L23>0),(F23-L23)*G23,F23*0.08*G23),IF(AND(ISNUMBER(V23),V23>0),IF(AND(ISNUMBER(L23),L23>0),(V23-L23)*G23,V23*0.08*G23),0))) | X23: =IF($A23="","",IF(D23="买入",0,IFERROR(IF(W23<>0,(H23-IFERROR(INDEX($H$2:$H22,MATCH(2,1/($C$2:$C22=$C23))),0))/W23,0),0))) | Y23: =IF($A23="","",Y22+X23) | Z23: =IF($A23="","",IF(X23>0,IF(LEFT(Z22,1)="胜","胜"&VALUE(RIGHT(Z22,LEN(Z22)-1))+1,"胜1"),IF(X23<0,IF(LEFT(Z22,1)="亏","亏"&VALUE(RIGHT(Z22,LEN(Z22)-1))+1,"亏1"),"平"))) | AA23: =IF($A23="","",MAX(0,(MAX($Y$2:Y23)-Y23)/MAX(1,MAX($Y$2:Y23))))
V24: =IF($A24="","",IF(OR(D24="卖出",D24="分红"),IFERROR(INDEX($F$2:$F23,MATCH(2,1/($C$2:$C23=$C24))),""),"")) | W24: =IF($A24="","",IF(D24="买入",IF(AND(ISNUMBER(L24),L24>0),(F24-L24)*G24,F24*0.08*G24),IF(AND(ISNUMBER(V24),V24>0),IF(AND(ISNUMBER(L24),L24>0),(V24-L24)*G24,V24*0.08*G24),0))) | X24: =IF($A24="","",IF(D24="买入",0,IFERROR(IF(W24<>0,(H24-IFERROR(INDEX($H$2:$H23,MATCH(2,1/($C$2:$C23=$C24))),0))/W24,0),0))) | Y24: =IF($A24="","",Y23+X24) | Z24: =IF($A24="","",IF(X24>0,IF(LEFT(Z23,1)="胜","胜"&VALUE(RIGHT(Z23,LEN(Z23)-1))+1,"胜1"),IF(X24<0,IF(LEFT(Z23,1)="亏","亏"&VALUE(RIGHT(Z23,LEN(Z23)-1))+1,"亏1"),"平"))) | AA24: =IF($A24="","",MAX(0,(MAX($Y$2:Y24)-Y24)/MAX(1,MAX($Y$2:Y24))))
V25: =IF($A25="","",IF(OR(D25="卖出",D25="分红"),IFERROR(INDEX($F$2:$F24,MATCH(2,1/($C$2:$C24=$C25))),""),"")) | W25: =IF($A25="","",IF(D25="买入",IF(AND(ISNUMBER(L25),L25>0),(F25-L25)*G25,F25*0.08*G25),IF(AND(ISNUMBER(V25),V25>0),IF(AND(ISNUMBER(L25),L25>0),(V25-L25)*G25,V25*0.08*G25),0))) | X25: =IF($A25="","",IF(D25="买入",0,IFERROR(IF(W25<>0,(H25-IFERROR(INDEX($H$2:$H24,MATCH(2,1/($C$2:$C24=$C25))),0))/W25,0),0))) | Y25: =IF($A25="","",Y24+X25) | Z25: =IF($A25="","",IF(X25>0,IF(LEFT(Z24,1)="胜","胜"&VALUE(RIGHT(Z24,LEN(Z24)-1))+1,"胜1"),IF(X25<0,IF(LEFT(Z24,1)="亏","亏"&VALUE(RIGHT(Z24,LEN(Z24)-1))+1,"亏1"),"平"))) | AA25: =IF($A25="","",MAX(0,(MAX($Y$2:Y25)-Y25)/MAX(1,MAX($Y$2:Y25))))
V26: =IF($A26="","",IF(OR(D26="卖出",D26="分红"),IFERROR(INDEX($F$2:$F25,MATCH(2,1/($C$2:$C25=$C26))),""),"")) | W26: =IF($A26="","",IF(D26="买入",IF(AND(ISNUMBER(L26),L26>0),(F26-L26)*G26,F26*0.08*G26),IF(AND(ISNUMBER(V26),V26>0),IF(AND(ISNUMBER(L26),L26>0),(V26-L26)*G26,V26*0.08*G26),0))) | X26: =IF($A26="","",IF(D26="买入",0,IFERROR(IF(W26<>0,(H26-IFERROR(INDEX($H$2:$H25,MATCH(2,1/($C$2:$C25=$C26))),0))/W26,0),0))) | Y26: =IF($A26="","",Y25+X26) | Z26: =IF($A26="","",IF(X26>0,IF(LEFT(Z25,1)="胜","胜"&VALUE(RIGHT(Z25,LEN(Z25)-1))+1,"胜1"),IF(X26<0,IF(LEFT(Z25,1)="亏","亏"&VALUE(RIGHT(Z25,LEN(Z25)-1))+1,"亏1"),"平"))) | AA26: =IF($A26="","",MAX(0,(MAX($Y$2:Y26)-Y26)/MAX(1,MAX($Y$2:Y26))))
V27: =IF($A27="","",IF(OR(D27="卖出",D27="分红"),IFERROR(INDEX($F$2:$F26,MATCH(2,1/($C$2:$C26=$C27))),""),"")) | W27: =IF($A27="","",IF(D27="买入",IF(AND(ISNUMBER(L27),L27>0),(F27-L27)*G27,F27*0.08*G27),IF(AND(ISNUMBER(V27),V27>0),IF(AND(ISNUMBER(L27),L27>0),(V27-L27)*G27,V27*0.08*G27),0))) | X27: =IF($A27="","",IF(D27="买入",0,IFERROR(IF(W27<>0,(H27-IFERROR(INDEX($H$2:$H26,MATCH(2,1/($C$2:$C26=$C27))),0))/W27,0),0))) | Y27: =IF($A27="","",Y26+X27) | Z27: =IF($A27="","",IF(X27>0,IF(LEFT(Z26,1)="胜","胜"&VALUE(RIGHT(Z26,LEN(Z26)-1))+1,"胜1"),IF(X27<0,IF(LEFT(Z26,1)="亏","亏"&VALUE(RIGHT(Z26,LEN(Z26)-1))+1,"亏1"),"平"))) | AA27: =IF($A27="","",MAX(0,(MAX($Y$2:Y27)-Y27)/MAX(1,MAX($Y$2:Y27))))
V28: =IF($A28="","",IF(OR(D28="卖出",D28="分红"),IFERROR(INDEX($F$2:$F27,MATCH(2,1/($C$2:$C27=$C28))),""),"")) | W28: =IF($A28="","",IF(D28="买入",IF(AND(ISNUMBER(L28),L28>0),(F28-L28)*G28,F28*0.08*G28),IF(AND(ISNUMBER(V28),V28>0),IF(AND(ISNUMBER(L28),L28>0),(V28-L28)*G28,V28*0.08*G28),0))) | X28: =IF($A28="","",IF(D28="买入",0,IFERROR(IF(W28<>0,(H28-IFERROR(INDEX($H$2:$H27,MATCH(2,1/($C$2:$C27=$C28))),0))/W28,0),0))) | Y28: =IF($A28="","",Y27+X28) | Z28: =IF($A28="","",IF(X28>0,IF(LEFT(Z27,1)="胜","胜"&VALUE(RIGHT(Z27,LEN(Z27)-1))+1,"胜1"),IF(X28<0,IF(LEFT(Z27,1)="亏","亏"&VALUE(RIGHT(Z27,LEN(Z27)-1))+1,"亏1"),"平"))) | AA28: =IF($A28="","",MAX(0,(MAX($Y$2:Y28)-Y28)/MAX(1,MAX($Y$2:Y28))))
V29: =IF($A29="","",IF(OR(D29="卖出",D29="分红"),IFERROR(INDEX($F$2:$F28,MATCH(2,1/($C$2:$C28=$C29))),""),"")) | W29: =IF($A29="","",IF(D29="买入",IF(AND(ISNUMBER(L29),L29>0),(F29-L29)*G29,F29*0.08*G29),IF(AND(ISNUMBER(V29),V29>0),IF(AND(ISNUMBER(L29),L29>0),(V29-L29)*G29,V29*0.08*G29),0))) | X29: =IF($A29="","",IF(D29="买入",0,IFERROR(IF(W29<>0,(H29-IFERROR(INDEX($H$2:$H28,MATCH(2,1/($C$2:$C28=$C29))),0))/W29,0),0))) | Y29: =IF($A29="","",Y28+X29) | Z29: =IF($A29="","",IF(X29>0,IF(LEFT(Z28,1)="胜","胜"&VALUE(RIGHT(Z28,LEN(Z28)-1))+1,"胜1"),IF(X29<0,IF(LEFT(Z28,1)="亏","亏"&VALUE(RIGHT(Z28,LEN(Z28)-1))+1,"亏1"),"平"))) | AA29: =IF($A29="","",MAX(0,(MAX($Y$2:Y29)-Y29)/MAX(1,MAX($Y$2:Y29))))
V30: =IF($A30="","",IF(OR(D30="卖出",D30="分红"),IFERROR(INDEX($F$2:$F29,MATCH(2,1/($C$2:$C29=$C30))),""),"")) | W30: =IF($A30="","",IF(D30="买入",IF(AND(ISNUMBER(L30),L30>0),(F30-L30)*G30,F30*0.08*G30),IF(AND(ISNUMBER(V30),V30>0),IF(AND(ISNUMBER(L30),L30>0),(V30-L30)*G30,V30*0.08*G30),0))) | X30: =IF($A30="","",IF(D30="买入",0,IFERROR(IF(W30<>0,(H30-IFERROR(INDEX($H$2:$H29,MATCH(2,1/($C$2:$C29=$C30))),0))/W30,0),0))) | Y30: =IF($A30="","",Y29+X30) | Z30: =IF($A30="","",IF(X30>0,IF(LEFT(Z29,1)="胜","胜"&VALUE(RIGHT(Z29,LEN(Z29)-1))+1,"胜1"),IF(X30<0,IF(LEFT(Z29,1)="亏","亏"&VALUE(RIGHT(Z29,LEN(Z29)-1))+1,"亏1"),"平"))) | AA30: =IF($A30="","",MAX(0,(MAX($Y$2:Y30)-Y30)/MAX(1,MAX($Y$2:Y30))))
V31: =IF($A31="","",IF(OR(D31="卖出",D31="分红"),IFERROR(INDEX($F$2:$F30,MATCH(2,1/($C$2:$C30=$C31))),""),"")) | W31: =IF($A31="","",IF(D31="买入",IF(AND(ISNUMBER(L31),L31>0),(F31-L31)*G31,F31*0.08*G31),IF(AND(ISNUMBER(V31),V31>0),IF(AND(ISNUMBER(L31),L31>0),(V31-L31)*G31,V31*0.08*G31),0))) | X31: =IF($A31="","",IF(D31="买入",0,IFERROR(IF(W31<>0,(H31-IFERROR(INDEX($H$2:$H30,MATCH(2,1/($C$2:$C30=$C31))),0))/W31,0),0))) | Y31: =IF($A31="","",Y30+X31) | Z31: =IF($A31="","",IF(X31>0,IF(LEFT(Z30,1)="胜","胜"&VALUE(RIGHT(Z30,LEN(Z30)-1))+1,"胜1"),IF(X31<0,IF(LEFT(Z30,1)="亏","亏"&VALUE(RIGHT(Z30,LEN(Z30)-1))+1,"亏1"),"平"))) | AA31: =IF($A31="","",MAX(0,(MAX($Y$2:Y31)-Y31)/MAX(1,MAX($Y$2:Y31))))
... V201: =IF($A201="","",IF(OR(D201="卖出",D201="分红"),IFERROR(INDEX($F$2:$F200,MATCH(2,1/($C$2:$C200=$C201))),""),"")) | W201: =IF($A201="","",IF(D201="买入",IF(AND(ISNUMBER(L201),L201>0),(F201-L201)*G201,F201*0.08*G201),IF(AND(ISNUMBER(V201),V201>0),IF(AND(ISNUMBER(L201),L201>0),(V201-L201)*G201,V201*0.08*G201),0))) | X201: =IF($A201="","",IF(D201="买入",0,IFERROR(IF(W201<>0,(H201-IFERROR(INDEX($H$2:$H200,MATCH(2,1/($C$2:$C200=$C201))),0))/W201,0),0))) | Y201: =IF($A201="","",Y200+X201) | Z201: =IF($A201="","",IF(X201>0,IF(LEFT(Z200,1)="胜","胜"&VALUE(RIGHT(Z200,LEN(Z200)-1))+1,"胜1"),IF(X201<0,IF(LEFT(Z200,1)="亏","亏"&VALUE(RIGHT(Z200,LEN(Z200)-1))+1,"亏1"),"平"))) | AA201: =IF($A201="","",MAX(0,(MAX($Y$2:Y201)-Y201)/MAX(1,MAX($Y$2:Y201))))
A203: 系统健康度仪表盘
A204: 总交易次数(不含分红) | B204: =COUNTIFS(A2:A200,"<>",D2:D200,"<>") -> 18
A205: 卖出次数 | B205: =COUNTIF(D2:D200,"卖出") -> 7
A206: 盈利次数(R>0) | B206: =COUNTIFS(X2:X200,">0") -> 2
A207: 亏损次数(R<0) | B207: =COUNTIFS(X2:X200,"<0") -> 1
A208: 胜率 | B208: =IFERROR(B206/B205,0) -> 0.28571429
A209: 平均R倍数 | B209: =IFERROR(AVERAGEIF(X2:X200,"<>0"),0) -> 2.220029
A210: 总R倍数 | B210: =IFERROR(Y200,0)
A211: 最大单笔R | B211: =IFERROR(MAX(X2:X200),0) -> 5.6764943
A212: 最大单笔亏损R | B212: =IFERROR(MIN(X2:X200),0) -> -0.21896099
A213: 最大连续盈利(笔) | B213: "见Z列(连胜/连亏)"
A214: 最大连续亏损(笔) | B214: "见Z列(连胜/连亏)"
A215: 累计R最大回撤 | B215: =IFERROR(AA200,0)
A216: 盈亏比 | B216: =IFERROR(AVERAGEIF(X2:X200,">0")/ABS(AVERAGEIF(X2:X200,"<0")),0) -> 15.708387
A217: 系统状态 | B217: =IF(B209>=0.5,"正期望系统 ✅",IF(B209>=0.2,"边缘系统 ⚠️","负期望系统 ❌")) -> 正期望系统 ✅
A219: 46227 | B219: 万华化学 | C219: 600309 | D219: 卖出 | E219: 减仓降超限 | F219: 74.56 | G219: 100 | H219: 7456 | I219: 5 | J219: 0 | K219: 20842.32 | N219: 合规 | O219: 30min卖点+仓位37%超限 | P219: 盈利+774元
A220: 46227 | B220: 方盛制药 | C220: 603998 | D220: 买入 | E220: 日线一买确认 | F220: 9.45 | G220: 100 | H220: 945 | I220: 1.5 | J220: 100 | K220: 20842.32 | L220: 8.9775 | M220: 破止损 | N220: 合规 | O220: 日线ratio=3.7% DL_P=0.70 valid | P220: 持仓中
A221: 46227 | B221: 建研院 | C221: 603183 | D221: 买入 | E221: 日线一买确认 | F221: 4.07 | G221: 200 | H221: 814 | I221: 1.5 | J221: 200 | K221: 20842.32 | L221: 3.8665 | M221: 破止损 | N221: 合规 | O221: 日线ratio=5.7% DL_P=0.70 valid | P221: 持仓中
A222: 46227 | B222: 曲美家居 | C222: 603818 | D222: 买入 | E222: 日线一买确认 | F222: 3.2 | G222: 500 | H222: 1600 | I222: 2.4 | J222: 500 | K222: 20842.32 | L222: 3.04 | M222: 破止损 | N222: 合规(已减量) | O222: 日线ratio=9.7% 原挂2100股减至500股 | P222: 持仓中
A223: 46227 | B223: 创力集团 | C223: 603012 | D223: 买入 | E223: 日线一买确认 | F223: 8.021 | G223: 100 | H223: 802 | I223: 1.5 | J223: 100 | K223: 20842.32 | L223: 7.61995 | M223: 破止损 | N223: 合规 | O223: 日线ratio=2.7% DL_P=0.70 全买点 | P223: 持仓中
A224: 46227 | B224: 新五丰 | C224: 600975 | D224: 买入 | E224: 日线一买确认 | F224: 4.804 | G224: 300 | H224: 1441 | I224: 2.2 | J224: 300 | K224: 20842.32 | L224: 4.5638 | M224: 破止损 | N224: 合规 | O224: 日线ratio=12.1% 三级全买点 | P224: 持仓中

Sheet 心态日志
A1: 日期 | B1: 非工作流看盘次数 | C1: 是否追价操作 | D1: 是否按系统执行 | E1: 情绪状态(1-5) | F1: 是否有止损外操作 | G1: 当日交易次数 | H1: 当日系统判定(全部合规) | I1: 焦虑事件描述 | J1: 今日心态感悟 | K1: 心态得分 | L1: 轻态化达标 | M1: 本周平均心态得分 | N1: 本周达标天数 | O1: 连续达标天数 | P1: 心态趋势
A2: 46225 | B2: 5 | C2: 0 | D2: 5 | E2: 3 | F2: 0 | G2: 0 | H2: 全部合规 | K2: 70 | L2: 未达标 | M2: =IF($A2="","",IFERROR(AVERAGEIFS(K$2:K2,WEEKNUM(A$2:A2,2),WEEKNUM(A2,2)),K2)) -> 70 | N2: =IF($A2="","",IFERROR(COUNTIFS(A$2:A2,"<>",L$2:L2,"达标",WEEKNUM(A$2:A2,2),WEEKNUM(A2,2)),0)) -> 0 | O2: =IF($A2="","",IF(L2="达标",IF(ROW()=2,1,IF(O1="",1,O1+1)),0)) -> 0 | P2: =IF($A2="","",IF(ROW()<=8,"基准周",IF(K2>75,"改善",IF(K2<60,"恶化","持平")))) -> 基准周
A3: 46226 | B3: 3 | C3: 0 | D3: 4 | E3: 3 | F3: 0 | G3: 1 | H3: 全部合规 | K3: 70 | L3: 未达标 | M3: =IF($A3="","",IFERROR(AVERAGEIFS(K$2:K3,WEEKNUM(A$2:A3,2),WEEKNUM(A3,2)),K3)) -> 70 | N3: =IF($A3="","",IFERROR(COUNTIFS(A$2:A3,"<>",L$2:L3,"达标",WEEKNUM(A$2:A3,2),WEEKNUM(A3,2)),0)) -> 0 | O3: =IF($A3="","",IF(L3="达标",IF(ROW()=2,1,IF(O2="",1,O2+1)),0)) -> 0 | P3: =IF($A3="","",IF(ROW()<=8,"基准周",IF(K3>k-4,"改善",IF(K3<k-4,"恶化","持平")))) -> 基准周
A4: 46227 | B4: 4 | C4: 0 | D4: 4 | E4: 3 | F4: 0 | G4: 6 | H4: 全部合规 | I4: 曲美家居原挂2100股(33%仓位)超限,减至500股后合规 | J4: 普跌日执行6笔交易,卖超限万华回收资金,建仓4只多级别买点标的。大盘1min买点ratio=55%未确认,属正常回调。严格执行仓位管理,未追涨未恐慌卖出。 | K4: =IF($A4="","",IF(B4=0,20,IF(B4=1,15,IF(B4=2,10,IF(B4=3,5,0))))+IF(C4="否",20,0)+IF(D4="是",20,0)+IF(E4=1,20,IF(E4=2,15,IF(E4=3,10,IF(E4=4,5,0))))+IF(F4="否",20,0)) -> 10 | L4: =IF($A4="","",IF(K4>=80,"达标","未达标")) -> 未达标 | M4: =IF($A4="","",IFERROR(AVERAGEIFS(K$2:K4,WEEKNUM(A$2:A4,2),WEEKNUM(A4,2)),K4)) -> 10 | N4: =IF($A4="","",IFERROR(COUNTIFS(A$2:A4,"<>",L$2:L4,"达标",WEEKNUM(A$2:A4,2),WEEKNUM(A4,2)),0)) -> 0 | O4: =IF($A4="","",IF(L4="达标",IF(ROW()=2,1,IF(O3="",1,O3+1)),0)) -> 0 | P4: =IF($A4="","",IF(ROW()<=8,"基准周",IF(K4>k-3,"改善",IF(K4<k-3,"恶化","持平")))) -> 基准周
K5: =IF($A5="","",IF(B5=0,20,IF(B5=1,15,IF(B5=2,10,IF(B5=3,5,0))))+IF(C5="否",20,0)+IF(D5="是",20,0)+IF(E5=1,20,IF(E5=2,15,IF(E5=3,10,IF(E5=4,5,0))))+IF(F5="否",20,0)) | L5: =IF($A5="","",IF(K5>=80,"达标","未达标")) | M5: =IF($A5="","",IFERROR(AVERAGEIFS(K$2:K5,WEEKNUM(A$2:A5,2),WEEKNUM(A5,2)),K5)) | N5: =IF($A5="","",IFERROR(COUNTIFS(A$2:A5,"<>",L$2:L5,"达标",WEEKNUM(A$2:A5,2),WEEKNUM(A5,2)),0)) | O5: =IF($A5="","",IF(L5="达标",IF(ROW()=2,1,IF(O4="",1,O4+1)),0)) | P5: =IF($A5="","",IF(ROW()<=8,"基准周",IF(K5>k-2,"改善",IF(K5<k-2,"恶化","持平"))))
K6: =IF($A6="","",IF(B6=0,20,IF(B6=1,15,IF(B6=2,10,IF(B6=3,5,0))))+IF(C6="否",20,0)+IF(D6="是",20,0)+IF(E6=1,20,IF(E6=2,15,IF(E6=3,10,IF(E6=4,5,0))))+IF(F6="否",20,0)) | L6: =IF($A6="","",IF(K6>=80,"达标","未达标")) | M6: =IF($A6="","",IFERROR(AVERAGEIFS(K$2:K6,WEEKNUM(A$2:A6,2),WEEKNUM(A6,2)),K6)) | N6: =IF($A6="","",IFERROR(COUNTIFS(A$2:A6,"<>",L$2:L6,"达标",WEEKNUM(A$2:A6,2),WEEKNUM(A6,2)),0)) | O6: =IF($A6="","",IF(L6="达标",IF(ROW()=2,1,IF(O5="",1,O5+1)),0)) | P6: =IF($A6="","",IF(ROW()<=8,"基准周",IF(K6>k-1,"改善",IF(K6<k-1,"恶化","持平"))))
K7: =IF($A7="","",IF(B7=0,20,IF(B7=1,15,IF(B7=2,10,IF(B7=3,5,0))))+IF(C7="否",20,0)+IF(D7="是",20,0)+IF(E7=1,20,IF(E7=2,15,IF(E7=3,10,IF(E7=4,5,0))))+IF(F7="否",20,0)) | L7: =IF($A7="","",IF(K7>=80,"达标","未达标")) | M7: =IF($A7="","",IFERROR(AVERAGEIFS(K$2:K7,WEEKNUM(A$2:A7,2),WEEKNUM(A7,2)),K7)) | N7: =IF($A7="","",IFERROR(COUNTIFS(A$2:A7,"<>",L$2:L7,"达标",WEEKNUM(A$2:A7,2),WEEKNUM(A7,2)),0)) | O7: =IF($A7="","",IF(L7="达标",IF(ROW()=2,1,IF(O6="",1,O6+1)),0)) | P7: =IF($A7="","",IF(ROW()<=8,"基准周",IF(K7>k0,"改善",IF(K7<k0,"恶化","持平"))))
K8: =IF($A8="","",IF(B8=0,20,IF(B8=1,15,IF(B8=2,10,IF(B8=3,5,0))))+IF(C8="否",20,0)+IF(D8="是",20,0)+IF(E8=1,20,IF(E8=2,15,IF(E8=3,10,IF(E8=4,5,0))))+IF(F8="否",20,0)) | L8: =IF($A8="","",IF(K8>=80,"达标","未达标")) | M8: =IF($A8="","",IFERROR(AVERAGEIFS(K$2:K8,WEEKNUM(A$2:A8,2),WEEKNUM(A8,2)),K8)) | N8: =IF($A8="","",IFERROR(COUNTIFS(A$2:A8,"<>",L$2:L8,"达标",WEEKNUM(A$2:A8,2),WEEKNUM(A8,2)),0)) | O8: =IF($A8="","",IF(L8="达标",IF(ROW()=2,1,IF(O7="",1,O7+1)),0)) | P8: =IF($A8="","",IF(ROW()<=8,"基准周",IF(K8>K1,"改善",IF(K8<K1,"恶化","持平"))))
K9: =IF($A9="","",IF(B9=0,20,IF(B9=1,15,IF(B9=2,10,IF(B9=3,5,0))))+IF(C9="否",20,0)+IF(D9="是",20,0)+IF(E9=1,20,IF(E9=2,15,IF(E9=3,10,IF(E9=4,5,0))))+IF(F9="否",20,0)) | L9: =IF($A9="","",IF(K9>=80,"达标","未达标")) | M9: =IF($A9="","",IFERROR(AVERAGEIFS(K$2:K9,WEEKNUM(A$2:A9,2),WEEKNUM(A9,2)),K9)) | N9: =IF($A9="","",IFERROR(COUNTIFS(A$2:A9,"<>",L$2:L9,"达标",WEEKNUM(A$2:A9,2),WEEKNUM(A9,2)),0)) | O9: =IF($A9="","",IF(L9="达标",IF(ROW()=2,1,IF(O8="",1,O8+1)),0)) | P9: =IF($A9="","",IF(ROW()<=8,"基准周",IF(K9>K2,"改善",IF(K9<K2,"恶化","持平"))))
K10: =IF($A10="","",IF(B10=0,20,IF(B10=1,15,IF(B10=2,10,IF(B10=3,5,0))))+IF(C10="否",20,0)+IF(D10="是",20,0)+IF(E10=1,20,IF(E10=2,15,IF(E10=3,10,IF(E10=4,5,0))))+IF(F10="否",20,0)) | L10: =IF($A10="","",IF(K10>=80,"达标","未达标")) | M10: =IF($A10="","",IFERROR(AVERAGEIFS(K$2:K10,WEEKNUM(A$2:A10,2),WEEKNUM(A10,2)),K10)) | N10: =IF($A10="","",IFERROR(COUNTIFS(A$2:A10,"<>",L$2:L10,"达标",WEEKNUM(A$2:A10,2),WEEKNUM(A10,2)),0)) | O10: =IF($A10="","",IF(L10="达标",IF(ROW()=2,1,IF(O9="",1,O9+1)),0)) | P10: =IF($A10="","",IF(ROW()<=8,"基准周",IF(K10>K3,"改善",IF(K10<K3,"恶化","持平"))))
K11: =IF($A11="","",IF(B11=0,20,IF(B11=1,15,IF(B11=2,10,IF(B11=3,5,0))))+IF(C11="否",20,0)+IF(D11="是",20,0)+IF(E11=1,20,IF(E11=2,15,IF(E11=3,10,IF(E11=4,5,0))))+IF(F11="否",20,0)) | L11: =IF($A11="","",IF(K11>=80,"达标","未达标")) | M11: =IF($A11="","",IFERROR(AVERAGEIFS(K$2:K11,WEEKNUM(A$2:A11,2),WEEKNUM(A11,2)),K11)) | N11: =IF($A11="","",IFERROR(COUNTIFS(A$2:A11,"<>",L$2:L11,"达标",WEEKNUM(A$2:A11,2),WEEKNUM(A11,2)),0)) | O11: =IF($A11="","",IF(L11="达标",IF(ROW()=2,1,IF(O10="",1,O10+1)),0)) | P11: =IF($A11="","",IF(ROW()<=8,"基准周",IF(K11>K4,"改善",IF(K11<K4,"恶化","持平"))))
K12: =IF($A12="","",IF(B12=0,20,IF(B12=1,15,IF(B12=2,10,IF(B12=3,5,0))))+IF(C12="否",20,0)+IF(D12="是",20,0)+IF(E12=1,20,IF(E12=2,15,IF(E12=3,10,IF(E12=4,5,0))))+IF(F12="否",20,0)) | L12: =IF($A12="","",IF(K12>=80,"达标","未达标")) | M12: =IF($A12="","",IFERROR(AVERAGEIFS(K$2:K12,WEEKNUM(A$2:A12,2),WEEKNUM(A12,2)),K12)) | N12: =IF($A12="","",IFERROR(COUNTIFS(A$2:A12,"<>",L$2:L12,"达标",WEEKNUM(A$2:A12,2),WEEKNUM(A12,2)),0)) | O12: =IF($A12="","",IF(L12="达标",IF(ROW()=2,1,IF(O11="",1,O11+1)),0)) | P12: =IF($A12="","",IF(ROW()<=8,"基准周",IF(K12>K5,"改善",IF(K12<K5,"恶化","持平"))))
K13: =IF($A13="","",IF(B13=0,20,IF(B13=1,15,IF(B13=2,10,IF(B13=3,5,0))))+IF(C13="否",20,0)+IF(D13="是",20,0)+IF(E13=1,20,IF(E13=2,15,IF(E13=3,10,IF(E13=4,5,0))))+IF(F13="否",20,0)) | L13: =IF($A13="","",IF(K13>=80,"达标","未达标")) | M13: =IF($A13="","",IFERROR(AVERAGEIFS(K$2:K13,WEEKNUM(A$2:A13,2),WEEKNUM(A13,2)),K13)) | N13: =IF($A13="","",IFERROR(COUNTIFS(A$2:A13,"<>",L$2:L13,"达标",WEEKNUM(A$2:A13,2),WEEKNUM(A13,2)),0)) | O13: =IF($A13="","",IF(L13="达标",IF(ROW()=2,1,IF(O12="",1,O12+1)),0)) | P13: =IF($A13="","",IF(ROW()<=8,"基准周",IF(K13>K6,"改善",IF(K13<K6,"恶化","持平"))))
K14: =IF($A14="","",IF(B14=0,20,IF(B14=1,15,IF(B14=2,10,IF(B14=3,5,0))))+IF(C14="否",20,0)+IF(D14="是",20,0)+IF(E14=1,20,IF(E14=2,15,IF(E14=3,10,IF(E14=4,5,0))))+IF(F14="否",20,0)) | L14: =IF($A14="","",IF(K14>=80,"达标","未达标")) | M14: =IF($A14="","",IFERROR(AVERAGEIFS(K$2:K14,WEEKNUM(A$2:A14,2),WEEKNUM(A14,2)),K14)) | N14: =IF($A14="","",IFERROR(COUNTIFS(A$2:A14,"<>",L$2:L14,"达标",WEEKNUM(A$2:A14,2),WEEKNUM(A14,2)),0)) | O14: =IF($A14="","",IF(L14="达标",IF(ROW()=2,1,IF(O13="",1,O13+1)),0)) | P14: =IF($A14="","",IF(ROW()<=8,"基准周",IF(K14>K7,"改善",IF(K14<K7,"恶化","持平"))))
K15: =IF($A15="","",IF(B15=0,20,IF(B15=1,15,IF(B15=2,10,IF(B15=3,5,0))))+IF(C15="否",20,0)+IF(D15="是",20,0)+IF(E15=1,20,IF(E15=2,15,IF(E15=3,10,IF(E15=4,5,0))))+IF(F15="否",20,0)) | L15: =IF($A15="","",IF(K15>=80,"达标","未达标")) | M15: =IF($A15="","",IFERROR(AVERAGEIFS(K$2:K15,WEEKNUM(A$2:A15,2),WEEKNUM(A15,2)),K15)) | N15: =IF($A15="","",IFERROR(COUNTIFS(A$2:A15,"<>",L$2:L15,"达标",WEEKNUM(A$2:A15,2),WEEKNUM(A15,2)),0)) | O15: =IF($A15="","",IF(L15="达标",IF(ROW()=2,1,IF(O14="",1,O14+1)),0)) | P15: =IF($A15="","",IF(ROW()<=8,"基准周",IF(K15>K8,"改善",IF(K15<K8,"恶化","持平"))))
K16: =IF($A16="","",IF(B16=0,20,IF(B16=1,15,IF(B16=2,10,IF(B16=3,5,0))))+IF(C16="否",20,0)+IF(D16="是",20,0)+IF(E16=1,20,IF(E16=2,15,IF(E16=3,10,IF(E16=4,5,0))))+IF(F16="否",20,0)) | L16: =IF($A16="","",IF(K16>=80,"达标","未达标")) | M16: =IF($A16="","",IFERROR(AVERAGEIFS(K$2:K16,WEEKNUM(A$2:A16,2),WEEKNUM(A16,2)),K16)) | N16: =IF($A16="","",IFERROR(COUNTIFS(A$2:A16,"<>",L$2:L16,"达标",WEEKNUM(A$2:A16,2),WEEKNUM(A16,2)),0)) | O16: =IF($A16="","",IF(L16="达标",IF(ROW()=2,1,IF(O15="",1,O15+1)),0)) | P16: =IF($A16="","",IF(ROW()<=8,"基准周",IF(K16>K9,"改善",IF(K16<K9,"恶化","持平"))))
K17: =IF($A17="","",IF(B17=0,20,IF(B17=1,15,IF(B17=2,10,IF(B17=3,5,0))))+IF(C17="否",20,0)+IF(D17="是",20,0)+IF(E17=1,20,IF(E17=2,15,IF(E17=3,10,IF(E17=4,5,0))))+IF(F17="否",20,0)) | L17: =IF($A17="","",IF(K17>=80,"达标","未达标")) | M17: =IF($A17="","",IFERROR(AVERAGEIFS(K$2:K17,WEEKNUM(A$2:A17,2),WEEKNUM(A17,2)),K17)) | N17: =IF($A17="","",IFERROR(COUNTIFS(A$2:A17,"<>",L$2:L17,"达标",WEEKNUM(A$2:A17,2),WEEKNUM(A17,2)),0)) | O17: =IF($A17="","",IF(L17="达标",IF(ROW()=2,1,IF(O16="",1,O16+1)),0)) | P17: =IF($A17="","",IF(ROW()<=8,"基准周",IF(K17>K10,"改善",IF(K17<K10,"恶化","持平"))))
K18: =IF($A18="","",IF(B18=0,20,IF(B18=1,15,IF(B18=2,10,IF(B18=3,5,0))))+IF(C18="否",20,0)+IF(D18="是",20,0)+IF(E18=1,20,IF(E18=2,15,IF(E18=3,10,IF(E18=4,5,0))))+IF(F18="否",20,0)) | L18: =IF($A18="","",IF(K18>=80,"达标","未达标")) | M18: =IF($A18="","",IFERROR(AVERAGEIFS(K$2:K18,WEEKNUM(A$2:A18,2),WEEKNUM(A18,2)),K18)) | N18: =IF($A18="","",IFERROR(COUNTIFS(A$2:A18,"<>",L$2:L18,"达标",WEEKNUM(A$2:A18,2),WEEKNUM(A18,2)),0)) | O18: =IF($A18="","",IF(L18="达标",IF(ROW()=2,1,IF(O17="",1,O17+1)),0)) | P18: =IF($A18="","",IF(ROW()<=8,"基准周",IF(K18>K11,"改善",IF(K18<K11,"恶化","持平"))))
K19: =IF($A19="","",IF(B19=0,20,IF(B19=1,15,IF(B19=2,10,IF(B19=3,5,0))))+IF(C19="否",20,0)+IF(D19="是",20,0)+IF(E19=1,20,IF(E19=2,15,IF(E19=3,10,IF(E19=4,5,0))))+IF(F19="否",20,0)) | L19: =IF($A19="","",IF(K19>=80,"达标","未达标")) | M19: =IF($A19="","",IFERROR(AVERAGEIFS(K$2:K19,WEEKNUM(A$2:A19,2),WEEKNUM(A19,2)),K19)) | N19: =IF($A19="","",IFERROR(COUNTIFS(A$2:A19,"<>",L$2:L19,"达标",WEEKNUM(A$2:A19,2),WEEKNUM(A19,2)),0)) | O19: =IF($A19="","",IF(L19="达标",IF(ROW()=2,1,IF(O18="",1,O18+1)),0)) | P19: =IF($A19="","",IF(ROW()<=8,"基准周",IF(K19>K12,"改善",IF(K19<K12,"恶化","持平"))))
... K201: =IF($A201="","",IF(B201=0,20,IF(B201=1,15,IF(B201=2,10,IF(B201=3,5,0))))+IF(C201="否",20,0)+IF(D201="是",20,0)+IF(E201=1,20,IF(E201=2,15,IF(E201=3,10,IF(E201=4,5,0))))+IF(F201="否",20,0)) | L201: =IF($A201="","",IF(K201>=80,"达标","未达标")) | M201: =IF($A201="","",IFERROR(AVERAGEIFS(K$2:K201,WEEKNUM(A$2:A201,2),WEEKNUM(A201,2)),K201)) | N201: =IF($A201="","",IFERROR(COUNTIFS(A$2:A201,"<>",L$2:L201,"达标",WEEKNUM(A$2:A201,2),WEEKNUM(A201,2)),0)) | O201: =IF($A201="","",IF(L201="达标",IF(ROW()=2,1,IF(O200="",1,O200+1)),0)) | P201: =IF($A201="","",IF(ROW()<=8,"基准周",IF(K201>K194,"改善",IF(K201<K194,"恶化","持平"))))
A203: 心态轻态化仪表盘
A204: 填写天数 | B204: =COUNTA(A2:A200) -> 3
A205: 达标天数 | B205: =COUNTIF(L2:L200,"达标") -> 0
A206: 达标率 | B206: =IFERROR(B205/B204,0) -> 0
A207: 平均心态得分 | B207: =IFERROR(AVERAGE(K2:K200),0) -> 50
A208: 最佳心态得分 | B208: =IFERROR(MAX(K2:K200),0) -> 70
A209: 最差心态得分 | B209: =IFERROR(MIN(K2:K200),0) -> 10
A210: 当前连续达标 | B210: =IFERROR(O200,0)
A211: 历史最长连续达标 | B211: =IFERROR(MAX(O2:O200),0) -> 0
A212: 平均看盘次数/天 | B212: =IFERROR(AVERAGE(B2:B200),0) -> 4
A213: 追价违规次数 | B213: =COUNTIF(C2:C200,"是") -> 0
A214: 系统偏离次数 | B214: =COUNTIF(D2:D200,"否") -> 0
A215: 止损外操作次数 | B215: =COUNTIF(F2:F200,"是") -> 0
A216: 平均情绪评分 | B216: =IFERROR(AVERAGE(E2:E200),0) -> 3
A217: 心态状态 | B217: =IF(B207>=80,"轻态 ✅",IF(B207>=60,"改善中 ⚠️","需调整 ❌")) -> 需调整 ❌
A220: 评分说明
A221: B列: 非工作流看盘次数 — 收盘后截图录入=工作流,不计入。盘中反复刷新App=焦虑看盘,计入。
A222: C列: 是否追价 — 系统未确认信号时主动买入=追价。系统确认后买入=正常执行。
A223: D列: 是否按系统执行 — 持仓表AB列结论 vs 实际操作是否一致。
A224: E列: 情绪1-5 — 1=平静(不急不躁) 2=轻微波动 3=有些焦虑 4=明显焦虑 5=极度焦虑影响判断。
A225: F列: 止损外操作 — 在止损价未触发时提前卖出,或超出仓位上限买入。
A226: 工作流截图: 每日收盘后1次账户总览+持仓明细截图,属于必要工作流,不计入B列。

Sheet 周复盘
A1: 周期 | B1: 周初总资产 | C1: 周末总资产 | D1: 周收益率 | E1: 本周最高资产 | F1: 本周最低资产 | G1: 本周最大回撤 | H1: 本周交易次数 | I1: 盈利交易数 | J1: 亏损交易数 | K1: 最近5笔胜负 | L1: 止损次数 | M1: 赚钱效应分数均值 | N1: 亏钱效应分数均值 | O1: 当前市场状态主判断 | P1: 本周最大问题 | Q1: 本周执行最好的点 | R1: 下周是否允许新开仓 | S1: 下周总仓位建议 | T1: 下周是否考虑转入 | U1: 下周重点观察股 | V1: 备注
D2: =IFERROR((C2-B2)/B2,0) -> 0 | G2: =IFERROR((F2-E2)/E2,0) -> 0 | R2: =IF($A2="","",IF(AND(N2<=2,G2>-15%),"是","否")) | T2: =IF($A2="","",IF(AND(M2>=3,N2<=2),"是","否"))
D3: =IFERROR((C3-B3)/B3,0) -> 0 | G3: =IFERROR((F3-E3)/E3,0) -> 0 | R3: =IF($A3="","",IF(AND(N3<=2,G3>-15%),"是","否")) | T3: =IF($A3="","",IF(AND(M3>=3,N3<=2),"是","否"))
D4: =IFERROR((C4-B4)/B4,0) -> 0 | G4: =IFERROR((F4-E4)/E4,0) -> 0 | R4: =IF($A4="","",IF(AND(N4<=2,G4>-15%),"是","否")) | T4: =IF($A4="","",IF(AND(M4>=3,N4<=2),"是","否"))
D5: =IFERROR((C5-B5)/B5,0) -> 0 | G5: =IFERROR((F5-E5)/E5,0) -> 0 | R5: =IF($A5="","",IF(AND(N5<=2,G5>-15%),"是","否")) | T5: =IF($A5="","",IF(AND(M5>=3,N5<=2),"是","否"))
D6: =IFERROR((C6-B6)/B6,0) -> 0 | G6: =IFERROR((F6-E6)/E6,0) -> 0 | R6: =IF($A6="","",IF(AND(N6<=2,G6>-15%),"是","否")) | T6: =IF($A6="","",IF(AND(M6>=3,N6<=2),"是","否"))
D7: =IFERROR((C7-B7)/B7,0) -> 0 | G7: =IFERROR((F7-E7)/E7,0) -> 0 | R7: =IF($A7="","",IF(AND(N7<=2,G7>-15%),"是","否")) | T7: =IF($A7="","",IF(AND(M7>=3,N7<=2),"是","否"))
D8: =IFERROR((C8-B8)/B8,0) -> 0 | G8: =IFERROR((F8-E8)/E8,0) -> 0 | R8: =IF($A8="","",IF(AND(N8<=2,G8>-15%),"是","否")) | T8: =IF($A8="","",IF(AND(M8>=3,N8<=2),"是","否"))
D9: =IFERROR((C9-B9)/B9,0) -> 0 | G9: =IFERROR((F9-E9)/E9,0) -> 0 | R9: =IF($A9="","",IF(AND(N9<=2,G9>-15%),"是","否")) | T9: =IF($A9="","",IF(AND(M9>=3,N9<=2),"是","否"))
D10: =IFERROR((C10-B10)/B10,0) -> 0 | G10: =IFERROR((F10-E10)/E10,0) -> 0 | R10: =IF($A10="","",IF(AND(N10<=2,G10>-15%),"是","否")) | T10: =IF($A10="","",IF(AND(M10>=3,N10<=2),"是","否"))
D11: =IFERROR((C11-B11)/B11,0) -> 0 | G11: =IFERROR((F11-E11)/E11,0) -> 0 | R11: =IF($A11="","",IF(AND(N11<=2,G11>-15%),"是","否")) | T11: =IF($A11="","",IF(AND(M11>=3,N11<=2),"是","否"))
D12: =IFERROR((C12-B12)/B12,0) -> 0 | G12: =IFERROR((F12-E12)/E12,0) -> 0 | R12: =IF($A12="","",IF(AND(N12<=2,G12>-15%),"是","否")) | T12: =IF($A12="","",IF(AND(M12>=3,N12<=2),"是","否"))
D13: =IFERROR((C13-B13)/B13,0) -> 0 | G13: =IFERROR((F13-E13)/E13,0) -> 0 | R13: =IF($A13="","",IF(AND(N13<=2,G13>-15%),"是","否")) | T13: =IF($A13="","",IF(AND(M13>=3,N13<=2),"是","否"))
... D201: =IFERROR((C201-B201)/B201,0) -> 0 | G201: =IFERROR((F201-E201)/E201,0) -> 0 | R201: =IF($A201="","",IF(AND(N201<=2,G201>-15%),"是","否")) | T201: =IF($A201="","",IF(AND(M201>=3,N201<=2),"是","否"))
